Workbook
Name CONTRATOS_LISTA: 'Resumen_Cartera'!$A$5:$A$281

Sheet Caratula_Ejecutiva
B4: O-LEASING · UNA APP DE ORANGE CREW
B5: REPORTE INTEGRAL DE AUDITORÍA Y SALDOS DE CARTERA
B6: Normatividad NIF C-15 / IFRS 16 · Fórmulas Financieras Vivas de Excel · Desarrollado por Orange Crew · Ejercicio Fiscal 2026
B8: CONTRATOS AUDITADOS | D8: INVERSIÓN NETA TOTAL | F8: RENTA MENSUAL TOTAL | H8: RESIDUAL TOTAL PACTADO
B9: ='Resumen_Cartera'!G282 | D9: ='Resumen_Cartera'!K282 | F9: ='Resumen_Cartera'!N282 | H9: ='Resumen_Cartera'!P282
B10: TASA MENSUAL PROMEDIO | D10: TOTAL INTERÉS LEASING | F10: TOTAL INTERÉS RESIDUAL | H10: INGRESO FINANCIERO TOTAL
B11: ='Resumen_Cartera'!R282 | D11: ='Resumen_Cartera'!V282 | F11: ='Resumen_Cartera'!W282 | H11: ='Resumen_Cartera'!X282
B13: ÍNDICE DE HOJAS Y METODOLOGÍA DEL LIBRO OFICIAL (O-LEASING · ORANGE CREW)
B14: No. | C14: Hoja de Cálculo (Clic para ir) | D14: Propósito y Contenido Contable | E14: Fórmulas Matemáticas Clave
B15: 1 | C15: =HYPERLINK("#'Resumen_Cartera'!A1", "Resumen_Cartera") | D15: Padrón completo de contratos en vertical con unidad vehicular, porcentajes y rentabilidad. | E15: RATE, PV, SUM, AVERAGE
B16: 2 | C16: =HYPERLINK("#'Calculo_Tasa_Implicita'!A1", "Calculo_Tasa_Implicita") | D16: Metodología NIF C-15 / IFRS 16 de cálculo de tasa mensual y comprobación a diferencia cero. | E16: RATE, PV, Comprobación PV, TIR
B17: 3 | C17: =HYPERLINK("#'Modelo_Amortizacion_Tipo'!A1", "Modelo_Amortizacion_Tipo") | D17: Demostración dinámica con selector desplegable de contrato y corte automático exacto al plazo. | E17: VLOOKUP, Saldo*Tasa, Renta-Interés, Corte
B18: 4 | C18: =HYPERLINK("#'Intereses_Leasing_Mensual'!A1", "Intereses_Leasing_Mensual") | D18: Matriz horizontal de intereses de leasing devengados mes a mes por contrato. | E18: IF(Saldo_Ant>0, ROUND(Saldo_Ant*Tasa, 2), '')
B19: 5 | C19: =HYPERLINK("#'Intereses_Residual_Mensual'!A1", "Intereses_Residual_Mensual") | D19: Matriz horizontal de intereses sobre el valor presente del residual (NIF C-15). | E19: IF(Saldo_Res_Ant>0, ROUND(Saldo_Res*Tasa, 2), '')
B20: 6 | C20: =HYPERLINK("#'Ingreso_Financiero_Total'!A1", "Ingreso_Financiero_Total") | D20: Matriz de ingreso financiero consolidado (Leasing + Residual) mes a mes. | E20: Intereses_Leasing_Mensual! + Residual!
B21: 7 | C21: =HYPERLINK("#'Amortizacion_Capital_Mensual'!A1", "Amortizacion_Capital_Mensual") | D21: Matriz horizontal de amortización de principal mes a mes. | E21: IF(Leasing>0, Renta - Leasing, '')
B22: 8 | C22: =HYPERLINK("#'Saldos_Capital_Mensual'!A1", "Saldos_Capital_Mensual") | D22: Saldo insoluto de principal mes a mes al cierre de cada periodo contable. | E22: IF(Cap>0, Saldo_Ant - Cap, '')
B23: 9 | C23: =HYPERLINK("#'Saldos_Intereses_Mensual'!A1", "Saldos_Intereses_Mensual") | D23: Saldo de intereses remanentes por devengar/cobrar desde cada corte mensual. | E23: IF(Int>0, Saldo_Ant - Int, '')
B24: 10 | C24: =HYPERLINK("#'Saldos_Cartera_Total'!A1", "Saldos_Cartera_Total") | D24: Saldo total exigible de mensualidades restantes (Capital + Intereses). | E24: Saldos_Capital! + Saldos_Intereses!
B25: 11 | C25: =HYPERLINK("#'Saldo_Residual_Activo'!A1", "Saldo_Residual_Activo") | D25: Evolución mensual del saldo activo del valor residual pactado. | E25: IF(Int_Res>0, Saldo_Ant + Int_Res, '')
B26: 12 | C26: =HYPERLINK("#'Saldos_Exigible_Global'!A1", "Saldos_Exigible_Global") | D26: Deuda integral total de cartera más valor residual activo. | E26: Saldos_Cartera_Total! + Saldo_Residual!
B27: 13 | C27: =HYPERLINK("#'Matriz_Consolidada'!A1", "Matriz_Consolidada") | D27: Bloques cronológicos multi-concepto con leasing, residual, ingreso y capital de cartera. | E27: Fórmulas inter-hoja vivas
B28: 14 | C28: =HYPERLINK("#'Matriz_Consolidada_Saldos'!A1", "Matriz_Consolidada_Saldos") | D28: Bloques cronológicos multi-concepto con los 5 rubros de saldos lado a lado. | E28: Fórmulas inter-hoja vivas
B30: O-LEASING es una aplicación financiera desarrollada y mantenida por ORANGE CREW. Todos los derechos reservados conforme a la LFDA.

Sheet Resumen_Cartera
A1: O-LEASING · UNA APP DE ORANGE CREW · Resumen de Cartera y Parámetros Financieros
A2: Parámetros contractuales, unidad adquirida, porcentajes iniciales y fórmulas matemáticas de rentabilidad · Auditoría Financiera NIF C-15 / IFRS 16 · Desarrollado por Orange Crew
A4: ID_Contrato | B4: Cliente | C4: Vehiculo | D4: Estatus | E4: Fecha_Alta | F4: Fecha_Vencimiento | G4: Plazo_Meses | H4: Valor_Sin_IVA | I4: Anticipo_Pct | J4: Anticipo_Monto | K4: Inversion_Neta | L4: Comision_Pct | M4: Comision_Apertura | N4: Renta_Sin_IVA | O4: Residual_Pct | P4: Residual_Pactado | Q4: Tasa_Mensual_Reg | R4: Tasa_Mensual_RATE | S4: Tasa_Nominal_Anual | T4: TIR_Anual_Efectiva | U4: VP_Residual | V4: Total_Interes_Leasing | W4: Total_Interes_Residual | X4: Ingreso_Financiero_Total | Y4: Ganancia_Neta | Z4: Margen_Sobre_Inv
A5: 0326-0003 | B5: Alberto Vázquez Solorio | C5: Volkswagen Tiguan R-Line 2026 | D5: ACTIVO | E5: 2026-09-16 | F5: 2030-09-16 | G5: 48 | H5: 645181.9 | I5: 0.3705 | J5: =ROUND(H5*I5, 2) | K5: =ROUND(H5-J5, 2) | L5: 0 | M5: =ROUND(H5*L5, 2) | N5: 8393.91 | O5: 0.28 | P5: =ROUND(H5*O5, 2) | Q5: 0.01206146 | R5: =IFERROR(RATE(G5, -N5, K5, -P5), Q5) | S5: =Q5*12 | T5: =((1+Q5)^12)-1 | U5: =IF(Q5>0, ROUND(P5/((1+Q5)^G5), 2), P5) | V5: =ROUND((N5*G5)-K5+P5, 2) | W5: =ROUND(P5-U5, 2) | X5: =ROUND(V5+W5, 2) | Y5: =ROUND((N5*G5+P5+M5)-K5, 2) | Z5: =IF(K5>0, Y5/K5, 0)
A6: 0472-0003 | B6: Miguel Zazueta Beltrán | C6: Jeep Grand Cherokee | D6: ACTIVO | E6: 2026-02-03 | F6: 2029-02-03 | G6: 36 | H6: 1217433.6 | I6: 0.3 | J6: =ROUND(H6*I6, 2) | K6: =ROUND(H6-J6, 2) | L6: 0.02 | M6: =ROUND(H6*L6, 2) | N6: 35031.5 | O6: 0.1 | P6: =ROUND(H6*O6, 2) | Q6: 0.02661776 | R6: =IFERROR(RATE(G6, -N6, K6, -P6), Q6) | S6: =Q6*12 | T6: =((1+Q6)^12)-1 | U6: =IF(Q6>0, ROUND(P6/((1+Q6)^G6), 2), P6) | V6: =ROUND((N6*G6)-K6+P6, 2) | W6: =ROUND(P6-U6, 2) | X6: =ROUND(V6+W6, 2) | Y6: =ROUND((N6*G6+P6+M6)-K6, 2) | Z6: =IF(K6>0, Y6/K6, 0)
A7: 0504-0004 | B7: Oscar Ivan Lozano Terriquez | C7: 700 BIGHORN "S" CREW CAB MT | D7: ACTIVO | E7: 2026-01-05 | F7: 2027-01-05 | G7: 12 | H7: 352500 | I7: 0.35 | J7: =ROUND(H7*I7, 2) | K7: =ROUND(H7-J7, 2) | L7: 0.02 | M7: =ROUND(H7*L7, 2) | N7: 19654.64 | O7: 0.1 | P7: =ROUND(H7*O7, 2) | Q7: 0.02415117 | R7: =IFERROR(RATE(G7, -N7, K7, -P7), Q7) | S7: =Q7*12 | T7: =((1+Q7)^12)-1 | U7: =IF(Q7>0, ROUND(P7/((1+Q7)^G7), 2), P7) | V7: =ROUND((N7*G7)-K7+P7, 2) | W7: =ROUND(P7-U7, 2) | X7: =ROUND(V7+W7, 2) | Y7: =ROUND((N7*G7+P7+M7)-K7, 2) | Z7: =IF(K7>0, Y7/K7, 0)
A8: 0506-0006 | B8: Electronic Accounting Sa de Cv | C8: X5 | D8: ACTIVO | E8: 2024-01-10 | F8: 2027-01-10 | G8: 36 | H8: 1622338.8 | I8: 0.1759 | J8: =ROUND(H8*I8, 2) | K8: =ROUND(H8-J8, 2) | L8: 0 | M8: =ROUND(H8*L8, 2) | N8: 35607.45 | O8: 0.35 | P8: =ROUND(H8*O8, 2) | Q8: 0.01430392 | R8: =IFERROR(RATE(G8, -N8, K8, -P8), Q8) | S8: =Q8*12 | T8: =((1+Q8)^12)-1 | U8: =IF(Q8>0, ROUND(P8/((1+Q8)^G8), 2), P8) | V8: =ROUND((N8*G8)-K8+P8, 2) | W8: =ROUND(P8-U8, 2) | X8: =ROUND(V8+W8, 2) | Y8: =ROUND((N8*G8+P8+M8)-K8, 2) | Z8: =IF(K8>0, Y8/K8, 0)
A9: 0506-0007 | B9: Electronic Acounting | C9: L200 Glx Diesel | D9: ACTIVO | E9: 2024-09-05 | F9: 2027-09-05 | G9: 36 | H9: 536762.93 | I9: 0 | J9: =ROUND(H9*I9, 2) | K9: =ROUND(H9-J9, 2) | L9: 0 | M9: =ROUND(H9*L9, 2) | N9: 16715.69 | O9: 0.35 | P9: =ROUND(H9*O9, 2) | Q9: 0.01820217 | R9: =IFERROR(RATE(G9, -N9, K9, -P9), Q9) | S9: =Q9*12 | T9: =((1+Q9)^12)-1 | U9: =IF(Q9>0, ROUND(P9/((1+Q9)^G9), 2), P9) | V9: =ROUND((N9*G9)-K9+P9, 2) | W9: =ROUND(P9-U9, 2) | X9: =ROUND(V9+W9, 2) | Y9: =ROUND((N9*G9+P9+M9)-K9, 2) | Z9: =IF(K9>0, Y9/K9, 0)
A10: 0519-0005 | B10: Tequilas el Mexicano S.A. de C.V. | C10: Attitude Sport | D10: ACTIVO | E10: 2025-07-14 | F10: 2029-07-14 | G10: 48 | H10: 352500 | I10: 0.1 | J10: =ROUND(H10*I10, 2) | K10: =ROUND(H10-J10, 2) | L10: 0 | M10: =ROUND(H10*L10, 2) | N10: 11483.47 | O10: 0.1 | P10: =ROUND(H10*O10, 2) | Q10: 0.02691789 | R10: =IFERROR(RATE(G10, -N10, K10, -P10), Q10) | S10: =Q10*12 | T10: =((1+Q10)^12)-1 | U10: =IF(Q10>0, ROUND(P10/((1+Q10)^G10), 2), P10) | V10: =ROUND((N10*G10)-K10+P10, 2) | W10: =ROUND(P10-U10, 2) | X10: =ROUND(V10+W10, 2) | Y10: =ROUND((N10*G10+P10+M10)-K10, 2) | Z10: =IF(K10>0, Y10/K10, 0)
A11: 0520-0003 | B11: Tractomotriz Diesel Leal, S.A. de C.V. | C11: Montero Sport | D11: ACTIVO | E11: 2025-11-28 | F11: 2028-11-28 | G11: 36 | H11: 621465.52 | I11: 0.4 | J11: =ROUND(H11*I11, 2) | K11: =ROUND(H11-J11, 2) | L11: 1 | M11: =ROUND(H11*L11, 2) | N11: 15182.88 | O11: 0.1 | P11: =ROUND(H11*O11, 2) | Q11: 0.02663641 | R11: =IFERROR(RATE(G11, -N11, K11, -P11), Q11) | S11: =Q11*12 | T11: =((1+Q11)^12)-1 | U11: =IF(Q11>0, ROUND(P11/((1+Q11)^G11), 2), P11) | V11: =ROUND((N11*G11)-K11+P11, 2) | W11: =ROUND(P11-U11, 2) | X11: =ROUND(V11+W11, 2) | Y11: =ROUND((N11*G11+P11+M11)-K11, 2) | Z11: =IF(K11>0, Y11/K11, 0)
A12: 0520-0004 | B12: Tractomotriz Diesel Leal, S.A. de C.V. | C12: Partner Maxi Pack | D12: ACTIVO | E12: 2025-12-04 | F12: 2028-12-04 | G12: 36 | H12: 400363.79 | I12: 0.4 | J12: =ROUND(H12*I12, 2) | K12: =ROUND(H12-J12, 2) | L12: 1 | M12: =ROUND(H12*L12, 2) | N12: 9781.2 | O12: 0.1 | P12: =ROUND(H12*O12, 2) | Q12: 0.02663643 | R12: =IFERROR(RATE(G12, -N12, K12, -P12), Q12) | S12: =Q12*12 | T12: =((1+Q12)^12)-1 | U12: =IF(Q12>0, ROUND(P12/((1+Q12)^G12), 2), P12) | V12: =ROUND((N12*G12)-K12+P12, 2) | W12: =ROUND(P12-U12, 2) | X12: =ROUND(V12+W12, 2) | Y12: =ROUND((N12*G12+P12+M12)-K12, 2) | Z12: =IF(K12>0, Y12/K12, 0)
A13: 0521-0002 | B13: Carlos Hiram leal Leal | C13: Xpander | D13: ACTIVO | E13: 2025-09-08 | F13: 2028-09-08 | G13: 36 | H13: 365988.79 | I13: 0.1 | J13: =ROUND(H13*I13, 2) | K13: =ROUND(H13-J13, 2) | L13: 1 | M13: =ROUND(H13*L13, 2) | N13: 13100.96 | O13: 0.2 | P13: =ROUND(H13*O13, 2) | Q13: 0.02662861 | R13: =IFERROR(RATE(G13, -N13, K13, -P13), Q13) | S13: =Q13*12 | T13: =((1+Q13)^12)-1 | U13: =IF(Q13>0, ROUND(P13/((1+Q13)^G13), 2), P13) | V13: =ROUND((N13*G13)-K13+P13, 2) | W13: =ROUND(P13-U13, 2) | X13: =ROUND(V13+W13, 2) | Y13: =ROUND((N13*G13+P13+M13)-K13, 2) | Z13: =IF(K13>0, Y13/K13, 0)
A14: 0524-0007 | B14: Lider En Derecho De Via y Construcción SA DE CV | C14: L200 Gls | D14: ACTIVO | E14: 2025-08-15 | F14: 2027-08-15 | G14: 24 | H14: 649987.07 | I14: 0.1 | J14: =ROUND(H14*I14, 2) | K14: =ROUND(H14-J14, 2) | L14: 0 | M14: =ROUND(H14*L14, 2) | N14: 27206.74 | O14: 0.3 | P14: =ROUND(H14*O14, 2) | Q14: 0.02620493 | R14: =IFERROR(RATE(G14, -N14, K14, -P14), Q14) | S14: =Q14*12 | T14: =((1+Q14)^12)-1 | U14: =IF(Q14>0, ROUND(P14/((1+Q14)^G14), 2), P14) | V14: =ROUND((N14*G14)-K14+P14, 2) | W14: =ROUND(P14-U14, 2) | X14: =ROUND(V14+W14, 2) | Y14: =ROUND((N14*G14+P14+M14)-K14, 2) | Z14: =IF(K14>0, Y14/K14, 0)
A15: 0524-0011 | B15: Lider En Derecho De Via y Construcción SA DE CV | C15: Wrangler Unlimited Sahara | D15: ACTIVO | E15: 2025-12-31 | F15: 2029-12-31 | G15: 48 | H15: 1058554.3 | I15: 0.2 | J15: =ROUND(H15*I15, 2) | K15: =ROUND(H15-J15, 2) | L15: 0.02 | M15: =ROUND(H15*L15, 2) | N15: 30510.75 | O15: 0.1 | P15: =ROUND(H15*O15, 2) | Q15: 0.0268869 | R15: =IFERROR(RATE(G15, -N15, K15, -P15), Q15) | S15: =Q15*12 | T15: =((1+Q15)^12)-1 | U15: =IF(Q15>0, ROUND(P15/((1+Q15)^G15), 2), P15) | V15: =ROUND((N15*G15)-K15+P15, 2) | W15: =ROUND(P15-U15, 2) | X15: =ROUND(V15+W15, 2) | Y15: =ROUND((N15*G15+P15+M15)-K15, 2) | Z15: =IF(K15>0, Y15/K15, 0)
A16: 0524-0012 | B16: Lider En Derecho De Via y Construcción SA DE CV | C16: L200 GLS | D16: ACTIVO | E16: 2026-03-17 | F16: 2030-03-17 | G16: 48 | H16: 624154.31 | I16: 0.1 | J16: =ROUND(H16*I16, 2) | K16: =ROUND(H16-J16, 2) | L16: 0.02 | M16: =ROUND(H16*L16, 2) | N16: 20333.22 | O16: 0.1 | P16: =ROUND(H16*O16, 2) | Q16: 0.0269179 | R16: =IFERROR(RATE(G16, -N16, K16, -P16), Q16) | S16: =Q16*12 | T16: =((1+Q16)^12)-1 | U16: =IF(Q16>0, ROUND(P16/((1+Q16)^G16), 2), P16) | V16: =ROUND((N16*G16)-K16+P16, 2) | W16: =ROUND(P16-U16, 2) | X16: =ROUND(V16+W16, 2) | Y16: =ROUND((N16*G16+P16+M16)-K16, 2) | Z16: =IF(K16>0, Y16/K16, 0)
... A281: 0786-0001 | B281: Consejería Jurídico Empresarial, S.C. | C281: Mitsubishi Outlander Sport Limited 2027 | D281: ACTIVO | E281: 2026-09-28 | F281: 2028-09-28 | G281: 24 | H281: 475727.59 | I281: 0.3 | J281: =ROUND(H281*I281, 2) | K281: =ROUND(H281-J281, 2) | L281: 0.02 | M281: =ROUND(H281*L281, 2) | N281: 15957.97 | O281: 0.2 | P281: =ROUND(H281*O281, 2) | Q281: 0.02615301 | R281: =IFERROR(RATE(G281, -N281, K281, -P281), Q281) | S281: =Q281*12 | T281: =((1+Q281)^12)-1 | U281: =IF(Q281>0, ROUND(P281/((1+Q281)^G281), 2), P281) | V281: =ROUND((N281*G281)-K281+P281, 2) | W281: =ROUND(P281-U281, 2) | X281: =ROUND(V281+W281, 2) | Y281: =ROUND((N281*G281+P281+M281)-K281, 2) | Z281: =IF(K281>0, Y281/K281, 0)
A282: TOTAL CARTERA | B282: 277 Contratos Registrados | H282: =SUM(H5:H281) | I282: =AVERAGE(I5:I281) | J282: =SUM(J5:J281) | K282: =SUM(K5:K281) | L282: =AVERAGE(L5:L281) | M282: =SUM(M5:M281) | N282: =SUM(N5:N281) | O282: =AVERAGE(O5:O281) | P282: =SUM(P5:P281) | Q282: =AVERAGE(Q5:Q281) | R282: =AVERAGE(R5:R281) | S282: =AVERAGE(S5:S281) | T282: =AVERAGE(T5:T281) | U282: =SUM(U5:U281) | V282: =SUM(V5:V281) | W282: =SUM(W5:W281) | X282: =SUM(X5:X281) | Y282: =SUM(Y5:Y281) | Z282: =IF(K282>0, Y282/K282, 0)

Sheet Calculo_Tasa_Implicita
A1: O-LEASING · UNA APP DE ORANGE CREW · Cálculo de Tasa Implícita y Comprobación de Flujos (NIF C-15 / IFRS 16)
A2: Determinación de tasa mensual mediante RATE(nper, -pmt, pv, -fv), unidad adquirida y comprobación PV con diferencia cero · Auditoría Financiera NIF C-15 / IFRS 16 · Desarrollado por Orange Crew
A4: ID_Contrato | B4: Cliente | C4: Vehiculo | D4: Estatus | E4: Plazo_Meses | F4: Valor_Sin_IVA | G4: Anticipo_Pct | H4: Anticipo_Monto | I4: Inversion_Neta | J4: Renta_Sin_IVA | K4: Residual_Pct | L4: Residual_Pactado | M4: Tasa_Mensual_Registrada | N4: Tasa_Calculada_RATE | O4: Comprobacion_PV | P4: Diferencia_Cuadre | Q4: Tasa_Nominal_Anual | R4: TIR_Anual_Efectiva | S4: Diferencia_vs_Registrada | T4: Estatus_Verificacion
A5: 0326-0003 | B5: Alberto Vázquez Solorio | C5: Volkswagen Tiguan R-Line 2026 | D5: ACTIVO | E5: 48 | F5: 645181.9 | G5: 0.3705 | H5: =ROUND(F5*G5, 2) | I5: =ROUND(F5-H5, 2) | J5: 8393.91 | K5: 0.28 | L5: =ROUND(F5*K5, 2) | M5: 0.01206146 | N5: =IFERROR(RATE(E5, -J5, I5, -L5), M5) | O5: =IF(N5>0, ROUND(PV(N5, E5, -J5, -L5), 2), I5) | P5: =ROUND(O5-I5, 2) | Q5: =N5*12 | R5: =((1+N5)^12)-1 | S5: =N5-M5 | T5: =IF(ABS(P5)<0.01, "EXACTO", "REVISAR")
A6: 0472-0003 | B6: Miguel Zazueta Beltrán | C6: Jeep Grand Cherokee | D6: ACTIVO | E6: 36 | F6: 1217433.6 | G6: 0.3 | H6: =ROUND(F6*G6, 2) | I6: =ROUND(F6-H6, 2) | J6: 35031.5 | K6: 0.1 | L6: =ROUND(F6*K6, 2) | M6: 0.02661776 | N6: =IFERROR(RATE(E6, -J6, I6, -L6), M6) | O6: =IF(N6>0, ROUND(PV(N6, E6, -J6, -L6), 2), I6) | P6: =ROUND(O6-I6, 2) | Q6: =N6*12 | R6: =((1+N6)^12)-1 | S6: =N6-M6 | T6: =IF(ABS(P6)<0.01, "EXACTO", "REVISAR")
A7: 0504-0004 | B7: Oscar Ivan Lozano Terriquez | C7: 700 BIGHORN "S" CREW CAB MT | D7: ACTIVO | E7: 12 | F7: 352500 | G7: 0.35 | H7: =ROUND(F7*G7, 2) | I7: =ROUND(F7-H7, 2) | J7: 19654.64 | K7: 0.1 | L7: =ROUND(F7*K7, 2) | M7: 0.02415117 | N7: =IFERROR(RATE(E7, -J7, I7, -L7), M7) | O7: =IF(N7>0, ROUND(PV(N7, E7, -J7, -L7), 2), I7) | P7: =ROUND(O7-I7, 2) | Q7: =N7*12 | R7: =((1+N7)^12)-1 | S7: =N7-M7 | T7: =IF(ABS(P7)<0.01, "EXACTO", "REVISAR")
A8: 0506-0006 | B8: Electronic Accounting Sa de Cv | C8: X5 | D8: ACTIVO | E8: 36 | F8: 1622338.8 | G8: 0.1759 | H8: =ROUND(F8*G8, 2) | I8: =ROUND(F8-H8, 2) | J8: 35607.45 | K8: 0.35 | L8: =ROUND(F8*K8, 2) | M8: 0.01430392 | N8: =IFERROR(RATE(E8, -J8, I8, -L8), M8) | O8: =IF(N8>0, ROUND(PV(N8, E8, -J8, -L8), 2), I8) | P8: =ROUND(O8-I8, 2) | Q8: =N8*12 | R8: =((1+N8)^12)-1 | S8: =N8-M8 | T8: =IF(ABS(P8)<0.01, "EXACTO", "REVISAR")
A9: 0506-0007 | B9: Electronic Acounting | C9: L200 Glx Diesel | D9: ACTIVO | E9: 36 | F9: 536762.93 | G9: 0 | H9: =ROUND(F9*G9, 2) | I9: =ROUND(F9-H9, 2) | J9: 16715.69 | K9: 0.35 | L9: =ROUND(F9*K9, 2) | M9: 0.01820217 | N9: =IFERROR(RATE(E9, -J9, I9, -L9), M9) | O9: =IF(N9>0, ROUND(PV(N9, E9, -J9, -L9), 2), I9) | P9: =ROUND(O9-I9, 2) | Q9: =N9*12 | R9: =((1+N9)^12)-1 | S9: =N9-M9 | T9: =IF(ABS(P9)<0.01, "EXACTO", "REVISAR")
A10: 0519-0005 | B10: Tequilas el Mexicano S.A. de C.V. | C10: Attitude Sport | D10: ACTIVO | E10: 48 | F10: 352500 | G10: 0.1 | H10: =ROUND(F10*G10, 2) | I10: =ROUND(F10-H10, 2) | J10: 11483.47 | K10: 0.1 | L10: =ROUND(F10*K10, 2) | M10: 0.02691789 | N10: =IFERROR(RATE(E10, -J10, I10, -L10), M10) | O10: =IF(N10>0, ROUND(PV(N10, E10, -J10, -L10), 2), I10) | P10: =ROUND(O10-I10, 2) | Q10: =N10*12 | R10: =((1+N10)^12)-1 | S10: =N10-M10 | T10: =IF(ABS(P10)<0.01, "EXACTO", "REVISAR")
A11: 0520-0003 | B11: Tractomotriz Diesel Leal, S.A. de C.V. | C11: Montero Sport | D11: ACTIVO | E11: 36 | F11: 621465.52 | G11: 0.4 | H11: =ROUND(F11*G11, 2) | I11: =ROUND(F11-H11, 2) | J11: 15182.88 | K11: 0.1 | L11: =ROUND(F11*K11, 2) | M11: 0.02663641 | N11: =IFERROR(RATE(E11, -J11, I11, -L11), M11) | O11: =IF(N11>0, ROUND(PV(N11, E11, -J11, -L11), 2), I11) | P11: =ROUND(O11-I11, 2) | Q11: =N11*12 | R11: =((1+N11)^12)-1 | S11: =N11-M11 | T11: =IF(ABS(P11)<0.01, "EXACTO", "REVISAR")
A12: 0520-0004 | B12: Tractomotriz Diesel Leal, S.A. de C.V. | C12: Partner Maxi Pack | D12: ACTIVO | E12: 36 | F12: 400363.79 | G12: 0.4 | H12: =ROUND(F12*G12, 2) | I12: =ROUND(F12-H12, 2) | J12: 9781.2 | K12: 0.1 | L12: =ROUND(F12*K12, 2) | M12: 0.02663643 | N12: =IFERROR(RATE(E12, -J12, I12, -L12), M12) | O12: =IF(N12>0, ROUND(PV(N12, E12, -J12, -L12), 2), I12) | P12: =ROUND(O12-I12, 2) | Q12: =N12*12 | R12: =((1+N12)^12)-1 | S12: =N12-M12 | T12: =IF(ABS(P12)<0.01, "EXACTO", "REVISAR")
A13: 0521-0002 | B13: Carlos Hiram leal Leal | C13: Xpander | D13: ACTIVO | E13: 36 | F13: 365988.79 | G13: 0.1 | H13: =ROUND(F13*G13, 2) | I13: =ROUND(F13-H13, 2) | J13: 13100.96 | K13: 0.2 | L13: =ROUND(F13*K13, 2) | M13: 0.02662861 | N13: =IFERROR(RATE(E13, -J13, I13, -L13), M13) | O13: =IF(N13>0, ROUND(PV(N13, E13, -J13, -L13), 2), I13) | P13: =ROUND(O13-I13, 2) | Q13: =N13*12 | R13: =((1+N13)^12)-1 | S13: =N13-M13 | T13: =IF(ABS(P13)<0.01, "EXACTO", "REVISAR")
A14: 0524-0007 | B14: Lider En Derecho De Via y Construcción SA DE CV | C14: L200 Gls | D14: ACTIVO | E14: 24 | F14: 649987.07 | G14: 0.1 | H14: =ROUND(F14*G14, 2) | I14: =ROUND(F14-H14, 2) | J14: 27206.74 | K14: 0.3 | L14: =ROUND(F14*K14, 2) | M14: 0.02620493 | N14: =IFERROR(RATE(E14, -J14, I14, -L14), M14) | O14: =IF(N14>0, ROUND(PV(N14, E14, -J14, -L14), 2), I14) | P14: =ROUND(O14-I14, 2) | Q14: =N14*12 | R14: =((1+N14)^12)-1 | S14: =N14-M14 | T14: =IF(ABS(P14)<0.01, "EXACTO", "REVISAR")
A15: 0524-0011 | B15: Lider En Derecho De Via y Construcción SA DE CV | C15: Wrangler Unlimited Sahara | D15: ACTIVO | E15: 48 | F15: 1058554.3 | G15: 0.2 | H15: =ROUND(F15*G15, 2) | I15: =ROUND(F15-H15, 2) | J15: 30510.75 | K15: 0.1 | L15: =ROUND(F15*K15, 2) | M15: 0.0268869 | N15: =IFERROR(RATE(E15, -J15, I15, -L15), M15) | O15: =IF(N15>0, ROUND(PV(N15, E15, -J15, -L15), 2), I15) | P15: =ROUND(O15-I15, 2) | Q15: =N15*12 | R15: =((1+N15)^12)-1 | S15: =N15-M15 | T15: =IF(ABS(P15)<0.01, "EXACTO", "REVISAR")
A16: 0524-0012 | B16: Lider En Derecho De Via y Construcción SA DE CV | C16: L200 GLS | D16: ACTIVO | E16: 48 | F16: 624154.31 | G16: 0.1 | H16: =ROUND(F16*G16, 2) | I16: =ROUND(F16-H16, 2) | J16: 20333.22 | K16: 0.1 | L16: =ROUND(F16*K16, 2) | M16: 0.0269179 | N16: =IFERROR(RATE(E16, -J16, I16, -L16), M16) | O16: =IF(N16>0, ROUND(PV(N16, E16, -J16, -L16), 2), I16) | P16: =ROUND(O16-I16, 2) | Q16: =N16*12 | R16: =((1+N16)^12)-1 | S16: =N16-M16 | T16: =IF(ABS(P16)<0.01, "EXACTO", "REVISAR")
... A281: 0786-0001 | B281: Consejería Jurídico Empresarial, S.C. | C281: Mitsubishi Outlander Sport Limited 2027 | D281: ACTIVO | E281: 24 | F281: 475727.59 | G281: 0.3 | H281: =ROUND(F281*G281, 2) | I281: =ROUND(F281-H281, 2) | J281: 15957.97 | K281: 0.2 | L281: =ROUND(F281*K281, 2) | M281: 0.02615301 | N281: =IFERROR(RATE(E281, -J281, I281, -L281), M281) | O281: =IF(N281>0, ROUND(PV(N281, E281, -J281, -L281), 2), I281) | P281: =ROUND(O281-I281, 2) | Q281: =N281*12 | R281: =((1+N281)^12)-1 | S281: =N281-M281 | T281: =IF(ABS(P281)<0.01, "EXACTO", "REVISAR")
A282: TOTAL CARTERA | B282: 277 Contratos | F282: =SUM(F5:F281) | G282: =AVERAGE(G5:G281) | H282: =SUM(H5:H281) | I282: =SUM(I5:I281) | J282: =SUM(J5:J281) | K282: =AVERAGE(K5:K281) | L282: =SUM(L5:L281) | M282: =AVERAGE(M5:M281) | N282: =AVERAGE(N5:N281) | O282: =SUM(O5:O281) | P282: =SUM(P5:P281) | Q282: =AVERAGE(Q5:Q281) | R282: =AVERAGE(R5:R281) | S282: =AVERAGE(S5:S281) | T282: AUDITADO

Sheet Modelo_Amortizacion_Tipo
A1: O-LEASING · UNA APP DE ORANGE CREW · Modelo de Amortización Dinámica con Fórmulas Nativas
A2: Seleccione cualquier contrato en la lista desplegable; la tabla actualiza todos los datos y se corta al mes exacto de terminación · Auditoría Financiera NIF C-15 / IFRS 16 · Desarrollado por Orange Crew
B4: SELECCIONAR CONTRATO: | C4: 0326-0003 | D4: <-- Seleccione de la lista desplegable o escriba el ID del contrato para actualizar toda la tabla
B5: Cliente: | C5: =IFERROR(VLOOKUP($C$4, 'Resumen_Cartera'!$A$5:$Z$281, 2, FALSE), "") | F5: Unidad / Vehículo: | G5: =IFERROR(VLOOKUP($C$4, 'Resumen_Cartera'!$A$5:$Z$281, 3, FALSE), "") | J5: Estatus: | K5: =IFERROR(VLOOKUP($C$4, 'Resumen_Cartera'!$A$5:$Z$281, 4, FALSE), "")
B6: Fecha Alta: | C6: =IFERROR(VLOOKUP($C$4, 'Resumen_Cartera'!$A$5:$Z$281, 5, FALSE), "") | D6: Fecha Vencimiento: | E6: =IFERROR(VLOOKUP($C$4, 'Resumen_Cartera'!$A$5:$Z$281, 6, FALSE), "") | F6: Plazo (Meses): | G6: =IFERROR(VLOOKUP($C$4, 'Resumen_Cartera'!$A$5:$Z$281, 7, FALSE), 0) | H6: Valor Sin IVA: | I6: =IFERROR(VLOOKUP($C$4, 'Resumen_Cartera'!$A$5:$Z$281, 8, FALSE), 0)
B7: Inversión Neta: | C7: =IFERROR(VLOOKUP($C$4, 'Resumen_Cartera'!$A$5:$Z$281, 11, FALSE), 0) | D7: Renta Mensual: | E7: =IFERROR(VLOOKUP($C$4, 'Resumen_Cartera'!$A$5:$Z$281, 14, FALSE), 0) | F7: Residual Pactado: | G7: =IFERROR(VLOOKUP($C$4, 'Resumen_Cartera'!$A$5:$Z$281, 16, FALSE), 0) | H7: VP Residual Inicial: | I7: =IFERROR(VLOOKUP($C$4, 'Resumen_Cartera'!$A$5:$Z$281, 21, FALSE), 0)
B8: Tasa Mensual: | C8: =IFERROR(VLOOKUP($C$4, 'Resumen_Cartera'!$A$5:$Z$281, 17, FALSE), 0) | D8: Tasa Nominal Anual: | E8: =IFERROR(VLOOKUP($C$4, 'Resumen_Cartera'!$A$5:$Z$281, 19, FALSE), 0) | F8: TIR Anual Efectiva: | G8: =IFERROR(VLOOKUP($C$4, 'Resumen_Cartera'!$A$5:$Z$281, 20, FALSE), 0) | H8: Ingreso Financiero: | I8: =IFERROR(VLOOKUP($C$4, 'Resumen_Cartera'!$A$5:$Z$281, 24, FALSE), 0)
A9: FÓRMULAS VIVAS DE AMORTIZACIÓN Y SALDOS: Interés = Saldo_Inicial * Tasa | Capital = Renta - Interés | Saldo Capital = Saldo_Inicial - Capital | Interés Residual = VP_Residual * Tasa | VP_Residual_Final = VP_Inicial + Interés_Residual | Saldo Intereses = SUM(Futuros) | Saldo Cartera = Saldo_Capital + Saldo_Intereses | Saldo Global = Saldo_Cartera + VP_Residual. La tabla se corta automáticamente al plazo contractual ($G$6 meses).
A10: Mes | B10: Saldo_Inicial_Capital | C10: Tasa_Mensual | D10: Interes_Leasing | E10: Renta_Sin_IVA | F10: Capital_Amortizado | G10: Saldo_Final_Capital | H10: VP_Residual_Inicial | I10: Interes_Residual | J10: VP_Residual_Final | K10: Ingreso_Financiero_Total | L10: Saldo_Intereses_Remanentes | M10: Saldo_Cartera_Total | N10: Saldo_Global_Exigible
A11: =IF(ROW()-10<=$G$6, ROW()-10, "") | B11: =IF($A11="", "", $C$7) | C11: =IF($A11="", "", $C$8) | D11: =IF($A11="", "", ROUND(B11*C11, 2)) | E11: =IF($A11="", "", $E$7) | F11: =IF($A11="", "", E11-D11) | G11: =IF($A11="", "", B11-F11) | H11: =IF($A11="", "", $I$7) | I11: =IF($A11="", "", ROUND(H11*C11, 2)) | J11: =IF($A11="", "", H11+I11) | K11: =IF($A11="", "", D11+I11) | L11: =IF($A11="", "", SUM(D12:$D$82)) | M11: =IF($A11="", "", G11+L11) | N11: =IF($A11="", "", M11+J11)
A12: =IF(ROW()-10<=$G$6, ROW()-10, "") | B12: =IF($A12="", "", G11) | C12: =IF($A12="", "", $C$8) | D12: =IF($A12="", "", ROUND(B12*C12, 2)) | E12: =IF($A12="", "", $E$7) | F12: =IF($A12="", "", E12-D12) | G12: =IF($A12="", "", B12-F12) | H12: =IF($A12="", "", J11) | I12: =IF($A12="", "", ROUND(H12*C12, 2)) | J12: =IF($A12="", "", H12+I12) | K12: =IF($A12="", "", D12+I12) | L12: =IF($A12="", "", SUM(D13:$D$82)) | M12: =IF($A12="", "", G12+L12) | N12: =IF($A12="", "", M12+J12)
A13: =IF(ROW()-10<=$G$6, ROW()-10, "") | B13: =IF($A13="", "", G12) | C13: =IF($A13="", "", $C$8) | D13: =IF($A13="", "", ROUND(B13*C13, 2)) | E13: =IF($A13="", "", $E$7) | F13: =IF($A13="", "", E13-D13) | G13: =IF($A13="", "", B13-F13) | H13: =IF($A13="", "", J12) | I13: =IF($A13="", "", ROUND(H13*C13, 2)) | J13: =IF($A13="", "", H13+I13) | K13: =IF($A13="", "", D13+I13) | L13: =IF($A13="", "", SUM(D14:$D$82)) | M13: =IF($A13="", "", G13+L13) | N13: =IF($A13="", "", M13+J13)
A14: =IF(ROW()-10<=$G$6, ROW()-10, "") | B14: =IF($A14="", "", G13) | C14: =IF($A14="", "", $C$8) | D14: =IF($A14="", "", ROUND(B14*C14, 2)) | E14: =IF($A14="", "", $E$7) | F14: =IF($A14="", "", E14-D14) | G14: =IF($A14="", "", B14-F14) | H14: =IF($A14="", "", J13) | I14: =IF($A14="", "", ROUND(H14*C14, 2)) | J14: =IF($A14="", "", H14+I14) | K14: =IF($A14="", "", D14+I14) | L14: =IF($A14="", "", SUM(D15:$D$82)) | M14: =IF($A14="", "", G14+L14) | N14: =IF($A14="", "", M14+J14)
A15: =IF(ROW()-10<=$G$6, ROW()-10, "") | B15: =IF($A15="", "", G14) | C15: =IF($A15="", "", $C$8) | D15: =IF($A15="", "", ROUND(B15*C15, 2)) | E15: =IF($A15="", "", $E$7) | F15: =IF($A15="", "", E15-D15) | G15: =IF($A15="", "", B15-F15) | H15: =IF($A15="", "", J14) | I15: =IF($A15="", "", ROUND(H15*C15, 2)) | J15: =IF($A15="", "", H15+I15) | K15: =IF($A15="", "", D15+I15) | L15: =IF($A15="", "", SUM(D16:$D$82)) | M15: =IF($A15="", "", G15+L15) | N15: =IF($A15="", "", M15+J15)
A16: =IF(ROW()-10<=$G$6, ROW()-10, "") | B16: =IF($A16="", "", G15) | C16: =IF($A16="", "", $C$8) | D16: =IF($A16="", "", ROUND(B16*C16, 2)) | E16: =IF($A16="", "", $E$7) | F16: =IF($A16="", "", E16-D16) | G16: =IF($A16="", "", B16-F16) | H16: =IF($A16="", "", J15) | I16: =IF($A16="", "", ROUND(H16*C16, 2)) | J16: =IF($A16="", "", H16+I16) | K16: =IF($A16="", "", D16+I16) | L16: =IF($A16="", "", SUM(D17:$D$82)) | M16: =IF($A16="", "", G16+L16) | N16: =IF($A16="", "", M16+J16)
A17: =IF(ROW()-10<=$G$6, ROW()-10, "") | B17: =IF($A17="", "", G16) | C17: =IF($A17="", "", $C$8) | D17: =IF($A17="", "", ROUND(B17*C17, 2)) | E17: =IF($A17="", "", $E$7) | F17: =IF($A17="", "", E17-D17) | G17: =IF($A17="", "", B17-F17) | H17: =IF($A17="", "", J16) | I17: =IF($A17="", "", ROUND(H17*C17, 2)) | J17: =IF($A17="", "", H17+I17) | K17: =IF($A17="", "", D17+I17) | L17: =IF($A17="", "", SUM(D18:$D$82)) | M17: =IF($A17="", "", G17+L17) | N17: =IF($A17="", "", M17+J17)
A18: =IF(ROW()-10<=$G$6, ROW()-10, "") | B18: =IF($A18="", "", G17) | C18: =IF($A18="", "", $C$8) | D18: =IF($A18="", "", ROUND(B18*C18, 2)) | E18: =IF($A18="", "", $E$7) | F18: =IF($A18="", "", E18-D18) | G18: =IF($A18="", "", B18-F18) | H18: =IF($A18="", "", J17) | I18: =IF($A18="", "", ROUND(H18*C18, 2)) | J18: =IF($A18="", "", H18+I18) | K18: =IF($A18="", "", D18+I18) | L18: =IF($A18="", "", SUM(D19:$D$82)) | M18: =IF($A18="", "", G18+L18) | N18: =IF($A18="", "", M18+J18)
A19: =IF(ROW()-10<=$G$6, ROW()-10, "") | B19: =IF($A19="", "", G18) | C19: =IF($A19="", "", $C$8) | D19: =IF($A19="", "", ROUND(B19*C19, 2)) | E19: =IF($A19="", "", $E$7) | F19: =IF($A19="", "", E19-D19) | G19: =IF($A19="", "", B19-F19) | H19: =IF($A19="", "", J18) | I19: =IF($A19="", "", ROUND(H19*C19, 2)) | J19: =IF($A19="", "", H19+I19) | K19: =IF($A19="", "", D19+I19) | L19: =IF($A19="", "", SUM(D20:$D$82)) | M19: =IF($A19="", "", G19+L19) | N19: =IF($A19="", "", M19+J19)
A20: =IF(ROW()-10<=$G$6, ROW()-10, "") | B20: =IF($A20="", "", G19) | C20: =IF($A20="", "", $C$8) | D20: =IF($A20="", "", ROUND(B20*C20, 2)) | E20: =IF($A20="", "", $E$7) | F20: =IF($A20="", "", E20-D20) | G20: =IF($A20="", "", B20-F20) | H20: =IF($A20="", "", J19) | I20: =IF($A20="", "", ROUND(H20*C20, 2)) | J20: =IF($A20="", "", H20+I20) | K20: =IF($A20="", "", D20+I20) | L20: =IF($A20="", "", SUM(D21:$D$82)) | M20: =IF($A20="", "", G20+L20) | N20: =IF($A20="", "", M20+J20)
A21: =IF(ROW()-10<=$G$6, ROW()-10, "") | B21: =IF($A21="", "", G20) | C21: =IF($A21="", "", $C$8) | D21: =IF($A21="", "", ROUND(B21*C21, 2)) | E21: =IF($A21="", "", $E$7) | F21: =IF($A21="", "", E21-D21) | G21: =IF($A21="", "", B21-F21) | H21: =IF($A21="", "", J20) | I21: =IF($A21="", "", ROUND(H21*C21, 2)) | J21: =IF($A21="", "", H21+I21) | K21: =IF($A21="", "", D21+I21) | L21: =IF($A21="", "", SUM(D22:$D$82)) | M21: =IF($A21="", "", G21+L21) | N21: =IF($A21="", "", M21+J21)
A22: =IF(ROW()-10<=$G$6, ROW()-10, "") | B22: =IF($A22="", "", G21) | C22: =IF($A22="", "", $C$8) | D22: =IF($A22="", "", ROUND(B22*C22, 2)) | E22: =IF($A22="", "", $E$7) | F22: =IF($A22="", "", E22-D22) | G22: =IF($A22="", "", B22-F22) | H22: =IF($A22="", "", J21) | I22: =IF($A22="", "", ROUND(H22*C22, 2)) | J22: =IF($A22="", "", H22+I22) | K22: =IF($A22="", "", D22+I22) | L22: =IF($A22="", "", SUM(D23:$D$82)) | M22: =IF($A22="", "", G22+L22) | N22: =IF($A22="", "", M22+J22)
A23: =IF(ROW()-10<=$G$6, ROW()-10, "") | B23: =IF($A23="", "", G22) | C23: =IF($A23="", "", $C$8) | D23: =IF($A23="", "", ROUND(B23*C23, 2)) | E23: =IF($A23="", "", $E$7) | F23: =IF($A23="", "", E23-D23) | G23: =IF($A23="", "", B23-F23) | H23: =IF($A23="", "", J22) | I23: =IF($A23="", "", ROUND(H23*C23, 2)) | J23: =IF($A23="", "", H23+I23) | K23: =IF($A23="", "", D23+I23) | L23: =IF($A23="", "", SUM(D24:$D$82)) | M23: =IF($A23="", "", G23+L23) | N23: =IF($A23="", "", M23+J23)
... A81: =IF(ROW()-10<=$G$6, ROW()-10, "") | B81: =IF($A81="", "", G80) | C81: =IF($A81="", "", $C$8) | D81: =IF($A81="", "", ROUND(B81*C81, 2)) | E81: =IF($A81="", "", $E$7) | F81: =IF($A81="", "", E81-D81) | G81: =IF($A81="", "", B81-F81) | H81: =IF($A81="", "", J80) | I81: =IF($A81="", "", ROUND(H81*C81, 2)) | J81: =IF($A81="", "", H81+I81) | K81: =IF($A81="", "", D81+I81) | L81: =IF($A81="", "", SUM(D82:$D$82)) | M81: =IF($A81="", "", G81+L81) | N81: =IF($A81="", "", M81+J81)
A82: =IF(ROW()-10<=$G$6, ROW()-10, "") | B82: =IF($A82="", "", G81) | C82: =IF($A82="", "", $C$8) | D82: =IF($A82="", "", ROUND(B82*C82, 2)) | E82: =IF($A82="", "", $E$7) | F82: =IF($A82="", "", E82-D82) | G82: =IF($A82="", "", B82-F82) | H82: =IF($A82="", "", J81) | I82: =IF($A82="", "", ROUND(H82*C82, 2)) | J82: =IF($A82="", "", H82+I82) | K82: =IF($A82="", "", D82+I82) | L82: =IF($A82="", "", 0) | M82: =IF($A82="", "", G82+L82) | N82: =IF($A82="", "", M82+J82)
A83: TOTALES DEL CONTRATO | D83: =SUM(D11:D82) | E83: =SUM(E11:E82) | F83: =SUM(F11:F82) | I83: =SUM(I11:I82) | K83: =SUM(K11:K82)

Sheet Intereses_Leasing_Mensual
A1: O-LEASING · UNA APP DE ORANGE CREW · Intereses de Leasing Devengados Mes a Mes
A2: Devengo mensual de intereses de leasing con fórmulas vivas de saldo de capital por tasa · Auditoría Financiera NIF C-15 / IFRS 16 · Desarrollado por Orange Crew
A4: ID_Contrato | B4: Cliente | C4: Vehiculo | D4: Estatus | E4: Fecha_Alta | F4: Fecha_Vencimiento | G4: Plazo | H4: Inversion_Neta | I4: 2026-01 | J4: 2026-02 | K4: 2026-03 | L4: 2026-04 | M4: 2026-05 | N4: 2026-06 | O4: 2026-07 | P4: 2026-08 | Q4: 2026-09 | R4: 2026-10 | S4: 2026-11 | T4: 2026-12 | U4: Total_Devengado_Leasing
A5: 0326-0003 | B5: Alberto Vázquez Solorio | C5: Volkswagen Tiguan R-Line 2026 | D5: ACTIVO | E5: 2026-09-16 | F5: 2030-09-16 | G5: 48 | H5: 406120.26 | Q5: =ROUND('Resumen_Cartera'!$K5 * 'Resumen_Cartera'!$Q5, 2) | R5: =IF(Saldos_Capital_Mensual!Q5>0, ROUND(Saldos_Capital_Mensual!Q5 * 'Resumen_Cartera'!$Q5, 2), "") | S5: =IF(Saldos_Capital_Mensual!R5>0, ROUND(Saldos_Capital_Mensual!R5 * 'Resumen_Cartera'!$Q5, 2), "") | T5: =IF(Saldos_Capital_Mensual!S5>0, ROUND(Saldos_Capital_Mensual!S5 * 'Resumen_Cartera'!$Q5, 2), "") | U5: =SUM(I5:T5)
A6: 0472-0003 | B6: Miguel Zazueta Beltrán | C6: Jeep Grand Cherokee | D6: ACTIVO | E6: 2026-02-03 | F6: 2029-02-03 | G6: 36 | H6: 852203.53 | J6: =ROUND('Resumen_Cartera'!$K6 * 'Resumen_Cartera'!$Q6, 2) | K6: =IF(Saldos_Capital_Mensual!J6>0, ROUND(Saldos_Capital_Mensual!J6 * 'Resumen_Cartera'!$Q6, 2), "") | L6: =IF(Saldos_Capital_Mensual!K6>0, ROUND(Saldos_Capital_Mensual!K6 * 'Resumen_Cartera'!$Q6, 2), "") | M6: =IF(Saldos_Capital_Mensual!L6>0, ROUND(Saldos_Capital_Mensual!L6 * 'Resumen_Cartera'!$Q6, 2), "") | N6: =IF(Saldos_Capital_Mensual!M6>0, ROUND(Saldos_Capital_Mensual!M6 * 'Resumen_Cartera'!$Q6, 2), "") | O6: =IF(Saldos_Capital_Mensual!N6>0, ROUND(Saldos_Capital_Mensual!N6 * 'Resumen_Cartera'!$Q6, 2), "") | P6: =IF(Saldos_Capital_Mensual!O6>0, ROUND(Saldos_Capital_Mensual!O6 * 'Resumen_Cartera'!$Q6, 2), "") | Q6: =IF(Saldos_Capital_Mensual!P6>0, ROUND(Saldos_Capital_Mensual!P6 * 'Resumen_Cartera'!$Q6, 2), "") | R6: =IF(Saldos_Capital_Mensual!Q6>0, ROUND(Saldos_Capital_Mensual!Q6 * 'Resumen_Cartera'!$Q6, 2), "") | ... T6: =IF(Saldos_Capital_Mensual!S6>0, ROUND(Saldos_Capital_Mensual!S6 * 'Resumen_Cartera'!$Q6, 2), "") | U6: =SUM(I6:T6)
A7: 0504-0004 | B7: Oscar Ivan Lozano Terriquez | C7: 700 BIGHORN "S" CREW CAB MT | D7: ACTIVO | E7: 2026-01-05 | F7: 2027-01-05 | G7: 12 | H7: 229125 | I7: =ROUND('Resumen_Cartera'!$K7 * 'Resumen_Cartera'!$Q7, 2) | J7: =IF(Saldos_Capital_Mensual!I7>0, ROUND(Saldos_Capital_Mensual!I7 * 'Resumen_Cartera'!$Q7, 2), "") | K7: =IF(Saldos_Capital_Mensual!J7>0, ROUND(Saldos_Capital_Mensual!J7 * 'Resumen_Cartera'!$Q7, 2), "") | L7: =IF(Saldos_Capital_Mensual!K7>0, ROUND(Saldos_Capital_Mensual!K7 * 'Resumen_Cartera'!$Q7, 2), "") | M7: =IF(Saldos_Capital_Mensual!L7>0, ROUND(Saldos_Capital_Mensual!L7 * 'Resumen_Cartera'!$Q7, 2), "") | N7: =IF(Saldos_Capital_Mensual!M7>0, ROUND(Saldos_Capital_Mensual!M7 * 'Resumen_Cartera'!$Q7, 2), "") | O7: =IF(Saldos_Capital_Mensual!N7>0, ROUND(Saldos_Capital_Mensual!N7 * 'Resumen_Cartera'!$Q7, 2), "") | P7: =IF(Saldos_Capital_Mensual!O7>0, ROUND(Saldos_Capital_Mensual!O7 * 'Resumen_Cartera'!$Q7, 2), "") | Q7: =IF(Saldos_Capital_Mensual!P7>0, ROUND(Saldos_Capital_Mensual!P7 * 'Resumen_Cartera'!$Q7, 2), "") | ... T7: =IF(Saldos_Capital_Mensual!S7>0, ROUND(Saldos_Capital_Mensual!S7 * 'Resumen_Cartera'!$Q7, 2), "") | U7: =SUM(I7:T7)
A8: 0506-0006 | B8: Electronic Accounting Sa de Cv | C8: X5 | D8: ACTIVO | E8: 2024-01-10 | F8: 2027-01-10 | G8: 36 | H8: 1336969.4 | I8: =ROUND(868919.79 * 'Resumen_Cartera'!$Q8, 2) | J8: =IF(Saldos_Capital_Mensual!I8>0, ROUND(Saldos_Capital_Mensual!I8 * 'Resumen_Cartera'!$Q8, 2), "") | K8: =IF(Saldos_Capital_Mensual!J8>0, ROUND(Saldos_Capital_Mensual!J8 * 'Resumen_Cartera'!$Q8, 2), "") | L8: =IF(Saldos_Capital_Mensual!K8>0, ROUND(Saldos_Capital_Mensual!K8 * 'Resumen_Cartera'!$Q8, 2), "") | M8: =IF(Saldos_Capital_Mensual!L8>0, ROUND(Saldos_Capital_Mensual!L8 * 'Resumen_Cartera'!$Q8, 2), "") | N8: =IF(Saldos_Capital_Mensual!M8>0, ROUND(Saldos_Capital_Mensual!M8 * 'Resumen_Cartera'!$Q8, 2), "") | O8: =IF(Saldos_Capital_Mensual!N8>0, ROUND(Saldos_Capital_Mensual!N8 * 'Resumen_Cartera'!$Q8, 2), "") | P8: =IF(Saldos_Capital_Mensual!O8>0, ROUND(Saldos_Capital_Mensual!O8 * 'Resumen_Cartera'!$Q8, 2), "") | Q8: =IF(Saldos_Capital_Mensual!P8>0, ROUND(Saldos_Capital_Mensual!P8 * 'Resumen_Cartera'!$Q8, 2), "") | ... T8: =IF(Saldos_Capital_Mensual!S8>0, ROUND(Saldos_Capital_Mensual!S8 * 'Resumen_Cartera'!$Q8, 2), "") | U8: =SUM(I8:T8)
A9: 0506-0007 | B9: Electronic Acounting | C9: L200 Glx Diesel | D9: ACTIVO | E9: 2024-09-05 | F9: 2027-09-05 | G9: 36 | H9: 536762.93 | I9: =ROUND(409096.92 * 'Resumen_Cartera'!$Q9, 2) | J9: =IF(Saldos_Capital_Mensual!I9>0, ROUND(Saldos_Capital_Mensual!I9 * 'Resumen_Cartera'!$Q9, 2), "") | K9: =IF(Saldos_Capital_Mensual!J9>0, ROUND(Saldos_Capital_Mensual!J9 * 'Resumen_Cartera'!$Q9, 2), "") | L9: =IF(Saldos_Capital_Mensual!K9>0, ROUND(Saldos_Capital_Mensual!K9 * 'Resumen_Cartera'!$Q9, 2), "") | M9: =IF(Saldos_Capital_Mensual!L9>0, ROUND(Saldos_Capital_Mensual!L9 * 'Resumen_Cartera'!$Q9, 2), "") | N9: =IF(Saldos_Capital_Mensual!M9>0, ROUND(Saldos_Capital_Mensual!M9 * 'Resumen_Cartera'!$Q9, 2), "") | O9: =IF(Saldos_Capital_Mensual!N9>0, ROUND(Saldos_Capital_Mensual!N9 * 'Resumen_Cartera'!$Q9, 2), "") | P9: =IF(Saldos_Capital_Mensual!O9>0, ROUND(Saldos_Capital_Mensual!O9 * 'Resumen_Cartera'!$Q9, 2), "") | Q9: =IF(Saldos_Capital_Mensual!P9>0, ROUND(Saldos_Capital_Mensual!P9 * 'Resumen_Cartera'!$Q9, 2), "") | ... T9: =IF(Saldos_Capital_Mensual!S9>0, ROUND(Saldos_Capital_Mensual!S9 * 'Resumen_Cartera'!$Q9, 2), "") | U9: =SUM(I9:T9)
A10: 0519-0005 | B10: Tequilas el Mexicano S.A. de C.V. | C10: Attitude Sport | D10: ACTIVO | E10: 2025-07-14 | F10: 2029-07-14 | G10: 48 | H10: 317250 | I10: =ROUND(298355.25 * 'Resumen_Cartera'!$Q10, 2) | J10: =IF(Saldos_Capital_Mensual!I10>0, ROUND(Saldos_Capital_Mensual!I10 * 'Resumen_Cartera'!$Q10, 2), "") | K10: =IF(Saldos_Capital_Mensual!J10>0, ROUND(Saldos_Capital_Mensual!J10 * 'Resumen_Cartera'!$Q10, 2), "") | L10: =IF(Saldos_Capital_Mensual!K10>0, ROUND(Saldos_Capital_Mensual!K10 * 'Resumen_Cartera'!$Q10, 2), "") | M10: =IF(Saldos_Capital_Mensual!L10>0, ROUND(Saldos_Capital_Mensual!L10 * 'Resumen_Cartera'!$Q10, 2), "") | N10: =IF(Saldos_Capital_Mensual!M10>0, ROUND(Saldos_Capital_Mensual!M10 * 'Resumen_Cartera'!$Q10, 2), "") | O10: =IF(Saldos_Capital_Mensual!N10>0, ROUND(Saldos_Capital_Mensual!N10 * 'Resumen_Cartera'!$Q10, 2), "") | P10: =IF(Saldos_Capital_Mensual!O10>0, ROUND(Saldos_Capital_Mensual!O10 * 'Resumen_Cartera'!$Q10, 2), "") | Q10: =IF(Saldos_Capital_Mensual!P10>0, ROUND(Saldos_Capital_Mensual!P10 * 'Resumen_Cartera'!$Q10, 2), "") | ... T10: =IF(Saldos_Capital_Mensual!S10>0, ROUND(Saldos_Capital_Mensual!S10 * 'Resumen_Cartera'!$Q10, 2), "") | U10: =SUM(I10:T10)
A11: 0520-0003 | B11: Tractomotriz Diesel Leal, S.A. de C.V. | C11: Montero Sport | D11: ACTIVO | E11: 2025-11-28 | F11: 2028-11-28 | G11: 36 | H11: 372879.31 | I11: =ROUND(362238.02 * 'Resumen_Cartera'!$Q11, 2) | J11: =IF(Saldos_Capital_Mensual!I11>0, ROUND(Saldos_Capital_Mensual!I11 * 'Resumen_Cartera'!$Q11, 2), "") | K11: =IF(Saldos_Capital_Mensual!J11>0, ROUND(Saldos_Capital_Mensual!J11 * 'Resumen_Cartera'!$Q11, 2), "") | L11: =IF(Saldos_Capital_Mensual!K11>0, ROUND(Saldos_Capital_Mensual!K11 * 'Resumen_Cartera'!$Q11, 2), "") | M11: =IF(Saldos_Capital_Mensual!L11>0, ROUND(Saldos_Capital_Mensual!L11 * 'Resumen_Cartera'!$Q11, 2), "") | N11: =IF(Saldos_Capital_Mensual!M11>0, ROUND(Saldos_Capital_Mensual!M11 * 'Resumen_Cartera'!$Q11, 2), "") | O11: =IF(Saldos_Capital_Mensual!N11>0, ROUND(Saldos_Capital_Mensual!N11 * 'Resumen_Cartera'!$Q11, 2), "") | P11: =IF(Saldos_Capital_Mensual!O11>0, ROUND(Saldos_Capital_Mensual!O11 * 'Resumen_Cartera'!$Q11, 2), "") | Q11: =IF(Saldos_Capital_Mensual!P11>0, ROUND(Saldos_Capital_Mensual!P11 * 'Resumen_Cartera'!$Q11, 2), "") | ... T11: =IF(Saldos_Capital_Mensual!S11>0, ROUND(Saldos_Capital_Mensual!S11 * 'Resumen_Cartera'!$Q11, 2), "") | U11: =SUM(I11:T11)
A12: 0520-0004 | B12: Tractomotriz Diesel Leal, S.A. de C.V. | C12: Partner Maxi Pack | D12: ACTIVO | E12: 2025-12-04 | F12: 2028-12-04 | G12: 36 | H12: 240218.27 | I12: =ROUND(236835.63 * 'Resumen_Cartera'!$Q12, 2) | J12: =IF(Saldos_Capital_Mensual!I12>0, ROUND(Saldos_Capital_Mensual!I12 * 'Resumen_Cartera'!$Q12, 2), "") | K12: =IF(Saldos_Capital_Mensual!J12>0, ROUND(Saldos_Capital_Mensual!J12 * 'Resumen_Cartera'!$Q12, 2), "") | L12: =IF(Saldos_Capital_Mensual!K12>0, ROUND(Saldos_Capital_Mensual!K12 * 'Resumen_Cartera'!$Q12, 2), "") | M12: =IF(Saldos_Capital_Mensual!L12>0, ROUND(Saldos_Capital_Mensual!L12 * 'Resumen_Cartera'!$Q12, 2), "") | N12: =IF(Saldos_Capital_Mensual!M12>0, ROUND(Saldos_Capital_Mensual!M12 * 'Resumen_Cartera'!$Q12, 2), "") | O12: =IF(Saldos_Capital_Mensual!N12>0, ROUND(Saldos_Capital_Mensual!N12 * 'Resumen_Cartera'!$Q12, 2), "") | P12: =IF(Saldos_Capital_Mensual!O12>0, ROUND(Saldos_Capital_Mensual!O12 * 'Resumen_Cartera'!$Q12, 2), "") | Q12: =IF(Saldos_Capital_Mensual!P12>0, ROUND(Saldos_Capital_Mensual!P12 * 'Resumen_Cartera'!$Q12, 2), "") | ... T12: =IF(Saldos_Capital_Mensual!S12>0, ROUND(Saldos_Capital_Mensual!S12 * 'Resumen_Cartera'!$Q12, 2), "") | U12: =SUM(I12:T12)
A13: 0521-0002 | B13: Carlos Hiram leal Leal | C13: Xpander | D13: ACTIVO | E13: 2025-09-08 | F13: 2028-09-08 | G13: 36 | H13: 329389.91 | I13: =ROUND(311366.72 * 'Resumen_Cartera'!$Q13, 2) | J13: =IF(Saldos_Capital_Mensual!I13>0, ROUND(Saldos_Capital_Mensual!I13 * 'Resumen_Cartera'!$Q13, 2), "") | K13: =IF(Saldos_Capital_Mensual!J13>0, ROUND(Saldos_Capital_Mensual!J13 * 'Resumen_Cartera'!$Q13, 2), "") | L13: =IF(Saldos_Capital_Mensual!K13>0, ROUND(Saldos_Capital_Mensual!K13 * 'Resumen_Cartera'!$Q13, 2), "") | M13: =IF(Saldos_Capital_Mensual!L13>0, ROUND(Saldos_Capital_Mensual!L13 * 'Resumen_Cartera'!$Q13, 2), "") | N13: =IF(Saldos_Capital_Mensual!M13>0, ROUND(Saldos_Capital_Mensual!M13 * 'Resumen_Cartera'!$Q13, 2), "") | O13: =IF(Saldos_Capital_Mensual!N13>0, ROUND(Saldos_Capital_Mensual!N13 * 'Resumen_Cartera'!$Q13, 2), "") | P13: =IF(Saldos_Capital_Mensual!O13>0, ROUND(Saldos_Capital_Mensual!O13 * 'Resumen_Cartera'!$Q13, 2), "") | Q13: =IF(Saldos_Capital_Mensual!P13>0, ROUND(Saldos_Capital_Mensual!P13 * 'Resumen_Cartera'!$Q13, 2), "") | ... T13: =IF(Saldos_Capital_Mensual!S13>0, ROUND(Saldos_Capital_Mensual!S13 * 'Resumen_Cartera'!$Q13, 2), "") | U13: =SUM(I13:T13)
A14: 0524-0007 | B14: Lider En Derecho De Via y Construcción SA DE CV | C14: L200 Gls | D14: ACTIVO | E14: 2025-08-15 | F14: 2027-08-15 | G14: 24 | H14: 584988.36 | I14: =ROUND(522407.52 * 'Resumen_Cartera'!$Q14, 2) | J14: =IF(Saldos_Capital_Mensual!I14>0, ROUND(Saldos_Capital_Mensual!I14 * 'Resumen_Cartera'!$Q14, 2), "") | K14: =IF(Saldos_Capital_Mensual!J14>0, ROUND(Saldos_Capital_Mensual!J14 * 'Resumen_Cartera'!$Q14, 2), "") | L14: =IF(Saldos_Capital_Mensual!K14>0, ROUND(Saldos_Capital_Mensual!K14 * 'Resumen_Cartera'!$Q14, 2), "") | M14: =IF(Saldos_Capital_Mensual!L14>0, ROUND(Saldos_Capital_Mensual!L14 * 'Resumen_Cartera'!$Q14, 2), "") | N14: =IF(Saldos_Capital_Mensual!M14>0, ROUND(Saldos_Capital_Mensual!M14 * 'Resumen_Cartera'!$Q14, 2), "") | O14: =IF(Saldos_Capital_Mensual!N14>0, ROUND(Saldos_Capital_Mensual!N14 * 'Resumen_Cartera'!$Q14, 2), "") | P14: =IF(Saldos_Capital_Mensual!O14>0, ROUND(Saldos_Capital_Mensual!O14 * 'Resumen_Cartera'!$Q14, 2), "") | Q14: =IF(Saldos_Capital_Mensual!P14>0, ROUND(Saldos_Capital_Mensual!P14 * 'Resumen_Cartera'!$Q14, 2), "") | ... T14: =IF(Saldos_Capital_Mensual!S14>0, ROUND(Saldos_Capital_Mensual!S14 * 'Resumen_Cartera'!$Q14, 2), "") | U14: =SUM(I14:T14)
A15: 0524-0011 | B15: Lider En Derecho De Via y Construcción SA DE CV | C15: Wrangler Unlimited Sahara | D15: ACTIVO | E15: 2025-12-31 | F15: 2029-12-31 | G15: 48 | H15: 846843.45 | I15: =ROUND(839101.7 * 'Resumen_Cartera'!$Q15, 2) | J15: =IF(Saldos_Capital_Mensual!I15>0, ROUND(Saldos_Capital_Mensual!I15 * 'Resumen_Cartera'!$Q15, 2), "") | K15: =IF(Saldos_Capital_Mensual!J15>0, ROUND(Saldos_Capital_Mensual!J15 * 'Resumen_Cartera'!$Q15, 2), "") | L15: =IF(Saldos_Capital_Mensual!K15>0, ROUND(Saldos_Capital_Mensual!K15 * 'Resumen_Cartera'!$Q15, 2), "") | M15: =IF(Saldos_Capital_Mensual!L15>0, ROUND(Saldos_Capital_Mensual!L15 * 'Resumen_Cartera'!$Q15, 2), "") | N15: =IF(Saldos_Capital_Mensual!M15>0, ROUND(Saldos_Capital_Mensual!M15 * 'Resumen_Cartera'!$Q15, 2), "") | O15: =IF(Saldos_Capital_Mensual!N15>0, ROUND(Saldos_Capital_Mensual!N15 * 'Resumen_Cartera'!$Q15, 2), "") | P15: =IF(Saldos_Capital_Mensual!O15>0, ROUND(Saldos_Capital_Mensual!O15 * 'Resumen_Cartera'!$Q15, 2), "") | Q15: =IF(Saldos_Capital_Mensual!P15>0, ROUND(Saldos_Capital_Mensual!P15 * 'Resumen_Cartera'!$Q15, 2), "") | ... T15: =IF(Saldos_Capital_Mensual!S15>0, ROUND(Saldos_Capital_Mensual!S15 * 'Resumen_Cartera'!$Q15, 2), "") | U15: =SUM(I15:T15)
A16: 0524-0012 | B16: Lider En Derecho De Via y Construcción SA DE CV | C16: L200 GLS | D16: ACTIVO | E16: 2026-03-17 | F16: 2030-03-17 | G16: 48 | H16: 561738.88 | K16: =ROUND('Resumen_Cartera'!$K16 * 'Resumen_Cartera'!$Q16, 2) | L16: =IF(Saldos_Capital_Mensual!K16>0, ROUND(Saldos_Capital_Mensual!K16 * 'Resumen_Cartera'!$Q16, 2), "") | M16: =IF(Saldos_Capital_Mensual!L16>0, ROUND(Saldos_Capital_Mensual!L16 * 'Resumen_Cartera'!$Q16, 2), "") | N16: =IF(Saldos_Capital_Mensual!M16>0, ROUND(Saldos_Capital_Mensual!M16 * 'Resumen_Cartera'!$Q16, 2), "") | O16: =IF(Saldos_Capital_Mensual!N16>0, ROUND(Saldos_Capital_Mensual!N16 * 'Resumen_Cartera'!$Q16, 2), "") | P16: =IF(Saldos_Capital_Mensual!O16>0, ROUND(Saldos_Capital_Mensual!O16 * 'Resumen_Cartera'!$Q16, 2), "") | Q16: =IF(Saldos_Capital_Mensual!P16>0, ROUND(Saldos_Capital_Mensual!P16 * 'Resumen_Cartera'!$Q16, 2), "") | R16: =IF(Saldos_Capital_Mensual!Q16>0, ROUND(Saldos_Capital_Mensual!Q16 * 'Resumen_Cartera'!$Q16, 2), "") | S16: =IF(Saldos_Capital_Mensual!R16>0, ROUND(Saldos_Capital_Mensual!R16 * 'Resumen_Cartera'!$Q16, 2), "") | T16: =IF(Saldos_Capital_Mensual!S16>0, ROUND(Saldos_Capital_Mensual!S16 * 'Resumen_Cartera'!$Q16, 2), "") | U16: =SUM(I16:T16)
A17: 0524-0013 | B17: Lider En Derecho De Via y Construcción SA DE CV | C17: L200 GLX | D17: ACTIVO | E17: 2026-06-23 | F17: 2029-06-23 | G17: 36 | H17: 597925 | N17: =ROUND('Resumen_Cartera'!$K17 * 'Resumen_Cartera'!$Q17, 2) | O17: =IF(Saldos_Capital_Mensual!N17>0, ROUND(Saldos_Capital_Mensual!N17 * 'Resumen_Cartera'!$Q17, 2), "") | P17: =IF(Saldos_Capital_Mensual!O17>0, ROUND(Saldos_Capital_Mensual!O17 * 'Resumen_Cartera'!$Q17, 2), "") | Q17: =IF(Saldos_Capital_Mensual!P17>0, ROUND(Saldos_Capital_Mensual!P17 * 'Resumen_Cartera'!$Q17, 2), "") | R17: =IF(Saldos_Capital_Mensual!Q17>0, ROUND(Saldos_Capital_Mensual!Q17 * 'Resumen_Cartera'!$Q17, 2), "") | S17: =IF(Saldos_Capital_Mensual!R17>0, ROUND(Saldos_Capital_Mensual!R17 * 'Resumen_Cartera'!$Q17, 2), "") | T17: =IF(Saldos_Capital_Mensual!S17>0, ROUND(Saldos_Capital_Mensual!S17 * 'Resumen_Cartera'!$Q17, 2), "") | U17: =SUM(I17:T17)
A18: 0524-0014 | B18: Lider En Derecho De Via y Construcción SA DE CV | C18: L200 GLX | D18: ACTIVO | E18: 2026-06-23 | F18: 2029-06-23 | G18: 36 | H18: 597925 | N18: =ROUND('Resumen_Cartera'!$K18 * 'Resumen_Cartera'!$Q18, 2) | O18: =IF(Saldos_Capital_Mensual!N18>0, ROUND(Saldos_Capital_Mensual!N18 * 'Resumen_Cartera'!$Q18, 2), "") | P18: =IF(Saldos_Capital_Mensual!O18>0, ROUND(Saldos_Capital_Mensual!O18 * 'Resumen_Cartera'!$Q18, 2), "") | Q18: =IF(Saldos_Capital_Mensual!P18>0, ROUND(Saldos_Capital_Mensual!P18 * 'Resumen_Cartera'!$Q18, 2), "") | R18: =IF(Saldos_Capital_Mensual!Q18>0, ROUND(Saldos_Capital_Mensual!Q18 * 'Resumen_Cartera'!$Q18, 2), "") | S18: =IF(Saldos_Capital_Mensual!R18>0, ROUND(Saldos_Capital_Mensual!R18 * 'Resumen_Cartera'!$Q18, 2), "") | T18: =IF(Saldos_Capital_Mensual!S18>0, ROUND(Saldos_Capital_Mensual!S18 * 'Resumen_Cartera'!$Q18, 2), "") | U18: =SUM(I18:T18)
A19: 0524-0015 | B19: Lider En Derecho De Via y Construcción SA DE CV | C19: Mitsubishi L200 GLX 2026 | D19: ACTIVO | E19: 2026-07-29 | F19: 2029-07-29 | G19: 36 | H19: 515452.59 | O19: =ROUND('Resumen_Cartera'!$K19 * 'Resumen_Cartera'!$Q19, 2) | P19: =IF(Saldos_Capital_Mensual!O19>0, ROUND(Saldos_Capital_Mensual!O19 * 'Resumen_Cartera'!$Q19, 2), "") | Q19: =IF(Saldos_Capital_Mensual!P19>0, ROUND(Saldos_Capital_Mensual!P19 * 'Resumen_Cartera'!$Q19, 2), "") | R19: =IF(Saldos_Capital_Mensual!Q19>0, ROUND(Saldos_Capital_Mensual!Q19 * 'Resumen_Cartera'!$Q19, 2), "") | S19: =IF(Saldos_Capital_Mensual!R19>0, ROUND(Saldos_Capital_Mensual!R19 * 'Resumen_Cartera'!$Q19, 2), "") | T19: =IF(Saldos_Capital_Mensual!S19>0, ROUND(Saldos_Capital_Mensual!S19 * 'Resumen_Cartera'!$Q19, 2), "") | U19: =SUM(I19:T19)
A20: 0524-0016 | B20: Lider En Derecho De Via y Construcción SA DE CV | C20: Mitsubishi L200 GLX 2026 | D20: ACTIVO | E20: 2026-07-29 | F20: 2029-07-29 | G20: 36 | H20: 515452.59 | O20: =ROUND('Resumen_Cartera'!$K20 * 'Resumen_Cartera'!$Q20, 2) | P20: =IF(Saldos_Capital_Mensual!O20>0, ROUND(Saldos_Capital_Mensual!O20 * 'Resumen_Cartera'!$Q20, 2), "") | Q20: =IF(Saldos_Capital_Mensual!P20>0, ROUND(Saldos_Capital_Mensual!P20 * 'Resumen_Cartera'!$Q20, 2), "") | R20: =IF(Saldos_Capital_Mensual!Q20>0, ROUND(Saldos_Capital_Mensual!Q20 * 'Resumen_Cartera'!$Q20, 2), "") | S20: =IF(Saldos_Capital_Mensual!R20>0, ROUND(Saldos_Capital_Mensual!R20 * 'Resumen_Cartera'!$Q20, 2), "") | T20: =IF(Saldos_Capital_Mensual!S20>0, ROUND(Saldos_Capital_Mensual!S20 * 'Resumen_Cartera'!$Q20, 2), "") | U20: =SUM(I20:T20)
A21: 0527-0003 | B21: Comercilizadora e Importadora Nabega Sa de Cv | C21: RAM 700 Big Horn CVT | D21: ACTIVO | E21: 2024-05-30 | F21: 2027-05-30 | G21: 36 | H21: 289586.21 | I21: =ROUND(221927.38 * 'Resumen_Cartera'!$Q21, 2) | J21: =IF(Saldos_Capital_Mensual!I21>0, ROUND(Saldos_Capital_Mensual!I21 * 'Resumen_Cartera'!$Q21, 2), "") | K21: =IF(Saldos_Capital_Mensual!J21>0, ROUND(Saldos_Capital_Mensual!J21 * 'Resumen_Cartera'!$Q21, 2), "") | L21: =IF(Saldos_Capital_Mensual!K21>0, ROUND(Saldos_Capital_Mensual!K21 * 'Resumen_Cartera'!$Q21, 2), "") | M21: =IF(Saldos_Capital_Mensual!L21>0, ROUND(Saldos_Capital_Mensual!L21 * 'Resumen_Cartera'!$Q21, 2), "") | N21: =IF(Saldos_Capital_Mensual!M21>0, ROUND(Saldos_Capital_Mensual!M21 * 'Resumen_Cartera'!$Q21, 2), "") | O21: =IF(Saldos_Capital_Mensual!N21>0, ROUND(Saldos_Capital_Mensual!N21 * 'Resumen_Cartera'!$Q21, 2), "") | P21: =IF(Saldos_Capital_Mensual!O21>0, ROUND(Saldos_Capital_Mensual!O21 * 'Resumen_Cartera'!$Q21, 2), "") | Q21: =IF(Saldos_Capital_Mensual!P21>0, ROUND(Saldos_Capital_Mensual!P21 * 'Resumen_Cartera'!$Q21, 2), "") | ... T21: =IF(Saldos_Capital_Mensual!S21>0, ROUND(Saldos_Capital_Mensual!S21 * 'Resumen_Cartera'!$Q21, 2), "") | U21: =SUM(I21:T21)
A22: 0527-0004 | B22: Comercilizadora e Importadora Nabega Sa de Cv | C22: Gmc Denali | D22: ACTIVO | E22: 2025-07-31 | F22: 2029-07-31 | G22: 48 | H22: 991086.21 | I22: =ROUND(939512.73 * 'Resumen_Cartera'!$Q22, 2) | J22: =IF(Saldos_Capital_Mensual!I22>0, ROUND(Saldos_Capital_Mensual!I22 * 'Resumen_Cartera'!$Q22, 2), "") | K22: =IF(Saldos_Capital_Mensual!J22>0, ROUND(Saldos_Capital_Mensual!J22 * 'Resumen_Cartera'!$Q22, 2), "") | L22: =IF(Saldos_Capital_Mensual!K22>0, ROUND(Saldos_Capital_Mensual!K22 * 'Resumen_Cartera'!$Q22, 2), "") | M22: =IF(Saldos_Capital_Mensual!L22>0, ROUND(Saldos_Capital_Mensual!L22 * 'Resumen_Cartera'!$Q22, 2), "") | N22: =IF(Saldos_Capital_Mensual!M22>0, ROUND(Saldos_Capital_Mensual!M22 * 'Resumen_Cartera'!$Q22, 2), "") | O22: =IF(Saldos_Capital_Mensual!N22>0, ROUND(Saldos_Capital_Mensual!N22 * 'Resumen_Cartera'!$Q22, 2), "") | P22: =IF(Saldos_Capital_Mensual!O22>0, ROUND(Saldos_Capital_Mensual!O22 * 'Resumen_Cartera'!$Q22, 2), "") | Q22: =IF(Saldos_Capital_Mensual!P22>0, ROUND(Saldos_Capital_Mensual!P22 * 'Resumen_Cartera'!$Q22, 2), "") | ... T22: =IF(Saldos_Capital_Mensual!S22>0, ROUND(Saldos_Capital_Mensual!S22 * 'Resumen_Cartera'!$Q22, 2), "") | U22: =SUM(I22:T22)
A23: 0527-0005 | B23: Comercilizadora e Importadora Nabega Sa de Cv | C23: Gle 450 Sport | D23: ACTIVO | E23: 2025-08-16 | F23: 2028-08-16 | G23: 36 | H23: 1050525 | I23: =ROUND(981905.12 * 'Resumen_Cartera'!$Q23, 2) | J23: =IF(Saldos_Capital_Mensual!I23>0, ROUND(Saldos_Capital_Mensual!I23 * 'Resumen_Cartera'!$Q23, 2), "") | K23: =IF(Saldos_Capital_Mensual!J23>0, ROUND(Saldos_Capital_Mensual!J23 * 'Resumen_Cartera'!$Q23, 2), "") | L23: =IF(Saldos_Capital_Mensual!K23>0, ROUND(Saldos_Capital_Mensual!K23 * 'Resumen_Cartera'!$Q23, 2), "") | M23: =IF(Saldos_Capital_Mensual!L23>0, ROUND(Saldos_Capital_Mensual!L23 * 'Resumen_Cartera'!$Q23, 2), "") | N23: =IF(Saldos_Capital_Mensual!M23>0, ROUND(Saldos_Capital_Mensual!M23 * 'Resumen_Cartera'!$Q23, 2), "") | O23: =IF(Saldos_Capital_Mensual!N23>0, ROUND(Saldos_Capital_Mensual!N23 * 'Resumen_Cartera'!$Q23, 2), "") | P23: =IF(Saldos_Capital_Mensual!O23>0, ROUND(Saldos_Capital_Mensual!O23 * 'Resumen_Cartera'!$Q23, 2), "") | Q23: =IF(Saldos_Capital_Mensual!P23>0, ROUND(Saldos_Capital_Mensual!P23 * 'Resumen_Cartera'!$Q23, 2), "") | ... T23: =IF(Saldos_Capital_Mensual!S23>0, ROUND(Saldos_Capital_Mensual!S23 * 'Resumen_Cartera'!$Q23, 2), "") | U23: =SUM(I23:T23)
A24: 0531-0002 | B24: Otcada Mex, S. de R.L. de C.V. | C24: Grand Cherokee Limited | D24: ACTIVO | E24: 2026-06-18 | F24: 2030-06-18 | G24: 48 | H24: 779340 | N24: =ROUND('Resumen_Cartera'!$K24 * 'Resumen_Cartera'!$Q24, 2) | O24: =IF(Saldos_Capital_Mensual!N24>0, ROUND(Saldos_Capital_Mensual!N24 * 'Resumen_Cartera'!$Q24, 2), "") | P24: =IF(Saldos_Capital_Mensual!O24>0, ROUND(Saldos_Capital_Mensual!O24 * 'Resumen_Cartera'!$Q24, 2), "") | Q24: =IF(Saldos_Capital_Mensual!P24>0, ROUND(Saldos_Capital_Mensual!P24 * 'Resumen_Cartera'!$Q24, 2), "") | R24: =IF(Saldos_Capital_Mensual!Q24>0, ROUND(Saldos_Capital_Mensual!Q24 * 'Resumen_Cartera'!$Q24, 2), "") | S24: =IF(Saldos_Capital_Mensual!R24>0, ROUND(Saldos_Capital_Mensual!R24 * 'Resumen_Cartera'!$Q24, 2), "") | T24: =IF(Saldos_Capital_Mensual!S24>0, ROUND(Saldos_Capital_Mensual!S24 * 'Resumen_Cartera'!$Q24, 2), "") | U24: =SUM(I24:T24)
A25: 0546-0007 | B25: Norma Elena Bonilla Lupio | C25: GLC 350 E 4MATIC | D25: ACTIVO | E25: 2025-10-14 | F25: 2027-10-14 | G25: 24 | H25: 866917.24 | I25: =ROUND(797841.04 * 'Resumen_Cartera'!$Q25, 2) | J25: =IF(Saldos_Capital_Mensual!I25>0, ROUND(Saldos_Capital_Mensual!I25 * 'Resumen_Cartera'!$Q25, 2), "") | K25: =IF(Saldos_Capital_Mensual!J25>0, ROUND(Saldos_Capital_Mensual!J25 * 'Resumen_Cartera'!$Q25, 2), "") | L25: =IF(Saldos_Capital_Mensual!K25>0, ROUND(Saldos_Capital_Mensual!K25 * 'Resumen_Cartera'!$Q25, 2), "") | M25: =IF(Saldos_Capital_Mensual!L25>0, ROUND(Saldos_Capital_Mensual!L25 * 'Resumen_Cartera'!$Q25, 2), "") | N25: =IF(Saldos_Capital_Mensual!M25>0, ROUND(Saldos_Capital_Mensual!M25 * 'Resumen_Cartera'!$Q25, 2), "") | O25: =IF(Saldos_Capital_Mensual!N25>0, ROUND(Saldos_Capital_Mensual!N25 * 'Resumen_Cartera'!$Q25, 2), "") | P25: =IF(Saldos_Capital_Mensual!O25>0, ROUND(Saldos_Capital_Mensual!O25 * 'Resumen_Cartera'!$Q25, 2), "") | Q25: =IF(Saldos_Capital_Mensual!P25>0, ROUND(Saldos_Capital_Mensual!P25 * 'Resumen_Cartera'!$Q25, 2), "") | ... T25: =IF(Saldos_Capital_Mensual!S25>0, ROUND(Saldos_Capital_Mensual!S25 * 'Resumen_Cartera'!$Q25, 2), "") | U25: =SUM(I25:T25)
A26: 0546-0008 | B26: Norma Elena Bonilla Lupio | C26: JT MOJAVE 4X4 | D26: ACTIVO | E26: 2026-01-08 | F26: 2028-01-08 | G26: 24 | H26: 817760.17 | I26: =ROUND('Resumen_Cartera'!$K26 * 'Resumen_Cartera'!$Q26, 2) | J26: =IF(Saldos_Capital_Mensual!I26>0, ROUND(Saldos_Capital_Mensual!I26 * 'Resumen_Cartera'!$Q26, 2), "") | K26: =IF(Saldos_Capital_Mensual!J26>0, ROUND(Saldos_Capital_Mensual!J26 * 'Resumen_Cartera'!$Q26, 2), "") | L26: =IF(Saldos_Capital_Mensual!K26>0, ROUND(Saldos_Capital_Mensual!K26 * 'Resumen_Cartera'!$Q26, 2), "") | M26: =IF(Saldos_Capital_Mensual!L26>0, ROUND(Saldos_Capital_Mensual!L26 * 'Resumen_Cartera'!$Q26, 2), "") | N26: =IF(Saldos_Capital_Mensual!M26>0, ROUND(Saldos_Capital_Mensual!M26 * 'Resumen_Cartera'!$Q26, 2), "") | O26: =IF(Saldos_Capital_Mensual!N26>0, ROUND(Saldos_Capital_Mensual!N26 * 'Resumen_Cartera'!$Q26, 2), "") | P26: =IF(Saldos_Capital_Mensual!O26>0, ROUND(Saldos_Capital_Mensual!O26 * 'Resumen_Cartera'!$Q26, 2), "") | Q26: =IF(Saldos_Capital_Mensual!P26>0, ROUND(Saldos_Capital_Mensual!P26 * 'Resumen_Cartera'!$Q26, 2), "") | ... T26: =IF(Saldos_Capital_Mensual!S26>0, ROUND(Saldos_Capital_Mensual!S26 * 'Resumen_Cartera'!$Q26, 2), "") | U26: =SUM(I26:T26)
A27: 0546-0009 | B27: Norma Elena Bonilla Lupio | C27: Ram 1200 Tradesman 2026 | D27: ACTIVO | E27: 2026-07-01 | F27: 2028-07-01 | G27: 24 | H27: 270028.97 | O27: =ROUND('Resumen_Cartera'!$K27 * 'Resumen_Cartera'!$Q27, 2) | P27: =IF(Saldos_Capital_Mensual!O27>0, ROUND(Saldos_Capital_Mensual!O27 * 'Resumen_Cartera'!$Q27, 2), "") | Q27: =IF(Saldos_Capital_Mensual!P27>0, ROUND(Saldos_Capital_Mensual!P27 * 'Resumen_Cartera'!$Q27, 2), "") | R27: =IF(Saldos_Capital_Mensual!Q27>0, ROUND(Saldos_Capital_Mensual!Q27 * 'Resumen_Cartera'!$Q27, 2), "") | S27: =IF(Saldos_Capital_Mensual!R27>0, ROUND(Saldos_Capital_Mensual!R27 * 'Resumen_Cartera'!$Q27, 2), "") | T27: =IF(Saldos_Capital_Mensual!S27>0, ROUND(Saldos_Capital_Mensual!S27 * 'Resumen_Cartera'!$Q27, 2), "") | U27: =SUM(I27:T27)
A28: 0551-0002 | B28: Agaveros Unidos de Tequila Jalisco Aun S de RL de Cv | C28: Ram 700 Laramie | D28: ACTIVO | E28: 2023-07-07 | F28: 2027-07-07 | G28: 48 | H28: 247353.45 | I28: =ROUND(169189.16 * 'Resumen_Cartera'!$Q28, 2) | J28: =IF(Saldos_Capital_Mensual!I28>0, ROUND(Saldos_Capital_Mensual!I28 * 'Resumen_Cartera'!$Q28, 2), "") | K28: =IF(Saldos_Capital_Mensual!J28>0, ROUND(Saldos_Capital_Mensual!J28 * 'Resumen_Cartera'!$Q28, 2), "") | L28: =IF(Saldos_Capital_Mensual!K28>0, ROUND(Saldos_Capital_Mensual!K28 * 'Resumen_Cartera'!$Q28, 2), "") | M28: =IF(Saldos_Capital_Mensual!L28>0, ROUND(Saldos_Capital_Mensual!L28 * 'Resumen_Cartera'!$Q28, 2), "") | N28: =IF(Saldos_Capital_Mensual!M28>0, ROUND(Saldos_Capital_Mensual!M28 * 'Resumen_Cartera'!$Q28, 2), "") | O28: =IF(Saldos_Capital_Mensual!N28>0, ROUND(Saldos_Capital_Mensual!N28 * 'Resumen_Cartera'!$Q28, 2), "") | P28: =IF(Saldos_Capital_Mensual!O28>0, ROUND(Saldos_Capital_Mensual!O28 * 'Resumen_Cartera'!$Q28, 2), "") | Q28: =IF(Saldos_Capital_Mensual!P28>0, ROUND(Saldos_Capital_Mensual!P28 * 'Resumen_Cartera'!$Q28, 2), "") | ... T28: =IF(Saldos_Capital_Mensual!S28>0, ROUND(Saldos_Capital_Mensual!S28 * 'Resumen_Cartera'!$Q28, 2), "") | U28: =SUM(I28:T28)
A29: 0552-0018 | B29: Transportes y Maniobras Portuarias | C29: Raizer | D29: ACTIVO | E29: 2024-11-29 | F29: 2026-11-29 | G29: 24 | H29: 720900 | I29: =ROUND(361248.01 * 'Resumen_Cartera'!$Q29, 2) | J29: =IF(Saldos_Capital_Mensual!I29>0, ROUND(Saldos_Capital_Mensual!I29 * 'Resumen_Cartera'!$Q29, 2), "") | K29: =IF(Saldos_Capital_Mensual!J29>0, ROUND(Saldos_Capital_Mensual!J29 * 'Resumen_Cartera'!$Q29, 2), "") | L29: =IF(Saldos_Capital_Mensual!K29>0, ROUND(Saldos_Capital_Mensual!K29 * 'Resumen_Cartera'!$Q29, 2), "") | M29: =IF(Saldos_Capital_Mensual!L29>0, ROUND(Saldos_Capital_Mensual!L29 * 'Resumen_Cartera'!$Q29, 2), "") | N29: =IF(Saldos_Capital_Mensual!M29>0, ROUND(Saldos_Capital_Mensual!M29 * 'Resumen_Cartera'!$Q29, 2), "") | O29: =IF(Saldos_Capital_Mensual!N29>0, ROUND(Saldos_Capital_Mensual!N29 * 'Resumen_Cartera'!$Q29, 2), "") | P29: =IF(Saldos_Capital_Mensual!O29>0, ROUND(Saldos_Capital_Mensual!O29 * 'Resumen_Cartera'!$Q29, 2), "") | Q29: =IF(Saldos_Capital_Mensual!P29>0, ROUND(Saldos_Capital_Mensual!P29 * 'Resumen_Cartera'!$Q29, 2), "") | R29: =IF(Saldos_Capital_Mensual!Q29>0, ROUND(Saldos_Capital_Mensual!Q29 * 'Resumen_Cartera'!$Q29, 2), "") | U29: =SUM(I29:T29)
A30: 0552-0019 | B30: Transportes y Maniobras Portuarias de Mexico Sa de Cv | C30: Remolque tipo Dolly | D30: ACTIVO | E30: 2024-12-20 | F30: 2026-12-20 | G30: 24 | H30: 219510 | I30: =ROUND(119241.47 * 'Resumen_Cartera'!$Q30, 2) | J30: =IF(Saldos_Capital_Mensual!I30>0, ROUND(Saldos_Capital_Mensual!I30 * 'Resumen_Cartera'!$Q30, 2), "") | K30: =IF(Saldos_Capital_Mensual!J30>0, ROUND(Saldos_Capital_Mensual!J30 * 'Resumen_Cartera'!$Q30, 2), "") | L30: =IF(Saldos_Capital_Mensual!K30>0, ROUND(Saldos_Capital_Mensual!K30 * 'Resumen_Cartera'!$Q30, 2), "") | M30: =IF(Saldos_Capital_Mensual!L30>0, ROUND(Saldos_Capital_Mensual!L30 * 'Resumen_Cartera'!$Q30, 2), "") | N30: =IF(Saldos_Capital_Mensual!M30>0, ROUND(Saldos_Capital_Mensual!M30 * 'Resumen_Cartera'!$Q30, 2), "") | O30: =IF(Saldos_Capital_Mensual!N30>0, ROUND(Saldos_Capital_Mensual!N30 * 'Resumen_Cartera'!$Q30, 2), "") | P30: =IF(Saldos_Capital_Mensual!O30>0, ROUND(Saldos_Capital_Mensual!O30 * 'Resumen_Cartera'!$Q30, 2), "") | Q30: =IF(Saldos_Capital_Mensual!P30>0, ROUND(Saldos_Capital_Mensual!P30 * 'Resumen_Cartera'!$Q30, 2), "") | ... S30: =IF(Saldos_Capital_Mensual!R30>0, ROUND(Saldos_Capital_Mensual!R30 * 'Resumen_Cartera'!$Q30, 2), "") | U30: =SUM(I30:T30)
A31: 0552-0020 | B31: Transportes y Maniobras Portuarias de Mexico Sa de Cv | C31: PLATAFORMA MULTIMODAL | D31: ACTIVO | E31: 2024-12-26 | F31: 2026-12-26 | G31: 24 | H31: 415530 | I31: =ROUND(225722.85 * 'Resumen_Cartera'!$Q31, 2) | J31: =IF(Saldos_Capital_Mensual!I31>0, ROUND(Saldos_Capital_Mensual!I31 * 'Resumen_Cartera'!$Q31, 2), "") | K31: =IF(Saldos_Capital_Mensual!J31>0, ROUND(Saldos_Capital_Mensual!J31 * 'Resumen_Cartera'!$Q31, 2), "") | L31: =IF(Saldos_Capital_Mensual!K31>0, ROUND(Saldos_Capital_Mensual!K31 * 'Resumen_Cartera'!$Q31, 2), "") | M31: =IF(Saldos_Capital_Mensual!L31>0, ROUND(Saldos_Capital_Mensual!L31 * 'Resumen_Cartera'!$Q31, 2), "") | N31: =IF(Saldos_Capital_Mensual!M31>0, ROUND(Saldos_Capital_Mensual!M31 * 'Resumen_Cartera'!$Q31, 2), "") | O31: =IF(Saldos_Capital_Mensual!N31>0, ROUND(Saldos_Capital_Mensual!N31 * 'Resumen_Cartera'!$Q31, 2), "") | P31: =IF(Saldos_Capital_Mensual!O31>0, ROUND(Saldos_Capital_Mensual!O31 * 'Resumen_Cartera'!$Q31, 2), "") | Q31: =IF(Saldos_Capital_Mensual!P31>0, ROUND(Saldos_Capital_Mensual!P31 * 'Resumen_Cartera'!$Q31, 2), "") | ... S31: =IF(Saldos_Capital_Mensual!R31>0, ROUND(Saldos_Capital_Mensual!R31 * 'Resumen_Cartera'!$Q31, 2), "") | U31: =SUM(I31:T31)
A32: 0552-0021 | B32: Transportes y Maniobras Portuarias de Mexico Sa de Cv | C32: PLATAFORMA MULTIMODAL | D32: ACTIVO | E32: 2024-12-26 | F32: 2026-12-26 | G32: 24 | H32: 415530 | I32: =ROUND(225722.85 * 'Resumen_Cartera'!$Q32, 2) | J32: =IF(Saldos_Capital_Mensual!I32>0, ROUND(Saldos_Capital_Mensual!I32 * 'Resumen_Cartera'!$Q32, 2), "") | K32: =IF(Saldos_Capital_Mensual!J32>0, ROUND(Saldos_Capital_Mensual!J32 * 'Resumen_Cartera'!$Q32, 2), "") | L32: =IF(Saldos_Capital_Mensual!K32>0, ROUND(Saldos_Capital_Mensual!K32 * 'Resumen_Cartera'!$Q32, 2), "") | M32: =IF(Saldos_Capital_Mensual!L32>0, ROUND(Saldos_Capital_Mensual!L32 * 'Resumen_Cartera'!$Q32, 2), "") | N32: =IF(Saldos_Capital_Mensual!M32>0, ROUND(Saldos_Capital_Mensual!M32 * 'Resumen_Cartera'!$Q32, 2), "") | O32: =IF(Saldos_Capital_Mensual!N32>0, ROUND(Saldos_Capital_Mensual!N32 * 'Resumen_Cartera'!$Q32, 2), "") | P32: =IF(Saldos_Capital_Mensual!O32>0, ROUND(Saldos_Capital_Mensual!O32 * 'Resumen_Cartera'!$Q32, 2), "") | Q32: =IF(Saldos_Capital_Mensual!P32>0, ROUND(Saldos_Capital_Mensual!P32 * 'Resumen_Cartera'!$Q32, 2), "") | ... S32: =IF(Saldos_Capital_Mensual!R32>0, ROUND(Saldos_Capital_Mensual!R32 * 'Resumen_Cartera'!$Q32, 2), "") | U32: =SUM(I32:T32)
A33: 0552-0022 | B33: Transportes y Maniobras Portuarias de Mexico Sa de Cv | C33: RZR | D33: ACTIVO | E33: 2024-12-26 | F33: 2026-12-26 | G33: 24 | H33: 737862.07 | I33: =ROUND(400872.11 * 'Resumen_Cartera'!$Q33, 2) | J33: =IF(Saldos_Capital_Mensual!I33>0, ROUND(Saldos_Capital_Mensual!I33 * 'Resumen_Cartera'!$Q33, 2), "") | K33: =IF(Saldos_Capital_Mensual!J33>0, ROUND(Saldos_Capital_Mensual!J33 * 'Resumen_Cartera'!$Q33, 2), "") | L33: =IF(Saldos_Capital_Mensual!K33>0, ROUND(Saldos_Capital_Mensual!K33 * 'Resumen_Cartera'!$Q33, 2), "") | M33: =IF(Saldos_Capital_Mensual!L33>0, ROUND(Saldos_Capital_Mensual!L33 * 'Resumen_Cartera'!$Q33, 2), "") | N33: =IF(Saldos_Capital_Mensual!M33>0, ROUND(Saldos_Capital_Mensual!M33 * 'Resumen_Cartera'!$Q33, 2), "") | O33: =IF(Saldos_Capital_Mensual!N33>0, ROUND(Saldos_Capital_Mensual!N33 * 'Resumen_Cartera'!$Q33, 2), "") | P33: =IF(Saldos_Capital_Mensual!O33>0, ROUND(Saldos_Capital_Mensual!O33 * 'Resumen_Cartera'!$Q33, 2), "") | Q33: =IF(Saldos_Capital_Mensual!P33>0, ROUND(Saldos_Capital_Mensual!P33 * 'Resumen_Cartera'!$Q33, 2), "") | ... S33: =IF(Saldos_Capital_Mensual!R33>0, ROUND(Saldos_Capital_Mensual!R33 * 'Resumen_Cartera'!$Q33, 2), "") | U33: =SUM(I33:T33)
A34: 0552-0023 | B34: Transportes y Maniobras Portuarias de Mexico Sa de Cv | C34: Iternational Lt | D34: ACTIVO | E34: 2025-08-27 | F34: 2027-08-27 | G34: 24 | H34: 1377931 | I34: =ROUND(1180748.71 * 'Resumen_Cartera'!$Q34, 2) | J34: =IF(Saldos_Capital_Mensual!I34>0, ROUND(Saldos_Capital_Mensual!I34 * 'Resumen_Cartera'!$Q34, 2), "") | K34: =IF(Saldos_Capital_Mensual!J34>0, ROUND(Saldos_Capital_Mensual!J34 * 'Resumen_Cartera'!$Q34, 2), "") | L34: =IF(Saldos_Capital_Mensual!K34>0, ROUND(Saldos_Capital_Mensual!K34 * 'Resumen_Cartera'!$Q34, 2), "") | M34: =IF(Saldos_Capital_Mensual!L34>0, ROUND(Saldos_Capital_Mensual!L34 * 'Resumen_Cartera'!$Q34, 2), "") | N34: =IF(Saldos_Capital_Mensual!M34>0, ROUND(Saldos_Capital_Mensual!M34 * 'Resumen_Cartera'!$Q34, 2), "") | O34: =IF(Saldos_Capital_Mensual!N34>0, ROUND(Saldos_Capital_Mensual!N34 * 'Resumen_Cartera'!$Q34, 2), "") | P34: =IF(Saldos_Capital_Mensual!O34>0, ROUND(Saldos_Capital_Mensual!O34 * 'Resumen_Cartera'!$Q34, 2), "") | Q34: =IF(Saldos_Capital_Mensual!P34>0, ROUND(Saldos_Capital_Mensual!P34 * 'Resumen_Cartera'!$Q34, 2), "") | ... T34: =IF(Saldos_Capital_Mensual!S34>0, ROUND(Saldos_Capital_Mensual!S34 * 'Resumen_Cartera'!$Q34, 2), "") | U34: =SUM(I34:T34)
A35: 0552-0024 | B35: Transportes y Maniobras Portuarias de Mexico Sa de Cv | C35: Iternational Lt | D35: ACTIVO | E35: 2025-08-27 | F35: 2027-08-27 | G35: 24 | H35: 1377931 | I35: =ROUND(1180748.71 * 'Resumen_Cartera'!$Q35, 2) | J35: =IF(Saldos_Capital_Mensual!I35>0, ROUND(Saldos_Capital_Mensual!I35 * 'Resumen_Cartera'!$Q35, 2), "") | K35: =IF(Saldos_Capital_Mensual!J35>0, ROUND(Saldos_Capital_Mensual!J35 * 'Resumen_Cartera'!$Q35, 2), "") | L35: =IF(Saldos_Capital_Mensual!K35>0, ROUND(Saldos_Capital_Mensual!K35 * 'Resumen_Cartera'!$Q35, 2), "") | M35: =IF(Saldos_Capital_Mensual!L35>0, ROUND(Saldos_Capital_Mensual!L35 * 'Resumen_Cartera'!$Q35, 2), "") | N35: =IF(Saldos_Capital_Mensual!M35>0, ROUND(Saldos_Capital_Mensual!M35 * 'Resumen_Cartera'!$Q35, 2), "") | O35: =IF(Saldos_Capital_Mensual!N35>0, ROUND(Saldos_Capital_Mensual!N35 * 'Resumen_Cartera'!$Q35, 2), "") | P35: =IF(Saldos_Capital_Mensual!O35>0, ROUND(Saldos_Capital_Mensual!O35 * 'Resumen_Cartera'!$Q35, 2), "") | Q35: =IF(Saldos_Capital_Mensual!P35>0, ROUND(Saldos_Capital_Mensual!P35 * 'Resumen_Cartera'!$Q35, 2), "") | ... T35: =IF(Saldos_Capital_Mensual!S35>0, ROUND(Saldos_Capital_Mensual!S35 * 'Resumen_Cartera'!$Q35, 2), "") | U35: =SUM(I35:T35)
A36: 0552-0025 | B36: Transportes y Maniobras Portuarias de Mexico Sa de Cv | C36: Iternational Lt | D36: ACTIVO | E36: 2025-08-27 | F36: 2027-08-27 | G36: 24 | H36: 1377931 | I36: =ROUND(1180748.71 * 'Resumen_Cartera'!$Q36, 2) | J36: =IF(Saldos_Capital_Mensual!I36>0, ROUND(Saldos_Capital_Mensual!I36 * 'Resumen_Cartera'!$Q36, 2), "") | K36: =IF(Saldos_Capital_Mensual!J36>0, ROUND(Saldos_Capital_Mensual!J36 * 'Resumen_Cartera'!$Q36, 2), "") | L36: =IF(Saldos_Capital_Mensual!K36>0, ROUND(Saldos_Capital_Mensual!K36 * 'Resumen_Cartera'!$Q36, 2), "") | M36: =IF(Saldos_Capital_Mensual!L36>0, ROUND(Saldos_Capital_Mensual!L36 * 'Resumen_Cartera'!$Q36, 2), "") | N36: =IF(Saldos_Capital_Mensual!M36>0, ROUND(Saldos_Capital_Mensual!M36 * 'Resumen_Cartera'!$Q36, 2), "") | O36: =IF(Saldos_Capital_Mensual!N36>0, ROUND(Saldos_Capital_Mensual!N36 * 'Resumen_Cartera'!$Q36, 2), "") | P36: =IF(Saldos_Capital_Mensual!O36>0, ROUND(Saldos_Capital_Mensual!O36 * 'Resumen_Cartera'!$Q36, 2), "") | Q36: =IF(Saldos_Capital_Mensual!P36>0, ROUND(Saldos_Capital_Mensual!P36 * 'Resumen_Cartera'!$Q36, 2), "") | ... T36: =IF(Saldos_Capital_Mensual!S36>0, ROUND(Saldos_Capital_Mensual!S36 * 'Resumen_Cartera'!$Q36, 2), "") | U36: =SUM(I36:T36)
A37: 0554-0003 | B37: TRANSPORTES DEL BAJIO TRANSCOLD SA DE CV | C37: RAM 4000 CHASIS PLANO LARGO "PL" | D37: ACTIVO | E37: 2022-11-24 | F37: 2026-11-24 | G37: 48 | H37: 643825.51 | I37: =ROUND(258312.84 * 'Resumen_Cartera'!$Q37, 2) | J37: =IF(Saldos_Capital_Mensual!I37>0, ROUND(Saldos_Capital_Mensual!I37 * 'Resumen_Cartera'!$Q37, 2), "") | K37: =IF(Saldos_Capital_Mensual!J37>0, ROUND(Saldos_Capital_Mensual!J37 * 'Resumen_Cartera'!$Q37, 2), "") | L37: =IF(Saldos_Capital_Mensual!K37>0, ROUND(Saldos_Capital_Mensual!K37 * 'Resumen_Cartera'!$Q37, 2), "") | M37: =IF(Saldos_Capital_Mensual!L37>0, ROUND(Saldos_Capital_Mensual!L37 * 'Resumen_Cartera'!$Q37, 2), "") | N37: =IF(Saldos_Capital_Mensual!M37>0, ROUND(Saldos_Capital_Mensual!M37 * 'Resumen_Cartera'!$Q37, 2), "") | O37: =IF(Saldos_Capital_Mensual!N37>0, ROUND(Saldos_Capital_Mensual!N37 * 'Resumen_Cartera'!$Q37, 2), "") | P37: =IF(Saldos_Capital_Mensual!O37>0, ROUND(Saldos_Capital_Mensual!O37 * 'Resumen_Cartera'!$Q37, 2), "") | Q37: =IF(Saldos_Capital_Mensual!P37>0, ROUND(Saldos_Capital_Mensual!P37 * 'Resumen_Cartera'!$Q37, 2), "") | R37: =IF(Saldos_Capital_Mensual!Q37>0, ROUND(Saldos_Capital_Mensual!Q37 * 'Resumen_Cartera'!$Q37, 2), "") | U37: =SUM(I37:T37)
A38: 0570-0006 | B38: Jalco Iluminacion Sa de Cv | C38: RAM 700 BIG HORN | D38: ACTIVO | E38: 2023-12-08 | F38: 2026-12-08 | G38: 36 | H38: 313370.69 | I38: =ROUND(204463.69 * 'Resumen_Cartera'!$Q38, 2) | J38: =IF(Saldos_Capital_Mensual!I38>0, ROUND(Saldos_Capital_Mensual!I38 * 'Resumen_Cartera'!$Q38, 2), "") | K38: =IF(Saldos_Capital_Mensual!J38>0, ROUND(Saldos_Capital_Mensual!J38 * 'Resumen_Cartera'!$Q38, 2), "") | L38: =IF(Saldos_Capital_Mensual!K38>0, ROUND(Saldos_Capital_Mensual!K38 * 'Resumen_Cartera'!$Q38, 2), "") | M38: =IF(Saldos_Capital_Mensual!L38>0, ROUND(Saldos_Capital_Mensual!L38 * 'Resumen_Cartera'!$Q38, 2), "") | N38: =IF(Saldos_Capital_Mensual!M38>0, ROUND(Saldos_Capital_Mensual!M38 * 'Resumen_Cartera'!$Q38, 2), "") | O38: =IF(Saldos_Capital_Mensual!N38>0, ROUND(Saldos_Capital_Mensual!N38 * 'Resumen_Cartera'!$Q38, 2), "") | P38: =IF(Saldos_Capital_Mensual!O38>0, ROUND(Saldos_Capital_Mensual!O38 * 'Resumen_Cartera'!$Q38, 2), "") | Q38: =IF(Saldos_Capital_Mensual!P38>0, ROUND(Saldos_Capital_Mensual!P38 * 'Resumen_Cartera'!$Q38, 2), "") | ... S38: =IF(Saldos_Capital_Mensual!R38>0, ROUND(Saldos_Capital_Mensual!R38 * 'Resumen_Cartera'!$Q38, 2), "") | U38: =SUM(I38:T38)
A39: 0573-0007 | B39: Ar Marketing Sa de Cv | C39: Promaster Rapid | D39: ACTIVO | E39: 2024-05-10 | F39: 2027-05-10 | G39: 36 | H39: 180311.55 | I39: =ROUND(127164.74 * 'Resumen_Cartera'!$Q39, 2) | J39: =IF(Saldos_Capital_Mensual!I39>0, ROUND(Saldos_Capital_Mensual!I39 * 'Resumen_Cartera'!$Q39, 2), "") | K39: =IF(Saldos_Capital_Mensual!J39>0, ROUND(Saldos_Capital_Mensual!J39 * 'Resumen_Cartera'!$Q39, 2), "") | L39: =IF(Saldos_Capital_Mensual!K39>0, ROUND(Saldos_Capital_Mensual!K39 * 'Resumen_Cartera'!$Q39, 2), "") | M39: =IF(Saldos_Capital_Mensual!L39>0, ROUND(Saldos_Capital_Mensual!L39 * 'Resumen_Cartera'!$Q39, 2), "") | N39: =IF(Saldos_Capital_Mensual!M39>0, ROUND(Saldos_Capital_Mensual!M39 * 'Resumen_Cartera'!$Q39, 2), "") | O39: =IF(Saldos_Capital_Mensual!N39>0, ROUND(Saldos_Capital_Mensual!N39 * 'Resumen_Cartera'!$Q39, 2), "") | P39: =IF(Saldos_Capital_Mensual!O39>0, ROUND(Saldos_Capital_Mensual!O39 * 'Resumen_Cartera'!$Q39, 2), "") | Q39: =IF(Saldos_Capital_Mensual!P39>0, ROUND(Saldos_Capital_Mensual!P39 * 'Resumen_Cartera'!$Q39, 2), "") | ... T39: =IF(Saldos_Capital_Mensual!S39>0, ROUND(Saldos_Capital_Mensual!S39 * 'Resumen_Cartera'!$Q39, 2), "") | U39: =SUM(I39:T39)
A40: 0573-0008 | B40: Ar Marketing Sa de Cv | C40: Promaster Rapid | D40: ACTIVO | E40: 2024-05-15 | F40: 2027-05-15 | G40: 36 | H40: 177354.65 | I40: =ROUND(125079.32 * 'Resumen_Cartera'!$Q40, 2) | J40: =IF(Saldos_Capital_Mensual!I40>0, ROUND(Saldos_Capital_Mensual!I40 * 'Resumen_Cartera'!$Q40, 2), "") | K40: =IF(Saldos_Capital_Mensual!J40>0, ROUND(Saldos_Capital_Mensual!J40 * 'Resumen_Cartera'!$Q40, 2), "") | L40: =IF(Saldos_Capital_Mensual!K40>0, ROUND(Saldos_Capital_Mensual!K40 * 'Resumen_Cartera'!$Q40, 2), "") | M40: =IF(Saldos_Capital_Mensual!L40>0, ROUND(Saldos_Capital_Mensual!L40 * 'Resumen_Cartera'!$Q40, 2), "") | N40: =IF(Saldos_Capital_Mensual!M40>0, ROUND(Saldos_Capital_Mensual!M40 * 'Resumen_Cartera'!$Q40, 2), "") | O40: =IF(Saldos_Capital_Mensual!N40>0, ROUND(Saldos_Capital_Mensual!N40 * 'Resumen_Cartera'!$Q40, 2), "") | P40: =IF(Saldos_Capital_Mensual!O40>0, ROUND(Saldos_Capital_Mensual!O40 * 'Resumen_Cartera'!$Q40, 2), "") | Q40: =IF(Saldos_Capital_Mensual!P40>0, ROUND(Saldos_Capital_Mensual!P40 * 'Resumen_Cartera'!$Q40, 2), "") | ... T40: =IF(Saldos_Capital_Mensual!S40>0, ROUND(Saldos_Capital_Mensual!S40 * 'Resumen_Cartera'!$Q40, 2), "") | U40: =SUM(I40:T40)
A41: 0573-0009 | B41: Ar Marketing Sa de Cv | C41: Partner | D41: ACTIVO | E41: 2025-11-28 | F41: 2028-11-28 | G41: 36 | H41: 174397.76 | I41: =ROUND(170138.94 * 'Resumen_Cartera'!$Q41, 2) | J41: =IF(Saldos_Capital_Mensual!I41>0, ROUND(Saldos_Capital_Mensual!I41 * 'Resumen_Cartera'!$Q41, 2), "") | K41: =IF(Saldos_Capital_Mensual!J41>0, ROUND(Saldos_Capital_Mensual!J41 * 'Resumen_Cartera'!$Q41, 2), "") | L41: =IF(Saldos_Capital_Mensual!K41>0, ROUND(Saldos_Capital_Mensual!K41 * 'Resumen_Cartera'!$Q41, 2), "") | M41: =IF(Saldos_Capital_Mensual!L41>0, ROUND(Saldos_Capital_Mensual!L41 * 'Resumen_Cartera'!$Q41, 2), "") | N41: =IF(Saldos_Capital_Mensual!M41>0, ROUND(Saldos_Capital_Mensual!M41 * 'Resumen_Cartera'!$Q41, 2), "") | O41: =IF(Saldos_Capital_Mensual!N41>0, ROUND(Saldos_Capital_Mensual!N41 * 'Resumen_Cartera'!$Q41, 2), "") | P41: =IF(Saldos_Capital_Mensual!O41>0, ROUND(Saldos_Capital_Mensual!O41 * 'Resumen_Cartera'!$Q41, 2), "") | Q41: =IF(Saldos_Capital_Mensual!P41>0, ROUND(Saldos_Capital_Mensual!P41 * 'Resumen_Cartera'!$Q41, 2), "") | ... T41: =IF(Saldos_Capital_Mensual!S41>0, ROUND(Saldos_Capital_Mensual!S41 * 'Resumen_Cartera'!$Q41, 2), "") | U41: =SUM(I41:T41)
A42: 0580-0001 | B42: YOLANDA AVALOS CARDENAS | C42: Mojave | D42: ACTIVO | E42: 2022-11-18 | F42: 2026-11-18 | G42: 48 | H42: 1004758.6 | I42: =ROUND(498029.69 * 'Resumen_Cartera'!$Q42, 2) | J42: =IF(Saldos_Capital_Mensual!I42>0, ROUND(Saldos_Capital_Mensual!I42 * 'Resumen_Cartera'!$Q42, 2), "") | K42: =IF(Saldos_Capital_Mensual!J42>0, ROUND(Saldos_Capital_Mensual!J42 * 'Resumen_Cartera'!$Q42, 2), "") | L42: =IF(Saldos_Capital_Mensual!K42>0, ROUND(Saldos_Capital_Mensual!K42 * 'Resumen_Cartera'!$Q42, 2), "") | M42: =IF(Saldos_Capital_Mensual!L42>0, ROUND(Saldos_Capital_Mensual!L42 * 'Resumen_Cartera'!$Q42, 2), "") | N42: =IF(Saldos_Capital_Mensual!M42>0, ROUND(Saldos_Capital_Mensual!M42 * 'Resumen_Cartera'!$Q42, 2), "") | O42: =IF(Saldos_Capital_Mensual!N42>0, ROUND(Saldos_Capital_Mensual!N42 * 'Resumen_Cartera'!$Q42, 2), "") | P42: =IF(Saldos_Capital_Mensual!O42>0, ROUND(Saldos_Capital_Mensual!O42 * 'Resumen_Cartera'!$Q42, 2), "") | Q42: =IF(Saldos_Capital_Mensual!P42>0, ROUND(Saldos_Capital_Mensual!P42 * 'Resumen_Cartera'!$Q42, 2), "") | R42: =IF(Saldos_Capital_Mensual!Q42>0, ROUND(Saldos_Capital_Mensual!Q42 * 'Resumen_Cartera'!$Q42, 2), "") | U42: =SUM(I42:T42)
A43: 0581-0001 | B43: Aditivos y Vitaminas Mexicanas Sa de Cv | C43: RAM 700 REGULAR CAB | D43: ACTIVO | E43: 2023-01-17 | F43: 2027-01-17 | G43: 48 | H43: 179163.8 | I43: =ROUND(102903.96 * 'Resumen_Cartera'!$Q43, 2) | J43: =IF(Saldos_Capital_Mensual!I43>0, ROUND(Saldos_Capital_Mensual!I43 * 'Resumen_Cartera'!$Q43, 2), "") | K43: =IF(Saldos_Capital_Mensual!J43>0, ROUND(Saldos_Capital_Mensual!J43 * 'Resumen_Cartera'!$Q43, 2), "") | L43: =IF(Saldos_Capital_Mensual!K43>0, ROUND(Saldos_Capital_Mensual!K43 * 'Resumen_Cartera'!$Q43, 2), "") | M43: =IF(Saldos_Capital_Mensual!L43>0, ROUND(Saldos_Capital_Mensual!L43 * 'Resumen_Cartera'!$Q43, 2), "") | N43: =IF(Saldos_Capital_Mensual!M43>0, ROUND(Saldos_Capital_Mensual!M43 * 'Resumen_Cartera'!$Q43, 2), "") | O43: =IF(Saldos_Capital_Mensual!N43>0, ROUND(Saldos_Capital_Mensual!N43 * 'Resumen_Cartera'!$Q43, 2), "") | P43: =IF(Saldos_Capital_Mensual!O43>0, ROUND(Saldos_Capital_Mensual!O43 * 'Resumen_Cartera'!$Q43, 2), "") | Q43: =IF(Saldos_Capital_Mensual!P43>0, ROUND(Saldos_Capital_Mensual!P43 * 'Resumen_Cartera'!$Q43, 2), "") | ... T43: =IF(Saldos_Capital_Mensual!S43>0, ROUND(Saldos_Capital_Mensual!S43 * 'Resumen_Cartera'!$Q43, 2), "") | U43: =SUM(I43:T43)
A44: 0581-0002 | B44: Aditivos y Vitaminas Mexicanas Sa de Cv | C44: Ram 700 Regular Cab | D44: ACTIVO | E44: 2024-09-18 | F44: 2028-09-18 | G44: 48 | H44: 252077.59 | I44: =ROUND(206977.86 * 'Resumen_Cartera'!$Q44, 2) | J44: =IF(Saldos_Capital_Mensual!I44>0, ROUND(Saldos_Capital_Mensual!I44 * 'Resumen_Cartera'!$Q44, 2), "") | K44: =IF(Saldos_Capital_Mensual!J44>0, ROUND(Saldos_Capital_Mensual!J44 * 'Resumen_Cartera'!$Q44, 2), "") | L44: =IF(Saldos_Capital_Mensual!K44>0, ROUND(Saldos_Capital_Mensual!K44 * 'Resumen_Cartera'!$Q44, 2), "") | M44: =IF(Saldos_Capital_Mensual!L44>0, ROUND(Saldos_Capital_Mensual!L44 * 'Resumen_Cartera'!$Q44, 2), "") | N44: =IF(Saldos_Capital_Mensual!M44>0, ROUND(Saldos_Capital_Mensual!M44 * 'Resumen_Cartera'!$Q44, 2), "") | O44: =IF(Saldos_Capital_Mensual!N44>0, ROUND(Saldos_Capital_Mensual!N44 * 'Resumen_Cartera'!$Q44, 2), "") | P44: =IF(Saldos_Capital_Mensual!O44>0, ROUND(Saldos_Capital_Mensual!O44 * 'Resumen_Cartera'!$Q44, 2), "") | Q44: =IF(Saldos_Capital_Mensual!P44>0, ROUND(Saldos_Capital_Mensual!P44 * 'Resumen_Cartera'!$Q44, 2), "") | ... T44: =IF(Saldos_Capital_Mensual!S44>0, ROUND(Saldos_Capital_Mensual!S44 * 'Resumen_Cartera'!$Q44, 2), "") | U44: =SUM(I44:T44)
A45: 0582-0003 | B45: Ensaladas Frescas de Occidente Sa de Cv | C45: Pulse | D45: ACTIVO | E45: 2024-07-02 | F45: 2028-07-02 | G45: 48 | H45: 274267.24 | I45: =ROUND(230630.96 * 'Resumen_Cartera'!$Q45, 2) | J45: =IF(Saldos_Capital_Mensual!I45>0, ROUND(Saldos_Capital_Mensual!I45 * 'Resumen_Cartera'!$Q45, 2), "") | K45: =IF(Saldos_Capital_Mensual!J45>0, ROUND(Saldos_Capital_Mensual!J45 * 'Resumen_Cartera'!$Q45, 2), "") | L45: =IF(Saldos_Capital_Mensual!K45>0, ROUND(Saldos_Capital_Mensual!K45 * 'Resumen_Cartera'!$Q45, 2), "") | M45: =IF(Saldos_Capital_Mensual!L45>0, ROUND(Saldos_Capital_Mensual!L45 * 'Resumen_Cartera'!$Q45, 2), "") | N45: =IF(Saldos_Capital_Mensual!M45>0, ROUND(Saldos_Capital_Mensual!M45 * 'Resumen_Cartera'!$Q45, 2), "") | O45: =IF(Saldos_Capital_Mensual!N45>0, ROUND(Saldos_Capital_Mensual!N45 * 'Resumen_Cartera'!$Q45, 2), "") | P45: =IF(Saldos_Capital_Mensual!O45>0, ROUND(Saldos_Capital_Mensual!O45 * 'Resumen_Cartera'!$Q45, 2), "") | Q45: =IF(Saldos_Capital_Mensual!P45>0, ROUND(Saldos_Capital_Mensual!P45 * 'Resumen_Cartera'!$Q45, 2), "") | ... T45: =IF(Saldos_Capital_Mensual!S45>0, ROUND(Saldos_Capital_Mensual!S45 * 'Resumen_Cartera'!$Q45, 2), "") | U45: =SUM(I45:T45)
A46: 0583-0004 | B46: Soluciones Profesionales para la Industria Alimentaria | C46: BIGHORN CREW CAB MT | D46: ACTIVO | E46: 2024-12-30 | F46: 2026-12-30 | G46: 24 | H46: 204775.86 | I46: =ROUND(128345.39 * 'Resumen_Cartera'!$Q46, 2) | J46: =IF(Saldos_Capital_Mensual!I46>0, ROUND(Saldos_Capital_Mensual!I46 * 'Resumen_Cartera'!$Q46, 2), "") | K46: =IF(Saldos_Capital_Mensual!J46>0, ROUND(Saldos_Capital_Mensual!J46 * 'Resumen_Cartera'!$Q46, 2), "") | L46: =IF(Saldos_Capital_Mensual!K46>0, ROUND(Saldos_Capital_Mensual!K46 * 'Resumen_Cartera'!$Q46, 2), "") | M46: =IF(Saldos_Capital_Mensual!L46>0, ROUND(Saldos_Capital_Mensual!L46 * 'Resumen_Cartera'!$Q46, 2), "") | N46: =IF(Saldos_Capital_Mensual!M46>0, ROUND(Saldos_Capital_Mensual!M46 * 'Resumen_Cartera'!$Q46, 2), "") | O46: =IF(Saldos_Capital_Mensual!N46>0, ROUND(Saldos_Capital_Mensual!N46 * 'Resumen_Cartera'!$Q46, 2), "") | P46: =IF(Saldos_Capital_Mensual!O46>0, ROUND(Saldos_Capital_Mensual!O46 * 'Resumen_Cartera'!$Q46, 2), "") | Q46: =IF(Saldos_Capital_Mensual!P46>0, ROUND(Saldos_Capital_Mensual!P46 * 'Resumen_Cartera'!$Q46, 2), "") | ... S46: =IF(Saldos_Capital_Mensual!R46>0, ROUND(Saldos_Capital_Mensual!R46 * 'Resumen_Cartera'!$Q46, 2), "") | U46: =SUM(I46:T46)
A47: 0583-0005 | B47: Soluciones Profesionales para la Industria Alimentaria | C47: 3008 | D47: ACTIVO | E47: 2025-01-09 | F47: 2028-01-09 | G47: 36 | H47: 298137.93 | I47: =ROUND(243409.7 * 'Resumen_Cartera'!$Q47, 2) | J47: =IF(Saldos_Capital_Mensual!I47>0, ROUND(Saldos_Capital_Mensual!I47 * 'Resumen_Cartera'!$Q47, 2), "") | K47: =IF(Saldos_Capital_Mensual!J47>0, ROUND(Saldos_Capital_Mensual!J47 * 'Resumen_Cartera'!$Q47, 2), "") | L47: =IF(Saldos_Capital_Mensual!K47>0, ROUND(Saldos_Capital_Mensual!K47 * 'Resumen_Cartera'!$Q47, 2), "") | M47: =IF(Saldos_Capital_Mensual!L47>0, ROUND(Saldos_Capital_Mensual!L47 * 'Resumen_Cartera'!$Q47, 2), "") | N47: =IF(Saldos_Capital_Mensual!M47>0, ROUND(Saldos_Capital_Mensual!M47 * 'Resumen_Cartera'!$Q47, 2), "") | O47: =IF(Saldos_Capital_Mensual!N47>0, ROUND(Saldos_Capital_Mensual!N47 * 'Resumen_Cartera'!$Q47, 2), "") | P47: =IF(Saldos_Capital_Mensual!O47>0, ROUND(Saldos_Capital_Mensual!O47 * 'Resumen_Cartera'!$Q47, 2), "") | Q47: =IF(Saldos_Capital_Mensual!P47>0, ROUND(Saldos_Capital_Mensual!P47 * 'Resumen_Cartera'!$Q47, 2), "") | ... T47: =IF(Saldos_Capital_Mensual!S47>0, ROUND(Saldos_Capital_Mensual!S47 * 'Resumen_Cartera'!$Q47, 2), "") | U47: =SUM(I47:T47)
A48: 0583-0006 | B48: Soluciones Profesionales para la Industria Alimentaria | C48: Montana | D48: ACTIVO | E48: 2025-11-19 | F48: 2027-11-19 | G48: 24 | H48: 337568.97 | I48: =ROUND(322680.75 * 'Resumen_Cartera'!$Q48, 2) | J48: =IF(Saldos_Capital_Mensual!I48>0, ROUND(Saldos_Capital_Mensual!I48 * 'Resumen_Cartera'!$Q48, 2), "") | K48: =IF(Saldos_Capital_Mensual!J48>0, ROUND(Saldos_Capital_Mensual!J48 * 'Resumen_Cartera'!$Q48, 2), "") | L48: =IF(Saldos_Capital_Mensual!K48>0, ROUND(Saldos_Capital_Mensual!K48 * 'Resumen_Cartera'!$Q48, 2), "") | M48: =IF(Saldos_Capital_Mensual!L48>0, ROUND(Saldos_Capital_Mensual!L48 * 'Resumen_Cartera'!$Q48, 2), "") | N48: =IF(Saldos_Capital_Mensual!M48>0, ROUND(Saldos_Capital_Mensual!M48 * 'Resumen_Cartera'!$Q48, 2), "") | O48: =IF(Saldos_Capital_Mensual!N48>0, ROUND(Saldos_Capital_Mensual!N48 * 'Resumen_Cartera'!$Q48, 2), "") | P48: =IF(Saldos_Capital_Mensual!O48>0, ROUND(Saldos_Capital_Mensual!O48 * 'Resumen_Cartera'!$Q48, 2), "") | Q48: =IF(Saldos_Capital_Mensual!P48>0, ROUND(Saldos_Capital_Mensual!P48 * 'Resumen_Cartera'!$Q48, 2), "") | ... T48: =IF(Saldos_Capital_Mensual!S48>0, ROUND(Saldos_Capital_Mensual!S48 * 'Resumen_Cartera'!$Q48, 2), "") | U48: =SUM(I48:T48)
A49: 0585-0002 | B49: Julio Alberto Ramos de la Mora | C49: Ram 1500 Limited | D49: ACTIVO | E49: 2025-01-08 | F49: 2028-01-08 | G49: 36 | H49: 1139931 | I49: =ROUND(983362.1 * 'Resumen_Cartera'!$Q49, 2) | J49: =IF(Saldos_Capital_Mensual!I49>0, ROUND(Saldos_Capital_Mensual!I49 * 'Resumen_Cartera'!$Q49, 2), "") | K49: =IF(Saldos_Capital_Mensual!J49>0, ROUND(Saldos_Capital_Mensual!J49 * 'Resumen_Cartera'!$Q49, 2), "") | L49: =IF(Saldos_Capital_Mensual!K49>0, ROUND(Saldos_Capital_Mensual!K49 * 'Resumen_Cartera'!$Q49, 2), "") | M49: =IF(Saldos_Capital_Mensual!L49>0, ROUND(Saldos_Capital_Mensual!L49 * 'Resumen_Cartera'!$Q49, 2), "") | N49: =IF(Saldos_Capital_Mensual!M49>0, ROUND(Saldos_Capital_Mensual!M49 * 'Resumen_Cartera'!$Q49, 2), "") | O49: =IF(Saldos_Capital_Mensual!N49>0, ROUND(Saldos_Capital_Mensual!N49 * 'Resumen_Cartera'!$Q49, 2), "") | P49: =IF(Saldos_Capital_Mensual!O49>0, ROUND(Saldos_Capital_Mensual!O49 * 'Resumen_Cartera'!$Q49, 2), "") | Q49: =IF(Saldos_Capital_Mensual!P49>0, ROUND(Saldos_Capital_Mensual!P49 * 'Resumen_Cartera'!$Q49, 2), "") | ... T49: =IF(Saldos_Capital_Mensual!S49>0, ROUND(Saldos_Capital_Mensual!S49 * 'Resumen_Cartera'!$Q49, 2), "") | U49: =SUM(I49:T49)
A50: 0585-0003 | B50: Julio Alberto Ramos de la Mora | C50: Wrangler Rubicon | D50: ACTIVO | E50: 2025-01-17 | F50: 2029-01-17 | G50: 48 | H50: 1014069 | I50: =ROUND(931202.04 * 'Resumen_Cartera'!$Q50, 2) | J50: =IF(Saldos_Capital_Mensual!I50>0, ROUND(Saldos_Capital_Mensual!I50 * 'Resumen_Cartera'!$Q50, 2), "") | K50: =IF(Saldos_Capital_Mensual!J50>0, ROUND(Saldos_Capital_Mensual!J50 * 'Resumen_Cartera'!$Q50, 2), "") | L50: =IF(Saldos_Capital_Mensual!K50>0, ROUND(Saldos_Capital_Mensual!K50 * 'Resumen_Cartera'!$Q50, 2), "") | M50: =IF(Saldos_Capital_Mensual!L50>0, ROUND(Saldos_Capital_Mensual!L50 * 'Resumen_Cartera'!$Q50, 2), "") | N50: =IF(Saldos_Capital_Mensual!M50>0, ROUND(Saldos_Capital_Mensual!M50 * 'Resumen_Cartera'!$Q50, 2), "") | O50: =IF(Saldos_Capital_Mensual!N50>0, ROUND(Saldos_Capital_Mensual!N50 * 'Resumen_Cartera'!$Q50, 2), "") | P50: =IF(Saldos_Capital_Mensual!O50>0, ROUND(Saldos_Capital_Mensual!O50 * 'Resumen_Cartera'!$Q50, 2), "") | Q50: =IF(Saldos_Capital_Mensual!P50>0, ROUND(Saldos_Capital_Mensual!P50 * 'Resumen_Cartera'!$Q50, 2), "") | ... T50: =IF(Saldos_Capital_Mensual!S50>0, ROUND(Saldos_Capital_Mensual!S50 * 'Resumen_Cartera'!$Q50, 2), "") | U50: =SUM(I50:T50)
A51: 0585-0004 | B51: Julio Alberto Ramos de la Mora | C51: Hrv Sport | D51: ACTIVO | E51: 2025-05-28 | F51: 2028-05-28 | G51: 36 | H51: 325810.34 | I51: =ROUND(285496.8 * 'Resumen_Cartera'!$Q51, 2) | J51: =IF(Saldos_Capital_Mensual!I51>0, ROUND(Saldos_Capital_Mensual!I51 * 'Resumen_Cartera'!$Q51, 2), "") | K51: =IF(Saldos_Capital_Mensual!J51>0, ROUND(Saldos_Capital_Mensual!J51 * 'Resumen_Cartera'!$Q51, 2), "") | L51: =IF(Saldos_Capital_Mensual!K51>0, ROUND(Saldos_Capital_Mensual!K51 * 'Resumen_Cartera'!$Q51, 2), "") | M51: =IF(Saldos_Capital_Mensual!L51>0, ROUND(Saldos_Capital_Mensual!L51 * 'Resumen_Cartera'!$Q51, 2), "") | N51: =IF(Saldos_Capital_Mensual!M51>0, ROUND(Saldos_Capital_Mensual!M51 * 'Resumen_Cartera'!$Q51, 2), "") | O51: =IF(Saldos_Capital_Mensual!N51>0, ROUND(Saldos_Capital_Mensual!N51 * 'Resumen_Cartera'!$Q51, 2), "") | P51: =IF(Saldos_Capital_Mensual!O51>0, ROUND(Saldos_Capital_Mensual!O51 * 'Resumen_Cartera'!$Q51, 2), "") | Q51: =IF(Saldos_Capital_Mensual!P51>0, ROUND(Saldos_Capital_Mensual!P51 * 'Resumen_Cartera'!$Q51, 2), "") | ... T51: =IF(Saldos_Capital_Mensual!S51>0, ROUND(Saldos_Capital_Mensual!S51 * 'Resumen_Cartera'!$Q51, 2), "") | U51: =SUM(I51:T51)
A52: 0585-0005 | B52: Julio Alberto Ramos de la Mora | C52: M9 GL HEV | D52: ACTIVO | E52: 2025-12-12 | F52: 2027-12-12 | G52: 24 | H52: 506793.1 | I52: =ROUND(493900.23 * 'Resumen_Cartera'!$Q52, 2) | J52: =IF(Saldos_Capital_Mensual!I52>0, ROUND(Saldos_Capital_Mensual!I52 * 'Resumen_Cartera'!$Q52, 2), "") | K52: =IF(Saldos_Capital_Mensual!J52>0, ROUND(Saldos_Capital_Mensual!J52 * 'Resumen_Cartera'!$Q52, 2), "") | L52: =IF(Saldos_Capital_Mensual!K52>0, ROUND(Saldos_Capital_Mensual!K52 * 'Resumen_Cartera'!$Q52, 2), "") | M52: =IF(Saldos_Capital_Mensual!L52>0, ROUND(Saldos_Capital_Mensual!L52 * 'Resumen_Cartera'!$Q52, 2), "") | N52: =IF(Saldos_Capital_Mensual!M52>0, ROUND(Saldos_Capital_Mensual!M52 * 'Resumen_Cartera'!$Q52, 2), "") | O52: =IF(Saldos_Capital_Mensual!N52>0, ROUND(Saldos_Capital_Mensual!N52 * 'Resumen_Cartera'!$Q52, 2), "") | P52: =IF(Saldos_Capital_Mensual!O52>0, ROUND(Saldos_Capital_Mensual!O52 * 'Resumen_Cartera'!$Q52, 2), "") | Q52: =IF(Saldos_Capital_Mensual!P52>0, ROUND(Saldos_Capital_Mensual!P52 * 'Resumen_Cartera'!$Q52, 2), "") | ... T52: =IF(Saldos_Capital_Mensual!S52>0, ROUND(Saldos_Capital_Mensual!S52 * 'Resumen_Cartera'!$Q52, 2), "") | U52: =SUM(I52:T52)
A53: 0587-0002 | B53: Allioth, S.C. | C53: Grand Cherokee L Summit | D53: ACTIVO | E53: 2026-02-09 | F53: 2027-02-09 | G53: 12 | H53: 548202.59 | J53: =ROUND('Resumen_Cartera'!$K53 * 'Resumen_Cartera'!$Q53, 2) | K53: =IF(Saldos_Capital_Mensual!J53>0, ROUND(Saldos_Capital_Mensual!J53 * 'Resumen_Cartera'!$Q53, 2), "") | L53: =IF(Saldos_Capital_Mensual!K53>0, ROUND(Saldos_Capital_Mensual!K53 * 'Resumen_Cartera'!$Q53, 2), "") | M53: =IF(Saldos_Capital_Mensual!L53>0, ROUND(Saldos_Capital_Mensual!L53 * 'Resumen_Cartera'!$Q53, 2), "") | N53: =IF(Saldos_Capital_Mensual!M53>0, ROUND(Saldos_Capital_Mensual!M53 * 'Resumen_Cartera'!$Q53, 2), "") | O53: =IF(Saldos_Capital_Mensual!N53>0, ROUND(Saldos_Capital_Mensual!N53 * 'Resumen_Cartera'!$Q53, 2), "") | P53: =IF(Saldos_Capital_Mensual!O53>0, ROUND(Saldos_Capital_Mensual!O53 * 'Resumen_Cartera'!$Q53, 2), "") | Q53: =IF(Saldos_Capital_Mensual!P53>0, ROUND(Saldos_Capital_Mensual!P53 * 'Resumen_Cartera'!$Q53, 2), "") | R53: =IF(Saldos_Capital_Mensual!Q53>0, ROUND(Saldos_Capital_Mensual!Q53 * 'Resumen_Cartera'!$Q53, 2), "") | ... T53: =IF(Saldos_Capital_Mensual!S53>0, ROUND(Saldos_Capital_Mensual!S53 * 'Resumen_Cartera'!$Q53, 2), "") | U53: =SUM(I53:T53)
A54: 0591-0002 | B54: Cervantech Servicios Tecnologicos Sc | C54: WRANGLER RUBICON | D54: ACTIVO | E54: 2023-10-27 | F54: 2026-10-27 | G54: 36 | H54: 884068.97 | I54: =ROUND(566086.78 * 'Resumen_Cartera'!$Q54, 2) | J54: =IF(Saldos_Capital_Mensual!I54>0, ROUND(Saldos_Capital_Mensual!I54 * 'Resumen_Cartera'!$Q54, 2), "") | K54: =IF(Saldos_Capital_Mensual!J54>0, ROUND(Saldos_Capital_Mensual!J54 * 'Resumen_Cartera'!$Q54, 2), "") | L54: =IF(Saldos_Capital_Mensual!K54>0, ROUND(Saldos_Capital_Mensual!K54 * 'Resumen_Cartera'!$Q54, 2), "") | M54: =IF(Saldos_Capital_Mensual!L54>0, ROUND(Saldos_Capital_Mensual!L54 * 'Resumen_Cartera'!$Q54, 2), "") | N54: =IF(Saldos_Capital_Mensual!M54>0, ROUND(Saldos_Capital_Mensual!M54 * 'Resumen_Cartera'!$Q54, 2), "") | O54: =IF(Saldos_Capital_Mensual!N54>0, ROUND(Saldos_Capital_Mensual!N54 * 'Resumen_Cartera'!$Q54, 2), "") | P54: =IF(Saldos_Capital_Mensual!O54>0, ROUND(Saldos_Capital_Mensual!O54 * 'Resumen_Cartera'!$Q54, 2), "") | Q54: =IF(Saldos_Capital_Mensual!P54>0, ROUND(Saldos_Capital_Mensual!P54 * 'Resumen_Cartera'!$Q54, 2), "") | U54: =SUM(I54:T54)
A55: 0593-0002 | B55: Metales y Minerales Moa Sa de Cv | C55: Ram 700 SLT Crew Cab | D55: ACTIVO | E55: 2023-07-04 | F55: 2027-07-04 | G55: 48 | H55: 284396.55 | I55: =ROUND(182736.12 * 'Resumen_Cartera'!$Q55, 2) | J55: =IF(Saldos_Capital_Mensual!I55>0, ROUND(Saldos_Capital_Mensual!I55 * 'Resumen_Cartera'!$Q55, 2), "") | K55: =IF(Saldos_Capital_Mensual!J55>0, ROUND(Saldos_Capital_Mensual!J55 * 'Resumen_Cartera'!$Q55, 2), "") | L55: =IF(Saldos_Capital_Mensual!K55>0, ROUND(Saldos_Capital_Mensual!K55 * 'Resumen_Cartera'!$Q55, 2), "") | M55: =IF(Saldos_Capital_Mensual!L55>0, ROUND(Saldos_Capital_Mensual!L55 * 'Resumen_Cartera'!$Q55, 2), "") | N55: =IF(Saldos_Capital_Mensual!M55>0, ROUND(Saldos_Capital_Mensual!M55 * 'Resumen_Cartera'!$Q55, 2), "") | O55: =IF(Saldos_Capital_Mensual!N55>0, ROUND(Saldos_Capital_Mensual!N55 * 'Resumen_Cartera'!$Q55, 2), "") | P55: =IF(Saldos_Capital_Mensual!O55>0, ROUND(Saldos_Capital_Mensual!O55 * 'Resumen_Cartera'!$Q55, 2), "") | Q55: =IF(Saldos_Capital_Mensual!P55>0, ROUND(Saldos_Capital_Mensual!P55 * 'Resumen_Cartera'!$Q55, 2), "") | ... T55: =IF(Saldos_Capital_Mensual!S55>0, ROUND(Saldos_Capital_Mensual!S55 * 'Resumen_Cartera'!$Q55, 2), "") | U55: =SUM(I55:T55)
A56: 0594-0001 | B56: Biotecnologia Estetica Sa de Cv | C56: Mobi Like | D56: ACTIVO | E56: 2023-02-23 | F56: 2027-02-23 | G56: 48 | H56: 188068.97 | I56: =ROUND(104866.53 * 'Resumen_Cartera'!$Q56, 2) | J56: =IF(Saldos_Capital_Mensual!I56>0, ROUND(Saldos_Capital_Mensual!I56 * 'Resumen_Cartera'!$Q56, 2), "") | K56: =IF(Saldos_Capital_Mensual!J56>0, ROUND(Saldos_Capital_Mensual!J56 * 'Resumen_Cartera'!$Q56, 2), "") | L56: =IF(Saldos_Capital_Mensual!K56>0, ROUND(Saldos_Capital_Mensual!K56 * 'Resumen_Cartera'!$Q56, 2), "") | M56: =IF(Saldos_Capital_Mensual!L56>0, ROUND(Saldos_Capital_Mensual!L56 * 'Resumen_Cartera'!$Q56, 2), "") | N56: =IF(Saldos_Capital_Mensual!M56>0, ROUND(Saldos_Capital_Mensual!M56 * 'Resumen_Cartera'!$Q56, 2), "") | O56: =IF(Saldos_Capital_Mensual!N56>0, ROUND(Saldos_Capital_Mensual!N56 * 'Resumen_Cartera'!$Q56, 2), "") | P56: =IF(Saldos_Capital_Mensual!O56>0, ROUND(Saldos_Capital_Mensual!O56 * 'Resumen_Cartera'!$Q56, 2), "") | Q56: =IF(Saldos_Capital_Mensual!P56>0, ROUND(Saldos_Capital_Mensual!P56 * 'Resumen_Cartera'!$Q56, 2), "") | ... T56: =IF(Saldos_Capital_Mensual!S56>0, ROUND(Saldos_Capital_Mensual!S56 * 'Resumen_Cartera'!$Q56, 2), "") | U56: =SUM(I56:T56)
A57: 0596-0004 | B57: Gruas Industriales Lb | C57: Ram 1500 TRX | D57: ACTIVO | E57: 2024-03-22 | F57: 2028-03-22 | G57: 48 | H57: 1355120.7 | I57: =ROUND(1037923.26 * 'Resumen_Cartera'!$Q57, 2) | J57: =IF(Saldos_Capital_Mensual!I57>0, ROUND(Saldos_Capital_Mensual!I57 * 'Resumen_Cartera'!$Q57, 2), "") | K57: =IF(Saldos_Capital_Mensual!J57>0, ROUND(Saldos_Capital_Mensual!J57 * 'Resumen_Cartera'!$Q57, 2), "") | L57: =IF(Saldos_Capital_Mensual!K57>0, ROUND(Saldos_Capital_Mensual!K57 * 'Resumen_Cartera'!$Q57, 2), "") | M57: =IF(Saldos_Capital_Mensual!L57>0, ROUND(Saldos_Capital_Mensual!L57 * 'Resumen_Cartera'!$Q57, 2), "") | N57: =IF(Saldos_Capital_Mensual!M57>0, ROUND(Saldos_Capital_Mensual!M57 * 'Resumen_Cartera'!$Q57, 2), "") | O57: =IF(Saldos_Capital_Mensual!N57>0, ROUND(Saldos_Capital_Mensual!N57 * 'Resumen_Cartera'!$Q57, 2), "") | P57: =IF(Saldos_Capital_Mensual!O57>0, ROUND(Saldos_Capital_Mensual!O57 * 'Resumen_Cartera'!$Q57, 2), "") | Q57: =IF(Saldos_Capital_Mensual!P57>0, ROUND(Saldos_Capital_Mensual!P57 * 'Resumen_Cartera'!$Q57, 2), "") | ... T57: =IF(Saldos_Capital_Mensual!S57>0, ROUND(Saldos_Capital_Mensual!S57 * 'Resumen_Cartera'!$Q57, 2), "") | U57: =SUM(I57:T57)
A58: 0596-0005 | B58: Gruas Industriales Lb Sa de Cv | C58: L200 Glx Gasolina | D58: ACTIVO | E58: 2024-07-19 | F58: 2028-07-19 | G58: 48 | H58: 374235.52 | I58: =ROUND(310989.36 * 'Resumen_Cartera'!$Q58, 2) | J58: =IF(Saldos_Capital_Mensual!I58>0, ROUND(Saldos_Capital_Mensual!I58 * 'Resumen_Cartera'!$Q58, 2), "") | K58: =IF(Saldos_Capital_Mensual!J58>0, ROUND(Saldos_Capital_Mensual!J58 * 'Resumen_Cartera'!$Q58, 2), "") | L58: =IF(Saldos_Capital_Mensual!K58>0, ROUND(Saldos_Capital_Mensual!K58 * 'Resumen_Cartera'!$Q58, 2), "") | M58: =IF(Saldos_Capital_Mensual!L58>0, ROUND(Saldos_Capital_Mensual!L58 * 'Resumen_Cartera'!$Q58, 2), "") | N58: =IF(Saldos_Capital_Mensual!M58>0, ROUND(Saldos_Capital_Mensual!M58 * 'Resumen_Cartera'!$Q58, 2), "") | O58: =IF(Saldos_Capital_Mensual!N58>0, ROUND(Saldos_Capital_Mensual!N58 * 'Resumen_Cartera'!$Q58, 2), "") | P58: =IF(Saldos_Capital_Mensual!O58>0, ROUND(Saldos_Capital_Mensual!O58 * 'Resumen_Cartera'!$Q58, 2), "") | Q58: =IF(Saldos_Capital_Mensual!P58>0, ROUND(Saldos_Capital_Mensual!P58 * 'Resumen_Cartera'!$Q58, 2), "") | ... T58: =IF(Saldos_Capital_Mensual!S58>0, ROUND(Saldos_Capital_Mensual!S58 * 'Resumen_Cartera'!$Q58, 2), "") | U58: =SUM(I58:T58)
A59: 0598-0001 | B59: Digitracking Solution Sa de Cv | C59: Ram 700 Laramie | D59: ACTIVO | E59: 2023-03-15 | F59: 2027-03-15 | G59: 48 | H59: 244336.2 | I59: =ROUND(150056.19 * 'Resumen_Cartera'!$Q59, 2) | J59: =IF(Saldos_Capital_Mensual!I59>0, ROUND(Saldos_Capital_Mensual!I59 * 'Resumen_Cartera'!$Q59, 2), "") | K59: =IF(Saldos_Capital_Mensual!J59>0, ROUND(Saldos_Capital_Mensual!J59 * 'Resumen_Cartera'!$Q59, 2), "") | L59: =IF(Saldos_Capital_Mensual!K59>0, ROUND(Saldos_Capital_Mensual!K59 * 'Resumen_Cartera'!$Q59, 2), "") | M59: =IF(Saldos_Capital_Mensual!L59>0, ROUND(Saldos_Capital_Mensual!L59 * 'Resumen_Cartera'!$Q59, 2), "") | N59: =IF(Saldos_Capital_Mensual!M59>0, ROUND(Saldos_Capital_Mensual!M59 * 'Resumen_Cartera'!$Q59, 2), "") | O59: =IF(Saldos_Capital_Mensual!N59>0, ROUND(Saldos_Capital_Mensual!N59 * 'Resumen_Cartera'!$Q59, 2), "") | P59: =IF(Saldos_Capital_Mensual!O59>0, ROUND(Saldos_Capital_Mensual!O59 * 'Resumen_Cartera'!$Q59, 2), "") | Q59: =IF(Saldos_Capital_Mensual!P59>0, ROUND(Saldos_Capital_Mensual!P59 * 'Resumen_Cartera'!$Q59, 2), "") | ... T59: =IF(Saldos_Capital_Mensual!S59>0, ROUND(Saldos_Capital_Mensual!S59 * 'Resumen_Cartera'!$Q59, 2), "") | U59: =SUM(I59:T59)
A60: 0600-0001 | B60: Dulce Marisol Gonzalez Cuevas | C60: Ram 700 Laramie | D60: ACTIVO | E60: 2023-03-15 | F60: 2027-03-15 | G60: 48 | H60: 209431.03 | I60: =ROUND(114742.68 * 'Resumen_Cartera'!$Q60, 2) | J60: =IF(Saldos_Capital_Mensual!I60>0, ROUND(Saldos_Capital_Mensual!I60 * 'Resumen_Cartera'!$Q60, 2), "") | K60: =IF(Saldos_Capital_Mensual!J60>0, ROUND(Saldos_Capital_Mensual!J60 * 'Resumen_Cartera'!$Q60, 2), "") | L60: =IF(Saldos_Capital_Mensual!K60>0, ROUND(Saldos_Capital_Mensual!K60 * 'Resumen_Cartera'!$Q60, 2), "") | M60: =IF(Saldos_Capital_Mensual!L60>0, ROUND(Saldos_Capital_Mensual!L60 * 'Resumen_Cartera'!$Q60, 2), "") | N60: =IF(Saldos_Capital_Mensual!M60>0, ROUND(Saldos_Capital_Mensual!M60 * 'Resumen_Cartera'!$Q60, 2), "") | O60: =IF(Saldos_Capital_Mensual!N60>0, ROUND(Saldos_Capital_Mensual!N60 * 'Resumen_Cartera'!$Q60, 2), "") | P60: =IF(Saldos_Capital_Mensual!O60>0, ROUND(Saldos_Capital_Mensual!O60 * 'Resumen_Cartera'!$Q60, 2), "") | Q60: =IF(Saldos_Capital_Mensual!P60>0, ROUND(Saldos_Capital_Mensual!P60 * 'Resumen_Cartera'!$Q60, 2), "") | ... T60: =IF(Saldos_Capital_Mensual!S60>0, ROUND(Saldos_Capital_Mensual!S60 * 'Resumen_Cartera'!$Q60, 2), "") | U60: =SUM(I60:T60)
A61: 0603-0002 | B61: Mario Alberto Velasco Santana | C61: Outlander Sport | D61: ACTIVO | E61: 2024-07-30 | F61: 2028-07-30 | G61: 48 | H61: 276258.62 | I61: =ROUND(233409.55 * 'Resumen_Cartera'!$Q61, 2) | J61: =IF(Saldos_Capital_Mensual!I61>0, ROUND(Saldos_Capital_Mensual!I61 * 'Resumen_Cartera'!$Q61, 2), "") | K61: =IF(Saldos_Capital_Mensual!J61>0, ROUND(Saldos_Capital_Mensual!J61 * 'Resumen_Cartera'!$Q61, 2), "") | L61: =IF(Saldos_Capital_Mensual!K61>0, ROUND(Saldos_Capital_Mensual!K61 * 'Resumen_Cartera'!$Q61, 2), "") | M61: =IF(Saldos_Capital_Mensual!L61>0, ROUND(Saldos_Capital_Mensual!L61 * 'Resumen_Cartera'!$Q61, 2), "") | N61: =IF(Saldos_Capital_Mensual!M61>0, ROUND(Saldos_Capital_Mensual!M61 * 'Resumen_Cartera'!$Q61, 2), "") | O61: =IF(Saldos_Capital_Mensual!N61>0, ROUND(Saldos_Capital_Mensual!N61 * 'Resumen_Cartera'!$Q61, 2), "") | P61: =IF(Saldos_Capital_Mensual!O61>0, ROUND(Saldos_Capital_Mensual!O61 * 'Resumen_Cartera'!$Q61, 2), "") | Q61: =IF(Saldos_Capital_Mensual!P61>0, ROUND(Saldos_Capital_Mensual!P61 * 'Resumen_Cartera'!$Q61, 2), "") | ... T61: =IF(Saldos_Capital_Mensual!S61>0, ROUND(Saldos_Capital_Mensual!S61 * 'Resumen_Cartera'!$Q61, 2), "") | U61: =SUM(I61:T61)
A62: 0605-0001 | B62: Nato Arquitectos Sa de Cv | C62: Compass High Altitude | D62: ACTIVO | E62: 2023-03-23 | F62: 2027-03-23 | G62: 48 | H62: 476663.8 | I62: =ROUND(291370.51 * 'Resumen_Cartera'!$Q62, 2) | J62: =IF(Saldos_Capital_Mensual!I62>0, ROUND(Saldos_Capital_Mensual!I62 * 'Resumen_Cartera'!$Q62, 2), "") | K62: =IF(Saldos_Capital_Mensual!J62>0, ROUND(Saldos_Capital_Mensual!J62 * 'Resumen_Cartera'!$Q62, 2), "") | L62: =IF(Saldos_Capital_Mensual!K62>0, ROUND(Saldos_Capital_Mensual!K62 * 'Resumen_Cartera'!$Q62, 2), "") | M62: =IF(Saldos_Capital_Mensual!L62>0, ROUND(Saldos_Capital_Mensual!L62 * 'Resumen_Cartera'!$Q62, 2), "") | N62: =IF(Saldos_Capital_Mensual!M62>0, ROUND(Saldos_Capital_Mensual!M62 * 'Resumen_Cartera'!$Q62, 2), "") | O62: =IF(Saldos_Capital_Mensual!N62>0, ROUND(Saldos_Capital_Mensual!N62 * 'Resumen_Cartera'!$Q62, 2), "") | P62: =IF(Saldos_Capital_Mensual!O62>0, ROUND(Saldos_Capital_Mensual!O62 * 'Resumen_Cartera'!$Q62, 2), "") | Q62: =IF(Saldos_Capital_Mensual!P62>0, ROUND(Saldos_Capital_Mensual!P62 * 'Resumen_Cartera'!$Q62, 2), "") | ... T62: =IF(Saldos_Capital_Mensual!S62>0, ROUND(Saldos_Capital_Mensual!S62 * 'Resumen_Cartera'!$Q62, 2), "") | U62: =SUM(I62:T62)
A63: 0605-0002 | B63: Nato Arquitectos Sa de Cv | C63: Hilux Diesel | D63: ACTIVO | E63: 2025-03-28 | F63: 2027-03-28 | G63: 24 | H63: 384362.07 | I63: =ROUND(270989.94 * 'Resumen_Cartera'!$Q63, 2) | J63: =IF(Saldos_Capital_Mensual!I63>0, ROUND(Saldos_Capital_Mensual!I63 * 'Resumen_Cartera'!$Q63, 2), "") | K63: =IF(Saldos_Capital_Mensual!J63>0, ROUND(Saldos_Capital_Mensual!J63 * 'Resumen_Cartera'!$Q63, 2), "") | L63: =IF(Saldos_Capital_Mensual!K63>0, ROUND(Saldos_Capital_Mensual!K63 * 'Resumen_Cartera'!$Q63, 2), "") | M63: =IF(Saldos_Capital_Mensual!L63>0, ROUND(Saldos_Capital_Mensual!L63 * 'Resumen_Cartera'!$Q63, 2), "") | N63: =IF(Saldos_Capital_Mensual!M63>0, ROUND(Saldos_Capital_Mensual!M63 * 'Resumen_Cartera'!$Q63, 2), "") | O63: =IF(Saldos_Capital_Mensual!N63>0, ROUND(Saldos_Capital_Mensual!N63 * 'Resumen_Cartera'!$Q63, 2), "") | P63: =IF(Saldos_Capital_Mensual!O63>0, ROUND(Saldos_Capital_Mensual!O63 * 'Resumen_Cartera'!$Q63, 2), "") | Q63: =IF(Saldos_Capital_Mensual!P63>0, ROUND(Saldos_Capital_Mensual!P63 * 'Resumen_Cartera'!$Q63, 2), "") | ... T63: =IF(Saldos_Capital_Mensual!S63>0, ROUND(Saldos_Capital_Mensual!S63 * 'Resumen_Cartera'!$Q63, 2), "") | U63: =SUM(I63:T63)
A64: 0605-0003 | B64: Nato Arquitectos Sa de Cv | C64: Ranger Crew Cab 4X4 XLT | D64: ACTIVO | E64: 2026-01-08 | F64: 2028-01-08 | G64: 24 | H64: 507439.65 | I64: =ROUND('Resumen_Cartera'!$K64 * 'Resumen_Cartera'!$Q64, 2) | J64: =IF(Saldos_Capital_Mensual!I64>0, ROUND(Saldos_Capital_Mensual!I64 * 'Resumen_Cartera'!$Q64, 2), "") | K64: =IF(Saldos_Capital_Mensual!J64>0, ROUND(Saldos_Capital_Mensual!J64 * 'Resumen_Cartera'!$Q64, 2), "") | L64: =IF(Saldos_Capital_Mensual!K64>0, ROUND(Saldos_Capital_Mensual!K64 * 'Resumen_Cartera'!$Q64, 2), "") | M64: =IF(Saldos_Capital_Mensual!L64>0, ROUND(Saldos_Capital_Mensual!L64 * 'Resumen_Cartera'!$Q64, 2), "") | N64: =IF(Saldos_Capital_Mensual!M64>0, ROUND(Saldos_Capital_Mensual!M64 * 'Resumen_Cartera'!$Q64, 2), "") | O64: =IF(Saldos_Capital_Mensual!N64>0, ROUND(Saldos_Capital_Mensual!N64 * 'Resumen_Cartera'!$Q64, 2), "") | P64: =IF(Saldos_Capital_Mensual!O64>0, ROUND(Saldos_Capital_Mensual!O64 * 'Resumen_Cartera'!$Q64, 2), "") | Q64: =IF(Saldos_Capital_Mensual!P64>0, ROUND(Saldos_Capital_Mensual!P64 * 'Resumen_Cartera'!$Q64, 2), "") | ... T64: =IF(Saldos_Capital_Mensual!S64>0, ROUND(Saldos_Capital_Mensual!S64 * 'Resumen_Cartera'!$Q64, 2), "") | U64: =SUM(I64:T64)
A65: 0605-0004 | B65: Nato Arquitectos Sa de Cv | C65: COLORADO DOBLE CABINA PAQ. "C" | D65: ACTIVO | E65: 2026-01-08 | F65: 2028-01-08 | G65: 24 | H65: 597353.45 | I65: =ROUND('Resumen_Cartera'!$K65 * 'Resumen_Cartera'!$Q65, 2) | J65: =IF(Saldos_Capital_Mensual!I65>0, ROUND(Saldos_Capital_Mensual!I65 * 'Resumen_Cartera'!$Q65, 2), "") | K65: =IF(Saldos_Capital_Mensual!J65>0, ROUND(Saldos_Capital_Mensual!J65 * 'Resumen_Cartera'!$Q65, 2), "") | L65: =IF(Saldos_Capital_Mensual!K65>0, ROUND(Saldos_Capital_Mensual!K65 * 'Resumen_Cartera'!$Q65, 2), "") | M65: =IF(Saldos_Capital_Mensual!L65>0, ROUND(Saldos_Capital_Mensual!L65 * 'Resumen_Cartera'!$Q65, 2), "") | N65: =IF(Saldos_Capital_Mensual!M65>0, ROUND(Saldos_Capital_Mensual!M65 * 'Resumen_Cartera'!$Q65, 2), "") | O65: =IF(Saldos_Capital_Mensual!N65>0, ROUND(Saldos_Capital_Mensual!N65 * 'Resumen_Cartera'!$Q65, 2), "") | P65: =IF(Saldos_Capital_Mensual!O65>0, ROUND(Saldos_Capital_Mensual!O65 * 'Resumen_Cartera'!$Q65, 2), "") | Q65: =IF(Saldos_Capital_Mensual!P65>0, ROUND(Saldos_Capital_Mensual!P65 * 'Resumen_Cartera'!$Q65, 2), "") | ... T65: =IF(Saldos_Capital_Mensual!S65>0, ROUND(Saldos_Capital_Mensual!S65 * 'Resumen_Cartera'!$Q65, 2), "") | U65: =SUM(I65:T65)
A66: 0606-0002 | B66: Mayoreo Automotriz ML S de Rl de CV | C66: Grand Cherokee 4xE | D66: ACTIVO | E66: 2026-03-17 | F66: 2027-03-17 | G66: 12 | H66: 276706.9 | K66: =ROUND('Resumen_Cartera'!$K66 * 'Resumen_Cartera'!$Q66, 2) | L66: =IF(Saldos_Capital_Mensual!K66>0, ROUND(Saldos_Capital_Mensual!K66 * 'Resumen_Cartera'!$Q66, 2), "") | M66: =IF(Saldos_Capital_Mensual!L66>0, ROUND(Saldos_Capital_Mensual!L66 * 'Resumen_Cartera'!$Q66, 2), "") | N66: =IF(Saldos_Capital_Mensual!M66>0, ROUND(Saldos_Capital_Mensual!M66 * 'Resumen_Cartera'!$Q66, 2), "") | O66: =IF(Saldos_Capital_Mensual!N66>0, ROUND(Saldos_Capital_Mensual!N66 * 'Resumen_Cartera'!$Q66, 2), "") | P66: =IF(Saldos_Capital_Mensual!O66>0, ROUND(Saldos_Capital_Mensual!O66 * 'Resumen_Cartera'!$Q66, 2), "") | Q66: =IF(Saldos_Capital_Mensual!P66>0, ROUND(Saldos_Capital_Mensual!P66 * 'Resumen_Cartera'!$Q66, 2), "") | R66: =IF(Saldos_Capital_Mensual!Q66>0, ROUND(Saldos_Capital_Mensual!Q66 * 'Resumen_Cartera'!$Q66, 2), "") | S66: =IF(Saldos_Capital_Mensual!R66>0, ROUND(Saldos_Capital_Mensual!R66 * 'Resumen_Cartera'!$Q66, 2), "") | T66: =IF(Saldos_Capital_Mensual!S66>0, ROUND(Saldos_Capital_Mensual!S66 * 'Resumen_Cartera'!$Q66, 2), "") | U66: =SUM(I66:T66)
A67: 0607-0004 | B67: Jose Guadalupe Dueñas Lomeli | C67: Rifter Allure Pack | D67: ACTIVO | E67: 2025-12-08 | F67: 2029-12-08 | G67: 48 | H67: 344758.62 | I67: =ROUND(341610.23 * 'Resumen_Cartera'!$Q67, 2) | J67: =IF(Saldos_Capital_Mensual!I67>0, ROUND(Saldos_Capital_Mensual!I67 * 'Resumen_Cartera'!$Q67, 2), "") | K67: =IF(Saldos_Capital_Mensual!J67>0, ROUND(Saldos_Capital_Mensual!J67 * 'Resumen_Cartera'!$Q67, 2), "") | L67: =IF(Saldos_Capital_Mensual!K67>0, ROUND(Saldos_Capital_Mensual!K67 * 'Resumen_Cartera'!$Q67, 2), "") | M67: =IF(Saldos_Capital_Mensual!L67>0, ROUND(Saldos_Capital_Mensual!L67 * 'Resumen_Cartera'!$Q67, 2), "") | N67: =IF(Saldos_Capital_Mensual!M67>0, ROUND(Saldos_Capital_Mensual!M67 * 'Resumen_Cartera'!$Q67, 2), "") | O67: =IF(Saldos_Capital_Mensual!N67>0, ROUND(Saldos_Capital_Mensual!N67 * 'Resumen_Cartera'!$Q67, 2), "") | P67: =IF(Saldos_Capital_Mensual!O67>0, ROUND(Saldos_Capital_Mensual!O67 * 'Resumen_Cartera'!$Q67, 2), "") | Q67: =IF(Saldos_Capital_Mensual!P67>0, ROUND(Saldos_Capital_Mensual!P67 * 'Resumen_Cartera'!$Q67, 2), "") | ... T67: =IF(Saldos_Capital_Mensual!S67>0, ROUND(Saldos_Capital_Mensual!S67 * 'Resumen_Cartera'!$Q67, 2), "") | U67: =SUM(I67:T67)
A68: 0607-0005 | B68: Jose Guadalupe Dueñas Lomeli | C68: Durango Hellcat SRT | D68: ACTIVO | E68: 2026-02-09 | F68: 2029-02-09 | G68: 36 | H68: 1687422.4 | J68: =ROUND('Resumen_Cartera'!$K68 * 'Resumen_Cartera'!$Q68, 2) | K68: =IF(Saldos_Capital_Mensual!J68>0, ROUND(Saldos_Capital_Mensual!J68 * 'Resumen_Cartera'!$Q68, 2), "") | L68: =IF(Saldos_Capital_Mensual!K68>0, ROUND(Saldos_Capital_Mensual!K68 * 'Resumen_Cartera'!$Q68, 2), "") | M68: =IF(Saldos_Capital_Mensual!L68>0, ROUND(Saldos_Capital_Mensual!L68 * 'Resumen_Cartera'!$Q68, 2), "") | N68: =IF(Saldos_Capital_Mensual!M68>0, ROUND(Saldos_Capital_Mensual!M68 * 'Resumen_Cartera'!$Q68, 2), "") | O68: =IF(Saldos_Capital_Mensual!N68>0, ROUND(Saldos_Capital_Mensual!N68 * 'Resumen_Cartera'!$Q68, 2), "") | P68: =IF(Saldos_Capital_Mensual!O68>0, ROUND(Saldos_Capital_Mensual!O68 * 'Resumen_Cartera'!$Q68, 2), "") | Q68: =IF(Saldos_Capital_Mensual!P68>0, ROUND(Saldos_Capital_Mensual!P68 * 'Resumen_Cartera'!$Q68, 2), "") | R68: =IF(Saldos_Capital_Mensual!Q68>0, ROUND(Saldos_Capital_Mensual!Q68 * 'Resumen_Cartera'!$Q68, 2), "") | ... T68: =IF(Saldos_Capital_Mensual!S68>0, ROUND(Saldos_Capital_Mensual!S68 * 'Resumen_Cartera'!$Q68, 2), "") | U68: =SUM(I68:T68)
A69: 0610-0003 | B69: Minelaza | C69: Song Plus | D69: ACTIVO | E69: 2026-04-15 | F69: 2029-04-15 | G69: 36 | H69: 604241.38 | L69: =ROUND('Resumen_Cartera'!$K69 * 'Resumen_Cartera'!$Q69, 2) | M69: =IF(Saldos_Capital_Mensual!L69>0, ROUND(Saldos_Capital_Mensual!L69 * 'Resumen_Cartera'!$Q69, 2), "") | N69: =IF(Saldos_Capital_Mensual!M69>0, ROUND(Saldos_Capital_Mensual!M69 * 'Resumen_Cartera'!$Q69, 2), "") | O69: =IF(Saldos_Capital_Mensual!N69>0, ROUND(Saldos_Capital_Mensual!N69 * 'Resumen_Cartera'!$Q69, 2), "") | P69: =IF(Saldos_Capital_Mensual!O69>0, ROUND(Saldos_Capital_Mensual!O69 * 'Resumen_Cartera'!$Q69, 2), "") | Q69: =IF(Saldos_Capital_Mensual!P69>0, ROUND(Saldos_Capital_Mensual!P69 * 'Resumen_Cartera'!$Q69, 2), "") | R69: =IF(Saldos_Capital_Mensual!Q69>0, ROUND(Saldos_Capital_Mensual!Q69 * 'Resumen_Cartera'!$Q69, 2), "") | S69: =IF(Saldos_Capital_Mensual!R69>0, ROUND(Saldos_Capital_Mensual!R69 * 'Resumen_Cartera'!$Q69, 2), "") | T69: =IF(Saldos_Capital_Mensual!S69>0, ROUND(Saldos_Capital_Mensual!S69 * 'Resumen_Cartera'!$Q69, 2), "") | U69: =SUM(I69:T69)
A70: 0612-0002 | B70: Distribuidora Lopez Moctezuma Sa de Cv | C70: Ram 700 Tradesman | D70: ACTIVO | E70: 2025-09-30 | F70: 2028-09-30 | G70: 36 | H70: 263715.52 | I70: =ROUND(249298.95 * 'Resumen_Cartera'!$Q70, 2) | J70: =IF(Saldos_Capital_Mensual!I70>0, ROUND(Saldos_Capital_Mensual!I70 * 'Resumen_Cartera'!$Q70, 2), "") | K70: =IF(Saldos_Capital_Mensual!J70>0, ROUND(Saldos_Capital_Mensual!J70 * 'Resumen_Cartera'!$Q70, 2), "") | L70: =IF(Saldos_Capital_Mensual!K70>0, ROUND(Saldos_Capital_Mensual!K70 * 'Resumen_Cartera'!$Q70, 2), "") | M70: =IF(Saldos_Capital_Mensual!L70>0, ROUND(Saldos_Capital_Mensual!L70 * 'Resumen_Cartera'!$Q70, 2), "") | N70: =IF(Saldos_Capital_Mensual!M70>0, ROUND(Saldos_Capital_Mensual!M70 * 'Resumen_Cartera'!$Q70, 2), "") | O70: =IF(Saldos_Capital_Mensual!N70>0, ROUND(Saldos_Capital_Mensual!N70 * 'Resumen_Cartera'!$Q70, 2), "") | P70: =IF(Saldos_Capital_Mensual!O70>0, ROUND(Saldos_Capital_Mensual!O70 * 'Resumen_Cartera'!$Q70, 2), "") | Q70: =IF(Saldos_Capital_Mensual!P70>0, ROUND(Saldos_Capital_Mensual!P70 * 'Resumen_Cartera'!$Q70, 2), "") | ... T70: =IF(Saldos_Capital_Mensual!S70>0, ROUND(Saldos_Capital_Mensual!S70 * 'Resumen_Cartera'!$Q70, 2), "") | U70: =SUM(I70:T70)
A71: 0612-0003 | B71: Distribuidora Lopez Moctezuma Sa de Cv | C71: Mitsubishi Xpander 2026 | D71: ACTIVO | E71: 2026-07-31 | F71: 2030-07-31 | G71: 48 | H71: 348642.15 | O71: =ROUND('Resumen_Cartera'!$K71 * 'Resumen_Cartera'!$Q71, 2) | P71: =IF(Saldos_Capital_Mensual!O71>0, ROUND(Saldos_Capital_Mensual!O71 * 'Resumen_Cartera'!$Q71, 2), "") | Q71: =IF(Saldos_Capital_Mensual!P71>0, ROUND(Saldos_Capital_Mensual!P71 * 'Resumen_Cartera'!$Q71, 2), "") | R71: =IF(Saldos_Capital_Mensual!Q71>0, ROUND(Saldos_Capital_Mensual!Q71 * 'Resumen_Cartera'!$Q71, 2), "") | S71: =IF(Saldos_Capital_Mensual!R71>0, ROUND(Saldos_Capital_Mensual!R71 * 'Resumen_Cartera'!$Q71, 2), "") | T71: =IF(Saldos_Capital_Mensual!S71>0, ROUND(Saldos_Capital_Mensual!S71 * 'Resumen_Cartera'!$Q71, 2), "") | U71: =SUM(I71:T71)
A72: 0616-0002 | B72: Commerce and Technology Connection Sas de Cv | C72: RAM 700 BIG HORN | D72: ACTIVO | E72: 2024-02-16 | F72: 2027-02-16 | G72: 36 | H72: 191327.59 | I72: =ROUND(128256.81 * 'Resumen_Cartera'!$Q72, 2) | J72: =IF(Saldos_Capital_Mensual!I72>0, ROUND(Saldos_Capital_Mensual!I72 * 'Resumen_Cartera'!$Q72, 2), "") | K72: =IF(Saldos_Capital_Mensual!J72>0, ROUND(Saldos_Capital_Mensual!J72 * 'Resumen_Cartera'!$Q72, 2), "") | L72: =IF(Saldos_Capital_Mensual!K72>0, ROUND(Saldos_Capital_Mensual!K72 * 'Resumen_Cartera'!$Q72, 2), "") | M72: =IF(Saldos_Capital_Mensual!L72>0, ROUND(Saldos_Capital_Mensual!L72 * 'Resumen_Cartera'!$Q72, 2), "") | N72: =IF(Saldos_Capital_Mensual!M72>0, ROUND(Saldos_Capital_Mensual!M72 * 'Resumen_Cartera'!$Q72, 2), "") | O72: =IF(Saldos_Capital_Mensual!N72>0, ROUND(Saldos_Capital_Mensual!N72 * 'Resumen_Cartera'!$Q72, 2), "") | P72: =IF(Saldos_Capital_Mensual!O72>0, ROUND(Saldos_Capital_Mensual!O72 * 'Resumen_Cartera'!$Q72, 2), "") | Q72: =IF(Saldos_Capital_Mensual!P72>0, ROUND(Saldos_Capital_Mensual!P72 * 'Resumen_Cartera'!$Q72, 2), "") | ... T72: =IF(Saldos_Capital_Mensual!S72>0, ROUND(Saldos_Capital_Mensual!S72 * 'Resumen_Cartera'!$Q72, 2), "") | U72: =SUM(I72:T72)
A73: 0616-0003 | B73: Commerce and Technology Connection Sas de Cv | C73: FASTBACK | D73: ACTIVO | E73: 2024-02-23 | F73: 2027-02-23 | G73: 36 | H73: 295146.55 | I73: =ROUND(190869.28 * 'Resumen_Cartera'!$Q73, 2) | J73: =IF(Saldos_Capital_Mensual!I73>0, ROUND(Saldos_Capital_Mensual!I73 * 'Resumen_Cartera'!$Q73, 2), "") | K73: =IF(Saldos_Capital_Mensual!J73>0, ROUND(Saldos_Capital_Mensual!J73 * 'Resumen_Cartera'!$Q73, 2), "") | L73: =IF(Saldos_Capital_Mensual!K73>0, ROUND(Saldos_Capital_Mensual!K73 * 'Resumen_Cartera'!$Q73, 2), "") | M73: =IF(Saldos_Capital_Mensual!L73>0, ROUND(Saldos_Capital_Mensual!L73 * 'Resumen_Cartera'!$Q73, 2), "") | N73: =IF(Saldos_Capital_Mensual!M73>0, ROUND(Saldos_Capital_Mensual!M73 * 'Resumen_Cartera'!$Q73, 2), "") | O73: =IF(Saldos_Capital_Mensual!N73>0, ROUND(Saldos_Capital_Mensual!N73 * 'Resumen_Cartera'!$Q73, 2), "") | P73: =IF(Saldos_Capital_Mensual!O73>0, ROUND(Saldos_Capital_Mensual!O73 * 'Resumen_Cartera'!$Q73, 2), "") | Q73: =IF(Saldos_Capital_Mensual!P73>0, ROUND(Saldos_Capital_Mensual!P73 * 'Resumen_Cartera'!$Q73, 2), "") | ... T73: =IF(Saldos_Capital_Mensual!S73>0, ROUND(Saldos_Capital_Mensual!S73 * 'Resumen_Cartera'!$Q73, 2), "") | U73: =SUM(I73:T73)
A74: 0616-0004 | B74: Commerce and Technology Connections Sas de Cv | C74: Argo | D74: ACTIVO | E74: 2024-05-20 | F74: 2027-05-20 | G74: 36 | H74: 178448.27 | I74: =ROUND(118425.58 * 'Resumen_Cartera'!$Q74, 2) | J74: =IF(Saldos_Capital_Mensual!I74>0, ROUND(Saldos_Capital_Mensual!I74 * 'Resumen_Cartera'!$Q74, 2), "") | K74: =IF(Saldos_Capital_Mensual!J74>0, ROUND(Saldos_Capital_Mensual!J74 * 'Resumen_Cartera'!$Q74, 2), "") | L74: =IF(Saldos_Capital_Mensual!K74>0, ROUND(Saldos_Capital_Mensual!K74 * 'Resumen_Cartera'!$Q74, 2), "") | M74: =IF(Saldos_Capital_Mensual!L74>0, ROUND(Saldos_Capital_Mensual!L74 * 'Resumen_Cartera'!$Q74, 2), "") | N74: =IF(Saldos_Capital_Mensual!M74>0, ROUND(Saldos_Capital_Mensual!M74 * 'Resumen_Cartera'!$Q74, 2), "") | O74: =IF(Saldos_Capital_Mensual!N74>0, ROUND(Saldos_Capital_Mensual!N74 * 'Resumen_Cartera'!$Q74, 2), "") | P74: =IF(Saldos_Capital_Mensual!O74>0, ROUND(Saldos_Capital_Mensual!O74 * 'Resumen_Cartera'!$Q74, 2), "") | Q74: =IF(Saldos_Capital_Mensual!P74>0, ROUND(Saldos_Capital_Mensual!P74 * 'Resumen_Cartera'!$Q74, 2), "") | ... T74: =IF(Saldos_Capital_Mensual!S74>0, ROUND(Saldos_Capital_Mensual!S74 * 'Resumen_Cartera'!$Q74, 2), "") | U74: =SUM(I74:T74)
A75: 0616-0005 | B75: Commerce and Technology Connection Sas de Cv | C75: Journey GT | D75: ACTIVO | E75: 2024-07-30 | F75: 2027-07-30 | G75: 36 | H75: 397008.62 | I75: =ROUND(293627.86 * 'Resumen_Cartera'!$Q75, 2) | J75: =IF(Saldos_Capital_Mensual!I75>0, ROUND(Saldos_Capital_Mensual!I75 * 'Resumen_Cartera'!$Q75, 2), "") | K75: =IF(Saldos_Capital_Mensual!J75>0, ROUND(Saldos_Capital_Mensual!J75 * 'Resumen_Cartera'!$Q75, 2), "") | L75: =IF(Saldos_Capital_Mensual!K75>0, ROUND(Saldos_Capital_Mensual!K75 * 'Resumen_Cartera'!$Q75, 2), "") | M75: =IF(Saldos_Capital_Mensual!L75>0, ROUND(Saldos_Capital_Mensual!L75 * 'Resumen_Cartera'!$Q75, 2), "") | N75: =IF(Saldos_Capital_Mensual!M75>0, ROUND(Saldos_Capital_Mensual!M75 * 'Resumen_Cartera'!$Q75, 2), "") | O75: =IF(Saldos_Capital_Mensual!N75>0, ROUND(Saldos_Capital_Mensual!N75 * 'Resumen_Cartera'!$Q75, 2), "") | P75: =IF(Saldos_Capital_Mensual!O75>0, ROUND(Saldos_Capital_Mensual!O75 * 'Resumen_Cartera'!$Q75, 2), "") | Q75: =IF(Saldos_Capital_Mensual!P75>0, ROUND(Saldos_Capital_Mensual!P75 * 'Resumen_Cartera'!$Q75, 2), "") | ... T75: =IF(Saldos_Capital_Mensual!S75>0, ROUND(Saldos_Capital_Mensual!S75 * 'Resumen_Cartera'!$Q75, 2), "") | U75: =SUM(I75:T75)
A76: 0618-0001 | B76: Juan Pablo Rodriguez Garcia | C76: JT MOJAVE | D76: ACTIVO | E76: 2023-06-16 | F76: 2027-06-16 | G76: 48 | H76: 1138887.9 | I76: =ROUND(722525.06 * 'Resumen_Cartera'!$Q76, 2) | J76: =IF(Saldos_Capital_Mensual!I76>0, ROUND(Saldos_Capital_Mensual!I76 * 'Resumen_Cartera'!$Q76, 2), "") | K76: =IF(Saldos_Capital_Mensual!J76>0, ROUND(Saldos_Capital_Mensual!J76 * 'Resumen_Cartera'!$Q76, 2), "") | L76: =IF(Saldos_Capital_Mensual!K76>0, ROUND(Saldos_Capital_Mensual!K76 * 'Resumen_Cartera'!$Q76, 2), "") | M76: =IF(Saldos_Capital_Mensual!L76>0, ROUND(Saldos_Capital_Mensual!L76 * 'Resumen_Cartera'!$Q76, 2), "") | N76: =IF(Saldos_Capital_Mensual!M76>0, ROUND(Saldos_Capital_Mensual!M76 * 'Resumen_Cartera'!$Q76, 2), "") | O76: =IF(Saldos_Capital_Mensual!N76>0, ROUND(Saldos_Capital_Mensual!N76 * 'Resumen_Cartera'!$Q76, 2), "") | P76: =IF(Saldos_Capital_Mensual!O76>0, ROUND(Saldos_Capital_Mensual!O76 * 'Resumen_Cartera'!$Q76, 2), "") | Q76: =IF(Saldos_Capital_Mensual!P76>0, ROUND(Saldos_Capital_Mensual!P76 * 'Resumen_Cartera'!$Q76, 2), "") | ... T76: =IF(Saldos_Capital_Mensual!S76>0, ROUND(Saldos_Capital_Mensual!S76 * 'Resumen_Cartera'!$Q76, 2), "") | U76: =SUM(I76:T76)
A77: 0619-0002 | B77: Horacio de la Vega Flores | C77: Bronco Sport | D77: ACTIVO | E77: 2025-09-11 | F77: 2028-09-11 | G77: 36 | H77: 470689.65 | I77: =ROUND(437800.24 * 'Resumen_Cartera'!$Q77, 2) | J77: =IF(Saldos_Capital_Mensual!I77>0, ROUND(Saldos_Capital_Mensual!I77 * 'Resumen_Cartera'!$Q77, 2), "") | K77: =IF(Saldos_Capital_Mensual!J77>0, ROUND(Saldos_Capital_Mensual!J77 * 'Resumen_Cartera'!$Q77, 2), "") | L77: =IF(Saldos_Capital_Mensual!K77>0, ROUND(Saldos_Capital_Mensual!K77 * 'Resumen_Cartera'!$Q77, 2), "") | M77: =IF(Saldos_Capital_Mensual!L77>0, ROUND(Saldos_Capital_Mensual!L77 * 'Resumen_Cartera'!$Q77, 2), "") | N77: =IF(Saldos_Capital_Mensual!M77>0, ROUND(Saldos_Capital_Mensual!M77 * 'Resumen_Cartera'!$Q77, 2), "") | O77: =IF(Saldos_Capital_Mensual!N77>0, ROUND(Saldos_Capital_Mensual!N77 * 'Resumen_Cartera'!$Q77, 2), "") | P77: =IF(Saldos_Capital_Mensual!O77>0, ROUND(Saldos_Capital_Mensual!O77 * 'Resumen_Cartera'!$Q77, 2), "") | Q77: =IF(Saldos_Capital_Mensual!P77>0, ROUND(Saldos_Capital_Mensual!P77 * 'Resumen_Cartera'!$Q77, 2), "") | ... T77: =IF(Saldos_Capital_Mensual!S77>0, ROUND(Saldos_Capital_Mensual!S77 * 'Resumen_Cartera'!$Q77, 2), "") | U77: =SUM(I77:T77)
A78: 0620-0001 | B78: Desarrollos Romo Srl de Cv | C78: RAM 700 BIG HORN | D78: ACTIVO | E78: 2023-07-20 | F78: 2027-07-20 | G78: 48 | H78: 279232.76 | I78: =ROUND(185801.82 * 'Resumen_Cartera'!$Q78, 2) | J78: =IF(Saldos_Capital_Mensual!I78>0, ROUND(Saldos_Capital_Mensual!I78 * 'Resumen_Cartera'!$Q78, 2), "") | K78: =IF(Saldos_Capital_Mensual!J78>0, ROUND(Saldos_Capital_Mensual!J78 * 'Resumen_Cartera'!$Q78, 2), "") | L78: =IF(Saldos_Capital_Mensual!K78>0, ROUND(Saldos_Capital_Mensual!K78 * 'Resumen_Cartera'!$Q78, 2), "") | M78: =IF(Saldos_Capital_Mensual!L78>0, ROUND(Saldos_Capital_Mensual!L78 * 'Resumen_Cartera'!$Q78, 2), "") | N78: =IF(Saldos_Capital_Mensual!M78>0, ROUND(Saldos_Capital_Mensual!M78 * 'Resumen_Cartera'!$Q78, 2), "") | O78: =IF(Saldos_Capital_Mensual!N78>0, ROUND(Saldos_Capital_Mensual!N78 * 'Resumen_Cartera'!$Q78, 2), "") | P78: =IF(Saldos_Capital_Mensual!O78>0, ROUND(Saldos_Capital_Mensual!O78 * 'Resumen_Cartera'!$Q78, 2), "") | Q78: =IF(Saldos_Capital_Mensual!P78>0, ROUND(Saldos_Capital_Mensual!P78 * 'Resumen_Cartera'!$Q78, 2), "") | ... T78: =IF(Saldos_Capital_Mensual!S78>0, ROUND(Saldos_Capital_Mensual!S78 * 'Resumen_Cartera'!$Q78, 2), "") | U78: =SUM(I78:T78)
A79: 0620-0002 | B79: Desarrollos Romo Srl de Cv | C79: RAM 700 BIG HORN | D79: ACTIVO | E79: 2023-07-20 | F79: 2027-07-20 | G79: 48 | H79: 279232.76 | I79: =ROUND(185801.82 * 'Resumen_Cartera'!$Q79, 2) | J79: =IF(Saldos_Capital_Mensual!I79>0, ROUND(Saldos_Capital_Mensual!I79 * 'Resumen_Cartera'!$Q79, 2), "") | K79: =IF(Saldos_Capital_Mensual!J79>0, ROUND(Saldos_Capital_Mensual!J79 * 'Resumen_Cartera'!$Q79, 2), "") | L79: =IF(Saldos_Capital_Mensual!K79>0, ROUND(Saldos_Capital_Mensual!K79 * 'Resumen_Cartera'!$Q79, 2), "") | M79: =IF(Saldos_Capital_Mensual!L79>0, ROUND(Saldos_Capital_Mensual!L79 * 'Resumen_Cartera'!$Q79, 2), "") | N79: =IF(Saldos_Capital_Mensual!M79>0, ROUND(Saldos_Capital_Mensual!M79 * 'Resumen_Cartera'!$Q79, 2), "") | O79: =IF(Saldos_Capital_Mensual!N79>0, ROUND(Saldos_Capital_Mensual!N79 * 'Resumen_Cartera'!$Q79, 2), "") | P79: =IF(Saldos_Capital_Mensual!O79>0, ROUND(Saldos_Capital_Mensual!O79 * 'Resumen_Cartera'!$Q79, 2), "") | Q79: =IF(Saldos_Capital_Mensual!P79>0, ROUND(Saldos_Capital_Mensual!P79 * 'Resumen_Cartera'!$Q79, 2), "") | ... T79: =IF(Saldos_Capital_Mensual!S79>0, ROUND(Saldos_Capital_Mensual!S79 * 'Resumen_Cartera'!$Q79, 2), "") | U79: =SUM(I79:T79)
A80: 0621-0008 | B80: Luis Alberto Ponce Ruiz | C80: Hilux | D80: ACTIVO | E80: 2025-10-30 | F80: 2026-10-30 | G80: 12 | H80: 256758.62 | I80: =ROUND(208874.88 * 'Resumen_Cartera'!$Q80, 2) | J80: =IF(Saldos_Capital_Mensual!I80>0, ROUND(Saldos_Capital_Mensual!I80 * 'Resumen_Cartera'!$Q80, 2), "") | K80: =IF(Saldos_Capital_Mensual!J80>0, ROUND(Saldos_Capital_Mensual!J80 * 'Resumen_Cartera'!$Q80, 2), "") | L80: =IF(Saldos_Capital_Mensual!K80>0, ROUND(Saldos_Capital_Mensual!K80 * 'Resumen_Cartera'!$Q80, 2), "") | M80: =IF(Saldos_Capital_Mensual!L80>0, ROUND(Saldos_Capital_Mensual!L80 * 'Resumen_Cartera'!$Q80, 2), "") | N80: =IF(Saldos_Capital_Mensual!M80>0, ROUND(Saldos_Capital_Mensual!M80 * 'Resumen_Cartera'!$Q80, 2), "") | O80: =IF(Saldos_Capital_Mensual!N80>0, ROUND(Saldos_Capital_Mensual!N80 * 'Resumen_Cartera'!$Q80, 2), "") | P80: =IF(Saldos_Capital_Mensual!O80>0, ROUND(Saldos_Capital_Mensual!O80 * 'Resumen_Cartera'!$Q80, 2), "") | Q80: =IF(Saldos_Capital_Mensual!P80>0, ROUND(Saldos_Capital_Mensual!P80 * 'Resumen_Cartera'!$Q80, 2), "") | U80: =SUM(I80:T80)
A81: 0623-0001 | B81: Seguridad y Automatismos Profesionales de Occidente S de SRL de Cv | C81: RAM 700 BIG HORN | D81: ACTIVO | E81: 2023-07-31 | F81: 2027-07-31 | G81: 48 | H81: 283112.07 | I81: =ROUND(185655.38 * 'Resumen_Cartera'!$Q81, 2) | J81: =IF(Saldos_Capital_Mensual!I81>0, ROUND(Saldos_Capital_Mensual!I81 * 'Resumen_Cartera'!$Q81, 2), "") | K81: =IF(Saldos_Capital_Mensual!J81>0, ROUND(Saldos_Capital_Mensual!J81 * 'Resumen_Cartera'!$Q81, 2), "") | L81: =IF(Saldos_Capital_Mensual!K81>0, ROUND(Saldos_Capital_Mensual!K81 * 'Resumen_Cartera'!$Q81, 2), "") | M81: =IF(Saldos_Capital_Mensual!L81>0, ROUND(Saldos_Capital_Mensual!L81 * 'Resumen_Cartera'!$Q81, 2), "") | N81: =IF(Saldos_Capital_Mensual!M81>0, ROUND(Saldos_Capital_Mensual!M81 * 'Resumen_Cartera'!$Q81, 2), "") | O81: =IF(Saldos_Capital_Mensual!N81>0, ROUND(Saldos_Capital_Mensual!N81 * 'Resumen_Cartera'!$Q81, 2), "") | P81: =IF(Saldos_Capital_Mensual!O81>0, ROUND(Saldos_Capital_Mensual!O81 * 'Resumen_Cartera'!$Q81, 2), "") | Q81: =IF(Saldos_Capital_Mensual!P81>0, ROUND(Saldos_Capital_Mensual!P81 * 'Resumen_Cartera'!$Q81, 2), "") | ... T81: =IF(Saldos_Capital_Mensual!S81>0, ROUND(Saldos_Capital_Mensual!S81 * 'Resumen_Cartera'!$Q81, 2), "") | U81: =SUM(I81:T81)
A82: 0626-0001 | B82: Hugo Ceja Moreno | C82: JT MOJAVE | D82: ACTIVO | E82: 2023-08-18 | F82: 2027-08-18 | G82: 48 | H82: 595810.34 | I82: =ROUND(387181.73 * 'Resumen_Cartera'!$Q82, 2) | J82: =IF(Saldos_Capital_Mensual!I82>0, ROUND(Saldos_Capital_Mensual!I82 * 'Resumen_Cartera'!$Q82, 2), "") | K82: =IF(Saldos_Capital_Mensual!J82>0, ROUND(Saldos_Capital_Mensual!J82 * 'Resumen_Cartera'!$Q82, 2), "") | L82: =IF(Saldos_Capital_Mensual!K82>0, ROUND(Saldos_Capital_Mensual!K82 * 'Resumen_Cartera'!$Q82, 2), "") | M82: =IF(Saldos_Capital_Mensual!L82>0, ROUND(Saldos_Capital_Mensual!L82 * 'Resumen_Cartera'!$Q82, 2), "") | N82: =IF(Saldos_Capital_Mensual!M82>0, ROUND(Saldos_Capital_Mensual!M82 * 'Resumen_Cartera'!$Q82, 2), "") | O82: =IF(Saldos_Capital_Mensual!N82>0, ROUND(Saldos_Capital_Mensual!N82 * 'Resumen_Cartera'!$Q82, 2), "") | P82: =IF(Saldos_Capital_Mensual!O82>0, ROUND(Saldos_Capital_Mensual!O82 * 'Resumen_Cartera'!$Q82, 2), "") | Q82: =IF(Saldos_Capital_Mensual!P82>0, ROUND(Saldos_Capital_Mensual!P82 * 'Resumen_Cartera'!$Q82, 2), "") | ... T82: =IF(Saldos_Capital_Mensual!S82>0, ROUND(Saldos_Capital_Mensual!S82 * 'Resumen_Cartera'!$Q82, 2), "") | U82: =SUM(I82:T82)
A83: 0632-0004 | B83: Art & Sourcing Sa de Cv | C83: Ram 700 Tradesman | D83: ACTIVO | E83: 2025-05-15 | F83: 2029-05-15 | G83: 48 | H83: 286215.52 | I83: =ROUND(263292.79 * 'Resumen_Cartera'!$Q83, 2) | J83: =IF(Saldos_Capital_Mensual!I83>0, ROUND(Saldos_Capital_Mensual!I83 * 'Resumen_Cartera'!$Q83, 2), "") | K83: =IF(Saldos_Capital_Mensual!J83>0, ROUND(Saldos_Capital_Mensual!J83 * 'Resumen_Cartera'!$Q83, 2), "") | L83: =IF(Saldos_Capital_Mensual!K83>0, ROUND(Saldos_Capital_Mensual!K83 * 'Resumen_Cartera'!$Q83, 2), "") | M83: =IF(Saldos_Capital_Mensual!L83>0, ROUND(Saldos_Capital_Mensual!L83 * 'Resumen_Cartera'!$Q83, 2), "") | N83: =IF(Saldos_Capital_Mensual!M83>0, ROUND(Saldos_Capital_Mensual!M83 * 'Resumen_Cartera'!$Q83, 2), "") | O83: =IF(Saldos_Capital_Mensual!N83>0, ROUND(Saldos_Capital_Mensual!N83 * 'Resumen_Cartera'!$Q83, 2), "") | P83: =IF(Saldos_Capital_Mensual!O83>0, ROUND(Saldos_Capital_Mensual!O83 * 'Resumen_Cartera'!$Q83, 2), "") | Q83: =IF(Saldos_Capital_Mensual!P83>0, ROUND(Saldos_Capital_Mensual!P83 * 'Resumen_Cartera'!$Q83, 2), "") | ... T83: =IF(Saldos_Capital_Mensual!S83>0, ROUND(Saldos_Capital_Mensual!S83 * 'Resumen_Cartera'!$Q83, 2), "") | U83: =SUM(I83:T83)
A84: 0632-0005 | B84: Art & Sourcing Sa de Cv | C84: Ram 700 | D84: ACTIVO | E84: 2025-11-25 | F84: 2027-11-25 | G84: 24 | H84: 244758.62 | I84: =ROUND(233418.47 * 'Resumen_Cartera'!$Q84, 2) | J84: =IF(Saldos_Capital_Mensual!I84>0, ROUND(Saldos_Capital_Mensual!I84 * 'Resumen_Cartera'!$Q84, 2), "") | K84: =IF(Saldos_Capital_Mensual!J84>0, ROUND(Saldos_Capital_Mensual!J84 * 'Resumen_Cartera'!$Q84, 2), "") | L84: =IF(Saldos_Capital_Mensual!K84>0, ROUND(Saldos_Capital_Mensual!K84 * 'Resumen_Cartera'!$Q84, 2), "") | M84: =IF(Saldos_Capital_Mensual!L84>0, ROUND(Saldos_Capital_Mensual!L84 * 'Resumen_Cartera'!$Q84, 2), "") | N84: =IF(Saldos_Capital_Mensual!M84>0, ROUND(Saldos_Capital_Mensual!M84 * 'Resumen_Cartera'!$Q84, 2), "") | O84: =IF(Saldos_Capital_Mensual!N84>0, ROUND(Saldos_Capital_Mensual!N84 * 'Resumen_Cartera'!$Q84, 2), "") | P84: =IF(Saldos_Capital_Mensual!O84>0, ROUND(Saldos_Capital_Mensual!O84 * 'Resumen_Cartera'!$Q84, 2), "") | Q84: =IF(Saldos_Capital_Mensual!P84>0, ROUND(Saldos_Capital_Mensual!P84 * 'Resumen_Cartera'!$Q84, 2), "") | ... T84: =IF(Saldos_Capital_Mensual!S84>0, ROUND(Saldos_Capital_Mensual!S84 * 'Resumen_Cartera'!$Q84, 2), "") | U84: =SUM(I84:T84)
A85: 0632-0006 | B85: Art & Sourcing Sa de Cv | C85: Mirage | D85: ACTIVO | E85: 2025-11-25 | F85: 2027-11-25 | G85: 24 | H85: 206553.1 | I85: =ROUND(196976.13 * 'Resumen_Cartera'!$Q85, 2) | J85: =IF(Saldos_Capital_Mensual!I85>0, ROUND(Saldos_Capital_Mensual!I85 * 'Resumen_Cartera'!$Q85, 2), "") | K85: =IF(Saldos_Capital_Mensual!J85>0, ROUND(Saldos_Capital_Mensual!J85 * 'Resumen_Cartera'!$Q85, 2), "") | L85: =IF(Saldos_Capital_Mensual!K85>0, ROUND(Saldos_Capital_Mensual!K85 * 'Resumen_Cartera'!$Q85, 2), "") | M85: =IF(Saldos_Capital_Mensual!L85>0, ROUND(Saldos_Capital_Mensual!L85 * 'Resumen_Cartera'!$Q85, 2), "") | N85: =IF(Saldos_Capital_Mensual!M85>0, ROUND(Saldos_Capital_Mensual!M85 * 'Resumen_Cartera'!$Q85, 2), "") | O85: =IF(Saldos_Capital_Mensual!N85>0, ROUND(Saldos_Capital_Mensual!N85 * 'Resumen_Cartera'!$Q85, 2), "") | P85: =IF(Saldos_Capital_Mensual!O85>0, ROUND(Saldos_Capital_Mensual!O85 * 'Resumen_Cartera'!$Q85, 2), "") | Q85: =IF(Saldos_Capital_Mensual!P85>0, ROUND(Saldos_Capital_Mensual!P85 * 'Resumen_Cartera'!$Q85, 2), "") | ... T85: =IF(Saldos_Capital_Mensual!S85>0, ROUND(Saldos_Capital_Mensual!S85 * 'Resumen_Cartera'!$Q85, 2), "") | U85: =SUM(I85:T85)
A86: 0632-0007 | B86: Art & Sourcing Sa de Cv | C86: JAC Camión X350 2026 | D86: ACTIVO | E86: 2026-08-24 | F86: 2028-08-24 | G86: 24 | H86: 417241.38 | P86: =ROUND('Resumen_Cartera'!$K86 * 'Resumen_Cartera'!$Q86, 2) | Q86: =IF(Saldos_Capital_Mensual!P86>0, ROUND(Saldos_Capital_Mensual!P86 * 'Resumen_Cartera'!$Q86, 2), "") | R86: =IF(Saldos_Capital_Mensual!Q86>0, ROUND(Saldos_Capital_Mensual!Q86 * 'Resumen_Cartera'!$Q86, 2), "") | S86: =IF(Saldos_Capital_Mensual!R86>0, ROUND(Saldos_Capital_Mensual!R86 * 'Resumen_Cartera'!$Q86, 2), "") | T86: =IF(Saldos_Capital_Mensual!S86>0, ROUND(Saldos_Capital_Mensual!S86 * 'Resumen_Cartera'!$Q86, 2), "") | U86: =SUM(I86:T86)
A87: 0634-0001 | B87: Jose de Jesus Vergara Rivera | C87: NP 300 Chasis Cabina TDI | D87: ACTIVO | E87: 2023-09-28 | F87: 2027-09-28 | G87: 48 | H87: 306827.58 | I87: =ROUND(214263.2 * 'Resumen_Cartera'!$Q87, 2) | J87: =IF(Saldos_Capital_Mensual!I87>0, ROUND(Saldos_Capital_Mensual!I87 * 'Resumen_Cartera'!$Q87, 2), "") | K87: =IF(Saldos_Capital_Mensual!J87>0, ROUND(Saldos_Capital_Mensual!J87 * 'Resumen_Cartera'!$Q87, 2), "") | L87: =IF(Saldos_Capital_Mensual!K87>0, ROUND(Saldos_Capital_Mensual!K87 * 'Resumen_Cartera'!$Q87, 2), "") | M87: =IF(Saldos_Capital_Mensual!L87>0, ROUND(Saldos_Capital_Mensual!L87 * 'Resumen_Cartera'!$Q87, 2), "") | N87: =IF(Saldos_Capital_Mensual!M87>0, ROUND(Saldos_Capital_Mensual!M87 * 'Resumen_Cartera'!$Q87, 2), "") | O87: =IF(Saldos_Capital_Mensual!N87>0, ROUND(Saldos_Capital_Mensual!N87 * 'Resumen_Cartera'!$Q87, 2), "") | P87: =IF(Saldos_Capital_Mensual!O87>0, ROUND(Saldos_Capital_Mensual!O87 * 'Resumen_Cartera'!$Q87, 2), "") | Q87: =IF(Saldos_Capital_Mensual!P87>0, ROUND(Saldos_Capital_Mensual!P87 * 'Resumen_Cartera'!$Q87, 2), "") | ... T87: =IF(Saldos_Capital_Mensual!S87>0, ROUND(Saldos_Capital_Mensual!S87 * 'Resumen_Cartera'!$Q87, 2), "") | U87: =SUM(I87:T87)
A88: 0634-0002 | B88: Jose de Jesus Vergara Rivera | C88: 700 Tradesman | D88: ACTIVO | E88: 2025-10-09 | F88: 2029-10-09 | G88: 48 | H88: 298629.31 | I88: =ROUND(291441.04 * 'Resumen_Cartera'!$Q88, 2) | J88: =IF(Saldos_Capital_Mensual!I88>0, ROUND(Saldos_Capital_Mensual!I88 * 'Resumen_Cartera'!$Q88, 2), "") | K88: =IF(Saldos_Capital_Mensual!J88>0, ROUND(Saldos_Capital_Mensual!J88 * 'Resumen_Cartera'!$Q88, 2), "") | L88: =IF(Saldos_Capital_Mensual!K88>0, ROUND(Saldos_Capital_Mensual!K88 * 'Resumen_Cartera'!$Q88, 2), "") | M88: =IF(Saldos_Capital_Mensual!L88>0, ROUND(Saldos_Capital_Mensual!L88 * 'Resumen_Cartera'!$Q88, 2), "") | N88: =IF(Saldos_Capital_Mensual!M88>0, ROUND(Saldos_Capital_Mensual!M88 * 'Resumen_Cartera'!$Q88, 2), "") | O88: =IF(Saldos_Capital_Mensual!N88>0, ROUND(Saldos_Capital_Mensual!N88 * 'Resumen_Cartera'!$Q88, 2), "") | P88: =IF(Saldos_Capital_Mensual!O88>0, ROUND(Saldos_Capital_Mensual!O88 * 'Resumen_Cartera'!$Q88, 2), "") | Q88: =IF(Saldos_Capital_Mensual!P88>0, ROUND(Saldos_Capital_Mensual!P88 * 'Resumen_Cartera'!$Q88, 2), "") | ... T88: =IF(Saldos_Capital_Mensual!S88>0, ROUND(Saldos_Capital_Mensual!S88 * 'Resumen_Cartera'!$Q88, 2), "") | U88: =SUM(I88:T88)
A89: 0635-0003 | B89: Ankara Food Services Sa de CV | C89: Glc 350 E | D89: ACTIVO | E89: 2025-03-21 | F89: 2028-03-21 | G89: 36 | H89: 1176983.2 | I89: =ROUND(949453.56 * 'Resumen_Cartera'!$Q89, 2) | J89: =IF(Saldos_Capital_Mensual!I89>0, ROUND(Saldos_Capital_Mensual!I89 * 'Resumen_Cartera'!$Q89, 2), "") | K89: =IF(Saldos_Capital_Mensual!J89>0, ROUND(Saldos_Capital_Mensual!J89 * 'Resumen_Cartera'!$Q89, 2), "") | L89: =IF(Saldos_Capital_Mensual!K89>0, ROUND(Saldos_Capital_Mensual!K89 * 'Resumen_Cartera'!$Q89, 2), "") | M89: =IF(Saldos_Capital_Mensual!L89>0, ROUND(Saldos_Capital_Mensual!L89 * 'Resumen_Cartera'!$Q89, 2), "") | N89: =IF(Saldos_Capital_Mensual!M89>0, ROUND(Saldos_Capital_Mensual!M89 * 'Resumen_Cartera'!$Q89, 2), "") | O89: =IF(Saldos_Capital_Mensual!N89>0, ROUND(Saldos_Capital_Mensual!N89 * 'Resumen_Cartera'!$Q89, 2), "") | P89: =IF(Saldos_Capital_Mensual!O89>0, ROUND(Saldos_Capital_Mensual!O89 * 'Resumen_Cartera'!$Q89, 2), "") | Q89: =IF(Saldos_Capital_Mensual!P89>0, ROUND(Saldos_Capital_Mensual!P89 * 'Resumen_Cartera'!$Q89, 2), "") | ... T89: =IF(Saldos_Capital_Mensual!S89>0, ROUND(Saldos_Capital_Mensual!S89 * 'Resumen_Cartera'!$Q89, 2), "") | U89: =SUM(I89:T89)
A90: 0635-0004 | B90: Ankara Food Services Sa de CV | C90: Partner | D90: ACTIVO | E90: 2025-04-29 | F90: 2028-04-29 | G90: 36 | H90: 292675.68 | I90: =ROUND(242402.92 * 'Resumen_Cartera'!$Q90, 2) | J90: =IF(Saldos_Capital_Mensual!I90>0, ROUND(Saldos_Capital_Mensual!I90 * 'Resumen_Cartera'!$Q90, 2), "") | K90: =IF(Saldos_Capital_Mensual!J90>0, ROUND(Saldos_Capital_Mensual!J90 * 'Resumen_Cartera'!$Q90, 2), "") | L90: =IF(Saldos_Capital_Mensual!K90>0, ROUND(Saldos_Capital_Mensual!K90 * 'Resumen_Cartera'!$Q90, 2), "") | M90: =IF(Saldos_Capital_Mensual!L90>0, ROUND(Saldos_Capital_Mensual!L90 * 'Resumen_Cartera'!$Q90, 2), "") | N90: =IF(Saldos_Capital_Mensual!M90>0, ROUND(Saldos_Capital_Mensual!M90 * 'Resumen_Cartera'!$Q90, 2), "") | O90: =IF(Saldos_Capital_Mensual!N90>0, ROUND(Saldos_Capital_Mensual!N90 * 'Resumen_Cartera'!$Q90, 2), "") | P90: =IF(Saldos_Capital_Mensual!O90>0, ROUND(Saldos_Capital_Mensual!O90 * 'Resumen_Cartera'!$Q90, 2), "") | Q90: =IF(Saldos_Capital_Mensual!P90>0, ROUND(Saldos_Capital_Mensual!P90 * 'Resumen_Cartera'!$Q90, 2), "") | ... T90: =IF(Saldos_Capital_Mensual!S90>0, ROUND(Saldos_Capital_Mensual!S90 * 'Resumen_Cartera'!$Q90, 2), "") | U90: =SUM(I90:T90)
A91: 0635-0005 | B91: Ankara Food Services Sa de CV | C91: Manager | D91: ACTIVO | E91: 2025-04-29 | F91: 2028-04-29 | G91: 36 | H91: 452623.78 | I91: =ROUND(374876.79 * 'Resumen_Cartera'!$Q91, 2) | J91: =IF(Saldos_Capital_Mensual!I91>0, ROUND(Saldos_Capital_Mensual!I91 * 'Resumen_Cartera'!$Q91, 2), "") | K91: =IF(Saldos_Capital_Mensual!J91>0, ROUND(Saldos_Capital_Mensual!J91 * 'Resumen_Cartera'!$Q91, 2), "") | L91: =IF(Saldos_Capital_Mensual!K91>0, ROUND(Saldos_Capital_Mensual!K91 * 'Resumen_Cartera'!$Q91, 2), "") | M91: =IF(Saldos_Capital_Mensual!L91>0, ROUND(Saldos_Capital_Mensual!L91 * 'Resumen_Cartera'!$Q91, 2), "") | N91: =IF(Saldos_Capital_Mensual!M91>0, ROUND(Saldos_Capital_Mensual!M91 * 'Resumen_Cartera'!$Q91, 2), "") | O91: =IF(Saldos_Capital_Mensual!N91>0, ROUND(Saldos_Capital_Mensual!N91 * 'Resumen_Cartera'!$Q91, 2), "") | P91: =IF(Saldos_Capital_Mensual!O91>0, ROUND(Saldos_Capital_Mensual!O91 * 'Resumen_Cartera'!$Q91, 2), "") | Q91: =IF(Saldos_Capital_Mensual!P91>0, ROUND(Saldos_Capital_Mensual!P91 * 'Resumen_Cartera'!$Q91, 2), "") | ... T91: =IF(Saldos_Capital_Mensual!S91>0, ROUND(Saldos_Capital_Mensual!S91 * 'Resumen_Cartera'!$Q91, 2), "") | U91: =SUM(I91:T91)
A92: 0635-0006 | B92: Ankara Food Services Sa de CV | C92: Mobi | D92: ACTIVO | E92: 2025-06-17 | F92: 2027-06-17 | G92: 24 | H92: 149051.72 | I92: =ROUND(114548.16 * 'Resumen_Cartera'!$Q92, 2) | J92: =IF(Saldos_Capital_Mensual!I92>0, ROUND(Saldos_Capital_Mensual!I92 * 'Resumen_Cartera'!$Q92, 2), "") | K92: =IF(Saldos_Capital_Mensual!J92>0, ROUND(Saldos_Capital_Mensual!J92 * 'Resumen_Cartera'!$Q92, 2), "") | L92: =IF(Saldos_Capital_Mensual!K92>0, ROUND(Saldos_Capital_Mensual!K92 * 'Resumen_Cartera'!$Q92, 2), "") | M92: =IF(Saldos_Capital_Mensual!L92>0, ROUND(Saldos_Capital_Mensual!L92 * 'Resumen_Cartera'!$Q92, 2), "") | N92: =IF(Saldos_Capital_Mensual!M92>0, ROUND(Saldos_Capital_Mensual!M92 * 'Resumen_Cartera'!$Q92, 2), "") | O92: =IF(Saldos_Capital_Mensual!N92>0, ROUND(Saldos_Capital_Mensual!N92 * 'Resumen_Cartera'!$Q92, 2), "") | P92: =IF(Saldos_Capital_Mensual!O92>0, ROUND(Saldos_Capital_Mensual!O92 * 'Resumen_Cartera'!$Q92, 2), "") | Q92: =IF(Saldos_Capital_Mensual!P92>0, ROUND(Saldos_Capital_Mensual!P92 * 'Resumen_Cartera'!$Q92, 2), "") | ... T92: =IF(Saldos_Capital_Mensual!S92>0, ROUND(Saldos_Capital_Mensual!S92 * 'Resumen_Cartera'!$Q92, 2), "") | U92: =SUM(I92:T92)
A93: 0635-0007 | B93: Ankara Food Services Sa de CV | C93: Mobi | D93: ACTIVO | E93: 2025-06-17 | F93: 2027-06-17 | G93: 24 | H93: 149051.72 | I93: =ROUND(114548.16 * 'Resumen_Cartera'!$Q93, 2) | J93: =IF(Saldos_Capital_Mensual!I93>0, ROUND(Saldos_Capital_Mensual!I93 * 'Resumen_Cartera'!$Q93, 2), "") | K93: =IF(Saldos_Capital_Mensual!J93>0, ROUND(Saldos_Capital_Mensual!J93 * 'Resumen_Cartera'!$Q93, 2), "") | L93: =IF(Saldos_Capital_Mensual!K93>0, ROUND(Saldos_Capital_Mensual!K93 * 'Resumen_Cartera'!$Q93, 2), "") | M93: =IF(Saldos_Capital_Mensual!L93>0, ROUND(Saldos_Capital_Mensual!L93 * 'Resumen_Cartera'!$Q93, 2), "") | N93: =IF(Saldos_Capital_Mensual!M93>0, ROUND(Saldos_Capital_Mensual!M93 * 'Resumen_Cartera'!$Q93, 2), "") | O93: =IF(Saldos_Capital_Mensual!N93>0, ROUND(Saldos_Capital_Mensual!N93 * 'Resumen_Cartera'!$Q93, 2), "") | P93: =IF(Saldos_Capital_Mensual!O93>0, ROUND(Saldos_Capital_Mensual!O93 * 'Resumen_Cartera'!$Q93, 2), "") | Q93: =IF(Saldos_Capital_Mensual!P93>0, ROUND(Saldos_Capital_Mensual!P93 * 'Resumen_Cartera'!$Q93, 2), "") | ... T93: =IF(Saldos_Capital_Mensual!S93>0, ROUND(Saldos_Capital_Mensual!S93 * 'Resumen_Cartera'!$Q93, 2), "") | U93: =SUM(I93:T93)
A94: 0635-0008 | B94: Ankara Food Services Sa de CV | C94: Wrangler 4 XE | D94: ACTIVO | E94: 2025-10-31 | F94: 2029-10-31 | G94: 48 | H94: 737534.48 | I94: =ROUND(717759.42 * 'Resumen_Cartera'!$Q94, 2) | J94: =IF(Saldos_Capital_Mensual!I94>0, ROUND(Saldos_Capital_Mensual!I94 * 'Resumen_Cartera'!$Q94, 2), "") | K94: =IF(Saldos_Capital_Mensual!J94>0, ROUND(Saldos_Capital_Mensual!J94 * 'Resumen_Cartera'!$Q94, 2), "") | L94: =IF(Saldos_Capital_Mensual!K94>0, ROUND(Saldos_Capital_Mensual!K94 * 'Resumen_Cartera'!$Q94, 2), "") | M94: =IF(Saldos_Capital_Mensual!L94>0, ROUND(Saldos_Capital_Mensual!L94 * 'Resumen_Cartera'!$Q94, 2), "") | N94: =IF(Saldos_Capital_Mensual!M94>0, ROUND(Saldos_Capital_Mensual!M94 * 'Resumen_Cartera'!$Q94, 2), "") | O94: =IF(Saldos_Capital_Mensual!N94>0, ROUND(Saldos_Capital_Mensual!N94 * 'Resumen_Cartera'!$Q94, 2), "") | P94: =IF(Saldos_Capital_Mensual!O94>0, ROUND(Saldos_Capital_Mensual!O94 * 'Resumen_Cartera'!$Q94, 2), "") | Q94: =IF(Saldos_Capital_Mensual!P94>0, ROUND(Saldos_Capital_Mensual!P94 * 'Resumen_Cartera'!$Q94, 2), "") | ... T94: =IF(Saldos_Capital_Mensual!S94>0, ROUND(Saldos_Capital_Mensual!S94 * 'Resumen_Cartera'!$Q94, 2), "") | U94: =SUM(I94:T94)
A95: 0640-0001 | B95: Marco Abner Hernand Barragan | C95: RIFTER | D95: ACTIVO | E95: 2023-12-13 | F95: 2027-12-13 | G95: 48 | H95: 401818.97 | I95: =ROUND(295359.09 * 'Resumen_Cartera'!$Q95, 2) | J95: =IF(Saldos_Capital_Mensual!I95>0, ROUND(Saldos_Capital_Mensual!I95 * 'Resumen_Cartera'!$Q95, 2), "") | K95: =IF(Saldos_Capital_Mensual!J95>0, ROUND(Saldos_Capital_Mensual!J95 * 'Resumen_Cartera'!$Q95, 2), "") | L95: =IF(Saldos_Capital_Mensual!K95>0, ROUND(Saldos_Capital_Mensual!K95 * 'Resumen_Cartera'!$Q95, 2), "") | M95: =IF(Saldos_Capital_Mensual!L95>0, ROUND(Saldos_Capital_Mensual!L95 * 'Resumen_Cartera'!$Q95, 2), "") | N95: =IF(Saldos_Capital_Mensual!M95>0, ROUND(Saldos_Capital_Mensual!M95 * 'Resumen_Cartera'!$Q95, 2), "") | O95: =IF(Saldos_Capital_Mensual!N95>0, ROUND(Saldos_Capital_Mensual!N95 * 'Resumen_Cartera'!$Q95, 2), "") | P95: =IF(Saldos_Capital_Mensual!O95>0, ROUND(Saldos_Capital_Mensual!O95 * 'Resumen_Cartera'!$Q95, 2), "") | Q95: =IF(Saldos_Capital_Mensual!P95>0, ROUND(Saldos_Capital_Mensual!P95 * 'Resumen_Cartera'!$Q95, 2), "") | ... T95: =IF(Saldos_Capital_Mensual!S95>0, ROUND(Saldos_Capital_Mensual!S95 * 'Resumen_Cartera'!$Q95, 2), "") | U95: =SUM(I95:T95)
A96: 0641-0001 | B96: Agrideaz Sa de Cv | C96: Pulse Audace | D96: ACTIVO | E96: 2023-11-30 | F96: 2026-11-30 | G96: 36 | H96: 227724.14 | I96: =ROUND(172778.08 * 'Resumen_Cartera'!$Q96, 2) | J96: =IF(Saldos_Capital_Mensual!I96>0, ROUND(Saldos_Capital_Mensual!I96 * 'Resumen_Cartera'!$Q96, 2), "") | K96: =IF(Saldos_Capital_Mensual!J96>0, ROUND(Saldos_Capital_Mensual!J96 * 'Resumen_Cartera'!$Q96, 2), "") | L96: =IF(Saldos_Capital_Mensual!K96>0, ROUND(Saldos_Capital_Mensual!K96 * 'Resumen_Cartera'!$Q96, 2), "") | M96: =IF(Saldos_Capital_Mensual!L96>0, ROUND(Saldos_Capital_Mensual!L96 * 'Resumen_Cartera'!$Q96, 2), "") | N96: =IF(Saldos_Capital_Mensual!M96>0, ROUND(Saldos_Capital_Mensual!M96 * 'Resumen_Cartera'!$Q96, 2), "") | O96: =IF(Saldos_Capital_Mensual!N96>0, ROUND(Saldos_Capital_Mensual!N96 * 'Resumen_Cartera'!$Q96, 2), "") | P96: =IF(Saldos_Capital_Mensual!O96>0, ROUND(Saldos_Capital_Mensual!O96 * 'Resumen_Cartera'!$Q96, 2), "") | Q96: =IF(Saldos_Capital_Mensual!P96>0, ROUND(Saldos_Capital_Mensual!P96 * 'Resumen_Cartera'!$Q96, 2), "") | R96: =IF(Saldos_Capital_Mensual!Q96>0, ROUND(Saldos_Capital_Mensual!Q96 * 'Resumen_Cartera'!$Q96, 2), "") | U96: =SUM(I96:T96)
A97: 0641-0002 | B97: Agrideaz Sa de Cv | C97: MOBI | D97: ACTIVO | E97: 2023-11-30 | F97: 2026-11-30 | G97: 36 | H97: 141206.9 | I97: =ROUND(107367.28 * 'Resumen_Cartera'!$Q97, 2) | J97: =IF(Saldos_Capital_Mensual!I97>0, ROUND(Saldos_Capital_Mensual!I97 * 'Resumen_Cartera'!$Q97, 2), "") | K97: =IF(Saldos_Capital_Mensual!J97>0, ROUND(Saldos_Capital_Mensual!J97 * 'Resumen_Cartera'!$Q97, 2), "") | L97: =IF(Saldos_Capital_Mensual!K97>0, ROUND(Saldos_Capital_Mensual!K97 * 'Resumen_Cartera'!$Q97, 2), "") | M97: =IF(Saldos_Capital_Mensual!L97>0, ROUND(Saldos_Capital_Mensual!L97 * 'Resumen_Cartera'!$Q97, 2), "") | N97: =IF(Saldos_Capital_Mensual!M97>0, ROUND(Saldos_Capital_Mensual!M97 * 'Resumen_Cartera'!$Q97, 2), "") | O97: =IF(Saldos_Capital_Mensual!N97>0, ROUND(Saldos_Capital_Mensual!N97 * 'Resumen_Cartera'!$Q97, 2), "") | P97: =IF(Saldos_Capital_Mensual!O97>0, ROUND(Saldos_Capital_Mensual!O97 * 'Resumen_Cartera'!$Q97, 2), "") | Q97: =IF(Saldos_Capital_Mensual!P97>0, ROUND(Saldos_Capital_Mensual!P97 * 'Resumen_Cartera'!$Q97, 2), "") | R97: =IF(Saldos_Capital_Mensual!Q97>0, ROUND(Saldos_Capital_Mensual!Q97 * 'Resumen_Cartera'!$Q97, 2), "") | U97: =SUM(I97:T97)
A98: 0642-0001 | B98: Incubadora de Occidente Sa de Cv | C98: GRAND CHEROKEE LIMITED | D98: ACTIVO | E98: 2023-12-22 | F98: 2027-12-22 | G98: 48 | H98: 884488.33 | I98: =ROUND(713219.34 * 'Resumen_Cartera'!$Q98, 2) | J98: =IF(Saldos_Capital_Mensual!I98>0, ROUND(Saldos_Capital_Mensual!I98 * 'Resumen_Cartera'!$Q98, 2), "") | K98: =IF(Saldos_Capital_Mensual!J98>0, ROUND(Saldos_Capital_Mensual!J98 * 'Resumen_Cartera'!$Q98, 2), "") | L98: =IF(Saldos_Capital_Mensual!K98>0, ROUND(Saldos_Capital_Mensual!K98 * 'Resumen_Cartera'!$Q98, 2), "") | M98: =IF(Saldos_Capital_Mensual!L98>0, ROUND(Saldos_Capital_Mensual!L98 * 'Resumen_Cartera'!$Q98, 2), "") | N98: =IF(Saldos_Capital_Mensual!M98>0, ROUND(Saldos_Capital_Mensual!M98 * 'Resumen_Cartera'!$Q98, 2), "") | O98: =IF(Saldos_Capital_Mensual!N98>0, ROUND(Saldos_Capital_Mensual!N98 * 'Resumen_Cartera'!$Q98, 2), "") | P98: =IF(Saldos_Capital_Mensual!O98>0, ROUND(Saldos_Capital_Mensual!O98 * 'Resumen_Cartera'!$Q98, 2), "") | Q98: =IF(Saldos_Capital_Mensual!P98>0, ROUND(Saldos_Capital_Mensual!P98 * 'Resumen_Cartera'!$Q98, 2), "") | ... T98: =IF(Saldos_Capital_Mensual!S98>0, ROUND(Saldos_Capital_Mensual!S98 * 'Resumen_Cartera'!$Q98, 2), "") | U98: =SUM(I98:T98)
A99: 0644-0005 | B99: Bakaya S.A.P.I. | C99: i118 | D99: ACTIVO | E99: 2025-12-10 | F99: 2028-12-10 | G99: 36 | H99: 639620.69 | I99: =ROUND(633065.59 * 'Resumen_Cartera'!$Q99, 2) | J99: =IF(Saldos_Capital_Mensual!I99>0, ROUND(Saldos_Capital_Mensual!I99 * 'Resumen_Cartera'!$Q99, 2), "") | K99: =IF(Saldos_Capital_Mensual!J99>0, ROUND(Saldos_Capital_Mensual!J99 * 'Resumen_Cartera'!$Q99, 2), "") | L99: =IF(Saldos_Capital_Mensual!K99>0, ROUND(Saldos_Capital_Mensual!K99 * 'Resumen_Cartera'!$Q99, 2), "") | M99: =IF(Saldos_Capital_Mensual!L99>0, ROUND(Saldos_Capital_Mensual!L99 * 'Resumen_Cartera'!$Q99, 2), "") | N99: =IF(Saldos_Capital_Mensual!M99>0, ROUND(Saldos_Capital_Mensual!M99 * 'Resumen_Cartera'!$Q99, 2), "") | O99: =IF(Saldos_Capital_Mensual!N99>0, ROUND(Saldos_Capital_Mensual!N99 * 'Resumen_Cartera'!$Q99, 2), "") | P99: =IF(Saldos_Capital_Mensual!O99>0, ROUND(Saldos_Capital_Mensual!O99 * 'Resumen_Cartera'!$Q99, 2), "") | Q99: =IF(Saldos_Capital_Mensual!P99>0, ROUND(Saldos_Capital_Mensual!P99 * 'Resumen_Cartera'!$Q99, 2), "") | ... T99: =IF(Saldos_Capital_Mensual!S99>0, ROUND(Saldos_Capital_Mensual!S99 * 'Resumen_Cartera'!$Q99, 2), "") | U99: =SUM(I99:T99)
A100: 0644-0006 | B100: Bkaya S.A.P.I. | C100: Highlander XLE | D100: ACTIVO | E100: 2026-02-25 | F100: 2029-02-25 | G100: 36 | H100: 754162.07 | J100: =ROUND('Resumen_Cartera'!$K100 * 'Resumen_Cartera'!$Q100, 2) | K100: =IF(Saldos_Capital_Mensual!J100>0, ROUND(Saldos_Capital_Mensual!J100 * 'Resumen_Cartera'!$Q100, 2), "") | L100: =IF(Saldos_Capital_Mensual!K100>0, ROUND(Saldos_Capital_Mensual!K100 * 'Resumen_Cartera'!$Q100, 2), "") | M100: =IF(Saldos_Capital_Mensual!L100>0, ROUND(Saldos_Capital_Mensual!L100 * 'Resumen_Cartera'!$Q100, 2), "") | N100: =IF(Saldos_Capital_Mensual!M100>0, ROUND(Saldos_Capital_Mensual!M100 * 'Resumen_Cartera'!$Q100, 2), "") | O100: =IF(Saldos_Capital_Mensual!N100>0, ROUND(Saldos_Capital_Mensual!N100 * 'Resumen_Cartera'!$Q100, 2), "") | P100: =IF(Saldos_Capital_Mensual!O100>0, ROUND(Saldos_Capital_Mensual!O100 * 'Resumen_Cartera'!$Q100, 2), "") | Q100: =IF(Saldos_Capital_Mensual!P100>0, ROUND(Saldos_Capital_Mensual!P100 * 'Resumen_Cartera'!$Q100, 2), "") | R100: =IF(Saldos_Capital_Mensual!Q100>0, ROUND(Saldos_Capital_Mensual!Q100 * 'Resumen_Cartera'!$Q100, 2), "") | ... T100: =IF(Saldos_Capital_Mensual!S100>0, ROUND(Saldos_Capital_Mensual!S100 * 'Resumen_Cartera'!$Q100, 2), "") | U100: =SUM(I100:T100)
A101: 0645-0001 | B101: Armando Duran Rubio | C101: Ram 1500 Bighorn | D101: ACTIVO | E101: 2023-12-28 | F101: 2027-12-28 | G101: 48 | H101: 665448.27 | I101: =ROUND(495476.08 * 'Resumen_Cartera'!$Q101, 2) | J101: =IF(Saldos_Capital_Mensual!I101>0, ROUND(Saldos_Capital_Mensual!I101 * 'Resumen_Cartera'!$Q101, 2), "") | K101: =IF(Saldos_Capital_Mensual!J101>0, ROUND(Saldos_Capital_Mensual!J101 * 'Resumen_Cartera'!$Q101, 2), "") | L101: =IF(Saldos_Capital_Mensual!K101>0, ROUND(Saldos_Capital_Mensual!K101 * 'Resumen_Cartera'!$Q101, 2), "") | M101: =IF(Saldos_Capital_Mensual!L101>0, ROUND(Saldos_Capital_Mensual!L101 * 'Resumen_Cartera'!$Q101, 2), "") | N101: =IF(Saldos_Capital_Mensual!M101>0, ROUND(Saldos_Capital_Mensual!M101 * 'Resumen_Cartera'!$Q101, 2), "") | O101: =IF(Saldos_Capital_Mensual!N101>0, ROUND(Saldos_Capital_Mensual!N101 * 'Resumen_Cartera'!$Q101, 2), "") | P101: =IF(Saldos_Capital_Mensual!O101>0, ROUND(Saldos_Capital_Mensual!O101 * 'Resumen_Cartera'!$Q101, 2), "") | Q101: =IF(Saldos_Capital_Mensual!P101>0, ROUND(Saldos_Capital_Mensual!P101 * 'Resumen_Cartera'!$Q101, 2), "") | ... T101: =IF(Saldos_Capital_Mensual!S101>0, ROUND(Saldos_Capital_Mensual!S101 * 'Resumen_Cartera'!$Q101, 2), "") | U101: =SUM(I101:T101)
...

Sheet Intereses_Residual_Mensual
A1: O-LEASING · UNA APP DE ORANGE CREW · Intereses de Valor Residual Devengados (NIF C-15)
A2: Acumulación y devengo mensual con fórmulas vivas sobre el saldo activo del residual · Auditoría Financiera NIF C-15 / IFRS 16 · Desarrollado por Orange Crew
A4: ID_Contrato | B4: Cliente | C4: Vehiculo | D4: Estatus | E4: Fecha_Alta | F4: Fecha_Vencimiento | G4: Plazo | H4: Residual_Pactado | I4: 2026-01 | J4: 2026-02 | K4: 2026-03 | L4: 2026-04 | M4: 2026-05 | N4: 2026-06 | O4: 2026-07 | P4: 2026-08 | Q4: 2026-09 | R4: 2026-10 | S4: 2026-11 | T4: 2026-12 | U4: Total_Devengado_Residual
A5: 0326-0003 | B5: Alberto Vázquez Solorio | C5: Volkswagen Tiguan R-Line 2026 | D5: ACTIVO | E5: 2026-09-16 | F5: 2030-09-16 | G5: 48 | H5: 180650.93 | Q5: =ROUND('Resumen_Cartera'!$U5 * 'Resumen_Cartera'!$Q5, 2) | R5: =IF(Saldo_Residual_Activo!Q5>0, ROUND(Saldo_Residual_Activo!Q5 * 'Resumen_Cartera'!$Q5, 2), "") | S5: =IF(Saldo_Residual_Activo!R5>0, ROUND(Saldo_Residual_Activo!R5 * 'Resumen_Cartera'!$Q5, 2), "") | T5: =IF(Saldo_Residual_Activo!S5>0, ROUND(Saldo_Residual_Activo!S5 * 'Resumen_Cartera'!$Q5, 2), "") | U5: =SUM(I5:T5)
A6: 0472-0003 | B6: Miguel Zazueta Beltrán | C6: Jeep Grand Cherokee | D6: ACTIVO | E6: 2026-02-03 | F6: 2029-02-03 | G6: 36 | H6: 121743.36 | J6: =ROUND('Resumen_Cartera'!$U6 * 'Resumen_Cartera'!$Q6, 2) | K6: =IF(Saldo_Residual_Activo!J6>0, ROUND(Saldo_Residual_Activo!J6 * 'Resumen_Cartera'!$Q6, 2), "") | L6: =IF(Saldo_Residual_Activo!K6>0, ROUND(Saldo_Residual_Activo!K6 * 'Resumen_Cartera'!$Q6, 2), "") | M6: =IF(Saldo_Residual_Activo!L6>0, ROUND(Saldo_Residual_Activo!L6 * 'Resumen_Cartera'!$Q6, 2), "") | N6: =IF(Saldo_Residual_Activo!M6>0, ROUND(Saldo_Residual_Activo!M6 * 'Resumen_Cartera'!$Q6, 2), "") | O6: =IF(Saldo_Residual_Activo!N6>0, ROUND(Saldo_Residual_Activo!N6 * 'Resumen_Cartera'!$Q6, 2), "") | P6: =IF(Saldo_Residual_Activo!O6>0, ROUND(Saldo_Residual_Activo!O6 * 'Resumen_Cartera'!$Q6, 2), "") | Q6: =IF(Saldo_Residual_Activo!P6>0, ROUND(Saldo_Residual_Activo!P6 * 'Resumen_Cartera'!$Q6, 2), "") | R6: =IF(Saldo_Residual_Activo!Q6>0, ROUND(Saldo_Residual_Activo!Q6 * 'Resumen_Cartera'!$Q6, 2), "") | ... T6: =IF(Saldo_Residual_Activo!S6>0, ROUND(Saldo_Residual_Activo!S6 * 'Resumen_Cartera'!$Q6, 2), "") | U6: =SUM(I6:T6)
A7: 0504-0004 | B7: Oscar Ivan Lozano Terriquez | C7: 700 BIGHORN "S" CREW CAB MT | D7: ACTIVO | E7: 2026-01-05 | F7: 2027-01-05 | G7: 12 | H7: 35250 | I7: =ROUND('Resumen_Cartera'!$U7 * 'Resumen_Cartera'!$Q7, 2) | J7: =IF(Saldo_Residual_Activo!I7>0, ROUND(Saldo_Residual_Activo!I7 * 'Resumen_Cartera'!$Q7, 2), "") | K7: =IF(Saldo_Residual_Activo!J7>0, ROUND(Saldo_Residual_Activo!J7 * 'Resumen_Cartera'!$Q7, 2), "") | L7: =IF(Saldo_Residual_Activo!K7>0, ROUND(Saldo_Residual_Activo!K7 * 'Resumen_Cartera'!$Q7, 2), "") | M7: =IF(Saldo_Residual_Activo!L7>0, ROUND(Saldo_Residual_Activo!L7 * 'Resumen_Cartera'!$Q7, 2), "") | N7: =IF(Saldo_Residual_Activo!M7>0, ROUND(Saldo_Residual_Activo!M7 * 'Resumen_Cartera'!$Q7, 2), "") | O7: =IF(Saldo_Residual_Activo!N7>0, ROUND(Saldo_Residual_Activo!N7 * 'Resumen_Cartera'!$Q7, 2), "") | P7: =IF(Saldo_Residual_Activo!O7>0, ROUND(Saldo_Residual_Activo!O7 * 'Resumen_Cartera'!$Q7, 2), "") | Q7: =IF(Saldo_Residual_Activo!P7>0, ROUND(Saldo_Residual_Activo!P7 * 'Resumen_Cartera'!$Q7, 2), "") | ... T7: =IF(Saldo_Residual_Activo!S7>0, ROUND(Saldo_Residual_Activo!S7 * 'Resumen_Cartera'!$Q7, 2), "") | U7: =SUM(I7:T7)
A8: 0506-0006 | B8: Electronic Accounting Sa de Cv | C8: X5 | D8: ACTIVO | E8: 2024-01-10 | F8: 2027-01-10 | G8: 36 | H8: 567818.58 | I8: =ROUND(478842.05 * 'Resumen_Cartera'!$Q8, 2) | J8: =IF(Saldo_Residual_Activo!I8>0, ROUND(Saldo_Residual_Activo!I8 * 'Resumen_Cartera'!$Q8, 2), "") | K8: =IF(Saldo_Residual_Activo!J8>0, ROUND(Saldo_Residual_Activo!J8 * 'Resumen_Cartera'!$Q8, 2), "") | L8: =IF(Saldo_Residual_Activo!K8>0, ROUND(Saldo_Residual_Activo!K8 * 'Resumen_Cartera'!$Q8, 2), "") | M8: =IF(Saldo_Residual_Activo!L8>0, ROUND(Saldo_Residual_Activo!L8 * 'Resumen_Cartera'!$Q8, 2), "") | N8: =IF(Saldo_Residual_Activo!M8>0, ROUND(Saldo_Residual_Activo!M8 * 'Resumen_Cartera'!$Q8, 2), "") | O8: =IF(Saldo_Residual_Activo!N8>0, ROUND(Saldo_Residual_Activo!N8 * 'Resumen_Cartera'!$Q8, 2), "") | P8: =IF(Saldo_Residual_Activo!O8>0, ROUND(Saldo_Residual_Activo!O8 * 'Resumen_Cartera'!$Q8, 2), "") | Q8: =IF(Saldo_Residual_Activo!P8>0, ROUND(Saldo_Residual_Activo!P8 * 'Resumen_Cartera'!$Q8, 2), "") | ... T8: =IF(Saldo_Residual_Activo!S8>0, ROUND(Saldo_Residual_Activo!S8 * 'Resumen_Cartera'!$Q8, 2), "") | U8: =SUM(I8:T8)
A9: 0506-0007 | B9: Electronic Acounting | C9: L200 Glx Diesel | D9: ACTIVO | E9: 2024-09-05 | F9: 2027-09-05 | G9: 36 | H9: 187867.03 | I9: =ROUND(130969.49 * 'Resumen_Cartera'!$Q9, 2) | J9: =IF(Saldo_Residual_Activo!I9>0, ROUND(Saldo_Residual_Activo!I9 * 'Resumen_Cartera'!$Q9, 2), "") | K9: =IF(Saldo_Residual_Activo!J9>0, ROUND(Saldo_Residual_Activo!J9 * 'Resumen_Cartera'!$Q9, 2), "") | L9: =IF(Saldo_Residual_Activo!K9>0, ROUND(Saldo_Residual_Activo!K9 * 'Resumen_Cartera'!$Q9, 2), "") | M9: =IF(Saldo_Residual_Activo!L9>0, ROUND(Saldo_Residual_Activo!L9 * 'Resumen_Cartera'!$Q9, 2), "") | N9: =IF(Saldo_Residual_Activo!M9>0, ROUND(Saldo_Residual_Activo!M9 * 'Resumen_Cartera'!$Q9, 2), "") | O9: =IF(Saldo_Residual_Activo!N9>0, ROUND(Saldo_Residual_Activo!N9 * 'Resumen_Cartera'!$Q9, 2), "") | P9: =IF(Saldo_Residual_Activo!O9>0, ROUND(Saldo_Residual_Activo!O9 * 'Resumen_Cartera'!$Q9, 2), "") | Q9: =IF(Saldo_Residual_Activo!P9>0, ROUND(Saldo_Residual_Activo!P9 * 'Resumen_Cartera'!$Q9, 2), "") | ... T9: =IF(Saldo_Residual_Activo!S9>0, ROUND(Saldo_Residual_Activo!S9 * 'Resumen_Cartera'!$Q9, 2), "") | U9: =SUM(I9:T9)
A10: 0519-0005 | B10: Tequilas el Mexicano S.A. de C.V. | C10: Attitude Sport | D10: ACTIVO | E10: 2025-07-14 | F10: 2029-07-14 | G10: 48 | H10: 35250 | I10: =ROUND(11552.05 * 'Resumen_Cartera'!$Q10, 2) | J10: =IF(Saldo_Residual_Activo!I10>0, ROUND(Saldo_Residual_Activo!I10 * 'Resumen_Cartera'!$Q10, 2), "") | K10: =IF(Saldo_Residual_Activo!J10>0, ROUND(Saldo_Residual_Activo!J10 * 'Resumen_Cartera'!$Q10, 2), "") | L10: =IF(Saldo_Residual_Activo!K10>0, ROUND(Saldo_Residual_Activo!K10 * 'Resumen_Cartera'!$Q10, 2), "") | M10: =IF(Saldo_Residual_Activo!L10>0, ROUND(Saldo_Residual_Activo!L10 * 'Resumen_Cartera'!$Q10, 2), "") | N10: =IF(Saldo_Residual_Activo!M10>0, ROUND(Saldo_Residual_Activo!M10 * 'Resumen_Cartera'!$Q10, 2), "") | O10: =IF(Saldo_Residual_Activo!N10>0, ROUND(Saldo_Residual_Activo!N10 * 'Resumen_Cartera'!$Q10, 2), "") | P10: =IF(Saldo_Residual_Activo!O10>0, ROUND(Saldo_Residual_Activo!O10 * 'Resumen_Cartera'!$Q10, 2), "") | Q10: =IF(Saldo_Residual_Activo!P10>0, ROUND(Saldo_Residual_Activo!P10 * 'Resumen_Cartera'!$Q10, 2), "") | ... T10: =IF(Saldo_Residual_Activo!S10>0, ROUND(Saldo_Residual_Activo!S10 * 'Resumen_Cartera'!$Q10, 2), "") | U10: =SUM(I10:T10)
A11: 0520-0003 | B11: Tractomotriz Diesel Leal, S.A. de C.V. | C11: Montero Sport | D11: ACTIVO | E11: 2025-11-28 | F11: 2028-11-28 | G11: 36 | H11: 62146.55 | I11: =ROUND(25424.38 * 'Resumen_Cartera'!$Q11, 2) | J11: =IF(Saldo_Residual_Activo!I11>0, ROUND(Saldo_Residual_Activo!I11 * 'Resumen_Cartera'!$Q11, 2), "") | K11: =IF(Saldo_Residual_Activo!J11>0, ROUND(Saldo_Residual_Activo!J11 * 'Resumen_Cartera'!$Q11, 2), "") | L11: =IF(Saldo_Residual_Activo!K11>0, ROUND(Saldo_Residual_Activo!K11 * 'Resumen_Cartera'!$Q11, 2), "") | M11: =IF(Saldo_Residual_Activo!L11>0, ROUND(Saldo_Residual_Activo!L11 * 'Resumen_Cartera'!$Q11, 2), "") | N11: =IF(Saldo_Residual_Activo!M11>0, ROUND(Saldo_Residual_Activo!M11 * 'Resumen_Cartera'!$Q11, 2), "") | O11: =IF(Saldo_Residual_Activo!N11>0, ROUND(Saldo_Residual_Activo!N11 * 'Resumen_Cartera'!$Q11, 2), "") | P11: =IF(Saldo_Residual_Activo!O11>0, ROUND(Saldo_Residual_Activo!O11 * 'Resumen_Cartera'!$Q11, 2), "") | Q11: =IF(Saldo_Residual_Activo!P11>0, ROUND(Saldo_Residual_Activo!P11 * 'Resumen_Cartera'!$Q11, 2), "") | ... T11: =IF(Saldo_Residual_Activo!S11>0, ROUND(Saldo_Residual_Activo!S11 * 'Resumen_Cartera'!$Q11, 2), "") | U11: =SUM(I11:T11)
A12: 0520-0004 | B12: Tractomotriz Diesel Leal, S.A. de C.V. | C12: Partner Maxi Pack | D12: ACTIVO | E12: 2025-12-04 | F12: 2028-12-04 | G12: 36 | H12: 40036.38 | I12: =ROUND(15954.06 * 'Resumen_Cartera'!$Q12, 2) | J12: =IF(Saldo_Residual_Activo!I12>0, ROUND(Saldo_Residual_Activo!I12 * 'Resumen_Cartera'!$Q12, 2), "") | K12: =IF(Saldo_Residual_Activo!J12>0, ROUND(Saldo_Residual_Activo!J12 * 'Resumen_Cartera'!$Q12, 2), "") | L12: =IF(Saldo_Residual_Activo!K12>0, ROUND(Saldo_Residual_Activo!K12 * 'Resumen_Cartera'!$Q12, 2), "") | M12: =IF(Saldo_Residual_Activo!L12>0, ROUND(Saldo_Residual_Activo!L12 * 'Resumen_Cartera'!$Q12, 2), "") | N12: =IF(Saldo_Residual_Activo!M12>0, ROUND(Saldo_Residual_Activo!M12 * 'Resumen_Cartera'!$Q12, 2), "") | O12: =IF(Saldo_Residual_Activo!N12>0, ROUND(Saldo_Residual_Activo!N12 * 'Resumen_Cartera'!$Q12, 2), "") | P12: =IF(Saldo_Residual_Activo!O12>0, ROUND(Saldo_Residual_Activo!O12 * 'Resumen_Cartera'!$Q12, 2), "") | Q12: =IF(Saldo_Residual_Activo!P12>0, ROUND(Saldo_Residual_Activo!P12 * 'Resumen_Cartera'!$Q12, 2), "") | ... T12: =IF(Saldo_Residual_Activo!S12>0, ROUND(Saldo_Residual_Activo!S12 * 'Resumen_Cartera'!$Q12, 2), "") | U12: =SUM(I12:T12)
A13: 0521-0002 | B13: Carlos Hiram leal Leal | C13: Xpander | D13: ACTIVO | E13: 2025-09-08 | F13: 2028-09-08 | G13: 36 | H13: 73197.76 | I13: =ROUND(31569.68 * 'Resumen_Cartera'!$Q13, 2) | J13: =IF(Saldo_Residual_Activo!I13>0, ROUND(Saldo_Residual_Activo!I13 * 'Resumen_Cartera'!$Q13, 2), "") | K13: =IF(Saldo_Residual_Activo!J13>0, ROUND(Saldo_Residual_Activo!J13 * 'Resumen_Cartera'!$Q13, 2), "") | L13: =IF(Saldo_Residual_Activo!K13>0, ROUND(Saldo_Residual_Activo!K13 * 'Resumen_Cartera'!$Q13, 2), "") | M13: =IF(Saldo_Residual_Activo!L13>0, ROUND(Saldo_Residual_Activo!L13 * 'Resumen_Cartera'!$Q13, 2), "") | N13: =IF(Saldo_Residual_Activo!M13>0, ROUND(Saldo_Residual_Activo!M13 * 'Resumen_Cartera'!$Q13, 2), "") | O13: =IF(Saldo_Residual_Activo!N13>0, ROUND(Saldo_Residual_Activo!N13 * 'Resumen_Cartera'!$Q13, 2), "") | P13: =IF(Saldo_Residual_Activo!O13>0, ROUND(Saldo_Residual_Activo!O13 * 'Resumen_Cartera'!$Q13, 2), "") | Q13: =IF(Saldo_Residual_Activo!P13>0, ROUND(Saldo_Residual_Activo!P13 * 'Resumen_Cartera'!$Q13, 2), "") | ... T13: =IF(Saldo_Residual_Activo!S13>0, ROUND(Saldo_Residual_Activo!S13 * 'Resumen_Cartera'!$Q13, 2), "") | U13: =SUM(I13:T13)
A14: 0524-0007 | B14: Lider En Derecho De Via y Construcción SA DE CV | C14: L200 Gls | D14: ACTIVO | E14: 2025-08-15 | F14: 2027-08-15 | G14: 24 | H14: 194996.12 | I14: =ROUND(119282.87 * 'Resumen_Cartera'!$Q14, 2) | J14: =IF(Saldo_Residual_Activo!I14>0, ROUND(Saldo_Residual_Activo!I14 * 'Resumen_Cartera'!$Q14, 2), "") | K14: =IF(Saldo_Residual_Activo!J14>0, ROUND(Saldo_Residual_Activo!J14 * 'Resumen_Cartera'!$Q14, 2), "") | L14: =IF(Saldo_Residual_Activo!K14>0, ROUND(Saldo_Residual_Activo!K14 * 'Resumen_Cartera'!$Q14, 2), "") | M14: =IF(Saldo_Residual_Activo!L14>0, ROUND(Saldo_Residual_Activo!L14 * 'Resumen_Cartera'!$Q14, 2), "") | N14: =IF(Saldo_Residual_Activo!M14>0, ROUND(Saldo_Residual_Activo!M14 * 'Resumen_Cartera'!$Q14, 2), "") | O14: =IF(Saldo_Residual_Activo!N14>0, ROUND(Saldo_Residual_Activo!N14 * 'Resumen_Cartera'!$Q14, 2), "") | P14: =IF(Saldo_Residual_Activo!O14>0, ROUND(Saldo_Residual_Activo!O14 * 'Resumen_Cartera'!$Q14, 2), "") | Q14: =IF(Saldo_Residual_Activo!P14>0, ROUND(Saldo_Residual_Activo!P14 * 'Resumen_Cartera'!$Q14, 2), "") | ... T14: =IF(Saldo_Residual_Activo!S14>0, ROUND(Saldo_Residual_Activo!S14 * 'Resumen_Cartera'!$Q14, 2), "") | U14: =SUM(I14:T14)
A15: 0524-0011 | B15: Lider En Derecho De Via y Construcción SA DE CV | C15: Wrangler Unlimited Sahara | D15: ACTIVO | E15: 2025-12-31 | F15: 2029-12-31 | G15: 48 | H15: 105855.43 | I15: =ROUND(30419.37 * 'Resumen_Cartera'!$Q15, 2) | J15: =IF(Saldo_Residual_Activo!I15>0, ROUND(Saldo_Residual_Activo!I15 * 'Resumen_Cartera'!$Q15, 2), "") | K15: =IF(Saldo_Residual_Activo!J15>0, ROUND(Saldo_Residual_Activo!J15 * 'Resumen_Cartera'!$Q15, 2), "") | L15: =IF(Saldo_Residual_Activo!K15>0, ROUND(Saldo_Residual_Activo!K15 * 'Resumen_Cartera'!$Q15, 2), "") | M15: =IF(Saldo_Residual_Activo!L15>0, ROUND(Saldo_Residual_Activo!L15 * 'Resumen_Cartera'!$Q15, 2), "") | N15: =IF(Saldo_Residual_Activo!M15>0, ROUND(Saldo_Residual_Activo!M15 * 'Resumen_Cartera'!$Q15, 2), "") | O15: =IF(Saldo_Residual_Activo!N15>0, ROUND(Saldo_Residual_Activo!N15 * 'Resumen_Cartera'!$Q15, 2), "") | P15: =IF(Saldo_Residual_Activo!O15>0, ROUND(Saldo_Residual_Activo!O15 * 'Resumen_Cartera'!$Q15, 2), "") | Q15: =IF(Saldo_Residual_Activo!P15>0, ROUND(Saldo_Residual_Activo!P15 * 'Resumen_Cartera'!$Q15, 2), "") | ... T15: =IF(Saldo_Residual_Activo!S15>0, ROUND(Saldo_Residual_Activo!S15 * 'Resumen_Cartera'!$Q15, 2), "") | U15: =SUM(I15:T15)
A16: 0524-0012 | B16: Lider En Derecho De Via y Construcción SA DE CV | C16: L200 GLS | D16: ACTIVO | E16: 2026-03-17 | F16: 2030-03-17 | G16: 48 | H16: 62415.43 | K16: =ROUND('Resumen_Cartera'!$U16 * 'Resumen_Cartera'!$Q16, 2) | L16: =IF(Saldo_Residual_Activo!K16>0, ROUND(Saldo_Residual_Activo!K16 * 'Resumen_Cartera'!$Q16, 2), "") | M16: =IF(Saldo_Residual_Activo!L16>0, ROUND(Saldo_Residual_Activo!L16 * 'Resumen_Cartera'!$Q16, 2), "") | N16: =IF(Saldo_Residual_Activo!M16>0, ROUND(Saldo_Residual_Activo!M16 * 'Resumen_Cartera'!$Q16, 2), "") | O16: =IF(Saldo_Residual_Activo!N16>0, ROUND(Saldo_Residual_Activo!N16 * 'Resumen_Cartera'!$Q16, 2), "") | P16: =IF(Saldo_Residual_Activo!O16>0, ROUND(Saldo_Residual_Activo!O16 * 'Resumen_Cartera'!$Q16, 2), "") | Q16: =IF(Saldo_Residual_Activo!P16>0, ROUND(Saldo_Residual_Activo!P16 * 'Resumen_Cartera'!$Q16, 2), "") | R16: =IF(Saldo_Residual_Activo!Q16>0, ROUND(Saldo_Residual_Activo!Q16 * 'Resumen_Cartera'!$Q16, 2), "") | S16: =IF(Saldo_Residual_Activo!R16>0, ROUND(Saldo_Residual_Activo!R16 * 'Resumen_Cartera'!$Q16, 2), "") | T16: =IF(Saldo_Residual_Activo!S16>0, ROUND(Saldo_Residual_Activo!S16 * 'Resumen_Cartera'!$Q16, 2), "") | U16: =SUM(I16:T16)
A17: 0524-0013 | B17: Lider En Derecho De Via y Construcción SA DE CV | C17: L200 GLX | D17: ACTIVO | E17: 2026-06-23 | F17: 2029-06-23 | G17: 36 | H17: 119585 | N17: =ROUND('Resumen_Cartera'!$U17 * 'Resumen_Cartera'!$Q17, 2) | O17: =IF(Saldo_Residual_Activo!N17>0, ROUND(Saldo_Residual_Activo!N17 * 'Resumen_Cartera'!$Q17, 2), "") | P17: =IF(Saldo_Residual_Activo!O17>0, ROUND(Saldo_Residual_Activo!O17 * 'Resumen_Cartera'!$Q17, 2), "") | Q17: =IF(Saldo_Residual_Activo!P17>0, ROUND(Saldo_Residual_Activo!P17 * 'Resumen_Cartera'!$Q17, 2), "") | R17: =IF(Saldo_Residual_Activo!Q17>0, ROUND(Saldo_Residual_Activo!Q17 * 'Resumen_Cartera'!$Q17, 2), "") | S17: =IF(Saldo_Residual_Activo!R17>0, ROUND(Saldo_Residual_Activo!R17 * 'Resumen_Cartera'!$Q17, 2), "") | T17: =IF(Saldo_Residual_Activo!S17>0, ROUND(Saldo_Residual_Activo!S17 * 'Resumen_Cartera'!$Q17, 2), "") | U17: =SUM(I17:T17)
A18: 0524-0014 | B18: Lider En Derecho De Via y Construcción SA DE CV | C18: L200 GLX | D18: ACTIVO | E18: 2026-06-23 | F18: 2029-06-23 | G18: 36 | H18: 119585 | N18: =ROUND('Resumen_Cartera'!$U18 * 'Resumen_Cartera'!$Q18, 2) | O18: =IF(Saldo_Residual_Activo!N18>0, ROUND(Saldo_Residual_Activo!N18 * 'Resumen_Cartera'!$Q18, 2), "") | P18: =IF(Saldo_Residual_Activo!O18>0, ROUND(Saldo_Residual_Activo!O18 * 'Resumen_Cartera'!$Q18, 2), "") | Q18: =IF(Saldo_Residual_Activo!P18>0, ROUND(Saldo_Residual_Activo!P18 * 'Resumen_Cartera'!$Q18, 2), "") | R18: =IF(Saldo_Residual_Activo!Q18>0, ROUND(Saldo_Residual_Activo!Q18 * 'Resumen_Cartera'!$Q18, 2), "") | S18: =IF(Saldo_Residual_Activo!R18>0, ROUND(Saldo_Residual_Activo!R18 * 'Resumen_Cartera'!$Q18, 2), "") | T18: =IF(Saldo_Residual_Activo!S18>0, ROUND(Saldo_Residual_Activo!S18 * 'Resumen_Cartera'!$Q18, 2), "") | U18: =SUM(I18:T18)
A19: 0524-0015 | B19: Lider En Derecho De Via y Construcción SA DE CV | C19: Mitsubishi L200 GLX 2026 | D19: ACTIVO | E19: 2026-07-29 | F19: 2029-07-29 | G19: 36 | H19: 103090.52 | O19: =ROUND('Resumen_Cartera'!$U19 * 'Resumen_Cartera'!$Q19, 2) | P19: =IF(Saldo_Residual_Activo!O19>0, ROUND(Saldo_Residual_Activo!O19 * 'Resumen_Cartera'!$Q19, 2), "") | Q19: =IF(Saldo_Residual_Activo!P19>0, ROUND(Saldo_Residual_Activo!P19 * 'Resumen_Cartera'!$Q19, 2), "") | R19: =IF(Saldo_Residual_Activo!Q19>0, ROUND(Saldo_Residual_Activo!Q19 * 'Resumen_Cartera'!$Q19, 2), "") | S19: =IF(Saldo_Residual_Activo!R19>0, ROUND(Saldo_Residual_Activo!R19 * 'Resumen_Cartera'!$Q19, 2), "") | T19: =IF(Saldo_Residual_Activo!S19>0, ROUND(Saldo_Residual_Activo!S19 * 'Resumen_Cartera'!$Q19, 2), "") | U19: =SUM(I19:T19)
A20: 0524-0016 | B20: Lider En Derecho De Via y Construcción SA DE CV | C20: Mitsubishi L200 GLX 2026 | D20: ACTIVO | E20: 2026-07-29 | F20: 2029-07-29 | G20: 36 | H20: 103090.52 | O20: =ROUND('Resumen_Cartera'!$U20 * 'Resumen_Cartera'!$Q20, 2) | P20: =IF(Saldo_Residual_Activo!O20>0, ROUND(Saldo_Residual_Activo!O20 * 'Resumen_Cartera'!$Q20, 2), "") | Q20: =IF(Saldo_Residual_Activo!P20>0, ROUND(Saldo_Residual_Activo!P20 * 'Resumen_Cartera'!$Q20, 2), "") | R20: =IF(Saldo_Residual_Activo!Q20>0, ROUND(Saldo_Residual_Activo!Q20 * 'Resumen_Cartera'!$Q20, 2), "") | S20: =IF(Saldo_Residual_Activo!R20>0, ROUND(Saldo_Residual_Activo!R20 * 'Resumen_Cartera'!$Q20, 2), "") | T20: =IF(Saldo_Residual_Activo!S20>0, ROUND(Saldo_Residual_Activo!S20 * 'Resumen_Cartera'!$Q20, 2), "") | U20: =SUM(I20:T20)
A21: 0527-0003 | B21: Comercilizadora e Importadora Nabega Sa de Cv | C21: RAM 700 Big Horn CVT | D21: ACTIVO | E21: 2024-05-30 | F21: 2027-05-30 | G21: 36 | H21: 126693.97 | I21: =ROUND(76265.33 * 'Resumen_Cartera'!$Q21, 2) | J21: =IF(Saldo_Residual_Activo!I21>0, ROUND(Saldo_Residual_Activo!I21 * 'Resumen_Cartera'!$Q21, 2), "") | K21: =IF(Saldo_Residual_Activo!J21>0, ROUND(Saldo_Residual_Activo!J21 * 'Resumen_Cartera'!$Q21, 2), "") | L21: =IF(Saldo_Residual_Activo!K21>0, ROUND(Saldo_Residual_Activo!K21 * 'Resumen_Cartera'!$Q21, 2), "") | M21: =IF(Saldo_Residual_Activo!L21>0, ROUND(Saldo_Residual_Activo!L21 * 'Resumen_Cartera'!$Q21, 2), "") | N21: =IF(Saldo_Residual_Activo!M21>0, ROUND(Saldo_Residual_Activo!M21 * 'Resumen_Cartera'!$Q21, 2), "") | O21: =IF(Saldo_Residual_Activo!N21>0, ROUND(Saldo_Residual_Activo!N21 * 'Resumen_Cartera'!$Q21, 2), "") | P21: =IF(Saldo_Residual_Activo!O21>0, ROUND(Saldo_Residual_Activo!O21 * 'Resumen_Cartera'!$Q21, 2), "") | Q21: =IF(Saldo_Residual_Activo!P21>0, ROUND(Saldo_Residual_Activo!P21 * 'Resumen_Cartera'!$Q21, 2), "") | ... T21: =IF(Saldo_Residual_Activo!S21>0, ROUND(Saldo_Residual_Activo!S21 * 'Resumen_Cartera'!$Q21, 2), "") | U21: =SUM(I21:T21)
A22: 0527-0004 | B22: Comercilizadora e Importadora Nabega Sa de Cv | C22: Gmc Denali | D22: ACTIVO | E22: 2025-07-31 | F22: 2029-07-31 | G22: 48 | H22: 220241.38 | I22: =ROUND(72006.59 * 'Resumen_Cartera'!$Q22, 2) | J22: =IF(Saldo_Residual_Activo!I22>0, ROUND(Saldo_Residual_Activo!I22 * 'Resumen_Cartera'!$Q22, 2), "") | K22: =IF(Saldo_Residual_Activo!J22>0, ROUND(Saldo_Residual_Activo!J22 * 'Resumen_Cartera'!$Q22, 2), "") | L22: =IF(Saldo_Residual_Activo!K22>0, ROUND(Saldo_Residual_Activo!K22 * 'Resumen_Cartera'!$Q22, 2), "") | M22: =IF(Saldo_Residual_Activo!L22>0, ROUND(Saldo_Residual_Activo!L22 * 'Resumen_Cartera'!$Q22, 2), "") | N22: =IF(Saldo_Residual_Activo!M22>0, ROUND(Saldo_Residual_Activo!M22 * 'Resumen_Cartera'!$Q22, 2), "") | O22: =IF(Saldo_Residual_Activo!N22>0, ROUND(Saldo_Residual_Activo!N22 * 'Resumen_Cartera'!$Q22, 2), "") | P22: =IF(Saldo_Residual_Activo!O22>0, ROUND(Saldo_Residual_Activo!O22 * 'Resumen_Cartera'!$Q22, 2), "") | Q22: =IF(Saldo_Residual_Activo!P22>0, ROUND(Saldo_Residual_Activo!P22 * 'Resumen_Cartera'!$Q22, 2), "") | ... T22: =IF(Saldo_Residual_Activo!S22>0, ROUND(Saldo_Residual_Activo!S22 * 'Resumen_Cartera'!$Q22, 2), "") | U22: =SUM(I22:T22)
A23: 0527-0005 | B23: Comercilizadora e Importadora Nabega Sa de Cv | C23: Gle 450 Sport | D23: ACTIVO | E23: 2025-08-16 | F23: 2028-08-16 | G23: 36 | H23: 300150 | I23: =ROUND(138864.97 * 'Resumen_Cartera'!$Q23, 2) | J23: =IF(Saldo_Residual_Activo!I23>0, ROUND(Saldo_Residual_Activo!I23 * 'Resumen_Cartera'!$Q23, 2), "") | K23: =IF(Saldo_Residual_Activo!J23>0, ROUND(Saldo_Residual_Activo!J23 * 'Resumen_Cartera'!$Q23, 2), "") | L23: =IF(Saldo_Residual_Activo!K23>0, ROUND(Saldo_Residual_Activo!K23 * 'Resumen_Cartera'!$Q23, 2), "") | M23: =IF(Saldo_Residual_Activo!L23>0, ROUND(Saldo_Residual_Activo!L23 * 'Resumen_Cartera'!$Q23, 2), "") | N23: =IF(Saldo_Residual_Activo!M23>0, ROUND(Saldo_Residual_Activo!M23 * 'Resumen_Cartera'!$Q23, 2), "") | O23: =IF(Saldo_Residual_Activo!N23>0, ROUND(Saldo_Residual_Activo!N23 * 'Resumen_Cartera'!$Q23, 2), "") | P23: =IF(Saldo_Residual_Activo!O23>0, ROUND(Saldo_Residual_Activo!O23 * 'Resumen_Cartera'!$Q23, 2), "") | Q23: =IF(Saldo_Residual_Activo!P23>0, ROUND(Saldo_Residual_Activo!P23 * 'Resumen_Cartera'!$Q23, 2), "") | ... T23: =IF(Saldo_Residual_Activo!S23>0, ROUND(Saldo_Residual_Activo!S23 * 'Resumen_Cartera'!$Q23, 2), "") | U23: =SUM(I23:T23)
A24: 0531-0002 | B24: Otcada Mex, S. de R.L. de C.V. | C24: Grand Cherokee Limited | D24: ACTIVO | E24: 2026-06-18 | F24: 2030-06-18 | G24: 48 | H24: 129890 | N24: =ROUND('Resumen_Cartera'!$U24 * 'Resumen_Cartera'!$Q24, 2) | O24: =IF(Saldo_Residual_Activo!N24>0, ROUND(Saldo_Residual_Activo!N24 * 'Resumen_Cartera'!$Q24, 2), "") | P24: =IF(Saldo_Residual_Activo!O24>0, ROUND(Saldo_Residual_Activo!O24 * 'Resumen_Cartera'!$Q24, 2), "") | Q24: =IF(Saldo_Residual_Activo!P24>0, ROUND(Saldo_Residual_Activo!P24 * 'Resumen_Cartera'!$Q24, 2), "") | R24: =IF(Saldo_Residual_Activo!Q24>0, ROUND(Saldo_Residual_Activo!Q24 * 'Resumen_Cartera'!$Q24, 2), "") | S24: =IF(Saldo_Residual_Activo!R24>0, ROUND(Saldo_Residual_Activo!R24 * 'Resumen_Cartera'!$Q24, 2), "") | T24: =IF(Saldo_Residual_Activo!S24>0, ROUND(Saldo_Residual_Activo!S24 * 'Resumen_Cartera'!$Q24, 2), "") | U24: =SUM(I24:T24)
A25: 0546-0007 | B25: Norma Elena Bonilla Lupio | C25: GLC 350 E 4MATIC | D25: ACTIVO | E25: 2025-10-14 | F25: 2027-10-14 | G25: 24 | H25: 144486.21 | I25: =ROUND(86908.08 * 'Resumen_Cartera'!$Q25, 2) | J25: =IF(Saldo_Residual_Activo!I25>0, ROUND(Saldo_Residual_Activo!I25 * 'Resumen_Cartera'!$Q25, 2), "") | K25: =IF(Saldo_Residual_Activo!J25>0, ROUND(Saldo_Residual_Activo!J25 * 'Resumen_Cartera'!$Q25, 2), "") | L25: =IF(Saldo_Residual_Activo!K25>0, ROUND(Saldo_Residual_Activo!K25 * 'Resumen_Cartera'!$Q25, 2), "") | M25: =IF(Saldo_Residual_Activo!L25>0, ROUND(Saldo_Residual_Activo!L25 * 'Resumen_Cartera'!$Q25, 2), "") | N25: =IF(Saldo_Residual_Activo!M25>0, ROUND(Saldo_Residual_Activo!M25 * 'Resumen_Cartera'!$Q25, 2), "") | O25: =IF(Saldo_Residual_Activo!N25>0, ROUND(Saldo_Residual_Activo!N25 * 'Resumen_Cartera'!$Q25, 2), "") | P25: =IF(Saldo_Residual_Activo!O25>0, ROUND(Saldo_Residual_Activo!O25 * 'Resumen_Cartera'!$Q25, 2), "") | Q25: =IF(Saldo_Residual_Activo!P25>0, ROUND(Saldo_Residual_Activo!P25 * 'Resumen_Cartera'!$Q25, 2), "") | ... T25: =IF(Saldo_Residual_Activo!S25>0, ROUND(Saldo_Residual_Activo!S25 * 'Resumen_Cartera'!$Q25, 2), "") | U25: =SUM(I25:T25)
A26: 0546-0008 | B26: Norma Elena Bonilla Lupio | C26: JT MOJAVE 4X4 | D26: ACTIVO | E26: 2026-01-08 | F26: 2028-01-08 | G26: 24 | H26: 136293.36 | I26: =ROUND('Resumen_Cartera'!$U26 * 'Resumen_Cartera'!$Q26, 2) | J26: =IF(Saldo_Residual_Activo!I26>0, ROUND(Saldo_Residual_Activo!I26 * 'Resumen_Cartera'!$Q26, 2), "") | K26: =IF(Saldo_Residual_Activo!J26>0, ROUND(Saldo_Residual_Activo!J26 * 'Resumen_Cartera'!$Q26, 2), "") | L26: =IF(Saldo_Residual_Activo!K26>0, ROUND(Saldo_Residual_Activo!K26 * 'Resumen_Cartera'!$Q26, 2), "") | M26: =IF(Saldo_Residual_Activo!L26>0, ROUND(Saldo_Residual_Activo!L26 * 'Resumen_Cartera'!$Q26, 2), "") | N26: =IF(Saldo_Residual_Activo!M26>0, ROUND(Saldo_Residual_Activo!M26 * 'Resumen_Cartera'!$Q26, 2), "") | O26: =IF(Saldo_Residual_Activo!N26>0, ROUND(Saldo_Residual_Activo!N26 * 'Resumen_Cartera'!$Q26, 2), "") | P26: =IF(Saldo_Residual_Activo!O26>0, ROUND(Saldo_Residual_Activo!O26 * 'Resumen_Cartera'!$Q26, 2), "") | Q26: =IF(Saldo_Residual_Activo!P26>0, ROUND(Saldo_Residual_Activo!P26 * 'Resumen_Cartera'!$Q26, 2), "") | ... T26: =IF(Saldo_Residual_Activo!S26>0, ROUND(Saldo_Residual_Activo!S26 * 'Resumen_Cartera'!$Q26, 2), "") | U26: =SUM(I26:T26)
A27: 0546-0009 | B27: Norma Elena Bonilla Lupio | C27: Ram 1200 Tradesman 2026 | D27: ACTIVO | E27: 2026-07-01 | F27: 2028-07-01 | G27: 24 | H27: 36450.26 | O27: =ROUND('Resumen_Cartera'!$U27 * 'Resumen_Cartera'!$Q27, 2) | P27: =IF(Saldo_Residual_Activo!O27>0, ROUND(Saldo_Residual_Activo!O27 * 'Resumen_Cartera'!$Q27, 2), "") | Q27: =IF(Saldo_Residual_Activo!P27>0, ROUND(Saldo_Residual_Activo!P27 * 'Resumen_Cartera'!$Q27, 2), "") | R27: =IF(Saldo_Residual_Activo!Q27>0, ROUND(Saldo_Residual_Activo!Q27 * 'Resumen_Cartera'!$Q27, 2), "") | S27: =IF(Saldo_Residual_Activo!R27>0, ROUND(Saldo_Residual_Activo!R27 * 'Resumen_Cartera'!$Q27, 2), "") | T27: =IF(Saldo_Residual_Activo!S27>0, ROUND(Saldo_Residual_Activo!S27 * 'Resumen_Cartera'!$Q27, 2), "") | U27: =SUM(I27:T27)
A28: 0551-0002 | B28: Agaveros Unidos de Tequila Jalisco Aun S de RL de Cv | C28: Ram 700 Laramie | D28: ACTIVO | E28: 2023-07-07 | F28: 2027-07-07 | G28: 48 | H28: 70672.41 | I28: =ROUND(39773.83 * 'Resumen_Cartera'!$Q28, 2) | J28: =IF(Saldo_Residual_Activo!I28>0, ROUND(Saldo_Residual_Activo!I28 * 'Resumen_Cartera'!$Q28, 2), "") | K28: =IF(Saldo_Residual_Activo!J28>0, ROUND(Saldo_Residual_Activo!J28 * 'Resumen_Cartera'!$Q28, 2), "") | L28: =IF(Saldo_Residual_Activo!K28>0, ROUND(Saldo_Residual_Activo!K28 * 'Resumen_Cartera'!$Q28, 2), "") | M28: =IF(Saldo_Residual_Activo!L28>0, ROUND(Saldo_Residual_Activo!L28 * 'Resumen_Cartera'!$Q28, 2), "") | N28: =IF(Saldo_Residual_Activo!M28>0, ROUND(Saldo_Residual_Activo!M28 * 'Resumen_Cartera'!$Q28, 2), "") | O28: =IF(Saldo_Residual_Activo!N28>0, ROUND(Saldo_Residual_Activo!N28 * 'Resumen_Cartera'!$Q28, 2), "") | P28: =IF(Saldo_Residual_Activo!O28>0, ROUND(Saldo_Residual_Activo!O28 * 'Resumen_Cartera'!$Q28, 2), "") | Q28: =IF(Saldo_Residual_Activo!P28>0, ROUND(Saldo_Residual_Activo!P28 * 'Resumen_Cartera'!$Q28, 2), "") | ... T28: =IF(Saldo_Residual_Activo!S28>0, ROUND(Saldo_Residual_Activo!S28 * 'Resumen_Cartera'!$Q28, 2), "") | U28: =SUM(I28:T28)
A29: 0552-0018 | B29: Transportes y Maniobras Portuarias | C29: Raizer | D29: ACTIVO | E29: 2024-11-29 | F29: 2026-11-29 | G29: 24 | H29: 8900 | I29: =ROUND(6823.74 * 'Resumen_Cartera'!$Q29, 2) | J29: =IF(Saldo_Residual_Activo!I29>0, ROUND(Saldo_Residual_Activo!I29 * 'Resumen_Cartera'!$Q29, 2), "") | K29: =IF(Saldo_Residual_Activo!J29>0, ROUND(Saldo_Residual_Activo!J29 * 'Resumen_Cartera'!$Q29, 2), "") | L29: =IF(Saldo_Residual_Activo!K29>0, ROUND(Saldo_Residual_Activo!K29 * 'Resumen_Cartera'!$Q29, 2), "") | M29: =IF(Saldo_Residual_Activo!L29>0, ROUND(Saldo_Residual_Activo!L29 * 'Resumen_Cartera'!$Q29, 2), "") | N29: =IF(Saldo_Residual_Activo!M29>0, ROUND(Saldo_Residual_Activo!M29 * 'Resumen_Cartera'!$Q29, 2), "") | O29: =IF(Saldo_Residual_Activo!N29>0, ROUND(Saldo_Residual_Activo!N29 * 'Resumen_Cartera'!$Q29, 2), "") | P29: =IF(Saldo_Residual_Activo!O29>0, ROUND(Saldo_Residual_Activo!O29 * 'Resumen_Cartera'!$Q29, 2), "") | Q29: =IF(Saldo_Residual_Activo!P29>0, ROUND(Saldo_Residual_Activo!P29 * 'Resumen_Cartera'!$Q29, 2), "") | R29: =IF(Saldo_Residual_Activo!Q29>0, ROUND(Saldo_Residual_Activo!Q29 * 'Resumen_Cartera'!$Q29, 2), "") | U29: =SUM(I29:T29)
A30: 0552-0019 | B30: Transportes y Maniobras Portuarias de Mexico Sa de Cv | C30: Remolque tipo Dolly | D30: ACTIVO | E30: 2024-12-20 | F30: 2026-12-20 | G30: 24 | H30: 2710 | I30: =ROUND(2023.33 * 'Resumen_Cartera'!$Q30, 2) | J30: =IF(Saldo_Residual_Activo!I30>0, ROUND(Saldo_Residual_Activo!I30 * 'Resumen_Cartera'!$Q30, 2), "") | K30: =IF(Saldo_Residual_Activo!J30>0, ROUND(Saldo_Residual_Activo!J30 * 'Resumen_Cartera'!$Q30, 2), "") | L30: =IF(Saldo_Residual_Activo!K30>0, ROUND(Saldo_Residual_Activo!K30 * 'Resumen_Cartera'!$Q30, 2), "") | M30: =IF(Saldo_Residual_Activo!L30>0, ROUND(Saldo_Residual_Activo!L30 * 'Resumen_Cartera'!$Q30, 2), "") | N30: =IF(Saldo_Residual_Activo!M30>0, ROUND(Saldo_Residual_Activo!M30 * 'Resumen_Cartera'!$Q30, 2), "") | O30: =IF(Saldo_Residual_Activo!N30>0, ROUND(Saldo_Residual_Activo!N30 * 'Resumen_Cartera'!$Q30, 2), "") | P30: =IF(Saldo_Residual_Activo!O30>0, ROUND(Saldo_Residual_Activo!O30 * 'Resumen_Cartera'!$Q30, 2), "") | Q30: =IF(Saldo_Residual_Activo!P30>0, ROUND(Saldo_Residual_Activo!P30 * 'Resumen_Cartera'!$Q30, 2), "") | ... S30: =IF(Saldo_Residual_Activo!R30>0, ROUND(Saldo_Residual_Activo!R30 * 'Resumen_Cartera'!$Q30, 2), "") | U30: =SUM(I30:T30)
A31: 0552-0020 | B31: Transportes y Maniobras Portuarias de Mexico Sa de Cv | C31: PLATAFORMA MULTIMODAL | D31: ACTIVO | E31: 2024-12-26 | F31: 2026-12-26 | G31: 24 | H31: 5130 | I31: =ROUND(3830.13 * 'Resumen_Cartera'!$Q31, 2) | J31: =IF(Saldo_Residual_Activo!I31>0, ROUND(Saldo_Residual_Activo!I31 * 'Resumen_Cartera'!$Q31, 2), "") | K31: =IF(Saldo_Residual_Activo!J31>0, ROUND(Saldo_Residual_Activo!J31 * 'Resumen_Cartera'!$Q31, 2), "") | L31: =IF(Saldo_Residual_Activo!K31>0, ROUND(Saldo_Residual_Activo!K31 * 'Resumen_Cartera'!$Q31, 2), "") | M31: =IF(Saldo_Residual_Activo!L31>0, ROUND(Saldo_Residual_Activo!L31 * 'Resumen_Cartera'!$Q31, 2), "") | N31: =IF(Saldo_Residual_Activo!M31>0, ROUND(Saldo_Residual_Activo!M31 * 'Resumen_Cartera'!$Q31, 2), "") | O31: =IF(Saldo_Residual_Activo!N31>0, ROUND(Saldo_Residual_Activo!N31 * 'Resumen_Cartera'!$Q31, 2), "") | P31: =IF(Saldo_Residual_Activo!O31>0, ROUND(Saldo_Residual_Activo!O31 * 'Resumen_Cartera'!$Q31, 2), "") | Q31: =IF(Saldo_Residual_Activo!P31>0, ROUND(Saldo_Residual_Activo!P31 * 'Resumen_Cartera'!$Q31, 2), "") | ... S31: =IF(Saldo_Residual_Activo!R31>0, ROUND(Saldo_Residual_Activo!R31 * 'Resumen_Cartera'!$Q31, 2), "") | U31: =SUM(I31:T31)
A32: 0552-0021 | B32: Transportes y Maniobras Portuarias de Mexico Sa de Cv | C32: PLATAFORMA MULTIMODAL | D32: ACTIVO | E32: 2024-12-26 | F32: 2026-12-26 | G32: 24 | H32: 5130 | I32: =ROUND(3830.13 * 'Resumen_Cartera'!$Q32, 2) | J32: =IF(Saldo_Residual_Activo!I32>0, ROUND(Saldo_Residual_Activo!I32 * 'Resumen_Cartera'!$Q32, 2), "") | K32: =IF(Saldo_Residual_Activo!J32>0, ROUND(Saldo_Residual_Activo!J32 * 'Resumen_Cartera'!$Q32, 2), "") | L32: =IF(Saldo_Residual_Activo!K32>0, ROUND(Saldo_Residual_Activo!K32 * 'Resumen_Cartera'!$Q32, 2), "") | M32: =IF(Saldo_Residual_Activo!L32>0, ROUND(Saldo_Residual_Activo!L32 * 'Resumen_Cartera'!$Q32, 2), "") | N32: =IF(Saldo_Residual_Activo!M32>0, ROUND(Saldo_Residual_Activo!M32 * 'Resumen_Cartera'!$Q32, 2), "") | O32: =IF(Saldo_Residual_Activo!N32>0, ROUND(Saldo_Residual_Activo!N32 * 'Resumen_Cartera'!$Q32, 2), "") | P32: =IF(Saldo_Residual_Activo!O32>0, ROUND(Saldo_Residual_Activo!O32 * 'Resumen_Cartera'!$Q32, 2), "") | Q32: =IF(Saldo_Residual_Activo!P32>0, ROUND(Saldo_Residual_Activo!P32 * 'Resumen_Cartera'!$Q32, 2), "") | ... S32: =IF(Saldo_Residual_Activo!R32>0, ROUND(Saldo_Residual_Activo!R32 * 'Resumen_Cartera'!$Q32, 2), "") | U32: =SUM(I32:T32)
A33: 0552-0022 | B33: Transportes y Maniobras Portuarias de Mexico Sa de Cv | C33: RZR | D33: ACTIVO | E33: 2024-12-26 | F33: 2026-12-26 | G33: 24 | H33: 9223.28 | I33: =ROUND(6886.2 * 'Resumen_Cartera'!$Q33, 2) | J33: =IF(Saldo_Residual_Activo!I33>0, ROUND(Saldo_Residual_Activo!I33 * 'Resumen_Cartera'!$Q33, 2), "") | K33: =IF(Saldo_Residual_Activo!J33>0, ROUND(Saldo_Residual_Activo!J33 * 'Resumen_Cartera'!$Q33, 2), "") | L33: =IF(Saldo_Residual_Activo!K33>0, ROUND(Saldo_Residual_Activo!K33 * 'Resumen_Cartera'!$Q33, 2), "") | M33: =IF(Saldo_Residual_Activo!L33>0, ROUND(Saldo_Residual_Activo!L33 * 'Resumen_Cartera'!$Q33, 2), "") | N33: =IF(Saldo_Residual_Activo!M33>0, ROUND(Saldo_Residual_Activo!M33 * 'Resumen_Cartera'!$Q33, 2), "") | O33: =IF(Saldo_Residual_Activo!N33>0, ROUND(Saldo_Residual_Activo!N33 * 'Resumen_Cartera'!$Q33, 2), "") | P33: =IF(Saldo_Residual_Activo!O33>0, ROUND(Saldo_Residual_Activo!O33 * 'Resumen_Cartera'!$Q33, 2), "") | Q33: =IF(Saldo_Residual_Activo!P33>0, ROUND(Saldo_Residual_Activo!P33 * 'Resumen_Cartera'!$Q33, 2), "") | ... S33: =IF(Saldo_Residual_Activo!R33>0, ROUND(Saldo_Residual_Activo!R33 * 'Resumen_Cartera'!$Q33, 2), "") | U33: =SUM(I33:T33)
A34: 0552-0023 | B34: Transportes y Maniobras Portuarias de Mexico Sa de Cv | C34: Iternational Lt | D34: ACTIVO | E34: 2025-08-27 | F34: 2027-08-27 | G34: 24 | H34: 153103.45 | I34: =ROUND(94198.22 * 'Resumen_Cartera'!$Q34, 2) | J34: =IF(Saldo_Residual_Activo!I34>0, ROUND(Saldo_Residual_Activo!I34 * 'Resumen_Cartera'!$Q34, 2), "") | K34: =IF(Saldo_Residual_Activo!J34>0, ROUND(Saldo_Residual_Activo!J34 * 'Resumen_Cartera'!$Q34, 2), "") | L34: =IF(Saldo_Residual_Activo!K34>0, ROUND(Saldo_Residual_Activo!K34 * 'Resumen_Cartera'!$Q34, 2), "") | M34: =IF(Saldo_Residual_Activo!L34>0, ROUND(Saldo_Residual_Activo!L34 * 'Resumen_Cartera'!$Q34, 2), "") | N34: =IF(Saldo_Residual_Activo!M34>0, ROUND(Saldo_Residual_Activo!M34 * 'Resumen_Cartera'!$Q34, 2), "") | O34: =IF(Saldo_Residual_Activo!N34>0, ROUND(Saldo_Residual_Activo!N34 * 'Resumen_Cartera'!$Q34, 2), "") | P34: =IF(Saldo_Residual_Activo!O34>0, ROUND(Saldo_Residual_Activo!O34 * 'Resumen_Cartera'!$Q34, 2), "") | Q34: =IF(Saldo_Residual_Activo!P34>0, ROUND(Saldo_Residual_Activo!P34 * 'Resumen_Cartera'!$Q34, 2), "") | ... T34: =IF(Saldo_Residual_Activo!S34>0, ROUND(Saldo_Residual_Activo!S34 * 'Resumen_Cartera'!$Q34, 2), "") | U34: =SUM(I34:T34)
A35: 0552-0024 | B35: Transportes y Maniobras Portuarias de Mexico Sa de Cv | C35: Iternational Lt | D35: ACTIVO | E35: 2025-08-27 | F35: 2027-08-27 | G35: 24 | H35: 153103.45 | I35: =ROUND(94198.22 * 'Resumen_Cartera'!$Q35, 2) | J35: =IF(Saldo_Residual_Activo!I35>0, ROUND(Saldo_Residual_Activo!I35 * 'Resumen_Cartera'!$Q35, 2), "") | K35: =IF(Saldo_Residual_Activo!J35>0, ROUND(Saldo_Residual_Activo!J35 * 'Resumen_Cartera'!$Q35, 2), "") | L35: =IF(Saldo_Residual_Activo!K35>0, ROUND(Saldo_Residual_Activo!K35 * 'Resumen_Cartera'!$Q35, 2), "") | M35: =IF(Saldo_Residual_Activo!L35>0, ROUND(Saldo_Residual_Activo!L35 * 'Resumen_Cartera'!$Q35, 2), "") | N35: =IF(Saldo_Residual_Activo!M35>0, ROUND(Saldo_Residual_Activo!M35 * 'Resumen_Cartera'!$Q35, 2), "") | O35: =IF(Saldo_Residual_Activo!N35>0, ROUND(Saldo_Residual_Activo!N35 * 'Resumen_Cartera'!$Q35, 2), "") | P35: =IF(Saldo_Residual_Activo!O35>0, ROUND(Saldo_Residual_Activo!O35 * 'Resumen_Cartera'!$Q35, 2), "") | Q35: =IF(Saldo_Residual_Activo!P35>0, ROUND(Saldo_Residual_Activo!P35 * 'Resumen_Cartera'!$Q35, 2), "") | ... T35: =IF(Saldo_Residual_Activo!S35>0, ROUND(Saldo_Residual_Activo!S35 * 'Resumen_Cartera'!$Q35, 2), "") | U35: =SUM(I35:T35)
A36: 0552-0025 | B36: Transportes y Maniobras Portuarias de Mexico Sa de Cv | C36: Iternational Lt | D36: ACTIVO | E36: 2025-08-27 | F36: 2027-08-27 | G36: 24 | H36: 153103.45 | I36: =ROUND(94198.22 * 'Resumen_Cartera'!$Q36, 2) | J36: =IF(Saldo_Residual_Activo!I36>0, ROUND(Saldo_Residual_Activo!I36 * 'Resumen_Cartera'!$Q36, 2), "") | K36: =IF(Saldo_Residual_Activo!J36>0, ROUND(Saldo_Residual_Activo!J36 * 'Resumen_Cartera'!$Q36, 2), "") | L36: =IF(Saldo_Residual_Activo!K36>0, ROUND(Saldo_Residual_Activo!K36 * 'Resumen_Cartera'!$Q36, 2), "") | M36: =IF(Saldo_Residual_Activo!L36>0, ROUND(Saldo_Residual_Activo!L36 * 'Resumen_Cartera'!$Q36, 2), "") | N36: =IF(Saldo_Residual_Activo!M36>0, ROUND(Saldo_Residual_Activo!M36 * 'Resumen_Cartera'!$Q36, 2), "") | O36: =IF(Saldo_Residual_Activo!N36>0, ROUND(Saldo_Residual_Activo!N36 * 'Resumen_Cartera'!$Q36, 2), "") | P36: =IF(Saldo_Residual_Activo!O36>0, ROUND(Saldo_Residual_Activo!O36 * 'Resumen_Cartera'!$Q36, 2), "") | Q36: =IF(Saldo_Residual_Activo!P36>0, ROUND(Saldo_Residual_Activo!P36 * 'Resumen_Cartera'!$Q36, 2), "") | ... T36: =IF(Saldo_Residual_Activo!S36>0, ROUND(Saldo_Residual_Activo!S36 * 'Resumen_Cartera'!$Q36, 2), "") | U36: =SUM(I36:T36)
A37: 0554-0003 | B37: TRANSPORTES DEL BAJIO TRANSCOLD SA DE CV | C37: RAM 4000 CHASIS PLANO LARGO "PL" | D37: ACTIVO | E37: 2022-11-24 | F37: 2026-11-24 | G37: 48 | H37: 69981.03 | I37: =ROUND(53141.04 * 'Resumen_Cartera'!$Q37, 2) | J37: =IF(Saldo_Residual_Activo!I37>0, ROUND(Saldo_Residual_Activo!I37 * 'Resumen_Cartera'!$Q37, 2), "") | K37: =IF(Saldo_Residual_Activo!J37>0, ROUND(Saldo_Residual_Activo!J37 * 'Resumen_Cartera'!$Q37, 2), "") | L37: =IF(Saldo_Residual_Activo!K37>0, ROUND(Saldo_Residual_Activo!K37 * 'Resumen_Cartera'!$Q37, 2), "") | M37: =IF(Saldo_Residual_Activo!L37>0, ROUND(Saldo_Residual_Activo!L37 * 'Resumen_Cartera'!$Q37, 2), "") | N37: =IF(Saldo_Residual_Activo!M37>0, ROUND(Saldo_Residual_Activo!M37 * 'Resumen_Cartera'!$Q37, 2), "") | O37: =IF(Saldo_Residual_Activo!N37>0, ROUND(Saldo_Residual_Activo!N37 * 'Resumen_Cartera'!$Q37, 2), "") | P37: =IF(Saldo_Residual_Activo!O37>0, ROUND(Saldo_Residual_Activo!O37 * 'Resumen_Cartera'!$Q37, 2), "") | Q37: =IF(Saldo_Residual_Activo!P37>0, ROUND(Saldo_Residual_Activo!P37 * 'Resumen_Cartera'!$Q37, 2), "") | R37: =IF(Saldo_Residual_Activo!Q37>0, ROUND(Saldo_Residual_Activo!Q37 * 'Resumen_Cartera'!$Q37, 2), "") | U37: =SUM(I37:T37)
A38: 0570-0006 | B38: Jalco Iluminacion Sa de Cv | C38: RAM 700 BIG HORN | D38: ACTIVO | E38: 2023-12-08 | F38: 2026-12-08 | G38: 36 | H38: 121866.38 | I38: =ROUND(86282.78 * 'Resumen_Cartera'!$Q38, 2) | J38: =IF(Saldo_Residual_Activo!I38>0, ROUND(Saldo_Residual_Activo!I38 * 'Resumen_Cartera'!$Q38, 2), "") | K38: =IF(Saldo_Residual_Activo!J38>0, ROUND(Saldo_Residual_Activo!J38 * 'Resumen_Cartera'!$Q38, 2), "") | L38: =IF(Saldo_Residual_Activo!K38>0, ROUND(Saldo_Residual_Activo!K38 * 'Resumen_Cartera'!$Q38, 2), "") | M38: =IF(Saldo_Residual_Activo!L38>0, ROUND(Saldo_Residual_Activo!L38 * 'Resumen_Cartera'!$Q38, 2), "") | N38: =IF(Saldo_Residual_Activo!M38>0, ROUND(Saldo_Residual_Activo!M38 * 'Resumen_Cartera'!$Q38, 2), "") | O38: =IF(Saldo_Residual_Activo!N38>0, ROUND(Saldo_Residual_Activo!N38 * 'Resumen_Cartera'!$Q38, 2), "") | P38: =IF(Saldo_Residual_Activo!O38>0, ROUND(Saldo_Residual_Activo!O38 * 'Resumen_Cartera'!$Q38, 2), "") | Q38: =IF(Saldo_Residual_Activo!P38>0, ROUND(Saldo_Residual_Activo!P38 * 'Resumen_Cartera'!$Q38, 2), "") | ... S38: =IF(Saldo_Residual_Activo!R38>0, ROUND(Saldo_Residual_Activo!R38 * 'Resumen_Cartera'!$Q38, 2), "") | U38: =SUM(I38:T38)
A39: 0573-0007 | B39: Ar Marketing Sa de Cv | C39: Promaster Rapid | D39: ACTIVO | E39: 2024-05-10 | F39: 2027-05-10 | G39: 36 | H39: 51517.59 | I39: =ROUND(30698.88 * 'Resumen_Cartera'!$Q39, 2) | J39: =IF(Saldo_Residual_Activo!I39>0, ROUND(Saldo_Residual_Activo!I39 * 'Resumen_Cartera'!$Q39, 2), "") | K39: =IF(Saldo_Residual_Activo!J39>0, ROUND(Saldo_Residual_Activo!J39 * 'Resumen_Cartera'!$Q39, 2), "") | L39: =IF(Saldo_Residual_Activo!K39>0, ROUND(Saldo_Residual_Activo!K39 * 'Resumen_Cartera'!$Q39, 2), "") | M39: =IF(Saldo_Residual_Activo!L39>0, ROUND(Saldo_Residual_Activo!L39 * 'Resumen_Cartera'!$Q39, 2), "") | N39: =IF(Saldo_Residual_Activo!M39>0, ROUND(Saldo_Residual_Activo!M39 * 'Resumen_Cartera'!$Q39, 2), "") | O39: =IF(Saldo_Residual_Activo!N39>0, ROUND(Saldo_Residual_Activo!N39 * 'Resumen_Cartera'!$Q39, 2), "") | P39: =IF(Saldo_Residual_Activo!O39>0, ROUND(Saldo_Residual_Activo!O39 * 'Resumen_Cartera'!$Q39, 2), "") | Q39: =IF(Saldo_Residual_Activo!P39>0, ROUND(Saldo_Residual_Activo!P39 * 'Resumen_Cartera'!$Q39, 2), "") | ... T39: =IF(Saldo_Residual_Activo!S39>0, ROUND(Saldo_Residual_Activo!S39 * 'Resumen_Cartera'!$Q39, 2), "") | U39: =SUM(I39:T39)
A40: 0573-0008 | B40: Ar Marketing Sa de Cv | C40: Promaster Rapid | D40: ACTIVO | E40: 2024-05-15 | F40: 2027-05-15 | G40: 36 | H40: 50672.76 | I40: =ROUND(30195.45 * 'Resumen_Cartera'!$Q40, 2) | J40: =IF(Saldo_Residual_Activo!I40>0, ROUND(Saldo_Residual_Activo!I40 * 'Resumen_Cartera'!$Q40, 2), "") | K40: =IF(Saldo_Residual_Activo!J40>0, ROUND(Saldo_Residual_Activo!J40 * 'Resumen_Cartera'!$Q40, 2), "") | L40: =IF(Saldo_Residual_Activo!K40>0, ROUND(Saldo_Residual_Activo!K40 * 'Resumen_Cartera'!$Q40, 2), "") | M40: =IF(Saldo_Residual_Activo!L40>0, ROUND(Saldo_Residual_Activo!L40 * 'Resumen_Cartera'!$Q40, 2), "") | N40: =IF(Saldo_Residual_Activo!M40>0, ROUND(Saldo_Residual_Activo!M40 * 'Resumen_Cartera'!$Q40, 2), "") | O40: =IF(Saldo_Residual_Activo!N40>0, ROUND(Saldo_Residual_Activo!N40 * 'Resumen_Cartera'!$Q40, 2), "") | P40: =IF(Saldo_Residual_Activo!O40>0, ROUND(Saldo_Residual_Activo!O40 * 'Resumen_Cartera'!$Q40, 2), "") | Q40: =IF(Saldo_Residual_Activo!P40>0, ROUND(Saldo_Residual_Activo!P40 * 'Resumen_Cartera'!$Q40, 2), "") | ... T40: =IF(Saldo_Residual_Activo!S40>0, ROUND(Saldo_Residual_Activo!S40 * 'Resumen_Cartera'!$Q40, 2), "") | U40: =SUM(I40:T40)
A41: 0573-0009 | B41: Ar Marketing Sa de Cv | C41: Partner | D41: ACTIVO | E41: 2025-11-28 | F41: 2028-11-28 | G41: 36 | H41: 49827.93 | I41: =ROUND(20325.84 * 'Resumen_Cartera'!$Q41, 2) | J41: =IF(Saldo_Residual_Activo!I41>0, ROUND(Saldo_Residual_Activo!I41 * 'Resumen_Cartera'!$Q41, 2), "") | K41: =IF(Saldo_Residual_Activo!J41>0, ROUND(Saldo_Residual_Activo!J41 * 'Resumen_Cartera'!$Q41, 2), "") | L41: =IF(Saldo_Residual_Activo!K41>0, ROUND(Saldo_Residual_Activo!K41 * 'Resumen_Cartera'!$Q41, 2), "") | M41: =IF(Saldo_Residual_Activo!L41>0, ROUND(Saldo_Residual_Activo!L41 * 'Resumen_Cartera'!$Q41, 2), "") | N41: =IF(Saldo_Residual_Activo!M41>0, ROUND(Saldo_Residual_Activo!M41 * 'Resumen_Cartera'!$Q41, 2), "") | O41: =IF(Saldo_Residual_Activo!N41>0, ROUND(Saldo_Residual_Activo!N41 * 'Resumen_Cartera'!$Q41, 2), "") | P41: =IF(Saldo_Residual_Activo!O41>0, ROUND(Saldo_Residual_Activo!O41 * 'Resumen_Cartera'!$Q41, 2), "") | Q41: =IF(Saldo_Residual_Activo!P41>0, ROUND(Saldo_Residual_Activo!P41 * 'Resumen_Cartera'!$Q41, 2), "") | ... T41: =IF(Saldo_Residual_Activo!S41>0, ROUND(Saldo_Residual_Activo!S41 * 'Resumen_Cartera'!$Q41, 2), "") | U41: =SUM(I41:T41)
A42: 0580-0001 | B42: YOLANDA AVALOS CARDENAS | C42: Mojave | D42: ACTIVO | E42: 2022-11-18 | F42: 2026-11-18 | G42: 48 | H42: 251189.66 | I42: =ROUND(191004.78 * 'Resumen_Cartera'!$Q42, 2) | J42: =IF(Saldo_Residual_Activo!I42>0, ROUND(Saldo_Residual_Activo!I42 * 'Resumen_Cartera'!$Q42, 2), "") | K42: =IF(Saldo_Residual_Activo!J42>0, ROUND(Saldo_Residual_Activo!J42 * 'Resumen_Cartera'!$Q42, 2), "") | L42: =IF(Saldo_Residual_Activo!K42>0, ROUND(Saldo_Residual_Activo!K42 * 'Resumen_Cartera'!$Q42, 2), "") | M42: =IF(Saldo_Residual_Activo!L42>0, ROUND(Saldo_Residual_Activo!L42 * 'Resumen_Cartera'!$Q42, 2), "") | N42: =IF(Saldo_Residual_Activo!M42>0, ROUND(Saldo_Residual_Activo!M42 * 'Resumen_Cartera'!$Q42, 2), "") | O42: =IF(Saldo_Residual_Activo!N42>0, ROUND(Saldo_Residual_Activo!N42 * 'Resumen_Cartera'!$Q42, 2), "") | P42: =IF(Saldo_Residual_Activo!O42>0, ROUND(Saldo_Residual_Activo!O42 * 'Resumen_Cartera'!$Q42, 2), "") | Q42: =IF(Saldo_Residual_Activo!P42>0, ROUND(Saldo_Residual_Activo!P42 * 'Resumen_Cartera'!$Q42, 2), "") | R42: =IF(Saldo_Residual_Activo!Q42>0, ROUND(Saldo_Residual_Activo!Q42 * 'Resumen_Cartera'!$Q42, 2), "") | U42: =SUM(I42:T42)
A43: 0581-0001 | B43: Aditivos y Vitaminas Mexicanas Sa de Cv | C43: RAM 700 REGULAR CAB | D43: ACTIVO | E43: 2023-01-17 | F43: 2027-01-17 | G43: 48 | H43: 51189.66 | I43: =ROUND(35051.24 * 'Resumen_Cartera'!$Q43, 2) | J43: =IF(Saldo_Residual_Activo!I43>0, ROUND(Saldo_Residual_Activo!I43 * 'Resumen_Cartera'!$Q43, 2), "") | K43: =IF(Saldo_Residual_Activo!J43>0, ROUND(Saldo_Residual_Activo!J43 * 'Resumen_Cartera'!$Q43, 2), "") | L43: =IF(Saldo_Residual_Activo!K43>0, ROUND(Saldo_Residual_Activo!K43 * 'Resumen_Cartera'!$Q43, 2), "") | M43: =IF(Saldo_Residual_Activo!L43>0, ROUND(Saldo_Residual_Activo!L43 * 'Resumen_Cartera'!$Q43, 2), "") | N43: =IF(Saldo_Residual_Activo!M43>0, ROUND(Saldo_Residual_Activo!M43 * 'Resumen_Cartera'!$Q43, 2), "") | O43: =IF(Saldo_Residual_Activo!N43>0, ROUND(Saldo_Residual_Activo!N43 * 'Resumen_Cartera'!$Q43, 2), "") | P43: =IF(Saldo_Residual_Activo!O43>0, ROUND(Saldo_Residual_Activo!O43 * 'Resumen_Cartera'!$Q43, 2), "") | Q43: =IF(Saldo_Residual_Activo!P43>0, ROUND(Saldo_Residual_Activo!P43 * 'Resumen_Cartera'!$Q43, 2), "") | ... T43: =IF(Saldo_Residual_Activo!S43>0, ROUND(Saldo_Residual_Activo!S43 * 'Resumen_Cartera'!$Q43, 2), "") | U43: =SUM(I43:T43)
A44: 0581-0002 | B44: Aditivos y Vitaminas Mexicanas Sa de Cv | C44: Ram 700 Regular Cab | D44: ACTIVO | E44: 2024-09-18 | F44: 2028-09-18 | G44: 48 | H44: 56017.24 | I44: =ROUND(28717.73 * 'Resumen_Cartera'!$Q44, 2) | J44: =IF(Saldo_Residual_Activo!I44>0, ROUND(Saldo_Residual_Activo!I44 * 'Resumen_Cartera'!$Q44, 2), "") | K44: =IF(Saldo_Residual_Activo!J44>0, ROUND(Saldo_Residual_Activo!J44 * 'Resumen_Cartera'!$Q44, 2), "") | L44: =IF(Saldo_Residual_Activo!K44>0, ROUND(Saldo_Residual_Activo!K44 * 'Resumen_Cartera'!$Q44, 2), "") | M44: =IF(Saldo_Residual_Activo!L44>0, ROUND(Saldo_Residual_Activo!L44 * 'Resumen_Cartera'!$Q44, 2), "") | N44: =IF(Saldo_Residual_Activo!M44>0, ROUND(Saldo_Residual_Activo!M44 * 'Resumen_Cartera'!$Q44, 2), "") | O44: =IF(Saldo_Residual_Activo!N44>0, ROUND(Saldo_Residual_Activo!N44 * 'Resumen_Cartera'!$Q44, 2), "") | P44: =IF(Saldo_Residual_Activo!O44>0, ROUND(Saldo_Residual_Activo!O44 * 'Resumen_Cartera'!$Q44, 2), "") | Q44: =IF(Saldo_Residual_Activo!P44>0, ROUND(Saldo_Residual_Activo!P44 * 'Resumen_Cartera'!$Q44, 2), "") | ... T44: =IF(Saldo_Residual_Activo!S44>0, ROUND(Saldo_Residual_Activo!S44 * 'Resumen_Cartera'!$Q44, 2), "") | U44: =SUM(I44:T44)
A45: 0582-0003 | B45: Ensaladas Frescas de Occidente Sa de Cv | C45: Pulse | D45: ACTIVO | E45: 2024-07-02 | F45: 2028-07-02 | G45: 48 | H45: 60948.28 | I45: =ROUND(21880.27 * 'Resumen_Cartera'!$Q45, 2) | J45: =IF(Saldo_Residual_Activo!I45>0, ROUND(Saldo_Residual_Activo!I45 * 'Resumen_Cartera'!$Q45, 2), "") | K45: =IF(Saldo_Residual_Activo!J45>0, ROUND(Saldo_Residual_Activo!J45 * 'Resumen_Cartera'!$Q45, 2), "") | L45: =IF(Saldo_Residual_Activo!K45>0, ROUND(Saldo_Residual_Activo!K45 * 'Resumen_Cartera'!$Q45, 2), "") | M45: =IF(Saldo_Residual_Activo!L45>0, ROUND(Saldo_Residual_Activo!L45 * 'Resumen_Cartera'!$Q45, 2), "") | N45: =IF(Saldo_Residual_Activo!M45>0, ROUND(Saldo_Residual_Activo!M45 * 'Resumen_Cartera'!$Q45, 2), "") | O45: =IF(Saldo_Residual_Activo!N45>0, ROUND(Saldo_Residual_Activo!N45 * 'Resumen_Cartera'!$Q45, 2), "") | P45: =IF(Saldo_Residual_Activo!O45>0, ROUND(Saldo_Residual_Activo!O45 * 'Resumen_Cartera'!$Q45, 2), "") | Q45: =IF(Saldo_Residual_Activo!P45>0, ROUND(Saldo_Residual_Activo!P45 * 'Resumen_Cartera'!$Q45, 2), "") | ... T45: =IF(Saldo_Residual_Activo!S45>0, ROUND(Saldo_Residual_Activo!S45 * 'Resumen_Cartera'!$Q45, 2), "") | U45: =SUM(I45:T45)
A46: 0583-0004 | B46: Soluciones Profesionales para la Industria Alimentaria | C46: BIGHORN CREW CAB MT | D46: ACTIVO | E46: 2024-12-30 | F46: 2026-12-30 | G46: 24 | H46: 34129.31 | I46: =ROUND(24129.41 * 'Resumen_Cartera'!$Q46, 2) | J46: =IF(Saldo_Residual_Activo!I46>0, ROUND(Saldo_Residual_Activo!I46 * 'Resumen_Cartera'!$Q46, 2), "") | K46: =IF(Saldo_Residual_Activo!J46>0, ROUND(Saldo_Residual_Activo!J46 * 'Resumen_Cartera'!$Q46, 2), "") | L46: =IF(Saldo_Residual_Activo!K46>0, ROUND(Saldo_Residual_Activo!K46 * 'Resumen_Cartera'!$Q46, 2), "") | M46: =IF(Saldo_Residual_Activo!L46>0, ROUND(Saldo_Residual_Activo!L46 * 'Resumen_Cartera'!$Q46, 2), "") | N46: =IF(Saldo_Residual_Activo!M46>0, ROUND(Saldo_Residual_Activo!M46 * 'Resumen_Cartera'!$Q46, 2), "") | O46: =IF(Saldo_Residual_Activo!N46>0, ROUND(Saldo_Residual_Activo!N46 * 'Resumen_Cartera'!$Q46, 2), "") | P46: =IF(Saldo_Residual_Activo!O46>0, ROUND(Saldo_Residual_Activo!O46 * 'Resumen_Cartera'!$Q46, 2), "") | Q46: =IF(Saldo_Residual_Activo!P46>0, ROUND(Saldo_Residual_Activo!P46 * 'Resumen_Cartera'!$Q46, 2), "") | ... S46: =IF(Saldo_Residual_Activo!R46>0, ROUND(Saldo_Residual_Activo!R46 * 'Resumen_Cartera'!$Q46, 2), "") | U46: =SUM(I46:T46)
A47: 0583-0005 | B47: Soluciones Profesionales para la Industria Alimentaria | C47: 3008 | D47: ACTIVO | E47: 2025-01-09 | F47: 2028-01-09 | G47: 36 | H47: 49689.66 | I47: =ROUND(23741.25 * 'Resumen_Cartera'!$Q47, 2) | J47: =IF(Saldo_Residual_Activo!I47>0, ROUND(Saldo_Residual_Activo!I47 * 'Resumen_Cartera'!$Q47, 2), "") | K47: =IF(Saldo_Residual_Activo!J47>0, ROUND(Saldo_Residual_Activo!J47 * 'Resumen_Cartera'!$Q47, 2), "") | L47: =IF(Saldo_Residual_Activo!K47>0, ROUND(Saldo_Residual_Activo!K47 * 'Resumen_Cartera'!$Q47, 2), "") | M47: =IF(Saldo_Residual_Activo!L47>0, ROUND(Saldo_Residual_Activo!L47 * 'Resumen_Cartera'!$Q47, 2), "") | N47: =IF(Saldo_Residual_Activo!M47>0, ROUND(Saldo_Residual_Activo!M47 * 'Resumen_Cartera'!$Q47, 2), "") | O47: =IF(Saldo_Residual_Activo!N47>0, ROUND(Saldo_Residual_Activo!N47 * 'Resumen_Cartera'!$Q47, 2), "") | P47: =IF(Saldo_Residual_Activo!O47>0, ROUND(Saldo_Residual_Activo!O47 * 'Resumen_Cartera'!$Q47, 2), "") | Q47: =IF(Saldo_Residual_Activo!P47>0, ROUND(Saldo_Residual_Activo!P47 * 'Resumen_Cartera'!$Q47, 2), "") | ... T47: =IF(Saldo_Residual_Activo!S47>0, ROUND(Saldo_Residual_Activo!S47 * 'Resumen_Cartera'!$Q47, 2), "") | U47: =SUM(I47:T47)
A48: 0583-0006 | B48: Soluciones Profesionales para la Industria Alimentaria | C48: Montana | D48: ACTIVO | E48: 2025-11-19 | F48: 2027-11-19 | G48: 24 | H48: 96448.28 | I48: =ROUND(54654.73 * 'Resumen_Cartera'!$Q48, 2) | J48: =IF(Saldo_Residual_Activo!I48>0, ROUND(Saldo_Residual_Activo!I48 * 'Resumen_Cartera'!$Q48, 2), "") | K48: =IF(Saldo_Residual_Activo!J48>0, ROUND(Saldo_Residual_Activo!J48 * 'Resumen_Cartera'!$Q48, 2), "") | L48: =IF(Saldo_Residual_Activo!K48>0, ROUND(Saldo_Residual_Activo!K48 * 'Resumen_Cartera'!$Q48, 2), "") | M48: =IF(Saldo_Residual_Activo!L48>0, ROUND(Saldo_Residual_Activo!L48 * 'Resumen_Cartera'!$Q48, 2), "") | N48: =IF(Saldo_Residual_Activo!M48>0, ROUND(Saldo_Residual_Activo!M48 * 'Resumen_Cartera'!$Q48, 2), "") | O48: =IF(Saldo_Residual_Activo!N48>0, ROUND(Saldo_Residual_Activo!N48 * 'Resumen_Cartera'!$Q48, 2), "") | P48: =IF(Saldo_Residual_Activo!O48>0, ROUND(Saldo_Residual_Activo!O48 * 'Resumen_Cartera'!$Q48, 2), "") | Q48: =IF(Saldo_Residual_Activo!P48>0, ROUND(Saldo_Residual_Activo!P48 * 'Resumen_Cartera'!$Q48, 2), "") | ... T48: =IF(Saldo_Residual_Activo!S48>0, ROUND(Saldo_Residual_Activo!S48 * 'Resumen_Cartera'!$Q48, 2), "") | U48: =SUM(I48:T48)
A49: 0585-0002 | B49: Julio Alberto Ramos de la Mora | C49: Ram 1500 Limited | D49: ACTIVO | E49: 2025-01-08 | F49: 2028-01-08 | G49: 36 | H49: 427474.14 | I49: =ROUND(203465.63 * 'Resumen_Cartera'!$Q49, 2) | J49: =IF(Saldo_Residual_Activo!I49>0, ROUND(Saldo_Residual_Activo!I49 * 'Resumen_Cartera'!$Q49, 2), "") | K49: =IF(Saldo_Residual_Activo!J49>0, ROUND(Saldo_Residual_Activo!J49 * 'Resumen_Cartera'!$Q49, 2), "") | L49: =IF(Saldo_Residual_Activo!K49>0, ROUND(Saldo_Residual_Activo!K49 * 'Resumen_Cartera'!$Q49, 2), "") | M49: =IF(Saldo_Residual_Activo!L49>0, ROUND(Saldo_Residual_Activo!L49 * 'Resumen_Cartera'!$Q49, 2), "") | N49: =IF(Saldo_Residual_Activo!M49>0, ROUND(Saldo_Residual_Activo!M49 * 'Resumen_Cartera'!$Q49, 2), "") | O49: =IF(Saldo_Residual_Activo!N49>0, ROUND(Saldo_Residual_Activo!N49 * 'Resumen_Cartera'!$Q49, 2), "") | P49: =IF(Saldo_Residual_Activo!O49>0, ROUND(Saldo_Residual_Activo!O49 * 'Resumen_Cartera'!$Q49, 2), "") | Q49: =IF(Saldo_Residual_Activo!P49>0, ROUND(Saldo_Residual_Activo!P49 * 'Resumen_Cartera'!$Q49, 2), "") | ... T49: =IF(Saldo_Residual_Activo!S49>0, ROUND(Saldo_Residual_Activo!S49 * 'Resumen_Cartera'!$Q49, 2), "") | U49: =SUM(I49:T49)
A50: 0585-0003 | B50: Julio Alberto Ramos de la Mora | C50: Wrangler Rubicon | D50: ACTIVO | E50: 2025-01-17 | F50: 2029-01-17 | G50: 48 | H50: 380275.86 | I50: =ROUND(123554.01 * 'Resumen_Cartera'!$Q50, 2) | J50: =IF(Saldo_Residual_Activo!I50>0, ROUND(Saldo_Residual_Activo!I50 * 'Resumen_Cartera'!$Q50, 2), "") | K50: =IF(Saldo_Residual_Activo!J50>0, ROUND(Saldo_Residual_Activo!J50 * 'Resumen_Cartera'!$Q50, 2), "") | L50: =IF(Saldo_Residual_Activo!K50>0, ROUND(Saldo_Residual_Activo!K50 * 'Resumen_Cartera'!$Q50, 2), "") | M50: =IF(Saldo_Residual_Activo!L50>0, ROUND(Saldo_Residual_Activo!L50 * 'Resumen_Cartera'!$Q50, 2), "") | N50: =IF(Saldo_Residual_Activo!M50>0, ROUND(Saldo_Residual_Activo!M50 * 'Resumen_Cartera'!$Q50, 2), "") | O50: =IF(Saldo_Residual_Activo!N50>0, ROUND(Saldo_Residual_Activo!N50 * 'Resumen_Cartera'!$Q50, 2), "") | P50: =IF(Saldo_Residual_Activo!O50>0, ROUND(Saldo_Residual_Activo!O50 * 'Resumen_Cartera'!$Q50, 2), "") | Q50: =IF(Saldo_Residual_Activo!P50>0, ROUND(Saldo_Residual_Activo!P50 * 'Resumen_Cartera'!$Q50, 2), "") | ... T50: =IF(Saldo_Residual_Activo!S50>0, ROUND(Saldo_Residual_Activo!S50 * 'Resumen_Cartera'!$Q50, 2), "") | U50: =SUM(I50:T50)
A51: 0585-0004 | B51: Julio Alberto Ramos de la Mora | C51: Hrv Sport | D51: ACTIVO | E51: 2025-05-28 | F51: 2028-05-28 | G51: 36 | H51: 54301.72 | I51: =ROUND(26010.4 * 'Resumen_Cartera'!$Q51, 2) | J51: =IF(Saldo_Residual_Activo!I51>0, ROUND(Saldo_Residual_Activo!I51 * 'Resumen_Cartera'!$Q51, 2), "") | K51: =IF(Saldo_Residual_Activo!J51>0, ROUND(Saldo_Residual_Activo!J51 * 'Resumen_Cartera'!$Q51, 2), "") | L51: =IF(Saldo_Residual_Activo!K51>0, ROUND(Saldo_Residual_Activo!K51 * 'Resumen_Cartera'!$Q51, 2), "") | M51: =IF(Saldo_Residual_Activo!L51>0, ROUND(Saldo_Residual_Activo!L51 * 'Resumen_Cartera'!$Q51, 2), "") | N51: =IF(Saldo_Residual_Activo!M51>0, ROUND(Saldo_Residual_Activo!M51 * 'Resumen_Cartera'!$Q51, 2), "") | O51: =IF(Saldo_Residual_Activo!N51>0, ROUND(Saldo_Residual_Activo!N51 * 'Resumen_Cartera'!$Q51, 2), "") | P51: =IF(Saldo_Residual_Activo!O51>0, ROUND(Saldo_Residual_Activo!O51 * 'Resumen_Cartera'!$Q51, 2), "") | Q51: =IF(Saldo_Residual_Activo!P51>0, ROUND(Saldo_Residual_Activo!P51 * 'Resumen_Cartera'!$Q51, 2), "") | ... T51: =IF(Saldo_Residual_Activo!S51>0, ROUND(Saldo_Residual_Activo!S51 * 'Resumen_Cartera'!$Q51, 2), "") | U51: =SUM(I51:T51)
A52: 0585-0005 | B52: Julio Alberto Ramos de la Mora | C52: M9 GL HEV | D52: ACTIVO | E52: 2025-12-12 | F52: 2027-12-12 | G52: 24 | H52: 84465.52 | I52: =ROUND(46792.99 * 'Resumen_Cartera'!$Q52, 2) | J52: =IF(Saldo_Residual_Activo!I52>0, ROUND(Saldo_Residual_Activo!I52 * 'Resumen_Cartera'!$Q52, 2), "") | K52: =IF(Saldo_Residual_Activo!J52>0, ROUND(Saldo_Residual_Activo!J52 * 'Resumen_Cartera'!$Q52, 2), "") | L52: =IF(Saldo_Residual_Activo!K52>0, ROUND(Saldo_Residual_Activo!K52 * 'Resumen_Cartera'!$Q52, 2), "") | M52: =IF(Saldo_Residual_Activo!L52>0, ROUND(Saldo_Residual_Activo!L52 * 'Resumen_Cartera'!$Q52, 2), "") | N52: =IF(Saldo_Residual_Activo!M52>0, ROUND(Saldo_Residual_Activo!M52 * 'Resumen_Cartera'!$Q52, 2), "") | O52: =IF(Saldo_Residual_Activo!N52>0, ROUND(Saldo_Residual_Activo!N52 * 'Resumen_Cartera'!$Q52, 2), "") | P52: =IF(Saldo_Residual_Activo!O52>0, ROUND(Saldo_Residual_Activo!O52 * 'Resumen_Cartera'!$Q52, 2), "") | Q52: =IF(Saldo_Residual_Activo!P52>0, ROUND(Saldo_Residual_Activo!P52 * 'Resumen_Cartera'!$Q52, 2), "") | ... T52: =IF(Saldo_Residual_Activo!S52>0, ROUND(Saldo_Residual_Activo!S52 * 'Resumen_Cartera'!$Q52, 2), "") | U52: =SUM(I52:T52)
