Workbook
Name CONTRATOS_LISTA: 'Reporte_Lineal'!$A$5:$A$281

Sheet Reporte_Lineal
A1: O-LEASING · UNA APP DE ORANGE CREW · Reporte Lineal de Cartera y Amortización Horizontal
A2: Contratos en vertical con amortización horizontal de Mes 1 a Mes 48 con fórmulas vivas de cálculo · Auditoría Financiera NIF C-15 / IFRS 16 · Desarrollado por Orange Crew
A3: DATOS CONTRACTUALES Y PARÁMETROS FINANCIEROS (NIF C-15 / IFRS 16) | AA3: MES 1 | AJ3: MES 2 | AS3: MES 3 | BB3: MES 4 | BK3: MES 5 | BT3: MES 6 | CC3: MES 7 | CL3: MES 8 | CU3: MES 9 | DD3: MES 10 | DM3: MES 11 | DV3: MES 12 | EE3: MES 13 | EN3: MES 14 | EW3: MES 15 | FF3: MES 16 | FO3: MES 17 | FX3: MES 18 | GG3: MES 19 | GP3: MES 20 | GY3: MES 21 | HH3: MES 22 | HQ3: MES 23 | HZ3: MES 24 | II3: MES 25 | IR3: MES 26 | JA3: MES 27 | JJ3: MES 28 | JS3: MES 29 | KB3: MES 30 | KK3: MES 31 | KT3: MES 32 | LC3: MES 33 | LL3: MES 34 | LU3: MES 35 | MD3: MES 36 | MM3: MES 37 | MV3: MES 38 | NE3: MES 39 | NN3: MES 40 | NW3: MES 41 | OF3: MES 42 | OO3: MES 43 | OX3: MES 44 | PG3: MES 45 | PP3: MES 46 | PY3: MES 47 | QH3: MES 48
A4: ID_Contrato | B4: Cliente | C4: Vehiculo | D4: Estatus | E4: Fecha_Alta | F4: Fecha_Vencimiento | G4: Plazo_Meses | H4: Valor_Sin_IVA | I4: Anticipo_Pct | J4: Anticipo_Monto | K4: Inversion_Neta | L4: Comision_Pct | M4: Comision_Apertura | N4: Renta_Sin_IVA | O4: Residual_Pct | P4: Residual_Pactado | Q4: Tasa_Mensual_Reg | R4: Tasa_Mensual_RATE | S4: Tasa_Nominal_Anual | T4: TIR_Anual_Efectiva | U4: VP_Residual | V4: Total_Interes_Leasing | W4: Total_Interes_Residual | X4: Ingreso_Financiero_Total | Y4: Ganancia_Neta | Z4: Margen_Sobre_Inv | AA4: Saldo_Inicial | AB4: Interes_Leasing | AC4: Renta | AD4: Capital | AE4: Saldo_Capital | AF4: Interes_Residual | AG4: Saldo_Residual | AH4: Ingreso_Financiero | AI4: Saldo_Cartera | AJ4: Saldo_Inicial | AK4: Interes_Leasing | AL4: Renta | AM4: Capital | AN4: Saldo_Capital | AO4: Interes_Residual | AP4: Saldo_Residual | AQ4: Ingreso_Financiero | AR4: Saldo_Cartera | AS4: Saldo_Inicial | AT4: Interes_Leasing | AU4: Renta | AV4: Capital | AW4: Saldo_Capital | AX4: Interes_Residual | AY4: Saldo_Residual | AZ4: Ingreso_Financiero | BA4: Saldo_Cartera | BB4: Saldo_Inicial | BC4: Interes_Leasing | BD4: Renta | BE4: Capital | BF4: Saldo_Capital | BG4: Interes_Residual | BH4: Saldo_Residual | BI4: Ingreso_Financiero | BJ4: Saldo_Cartera | BK4: Saldo_Inicial | BL4: Interes_Leasing | BM4: Renta | BN4: Capital | BO4: Saldo_Capital | BP4: Interes_Residual | BQ4: Saldo_Residual | BR4: Ingreso_Financiero | BS4: Saldo_Cartera | BT4: Saldo_Inicial | BU4: Interes_Leasing | BV4: Renta | BW4: Capital | BX4: Saldo_Capital | BY4: Interes_Residual | BZ4: Saldo_Residual | CA4: Ingreso_Financiero | CB4: Saldo_Cartera | CC4: Saldo_Inicial | CD4: Interes_Leasing | CE4: Renta | CF4: Capital | CG4: Saldo_Capital | CH4: Interes_Residual | CI4: Saldo_Residual | CJ4: Ingreso_Financiero | CK4: Saldo_Cartera | CL4: Saldo_Inicial | CM4: Interes_Leasing | CN4: Renta | CO4: Capital | CP4: Saldo_Capital | CQ4: Interes_Residual | CR4: Saldo_Residual | CS4: Ingreso_Financiero | CT4: Saldo_Cartera | CU4: Saldo_Inicial | CV4: Interes_Leasing | CW4: Renta | CX4: Capital | CY4: Saldo_Capital | CZ4: Interes_Residual | DA4: Saldo_Residual | DB4: Ingreso_Financiero | DC4: Saldo_Cartera | DD4: Saldo_Inicial | DE4: Interes_Leasing | DF4: Renta | DG4: Capital | DH4: Saldo_Capital | DI4: Interes_Residual | DJ4: Saldo_Residual | DK4: Ingreso_Financiero | DL4: Saldo_Cartera | DM4: Saldo_Inicial | DN4: Interes_Leasing | DO4: Renta | DP4: Capital | DQ4: Saldo_Capital | DR4: Interes_Residual | DS4: Saldo_Residual | DT4: Ingreso_Financiero | DU4: Saldo_Cartera | DV4: Saldo_Inicial | DW4: Interes_Leasing | DX4: Renta | DY4: Capital | DZ4: Saldo_Capital | EA4: Interes_Residual | EB4: Saldo_Residual | EC4: Ingreso_Financiero | ED4: Saldo_Cartera | EE4: Saldo_Inicial | EF4: Interes_Leasing | EG4: Renta | EH4: Capital | EI4: Saldo_Capital | EJ4: Interes_Residual | EK4: Saldo_Residual | EL4: Ingreso_Financiero | EM4: Saldo_Cartera | EN4: Saldo_Inicial | EO4: Interes_Leasing | EP4: Renta | EQ4: Capital | ER4: Saldo_Capital | ES4: Interes_Residual | ET4: Saldo_Residual | EU4: Ingreso_Financiero | EV4: Saldo_Cartera | EW4: Saldo_Inicial | EX4: Interes_Leasing | EY4: Renta | EZ4: Capital | FA4: Saldo_Capital | FB4: Interes_Residual | FC4: Saldo_Residual | FD4: Ingreso_Financiero | FE4: Saldo_Cartera | FF4: Saldo_Inicial | FG4: Interes_Leasing | FH4: Renta | FI4: Capital | FJ4: Saldo_Capital | FK4: Interes_Residual | FL4: Saldo_Residual | FM4: Ingreso_Financiero | FN4: Saldo_Cartera | FO4: Saldo_Inicial | FP4: Interes_Leasing | FQ4: Renta | FR4: Capital | FS4: Saldo_Capital | FT4: Interes_Residual | FU4: Saldo_Residual | FV4: Ingreso_Financiero | FW4: Saldo_Cartera | FX4: Saldo_Inicial | FY4: Interes_Leasing | FZ4: Renta | GA4: Capital | GB4: Saldo_Capital | GC4: Interes_Residual | GD4: Saldo_Residual | GE4: Ingreso_Financiero | GF4: Saldo_Cartera | GG4: Saldo_Inicial | GH4: Interes_Leasing | GI4: Renta | GJ4: Capital | GK4: Saldo_Capital | GL4: Interes_Residual | GM4: Saldo_Residual | GN4: Ingreso_Financiero | GO4: Saldo_Cartera | GP4: Saldo_Inicial | GQ4: Interes_Leasing | GR4: Renta | GS4: Capital | GT4: Saldo_Capital | GU4: Interes_Residual | GV4: Saldo_Residual | GW4: Ingreso_Financiero | GX4: Saldo_Cartera | GY4: Saldo_Inicial | GZ4: Interes_Leasing | HA4: Renta | HB4: Capital | HC4: Saldo_Capital | HD4: Interes_Residual | HE4: Saldo_Residual | HF4: Ingreso_Financiero | HG4: Saldo_Cartera | HH4: Saldo_Inicial | HI4: Interes_Leasing | HJ4: Renta | HK4: Capital | HL4: Saldo_Capital | HM4: Interes_Residual | HN4: Saldo_Residual | HO4: Ingreso_Financiero | HP4: Saldo_Cartera | HQ4: Saldo_Inicial | HR4: Interes_Leasing | HS4: Renta | HT4: Capital | HU4: Saldo_Capital | HV4: Interes_Residual | HW4: Saldo_Residual | HX4: Ingreso_Financiero | HY4: Saldo_Cartera | HZ4: Saldo_Inicial | IA4: Interes_Leasing | IB4: Renta | IC4: Capital | ID4: Saldo_Capital | IE4: Interes_Residual | IF4: Saldo_Residual | IG4: Ingreso_Financiero | IH4: Saldo_Cartera | II4: Saldo_Inicial | IJ4: Interes_Leasing | IK4: Renta | IL4: Capital | IM4: Saldo_Capital | IN4: Interes_Residual | IO4: Saldo_Residual | IP4: Ingreso_Financiero | IQ4: Saldo_Cartera | IR4: Saldo_Inicial | IS4: Interes_Leasing | IT4: Renta | IU4: Capital | IV4: Saldo_Capital | IW4: Interes_Residual | IX4: Saldo_Residual | IY4: Ingreso_Financiero | IZ4: Saldo_Cartera | JA4: Saldo_Inicial | JB4: Interes_Leasing | JC4: Renta | JD4: Capital | JE4: Saldo_Capital | JF4: Interes_Residual | JG4: Saldo_Residual | JH4: Ingreso_Financiero | JI4: Saldo_Cartera | JJ4: Saldo_Inicial | JK4: Interes_Leasing | JL4: Renta | JM4: Capital | JN4: Saldo_Capital | JO4: Interes_Residual | JP4: Saldo_Residual | JQ4: Ingreso_Financiero | JR4: Saldo_Cartera | JS4: Saldo_Inicial | JT4: Interes_Leasing | JU4: Renta | JV4: Capital | JW4: Saldo_Capital | JX4: Interes_Residual | JY4: Saldo_Residual | JZ4: Ingreso_Financiero | KA4: Saldo_Cartera | KB4: Saldo_Inicial | KC4: Interes_Leasing | KD4: Renta | KE4: Capital | KF4: Saldo_Capital | KG4: Interes_Residual | KH4: Saldo_Residual | KI4: Ingreso_Financiero | KJ4: Saldo_Cartera | KK4: Saldo_Inicial | KL4: Interes_Leasing | KM4: Renta | KN4: Capital | KO4: Saldo_Capital | KP4: Interes_Residual | KQ4: Saldo_Residual | KR4: Ingreso_Financiero | KS4: Saldo_Cartera | KT4: Saldo_Inicial | KU4: Interes_Leasing | KV4: Renta | KW4: Capital | KX4: Saldo_Capital | KY4: Interes_Residual | KZ4: Saldo_Residual | LA4: Ingreso_Financiero | LB4: Saldo_Cartera | LC4: Saldo_Inicial | LD4: Interes_Leasing | LE4: Renta | LF4: Capital | LG4: Saldo_Capital | LH4: Interes_Residual | LI4: Saldo_Residual | LJ4: Ingreso_Financiero | LK4: Saldo_Cartera | LL4: Saldo_Inicial | LM4: Interes_Leasing | LN4: Renta | LO4: Capital | LP4: Saldo_Capital | LQ4: Interes_Residual | LR4: Saldo_Residual | LS4: Ingreso_Financiero | LT4: Saldo_Cartera | LU4: Saldo_Inicial | LV4: Interes_Leasing | LW4: Renta | LX4: Capital | LY4: Saldo_Capital | LZ4: Interes_Residual | MA4: Saldo_Residual | MB4: Ingreso_Financiero | MC4: Saldo_Cartera | MD4: Saldo_Inicial | ME4: Interes_Leasing | MF4: Renta | MG4: Capital | MH4: Saldo_Capital | MI4: Interes_Residual | MJ4: Saldo_Residual | MK4: Ingreso_Financiero | ML4: Saldo_Cartera | MM4: Saldo_Inicial | MN4: Interes_Leasing | MO4: Renta | MP4: Capital | MQ4: Saldo_Capital | MR4: Interes_Residual | MS4: Saldo_Residual | MT4: Ingreso_Financiero | MU4: Saldo_Cartera | MV4: Saldo_Inicial | MW4: Interes_Leasing | MX4: Renta | MY4: Capital | MZ4: Saldo_Capital | NA4: Interes_Residual | NB4: Saldo_Residual | NC4: Ingreso_Financiero | ND4: Saldo_Cartera | NE4: Saldo_Inicial | NF4: Interes_Leasing | NG4: Renta | NH4: Capital | NI4: Saldo_Capital | NJ4: Interes_Residual | NK4: Saldo_Residual | NL4: Ingreso_Financiero | NM4: Saldo_Cartera | NN4: Saldo_Inicial | NO4: Interes_Leasing | NP4: Renta | NQ4: Capital | NR4: Saldo_Capital | NS4: Interes_Residual | NT4: Saldo_Residual | NU4: Ingreso_Financiero | NV4: Saldo_Cartera | NW4: Saldo_Inicial | NX4: Interes_Leasing | NY4: Renta | NZ4: Capital | OA4: Saldo_Capital | OB4: Interes_Residual | OC4: Saldo_Residual | OD4: Ingreso_Financiero | OE4: Saldo_Cartera | OF4: Saldo_Inicial | OG4: Interes_Leasing | OH4: Renta | OI4: Capital | OJ4: Saldo_Capital | OK4: Interes_Residual | OL4: Saldo_Residual | OM4: Ingreso_Financiero | ON4: Saldo_Cartera | OO4: Saldo_Inicial | OP4: Interes_Leasing | OQ4: Renta | OR4: Capital | OS4: Saldo_Capital | OT4: Interes_Residual | OU4: Saldo_Residual | OV4: Ingreso_Financiero | OW4: Saldo_Cartera | OX4: Saldo_Inicial | OY4: Interes_Leasing | OZ4: Renta | PA4: Capital | PB4: Saldo_Capital | PC4: Interes_Residual | PD4: Saldo_Residual | PE4: Ingreso_Financiero | PF4: Saldo_Cartera | PG4: Saldo_Inicial | PH4: Interes_Leasing | PI4: Renta | PJ4: Capital | PK4: Saldo_Capital | PL4: Interes_Residual | PM4: Saldo_Residual | PN4: Ingreso_Financiero | PO4: Saldo_Cartera | PP4: Saldo_Inicial | PQ4: Interes_Leasing | PR4: Renta | PS4: Capital | PT4: Saldo_Capital | PU4: Interes_Residual | PV4: Saldo_Residual | PW4: Ingreso_Financiero | PX4: Saldo_Cartera | PY4: Saldo_Inicial | PZ4: Interes_Leasing | QA4: Renta | QB4: Capital | QC4: Saldo_Capital | QD4: Interes_Residual | QE4: Saldo_Residual | QF4: Ingreso_Financiero | QG4: Saldo_Cartera | QH4: Saldo_Inicial | QI4: Interes_Leasing | QJ4: Renta | QK4: Capital | QL4: Saldo_Capital | QM4: Interes_Residual | QN4: Saldo_Residual | QO4: Ingreso_Financiero | QP4: Saldo_Cartera
A5: 0326-0003 | B5: Alberto Vázquez Solorio | C5: Volkswagen Tiguan R-Line 2026 | D5: ACTIVO | E5: 2026-09-16 | F5: 2030-09-16 | G5: 48 | H5: 645181.9 | I5: 0.3705 | J5: =ROUND(H5*I5, 2) | K5: =ROUND(H5-J5, 2) | L5: 0 | M5: =ROUND(H5*L5, 2) | N5: 8393.91 | O5: 0.28 | P5: =ROUND(H5*O5, 2) | Q5: 0.01206146 | R5: =RATE(G5, -N5, K5, -P5) | S5: =ROUND(Q5*12, 8) | T5: =ROUND(((1+Q5)^12)-1, 8) | U5: =ROUND(PV(Q5, G5, 0, -P5), 2) | V5: =SUMIF($AA$4:$QP$4, "Interes_Leasing", AA5:QP5) | W5: =SUMIF($AA$4:$QP$4, "Interes_Residual", AA5:QP5) | X5: =ROUND(V5+W5, 2) | Y5: =ROUND((N5*G5+P5+M5)-K5, 2) | Z5: =ROUND(Y5/K5, 4) | AA5: =IF(1<=$G5, $K5, "") | AB5: =IF(1<=$G5, ROUND(AA5*$Q5, 2), "") | AC5: =IF(1<=$G5, $N5, "") | AD5: =IF(1<=$G5, AC5-AB5, "") | AE5: =IF(1<=$G5, AA5-AD5, "") | AF5: =IF(1<=$G5, ROUND($U5*$Q5, 2), "") | AG5: =IF(1<=$G5, $U5+AF5, "") | AH5: =IF(1<=$G5, AB5+AF5, "") | AI5: =IF(1<=$G5, ($G5-1)*$N5, "") | AJ5: =IF(2<=$G5, AE5, "") | AK5: =IF(2<=$G5, ROUND(AJ5*$Q5, 2), "") | AL5: =IF(2<=$G5, $N5, "") | AM5: =IF(2<=$G5, AL5-AK5, "") | AN5: =IF(2<=$G5, AJ5-AM5, "") | AO5: =IF(2<=$G5, ROUND(AG5*$Q5, 2), "") | AP5: =IF(2<=$G5, AG5+AO5, "") | AQ5: =IF(2<=$G5, AK5+AO5, "") | AR5: =IF(2<=$G5, ($G5-2)*$N5, "") | AS5: =IF(3<=$G5, AN5, "") | AT5: =IF(3<=$G5, ROUND(AS5*$Q5, 2), "") | AU5: =IF(3<=$G5, $N5, "") | AV5: =IF(3<=$G5, AU5-AT5, "") | AW5: =IF(3<=$G5, AS5-AV5, "") | AX5: =IF(3<=$G5, ROUND(AP5*$Q5, 2), "") | AY5: =IF(3<=$G5, AP5+AX5, "") | AZ5: =IF(3<=$G5, AT5+AX5, "") | BA5: =IF(3<=$G5, ($G5-3)*$N5, "") | BB5: =IF(4<=$G5, AW5, "") | BC5: =IF(4<=$G5, ROUND(BB5*$Q5, 2), "") | BD5: =IF(4<=$G5, $N5, "") | BE5: =IF(4<=$G5, BD5-BC5, "") | BF5: =IF(4<=$G5, BB5-BE5, "") | BG5: =IF(4<=$G5, ROUND(AY5*$Q5, 2), "") | BH5: =IF(4<=$G5, AY5+BG5, "") | BI5: =IF(4<=$G5, BC5+BG5, "") | BJ5: =IF(4<=$G5, ($G5-4)*$N5, "") | BK5: =IF(5<=$G5, BF5, "") | BL5: =IF(5<=$G5, ROUND(BK5*$Q5, 2), "") | BM5: =IF(5<=$G5, $N5, "") | BN5: =IF(5<=$G5, BM5-BL5, "") | BO5: =IF(5<=$G5, BK5-BN5, "") | BP5: =IF(5<=$G5, ROUND(BH5*$Q5, 2), "") | BQ5: =IF(5<=$G5, BH5+BP5, "") | BR5: =IF(5<=$G5, BL5+BP5, "") | BS5: =IF(5<=$G5, ($G5-5)*$N5, "") | BT5: =IF(6<=$G5, BO5, "") | BU5: =IF(6<=$G5, ROUND(BT5*$Q5, 2), "") | BV5: =IF(6<=$G5, $N5, "") | BW5: =IF(6<=$G5, BV5-BU5, "") | BX5: =IF(6<=$G5, BT5-BW5, "") | BY5: =IF(6<=$G5, ROUND(BQ5*$Q5, 2), "") | BZ5: =IF(6<=$G5, BQ5+BY5, "") | CA5: =IF(6<=$G5, BU5+BY5, "") | CB5: =IF(6<=$G5, ($G5-6)*$N5, "") | CC5: =IF(7<=$G5, BX5, "") | CD5: =IF(7<=$G5, ROUND(CC5*$Q5, 2), "") | CE5: =IF(7<=$G5, $N5, "") | CF5: =IF(7<=$G5, CE5-CD5, "") | CG5: =IF(7<=$G5, CC5-CF5, "") | CH5: =IF(7<=$G5, ROUND(BZ5*$Q5, 2), "") | CI5: =IF(7<=$G5, BZ5+CH5, "") | CJ5: =IF(7<=$G5, CD5+CH5, "") | CK5: =IF(7<=$G5, ($G5-7)*$N5, "") | CL5: =IF(8<=$G5, CG5, "") | CM5: =IF(8<=$G5, ROUND(CL5*$Q5, 2), "") | CN5: =IF(8<=$G5, $N5, "") | CO5: =IF(8<=$G5, CN5-CM5, "") | CP5: =IF(8<=$G5, CL5-CO5, "") | CQ5: =IF(8<=$G5, ROUND(CI5*$Q5, 2), "") | CR5: =IF(8<=$G5, CI5+CQ5, "") | CS5: =IF(8<=$G5, CM5+CQ5, "") | CT5: =IF(8<=$G5, ($G5-8)*$N5, "") | CU5: =IF(9<=$G5, CP5, "") | CV5: =IF(9<=$G5, ROUND(CU5*$Q5, 2), "") | CW5: =IF(9<=$G5, $N5, "") | CX5: =IF(9<=$G5, CW5-CV5, "") | CY5: =IF(9<=$G5, CU5-CX5, "") | CZ5: =IF(9<=$G5, ROUND(CR5*$Q5, 2), "") | DA5: =IF(9<=$G5, CR5+CZ5, "") | DB5: =IF(9<=$G5, CV5+CZ5, "") | DC5: =IF(9<=$G5, ($G5-9)*$N5, "") | DD5: =IF(10<=$G5, CY5, "") | DE5: =IF(10<=$G5, ROUND(DD5*$Q5, 2), "") | DF5: =IF(10<=$G5, $N5, "") | DG5: =IF(10<=$G5, DF5-DE5, "") | DH5: =IF(10<=$G5, DD5-DG5, "") | DI5: =IF(10<=$G5, ROUND(DA5*$Q5, 2), "") | DJ5: =IF(10<=$G5, DA5+DI5, "") | DK5: =IF(10<=$G5, DE5+DI5, "") | DL5: =IF(10<=$G5, ($G5-10)*$N5, "") | DM5: =IF(11<=$G5, DH5, "") | DN5: =IF(11<=$G5, ROUND(DM5*$Q5, 2), "") | DO5: =IF(11<=$G5, $N5, "") | DP5: =IF(11<=$G5, DO5-DN5, "") | DQ5: =IF(11<=$G5, DM5-DP5, "") | DR5: =IF(11<=$G5, ROUND(DJ5*$Q5, 2), "") | DS5: =IF(11<=$G5, DJ5+DR5, "") | DT5: =IF(11<=$G5, DN5+DR5, "") | DU5: =IF(11<=$G5, ($G5-11)*$N5, "") | DV5: =IF(12<=$G5, DQ5, "") | DW5: =IF(12<=$G5, ROUND(DV5*$Q5, 2), "") | DX5: =IF(12<=$G5, $N5, "") | DY5: =IF(12<=$G5, DX5-DW5, "") | DZ5: =IF(12<=$G5, DV5-DY5, "") | EA5: =IF(12<=$G5, ROUND(DS5*$Q5, 2), "") | EB5: =IF(12<=$G5, DS5+EA5, "") | EC5: =IF(12<=$G5, DW5+EA5, "") | ED5: =IF(12<=$G5, ($G5-12)*$N5, "") | EE5: =IF(13<=$G5, DZ5, "") | EF5: =IF(13<=$G5, ROUND(EE5*$Q5, 2), "") | EG5: =IF(13<=$G5, $N5, "") | EH5: =IF(13<=$G5, EG5-EF5, "") | EI5: =IF(13<=$G5, EE5-EH5, "") | EJ5: =IF(13<=$G5, ROUND(EB5*$Q5, 2), "") | EK5: =IF(13<=$G5, EB5+EJ5, "") | EL5: =IF(13<=$G5, EF5+EJ5, "") | EM5: =IF(13<=$G5, ($G5-13)*$N5, "") | EN5: =IF(14<=$G5, EI5, "") | EO5: =IF(14<=$G5, ROUND(EN5*$Q5, 2), "") | EP5: =IF(14<=$G5, $N5, "") | EQ5: =IF(14<=$G5, EP5-EO5, "") | ER5: =IF(14<=$G5, EN5-EQ5, "") | ES5: =IF(14<=$G5, ROUND(EK5*$Q5, 2), "") | ET5: =IF(14<=$G5, EK5+ES5, "") | EU5: =IF(14<=$G5, EO5+ES5, "") | EV5: =IF(14<=$G5, ($G5-14)*$N5, "") | EW5: =IF(15<=$G5, ER5, "") | EX5: =IF(15<=$G5, ROUND(EW5*$Q5, 2), "") | EY5: =IF(15<=$G5, $N5, "") | EZ5: =IF(15<=$G5, EY5-EX5, "") | FA5: =IF(15<=$G5, EW5-EZ5, "") | FB5: =IF(15<=$G5, ROUND(ET5*$Q5, 2), "") | FC5: =IF(15<=$G5, ET5+FB5, "") | FD5: =IF(15<=$G5, EX5+FB5, "") | FE5: =IF(15<=$G5, ($G5-15)*$N5, "") | FF5: =IF(16<=$G5, FA5, "") | FG5: =IF(16<=$G5, ROUND(FF5*$Q5, 2), "") | FH5: =IF(16<=$G5, $N5, "") | FI5: =IF(16<=$G5, FH5-FG5, "") | FJ5: =IF(16<=$G5, FF5-FI5, "") | FK5: =IF(16<=$G5, ROUND(FC5*$Q5, 2), "") | FL5: =IF(16<=$G5, FC5+FK5, "") | FM5: =IF(16<=$G5, FG5+FK5, "") | FN5: =IF(16<=$G5, ($G5-16)*$N5, "") | FO5: =IF(17<=$G5, FJ5, "") | FP5: =IF(17<=$G5, ROUND(FO5*$Q5, 2), "") | FQ5: =IF(17<=$G5, $N5, "") | FR5: =IF(17<=$G5, FQ5-FP5, "") | FS5: =IF(17<=$G5, FO5-FR5, "") | FT5: =IF(17<=$G5, ROUND(FL5*$Q5, 2), "") | FU5: =IF(17<=$G5, FL5+FT5, "") | FV5: =IF(17<=$G5, FP5+FT5, "") | FW5: =IF(17<=$G5, ($G5-17)*$N5, "") | FX5: =IF(18<=$G5, FS5, "") | FY5: =IF(18<=$G5, ROUND(FX5*$Q5, 2), "") | FZ5: =IF(18<=$G5, $N5, "") | GA5: =IF(18<=$G5, FZ5-FY5, "") | GB5: =IF(18<=$G5, FX5-GA5, "") | GC5: =IF(18<=$G5, ROUND(FU5*$Q5, 2), "") | GD5: =IF(18<=$G5, FU5+GC5, "") | GE5: =IF(18<=$G5, FY5+GC5, "") | GF5: =IF(18<=$G5, ($G5-18)*$N5, "") | GG5: =IF(19<=$G5, GB5, "") | GH5: =IF(19<=$G5, ROUND(GG5*$Q5, 2), "") | GI5: =IF(19<=$G5, $N5, "") | GJ5: =IF(19<=$G5, GI5-GH5, "") | GK5: =IF(19<=$G5, GG5-GJ5, "") | GL5: =IF(19<=$G5, ROUND(GD5*$Q5, 2), "") | GM5: =IF(19<=$G5, GD5+GL5, "") | GN5: =IF(19<=$G5, GH5+GL5, "") | GO5: =IF(19<=$G5, ($G5-19)*$N5, "") | GP5: =IF(20<=$G5, GK5, "") | GQ5: =IF(20<=$G5, ROUND(GP5*$Q5, 2), "") | GR5: =IF(20<=$G5, $N5, "") | GS5: =IF(20<=$G5, GR5-GQ5, "") | GT5: =IF(20<=$G5, GP5-GS5, "") | GU5: =IF(20<=$G5, ROUND(GM5*$Q5, 2), "") | GV5: =IF(20<=$G5, GM5+GU5, "") | GW5: =IF(20<=$G5, GQ5+GU5, "") | GX5: =IF(20<=$G5, ($G5-20)*$N5, "") | GY5: =IF(21<=$G5, GT5, "") | GZ5: =IF(21<=$G5, ROUND(GY5*$Q5, 2), "") | HA5: =IF(21<=$G5, $N5, "") | HB5: =IF(21<=$G5, HA5-GZ5, "") | HC5: =IF(21<=$G5, GY5-HB5, "") | HD5: =IF(21<=$G5, ROUND(GV5*$Q5, 2), "") | HE5: =IF(21<=$G5, GV5+HD5, "") | HF5: =IF(21<=$G5, GZ5+HD5, "") | HG5: =IF(21<=$G5, ($G5-21)*$N5, "") | HH5: =IF(22<=$G5, HC5, "") | HI5: =IF(22<=$G5, ROUND(HH5*$Q5, 2), "") | HJ5: =IF(22<=$G5, $N5, "") | HK5: =IF(22<=$G5, HJ5-HI5, "") | HL5: =IF(22<=$G5, HH5-HK5, "") | HM5: =IF(22<=$G5, ROUND(HE5*$Q5, 2), "") | HN5: =IF(22<=$G5, HE5+HM5, "") | HO5: =IF(22<=$G5, HI5+HM5, "") | HP5: =IF(22<=$G5, ($G5-22)*$N5, "") | HQ5: =IF(23<=$G5, HL5, "") | HR5: =IF(23<=$G5, ROUND(HQ5*$Q5, 2), "") | HS5: =IF(23<=$G5, $N5, "") | HT5: =IF(23<=$G5, HS5-HR5, "") | HU5: =IF(23<=$G5, HQ5-HT5, "") | HV5: =IF(23<=$G5, ROUND(HN5*$Q5, 2), "") | HW5: =IF(23<=$G5, HN5+HV5, "") | HX5: =IF(23<=$G5, HR5+HV5, "") | HY5: =IF(23<=$G5, ($G5-23)*$N5, "") | HZ5: =IF(24<=$G5, HU5, "") | IA5: =IF(24<=$G5, ROUND(HZ5*$Q5, 2), "") | IB5: =IF(24<=$G5, $N5, "") | IC5: =IF(24<=$G5, IB5-IA5, "") | ID5: =IF(24<=$G5, HZ5-IC5, "") | IE5: =IF(24<=$G5, ROUND(HW5*$Q5, 2), "") | IF5: =IF(24<=$G5, HW5+IE5, "") | IG5: =IF(24<=$G5, IA5+IE5, "") | IH5: =IF(24<=$G5, ($G5-24)*$N5, "") | II5: =IF(25<=$G5, ID5, "") | IJ5: =IF(25<=$G5, ROUND(II5*$Q5, 2), "") | IK5: =IF(25<=$G5, $N5, "") | IL5: =IF(25<=$G5, IK5-IJ5, "") | IM5: =IF(25<=$G5, II5-IL5, "") | IN5: =IF(25<=$G5, ROUND(IF5*$Q5, 2), "") | IO5: =IF(25<=$G5, IF5+IN5, "") | IP5: =IF(25<=$G5, IJ5+IN5, "") | IQ5: =IF(25<=$G5, ($G5-25)*$N5, "") | IR5: =IF(26<=$G5, IM5, "") | IS5: =IF(26<=$G5, ROUND(IR5*$Q5, 2), "") | IT5: =IF(26<=$G5, $N5, "") | IU5: =IF(26<=$G5, IT5-IS5, "") | IV5: =IF(26<=$G5, IR5-IU5, "") | IW5: =IF(26<=$G5, ROUND(IO5*$Q5, 2), "") | IX5: =IF(26<=$G5, IO5+IW5, "") | IY5: =IF(26<=$G5, IS5+IW5, "") | IZ5: =IF(26<=$G5, ($G5-26)*$N5, "") | JA5: =IF(27<=$G5, IV5, "") | JB5: =IF(27<=$G5, ROUND(JA5*$Q5, 2), "") | JC5: =IF(27<=$G5, $N5, "") | JD5: =IF(27<=$G5, JC5-JB5, "") | JE5: =IF(27<=$G5, JA5-JD5, "") | JF5: =IF(27<=$G5, ROUND(IX5*$Q5, 2), "") | JG5: =IF(27<=$G5, IX5+JF5, "") | JH5: =IF(27<=$G5, JB5+JF5, "") | JI5: =IF(27<=$G5, ($G5-27)*$N5, "") | JJ5: =IF(28<=$G5, JE5, "") | JK5: =IF(28<=$G5, ROUND(JJ5*$Q5, 2), "") | JL5: =IF(28<=$G5, $N5, "") | JM5: =IF(28<=$G5, JL5-JK5, "") | JN5: =IF(28<=$G5, JJ5-JM5, "") | JO5: =IF(28<=$G5, ROUND(JG5*$Q5, 2), "") | JP5: =IF(28<=$G5, JG5+JO5, "") | JQ5: =IF(28<=$G5, JK5+JO5, "") | JR5: =IF(28<=$G5, ($G5-28)*$N5, "") | JS5: =IF(29<=$G5, JN5, "") | JT5: =IF(29<=$G5, ROUND(JS5*$Q5, 2), "") | JU5: =IF(29<=$G5, $N5, "") | JV5: =IF(29<=$G5, JU5-JT5, "") | JW5: =IF(29<=$G5, JS5-JV5, "") | JX5: =IF(29<=$G5, ROUND(JP5*$Q5, 2), "") | JY5: =IF(29<=$G5, JP5+JX5, "") | JZ5: =IF(29<=$G5, JT5+JX5, "") | KA5: =IF(29<=$G5, ($G5-29)*$N5, "") | KB5: =IF(30<=$G5, JW5, "") | KC5: =IF(30<=$G5, ROUND(KB5*$Q5, 2), "") | KD5: =IF(30<=$G5, $N5, "") | KE5: =IF(30<=$G5, KD5-KC5, "") | KF5: =IF(30<=$G5, KB5-KE5, "") | KG5: =IF(30<=$G5, ROUND(JY5*$Q5, 2), "") | KH5: =IF(30<=$G5, JY5+KG5, "") | KI5: =IF(30<=$G5, KC5+KG5, "") | KJ5: =IF(30<=$G5, ($G5-30)*$N5, "") | KK5: =IF(31<=$G5, KF5, "") | KL5: =IF(31<=$G5, ROUND(KK5*$Q5, 2), "") | KM5: =IF(31<=$G5, $N5, "") | KN5: =IF(31<=$G5, KM5-KL5, "") | KO5: =IF(31<=$G5, KK5-KN5, "") | KP5: =IF(31<=$G5, ROUND(KH5*$Q5, 2), "") | KQ5: =IF(31<=$G5, KH5+KP5, "") | KR5: =IF(31<=$G5, KL5+KP5, "") | KS5: =IF(31<=$G5, ($G5-31)*$N5, "") | KT5: =IF(32<=$G5, KO5, "") | KU5: =IF(32<=$G5, ROUND(KT5*$Q5, 2), "") | KV5: =IF(32<=$G5, $N5, "") | KW5: =IF(32<=$G5, KV5-KU5, "") | KX5: =IF(32<=$G5, KT5-KW5, "") | KY5: =IF(32<=$G5, ROUND(KQ5*$Q5, 2), "") | KZ5: =IF(32<=$G5, KQ5+KY5, "") | LA5: =IF(32<=$G5, KU5+KY5, "") | LB5: =IF(32<=$G5, ($G5-32)*$N5, "") | LC5: =IF(33<=$G5, KX5, "") | LD5: =IF(33<=$G5, ROUND(LC5*$Q5, 2), "") | LE5: =IF(33<=$G5, $N5, "") | LF5: =IF(33<=$G5, LE5-LD5, "") | LG5: =IF(33<=$G5, LC5-LF5, "") | LH5: =IF(33<=$G5, ROUND(KZ5*$Q5, 2), "") | LI5: =IF(33<=$G5, KZ5+LH5, "") | LJ5: =IF(33<=$G5, LD5+LH5, "") | LK5: =IF(33<=$G5, ($G5-33)*$N5, "") | LL5: =IF(34<=$G5, LG5, "") | LM5: =IF(34<=$G5, ROUND(LL5*$Q5, 2), "") | LN5: =IF(34<=$G5, $N5, "") | LO5: =IF(34<=$G5, LN5-LM5, "") | LP5: =IF(34<=$G5, LL5-LO5, "") | LQ5: =IF(34<=$G5, ROUND(LI5*$Q5, 2), "") | LR5: =IF(34<=$G5, LI5+LQ5, "") | LS5: =IF(34<=$G5, LM5+LQ5, "") | LT5: =IF(34<=$G5, ($G5-34)*$N5, "") | LU5: =IF(35<=$G5, LP5, "") | LV5: =IF(35<=$G5, ROUND(LU5*$Q5, 2), "") | LW5: =IF(35<=$G5, $N5, "") | LX5: =IF(35<=$G5, LW5-LV5, "") | LY5: =IF(35<=$G5, LU5-LX5, "") | LZ5: =IF(35<=$G5, ROUND(LR5*$Q5, 2), "") | MA5: =IF(35<=$G5, LR5+LZ5, "") | MB5: =IF(35<=$G5, LV5+LZ5, "") | MC5: =IF(35<=$G5, ($G5-35)*$N5, "") | MD5: =IF(36<=$G5, LY5, "") | ME5: =IF(36<=$G5, ROUND(MD5*$Q5, 2), "") | MF5: =IF(36<=$G5, $N5, "") | MG5: =IF(36<=$G5, MF5-ME5, "") | MH5: =IF(36<=$G5, MD5-MG5, "") | MI5: =IF(36<=$G5, ROUND(MA5*$Q5, 2), "") | MJ5: =IF(36<=$G5, MA5+MI5, "") | MK5: =IF(36<=$G5, ME5+MI5, "") | ML5: =IF(36<=$G5, ($G5-36)*$N5, "") | MM5: =IF(37<=$G5, MH5, "") | MN5: =IF(37<=$G5, ROUND(MM5*$Q5, 2), "") | MO5: =IF(37<=$G5, $N5, "") | MP5: =IF(37<=$G5, MO5-MN5, "") | MQ5: =IF(37<=$G5, MM5-MP5, "") | MR5: =IF(37<=$G5, ROUND(MJ5*$Q5, 2), "") | MS5: =IF(37<=$G5, MJ5+MR5, "") | MT5: =IF(37<=$G5, MN5+MR5, "") | MU5: =IF(37<=$G5, ($G5-37)*$N5, "") | MV5: =IF(38<=$G5, MQ5, "") | MW5: =IF(38<=$G5, ROUND(MV5*$Q5, 2), "") | MX5: =IF(38<=$G5, $N5, "") | MY5: =IF(38<=$G5, MX5-MW5, "") | MZ5: =IF(38<=$G5, MV5-MY5, "") | NA5: =IF(38<=$G5, ROUND(MS5*$Q5, 2), "") | NB5: =IF(38<=$G5, MS5+NA5, "") | NC5: =IF(38<=$G5, MW5+NA5, "") | ND5: =IF(38<=$G5, ($G5-38)*$N5, "") | NE5: =IF(39<=$G5, MZ5, "") | NF5: =IF(39<=$G5, ROUND(NE5*$Q5, 2), "") | NG5: =IF(39<=$G5, $N5, "") | NH5: =IF(39<=$G5, NG5-NF5, "") | NI5: =IF(39<=$G5, NE5-NH5, "") | NJ5: =IF(39<=$G5, ROUND(NB5*$Q5, 2), "") | NK5: =IF(39<=$G5, NB5+NJ5, "") | NL5: =IF(39<=$G5, NF5+NJ5, "") | NM5: =IF(39<=$G5, ($G5-39)*$N5, "") | NN5: =IF(40<=$G5, NI5, "") | NO5: =IF(40<=$G5, ROUND(NN5*$Q5, 2), "") | NP5: =IF(40<=$G5, $N5, "") | NQ5: =IF(40<=$G5, NP5-NO5, "") | NR5: =IF(40<=$G5, NN5-NQ5, "") | NS5: =IF(40<=$G5, ROUND(NK5*$Q5, 2), "") | NT5: =IF(40<=$G5, NK5+NS5, "") | NU5: =IF(40<=$G5, NO5+NS5, "") | NV5: =IF(40<=$G5, ($G5-40)*$N5, "") | NW5: =IF(41<=$G5, NR5, "") | NX5: =IF(41<=$G5, ROUND(NW5*$Q5, 2), "") | NY5: =IF(41<=$G5, $N5, "") | NZ5: =IF(41<=$G5, NY5-NX5, "") | OA5: =IF(41<=$G5, NW5-NZ5, "") | OB5: =IF(41<=$G5, ROUND(NT5*$Q5, 2), "") | OC5: =IF(41<=$G5, NT5+OB5, "") | OD5: =IF(41<=$G5, NX5+OB5, "") | OE5: =IF(41<=$G5, ($G5-41)*$N5, "") | OF5: =IF(42<=$G5, OA5, "") | OG5: =IF(42<=$G5, ROUND(OF5*$Q5, 2), "") | OH5: =IF(42<=$G5, $N5, "") | OI5: =IF(42<=$G5, OH5-OG5, "") | OJ5: =IF(42<=$G5, OF5-OI5, "") | OK5: =IF(42<=$G5, ROUND(OC5*$Q5, 2), "") | OL5: =IF(42<=$G5, OC5+OK5, "") | OM5: =IF(42<=$G5, OG5+OK5, "") | ON5: =IF(42<=$G5, ($G5-42)*$N5, "") | OO5: =IF(43<=$G5, OJ5, "") | OP5: =IF(43<=$G5, ROUND(OO5*$Q5, 2), "") | OQ5: =IF(43<=$G5, $N5, "") | OR5: =IF(43<=$G5, OQ5-OP5, "") | OS5: =IF(43<=$G5, OO5-OR5, "") | OT5: =IF(43<=$G5, ROUND(OL5*$Q5, 2), "") | OU5: =IF(43<=$G5, OL5+OT5, "") | OV5: =IF(43<=$G5, OP5+OT5, "") | OW5: =IF(43<=$G5, ($G5-43)*$N5, "") | OX5: =IF(44<=$G5, OS5, "") | OY5: =IF(44<=$G5, ROUND(OX5*$Q5, 2), "") | OZ5: =IF(44<=$G5, $N5, "") | PA5: =IF(44<=$G5, OZ5-OY5, "") | PB5: =IF(44<=$G5, OX5-PA5, "") | PC5: =IF(44<=$G5, ROUND(OU5*$Q5, 2), "") | PD5: =IF(44<=$G5, OU5+PC5, "") | PE5: =IF(44<=$G5, OY5+PC5, "") | PF5: =IF(44<=$G5, ($G5-44)*$N5, "") | PG5: =IF(45<=$G5, PB5, "") | PH5: =IF(45<=$G5, ROUND(PG5*$Q5, 2), "") | PI5: =IF(45<=$G5, $N5, "") | PJ5: =IF(45<=$G5, PI5-PH5, "") | PK5: =IF(45<=$G5, PG5-PJ5, "") | PL5: =IF(45<=$G5, ROUND(PD5*$Q5, 2), "") | PM5: =IF(45<=$G5, PD5+PL5, "") | PN5: =IF(45<=$G5, PH5+PL5, "") | PO5: =IF(45<=$G5, ($G5-45)*$N5, "") | PP5: =IF(46<=$G5, PK5, "") | PQ5: =IF(46<=$G5, ROUND(PP5*$Q5, 2), "") | PR5: =IF(46<=$G5, $N5, "") | PS5: =IF(46<=$G5, PR5-PQ5, "") | PT5: =IF(46<=$G5, PP5-PS5, "") | PU5: =IF(46<=$G5, ROUND(PM5*$Q5, 2), "") | PV5: =IF(46<=$G5, PM5+PU5, "") | PW5: =IF(46<=$G5, PQ5+PU5, "") | PX5: =IF(46<=$G5, ($G5-46)*$N5, "") | PY5: =IF(47<=$G5, PT5, "") | PZ5: =IF(47<=$G5, ROUND(PY5*$Q5, 2), "") | QA5: =IF(47<=$G5, $N5, "") | QB5: =IF(47<=$G5, QA5-PZ5, "") | QC5: =IF(47<=$G5, PY5-QB5, "") | QD5: =IF(47<=$G5, ROUND(PV5*$Q5, 2), "") | QE5: =IF(47<=$G5, PV5+QD5, "") | QF5: =IF(47<=$G5, PZ5+QD5, "") | QG5: =IF(47<=$G5, ($G5-47)*$N5, "") | QH5: =IF(48<=$G5, QC5, "") | QI5: =IF(48<=$G5, ROUND(QH5*$Q5, 2), "") | QJ5: =IF(48<=$G5, $N5, "") | QK5: =IF(48<=$G5, QJ5-QI5, "") | QL5: =IF(48<=$G5, QH5-QK5, "") | QM5: =IF(48<=$G5, ROUND(QE5*$Q5, 2), "") | QN5: =IF(48<=$G5, QE5+QM5, "") | QO5: =IF(48<=$G5, QI5+QM5, "") | QP5: =IF(48<=$G5, ($G5-48)*$N5, "")
A6: 0472-0003 | B6: Miguel Zazueta Beltrán | C6: Jeep Grand Cherokee | D6: ACTIVO | E6: 2026-02-03 | F6: 2029-02-03 | G6: 36 | H6: 1217433.6 | I6: 0.3 | J6: =ROUND(H6*I6, 2) | K6: =ROUND(H6-J6, 2) | L6: 0.02 | M6: =ROUND(H6*L6, 2) | N6: 35031.5 | O6: 0.1 | P6: =ROUND(H6*O6, 2) | Q6: 0.02661776 | R6: =RATE(G6, -N6, K6, -P6) | S6: =ROUND(Q6*12, 8) | T6: =ROUND(((1+Q6)^12)-1, 8) | U6: =ROUND(PV(Q6, G6, 0, -P6), 2) | V6: =SUMIF($AA$4:$QP$4, "Interes_Leasing", AA6:QP6) | W6: =SUMIF($AA$4:$QP$4, "Interes_Residual", AA6:QP6) | X6: =ROUND(V6+W6, 2) | Y6: =ROUND((N6*G6+P6+M6)-K6, 2) | Z6: =ROUND(Y6/K6, 4) | AA6: =IF(1<=$G6, $K6, "") | AB6: =IF(1<=$G6, ROUND(AA6*$Q6, 2), "") | AC6: =IF(1<=$G6, $N6, "") | AD6: =IF(1<=$G6, AC6-AB6, "") | AE6: =IF(1<=$G6, AA6-AD6, "") | AF6: =IF(1<=$G6, ROUND($U6*$Q6, 2), "") | AG6: =IF(1<=$G6, $U6+AF6, "") | AH6: =IF(1<=$G6, AB6+AF6, "") | AI6: =IF(1<=$G6, ($G6-1)*$N6, "") | AJ6: =IF(2<=$G6, AE6, "") | AK6: =IF(2<=$G6, ROUND(AJ6*$Q6, 2), "") | AL6: =IF(2<=$G6, $N6, "") | AM6: =IF(2<=$G6, AL6-AK6, "") | AN6: =IF(2<=$G6, AJ6-AM6, "") | AO6: =IF(2<=$G6, ROUND(AG6*$Q6, 2), "") | AP6: =IF(2<=$G6, AG6+AO6, "") | AQ6: =IF(2<=$G6, AK6+AO6, "") | AR6: =IF(2<=$G6, ($G6-2)*$N6, "") | AS6: =IF(3<=$G6, AN6, "") | AT6: =IF(3<=$G6, ROUND(AS6*$Q6, 2), "") | AU6: =IF(3<=$G6, $N6, "") | AV6: =IF(3<=$G6, AU6-AT6, "") | AW6: =IF(3<=$G6, AS6-AV6, "") | AX6: =IF(3<=$G6, ROUND(AP6*$Q6, 2), "") | AY6: =IF(3<=$G6, AP6+AX6, "") | AZ6: =IF(3<=$G6, AT6+AX6, "") | BA6: =IF(3<=$G6, ($G6-3)*$N6, "") | BB6: =IF(4<=$G6, AW6, "") | BC6: =IF(4<=$G6, ROUND(BB6*$Q6, 2), "") | BD6: =IF(4<=$G6, $N6, "") | BE6: =IF(4<=$G6, BD6-BC6, "") | BF6: =IF(4<=$G6, BB6-BE6, "") | BG6: =IF(4<=$G6, ROUND(AY6*$Q6, 2), "") | BH6: =IF(4<=$G6, AY6+BG6, "") | BI6: =IF(4<=$G6, BC6+BG6, "") | BJ6: =IF(4<=$G6, ($G6-4)*$N6, "") | BK6: =IF(5<=$G6, BF6, "") | BL6: =IF(5<=$G6, ROUND(BK6*$Q6, 2), "") | BM6: =IF(5<=$G6, $N6, "") | BN6: =IF(5<=$G6, BM6-BL6, "") | BO6: =IF(5<=$G6, BK6-BN6, "") | BP6: =IF(5<=$G6, ROUND(BH6*$Q6, 2), "") | BQ6: =IF(5<=$G6, BH6+BP6, "") | BR6: =IF(5<=$G6, BL6+BP6, "") | BS6: =IF(5<=$G6, ($G6-5)*$N6, "") | BT6: =IF(6<=$G6, BO6, "") | BU6: =IF(6<=$G6, ROUND(BT6*$Q6, 2), "") | BV6: =IF(6<=$G6, $N6, "") | BW6: =IF(6<=$G6, BV6-BU6, "") | BX6: =IF(6<=$G6, BT6-BW6, "") | BY6: =IF(6<=$G6, ROUND(BQ6*$Q6, 2), "") | BZ6: =IF(6<=$G6, BQ6+BY6, "") | CA6: =IF(6<=$G6, BU6+BY6, "") | CB6: =IF(6<=$G6, ($G6-6)*$N6, "") | CC6: =IF(7<=$G6, BX6, "") | CD6: =IF(7<=$G6, ROUND(CC6*$Q6, 2), "") | CE6: =IF(7<=$G6, $N6, "") | CF6: =IF(7<=$G6, CE6-CD6, "") | CG6: =IF(7<=$G6, CC6-CF6, "") | CH6: =IF(7<=$G6, ROUND(BZ6*$Q6, 2), "") | CI6: =IF(7<=$G6, BZ6+CH6, "") | CJ6: =IF(7<=$G6, CD6+CH6, "") | CK6: =IF(7<=$G6, ($G6-7)*$N6, "") | CL6: =IF(8<=$G6, CG6, "") | CM6: =IF(8<=$G6, ROUND(CL6*$Q6, 2), "") | CN6: =IF(8<=$G6, $N6, "") | CO6: =IF(8<=$G6, CN6-CM6, "") | CP6: =IF(8<=$G6, CL6-CO6, "") | CQ6: =IF(8<=$G6, ROUND(CI6*$Q6, 2), "") | CR6: =IF(8<=$G6, CI6+CQ6, "") | CS6: =IF(8<=$G6, CM6+CQ6, "") | CT6: =IF(8<=$G6, ($G6-8)*$N6, "") | CU6: =IF(9<=$G6, CP6, "") | CV6: =IF(9<=$G6, ROUND(CU6*$Q6, 2), "") | CW6: =IF(9<=$G6, $N6, "") | CX6: =IF(9<=$G6, CW6-CV6, "") | CY6: =IF(9<=$G6, CU6-CX6, "") | CZ6: =IF(9<=$G6, ROUND(CR6*$Q6, 2), "") | DA6: =IF(9<=$G6, CR6+CZ6, "") | DB6: =IF(9<=$G6, CV6+CZ6, "") | DC6: =IF(9<=$G6, ($G6-9)*$N6, "") | DD6: =IF(10<=$G6, CY6, "") | DE6: =IF(10<=$G6, ROUND(DD6*$Q6, 2), "") | DF6: =IF(10<=$G6, $N6, "") | DG6: =IF(10<=$G6, DF6-DE6, "") | DH6: =IF(10<=$G6, DD6-DG6, "") | DI6: =IF(10<=$G6, ROUND(DA6*$Q6, 2), "") | DJ6: =IF(10<=$G6, DA6+DI6, "") | DK6: =IF(10<=$G6, DE6+DI6, "") | DL6: =IF(10<=$G6, ($G6-10)*$N6, "") | DM6: =IF(11<=$G6, DH6, "") | DN6: =IF(11<=$G6, ROUND(DM6*$Q6, 2), "") | DO6: =IF(11<=$G6, $N6, "") | DP6: =IF(11<=$G6, DO6-DN6, "") | DQ6: =IF(11<=$G6, DM6-DP6, "") | DR6: =IF(11<=$G6, ROUND(DJ6*$Q6, 2), "") | DS6: =IF(11<=$G6, DJ6+DR6, "") | DT6: =IF(11<=$G6, DN6+DR6, "") | DU6: =IF(11<=$G6, ($G6-11)*$N6, "") | DV6: =IF(12<=$G6, DQ6, "") | DW6: =IF(12<=$G6, ROUND(DV6*$Q6, 2), "") | DX6: =IF(12<=$G6, $N6, "") | DY6: =IF(12<=$G6, DX6-DW6, "") | DZ6: =IF(12<=$G6, DV6-DY6, "") | EA6: =IF(12<=$G6, ROUND(DS6*$Q6, 2), "") | EB6: =IF(12<=$G6, DS6+EA6, "") | EC6: =IF(12<=$G6, DW6+EA6, "") | ED6: =IF(12<=$G6, ($G6-12)*$N6, "") | EE6: =IF(13<=$G6, DZ6, "") | EF6: =IF(13<=$G6, ROUND(EE6*$Q6, 2), "") | EG6: =IF(13<=$G6, $N6, "") | EH6: =IF(13<=$G6, EG6-EF6, "") | EI6: =IF(13<=$G6, EE6-EH6, "") | EJ6: =IF(13<=$G6, ROUND(EB6*$Q6, 2), "") | EK6: =IF(13<=$G6, EB6+EJ6, "") | EL6: =IF(13<=$G6, EF6+EJ6, "") | EM6: =IF(13<=$G6, ($G6-13)*$N6, "") | EN6: =IF(14<=$G6, EI6, "") | EO6: =IF(14<=$G6, ROUND(EN6*$Q6, 2), "") | EP6: =IF(14<=$G6, $N6, "") | EQ6: =IF(14<=$G6, EP6-EO6, "") | ER6: =IF(14<=$G6, EN6-EQ6, "") | ES6: =IF(14<=$G6, ROUND(EK6*$Q6, 2), "") | ET6: =IF(14<=$G6, EK6+ES6, "") | EU6: =IF(14<=$G6, EO6+ES6, "") | EV6: =IF(14<=$G6, ($G6-14)*$N6, "") | EW6: =IF(15<=$G6, ER6, "") | EX6: =IF(15<=$G6, ROUND(EW6*$Q6, 2), "") | EY6: =IF(15<=$G6, $N6, "") | EZ6: =IF(15<=$G6, EY6-EX6, "") | FA6: =IF(15<=$G6, EW6-EZ6, "") | FB6: =IF(15<=$G6, ROUND(ET6*$Q6, 2), "") | FC6: =IF(15<=$G6, ET6+FB6, "") | FD6: =IF(15<=$G6, EX6+FB6, "") | FE6: =IF(15<=$G6, ($G6-15)*$N6, "") | FF6: =IF(16<=$G6, FA6, "") | FG6: =IF(16<=$G6, ROUND(FF6*$Q6, 2), "") | FH6: =IF(16<=$G6, $N6, "") | FI6: =IF(16<=$G6, FH6-FG6, "") | FJ6: =IF(16<=$G6, FF6-FI6, "") | FK6: =IF(16<=$G6, ROUND(FC6*$Q6, 2), "") | FL6: =IF(16<=$G6, FC6+FK6, "") | FM6: =IF(16<=$G6, FG6+FK6, "") | FN6: =IF(16<=$G6, ($G6-16)*$N6, "") | FO6: =IF(17<=$G6, FJ6, "") | FP6: =IF(17<=$G6, ROUND(FO6*$Q6, 2), "") | FQ6: =IF(17<=$G6, $N6, "") | FR6: =IF(17<=$G6, FQ6-FP6, "") | FS6: =IF(17<=$G6, FO6-FR6, "") | FT6: =IF(17<=$G6, ROUND(FL6*$Q6, 2), "") | FU6: =IF(17<=$G6, FL6+FT6, "") | FV6: =IF(17<=$G6, FP6+FT6, "") | FW6: =IF(17<=$G6, ($G6-17)*$N6, "") | FX6: =IF(18<=$G6, FS6, "") | FY6: =IF(18<=$G6, ROUND(FX6*$Q6, 2), "") | FZ6: =IF(18<=$G6, $N6, "") | GA6: =IF(18<=$G6, FZ6-FY6, "") | GB6: =IF(18<=$G6, FX6-GA6, "") | GC6: =IF(18<=$G6, ROUND(FU6*$Q6, 2), "") | GD6: =IF(18<=$G6, FU6+GC6, "") | GE6: =IF(18<=$G6, FY6+GC6, "") | GF6: =IF(18<=$G6, ($G6-18)*$N6, "") | GG6: =IF(19<=$G6, GB6, "") | GH6: =IF(19<=$G6, ROUND(GG6*$Q6, 2), "") | GI6: =IF(19<=$G6, $N6, "") | GJ6: =IF(19<=$G6, GI6-GH6, "") | GK6: =IF(19<=$G6, GG6-GJ6, "") | GL6: =IF(19<=$G6, ROUND(GD6*$Q6, 2), "") | GM6: =IF(19<=$G6, GD6+GL6, "") | GN6: =IF(19<=$G6, GH6+GL6, "") | GO6: =IF(19<=$G6, ($G6-19)*$N6, "") | GP6: =IF(20<=$G6, GK6, "") | GQ6: =IF(20<=$G6, ROUND(GP6*$Q6, 2), "") | GR6: =IF(20<=$G6, $N6, "") | GS6: =IF(20<=$G6, GR6-GQ6, "") | GT6: =IF(20<=$G6, GP6-GS6, "") | GU6: =IF(20<=$G6, ROUND(GM6*$Q6, 2), "") | GV6: =IF(20<=$G6, GM6+GU6, "") | GW6: =IF(20<=$G6, GQ6+GU6, "") | GX6: =IF(20<=$G6, ($G6-20)*$N6, "") | GY6: =IF(21<=$G6, GT6, "") | GZ6: =IF(21<=$G6, ROUND(GY6*$Q6, 2), "") | HA6: =IF(21<=$G6, $N6, "") | HB6: =IF(21<=$G6, HA6-GZ6, "") | HC6: =IF(21<=$G6, GY6-HB6, "") | HD6: =IF(21<=$G6, ROUND(GV6*$Q6, 2), "") | HE6: =IF(21<=$G6, GV6+HD6, "") | HF6: =IF(21<=$G6, GZ6+HD6, "") | HG6: =IF(21<=$G6, ($G6-21)*$N6, "") | HH6: =IF(22<=$G6, HC6, "") | HI6: =IF(22<=$G6, ROUND(HH6*$Q6, 2), "") | HJ6: =IF(22<=$G6, $N6, "") | HK6: =IF(22<=$G6, HJ6-HI6, "") | HL6: =IF(22<=$G6, HH6-HK6, "") | HM6: =IF(22<=$G6, ROUND(HE6*$Q6, 2), "") | HN6: =IF(22<=$G6, HE6+HM6, "") | HO6: =IF(22<=$G6, HI6+HM6, "") | HP6: =IF(22<=$G6, ($G6-22)*$N6, "") | HQ6: =IF(23<=$G6, HL6, "") | HR6: =IF(23<=$G6, ROUND(HQ6*$Q6, 2), "") | HS6: =IF(23<=$G6, $N6, "") | HT6: =IF(23<=$G6, HS6-HR6, "") | HU6: =IF(23<=$G6, HQ6-HT6, "") | HV6: =IF(23<=$G6, ROUND(HN6*$Q6, 2), "") | HW6: =IF(23<=$G6, HN6+HV6, "") | HX6: =IF(23<=$G6, HR6+HV6, "") | HY6: =IF(23<=$G6, ($G6-23)*$N6, "") | HZ6: =IF(24<=$G6, HU6, "") | IA6: =IF(24<=$G6, ROUND(HZ6*$Q6, 2), "") | IB6: =IF(24<=$G6, $N6, "") | IC6: =IF(24<=$G6, IB6-IA6, "") | ID6: =IF(24<=$G6, HZ6-IC6, "") | IE6: =IF(24<=$G6, ROUND(HW6*$Q6, 2), "") | IF6: =IF(24<=$G6, HW6+IE6, "") | IG6: =IF(24<=$G6, IA6+IE6, "") | IH6: =IF(24<=$G6, ($G6-24)*$N6, "") | II6: =IF(25<=$G6, ID6, "") | IJ6: =IF(25<=$G6, ROUND(II6*$Q6, 2), "") | IK6: =IF(25<=$G6, $N6, "") | IL6: =IF(25<=$G6, IK6-IJ6, "") | IM6: =IF(25<=$G6, II6-IL6, "") | IN6: =IF(25<=$G6, ROUND(IF6*$Q6, 2), "") | IO6: =IF(25<=$G6, IF6+IN6, "") | IP6: =IF(25<=$G6, IJ6+IN6, "") | IQ6: =IF(25<=$G6, ($G6-25)*$N6, "") | IR6: =IF(26<=$G6, IM6, "") | IS6: =IF(26<=$G6, ROUND(IR6*$Q6, 2), "") | IT6: =IF(26<=$G6, $N6, "") | IU6: =IF(26<=$G6, IT6-IS6, "") | IV6: =IF(26<=$G6, IR6-IU6, "") | IW6: =IF(26<=$G6, ROUND(IO6*$Q6, 2), "") | IX6: =IF(26<=$G6, IO6+IW6, "") | IY6: =IF(26<=$G6, IS6+IW6, "") | IZ6: =IF(26<=$G6, ($G6-26)*$N6, "") | JA6: =IF(27<=$G6, IV6, "") | JB6: =IF(27<=$G6, ROUND(JA6*$Q6, 2), "") | JC6: =IF(27<=$G6, $N6, "") | JD6: =IF(27<=$G6, JC6-JB6, "") | JE6: =IF(27<=$G6, JA6-JD6, "") | JF6: =IF(27<=$G6, ROUND(IX6*$Q6, 2), "") | JG6: =IF(27<=$G6, IX6+JF6, "") | JH6: =IF(27<=$G6, JB6+JF6, "") | JI6: =IF(27<=$G6, ($G6-27)*$N6, "") | JJ6: =IF(28<=$G6, JE6, "") | JK6: =IF(28<=$G6, ROUND(JJ6*$Q6, 2), "") | JL6: =IF(28<=$G6, $N6, "") | JM6: =IF(28<=$G6, JL6-JK6, "") | JN6: =IF(28<=$G6, JJ6-JM6, "") | JO6: =IF(28<=$G6, ROUND(JG6*$Q6, 2), "") | JP6: =IF(28<=$G6, JG6+JO6, "") | JQ6: =IF(28<=$G6, JK6+JO6, "") | JR6: =IF(28<=$G6, ($G6-28)*$N6, "") | JS6: =IF(29<=$G6, JN6, "") | JT6: =IF(29<=$G6, ROUND(JS6*$Q6, 2), "") | JU6: =IF(29<=$G6, $N6, "") | JV6: =IF(29<=$G6, JU6-JT6, "") | JW6: =IF(29<=$G6, JS6-JV6, "") | JX6: =IF(29<=$G6, ROUND(JP6*$Q6, 2), "") | JY6: =IF(29<=$G6, JP6+JX6, "") | JZ6: =IF(29<=$G6, JT6+JX6, "") | KA6: =IF(29<=$G6, ($G6-29)*$N6, "") | KB6: =IF(30<=$G6, JW6, "") | KC6: =IF(30<=$G6, ROUND(KB6*$Q6, 2), "") | KD6: =IF(30<=$G6, $N6, "") | KE6: =IF(30<=$G6, KD6-KC6, "") | KF6: =IF(30<=$G6, KB6-KE6, "") | KG6: =IF(30<=$G6, ROUND(JY6*$Q6, 2), "") | KH6: =IF(30<=$G6, JY6+KG6, "") | KI6: =IF(30<=$G6, KC6+KG6, "") | KJ6: =IF(30<=$G6, ($G6-30)*$N6, "") | KK6: =IF(31<=$G6, KF6, "") | KL6: =IF(31<=$G6, ROUND(KK6*$Q6, 2), "") | KM6: =IF(31<=$G6, $N6, "") | KN6: =IF(31<=$G6, KM6-KL6, "") | KO6: =IF(31<=$G6, KK6-KN6, "") | KP6: =IF(31<=$G6, ROUND(KH6*$Q6, 2), "") | KQ6: =IF(31<=$G6, KH6+KP6, "") | KR6: =IF(31<=$G6, KL6+KP6, "") | KS6: =IF(31<=$G6, ($G6-31)*$N6, "") | KT6: =IF(32<=$G6, KO6, "") | KU6: =IF(32<=$G6, ROUND(KT6*$Q6, 2), "") | KV6: =IF(32<=$G6, $N6, "") | KW6: =IF(32<=$G6, KV6-KU6, "") | KX6: =IF(32<=$G6, KT6-KW6, "") | KY6: =IF(32<=$G6, ROUND(KQ6*$Q6, 2), "") | KZ6: =IF(32<=$G6, KQ6+KY6, "") | LA6: =IF(32<=$G6, KU6+KY6, "") | LB6: =IF(32<=$G6, ($G6-32)*$N6, "") | LC6: =IF(33<=$G6, KX6, "") | LD6: =IF(33<=$G6, ROUND(LC6*$Q6, 2), "") | LE6: =IF(33<=$G6, $N6, "") | LF6: =IF(33<=$G6, LE6-LD6, "") | LG6: =IF(33<=$G6, LC6-LF6, "") | LH6: =IF(33<=$G6, ROUND(KZ6*$Q6, 2), "") | LI6: =IF(33<=$G6, KZ6+LH6, "") | LJ6: =IF(33<=$G6, LD6+LH6, "") | LK6: =IF(33<=$G6, ($G6-33)*$N6, "") | LL6: =IF(34<=$G6, LG6, "") | LM6: =IF(34<=$G6, ROUND(LL6*$Q6, 2), "") | LN6: =IF(34<=$G6, $N6, "") | LO6: =IF(34<=$G6, LN6-LM6, "") | LP6: =IF(34<=$G6, LL6-LO6, "") | LQ6: =IF(34<=$G6, ROUND(LI6*$Q6, 2), "") | LR6: =IF(34<=$G6, LI6+LQ6, "") | LS6: =IF(34<=$G6, LM6+LQ6, "") | LT6: =IF(34<=$G6, ($G6-34)*$N6, "") | LU6: =IF(35<=$G6, LP6, "") | LV6: =IF(35<=$G6, ROUND(LU6*$Q6, 2), "") | LW6: =IF(35<=$G6, $N6, "") | LX6: =IF(35<=$G6, LW6-LV6, "") | LY6: =IF(35<=$G6, LU6-LX6, "") | LZ6: =IF(35<=$G6, ROUND(LR6*$Q6, 2), "") | MA6: =IF(35<=$G6, LR6+LZ6, "") | MB6: =IF(35<=$G6, LV6+LZ6, "") | MC6: =IF(35<=$G6, ($G6-35)*$N6, "") | MD6: =IF(36<=$G6, LY6, "") | ME6: =IF(36<=$G6, ROUND(MD6*$Q6, 2), "") | MF6: =IF(36<=$G6, $N6, "") | MG6: =IF(36<=$G6, MF6-ME6, "") | MH6: =IF(36<=$G6, MD6-MG6, "") | MI6: =IF(36<=$G6, ROUND(MA6*$Q6, 2), "") | MJ6: =IF(36<=$G6, MA6+MI6, "") | MK6: =IF(36<=$G6, ME6+MI6, "") | ML6: =IF(36<=$G6, ($G6-36)*$N6, "") | MM6: =IF(37<=$G6, MH6, "") | MN6: =IF(37<=$G6, ROUND(MM6*$Q6, 2), "") | MO6: =IF(37<=$G6, $N6, "") | MP6: =IF(37<=$G6, MO6-MN6, "") | MQ6: =IF(37<=$G6, MM6-MP6, "") | MR6: =IF(37<=$G6, ROUND(MJ6*$Q6, 2), "") | MS6: =IF(37<=$G6, MJ6+MR6, "") | MT6: =IF(37<=$G6, MN6+MR6, "") | MU6: =IF(37<=$G6, ($G6-37)*$N6, "") | MV6: =IF(38<=$G6, MQ6, "") | MW6: =IF(38<=$G6, ROUND(MV6*$Q6, 2), "") | MX6: =IF(38<=$G6, $N6, "") | MY6: =IF(38<=$G6, MX6-MW6, "") | MZ6: =IF(38<=$G6, MV6-MY6, "") | NA6: =IF(38<=$G6, ROUND(MS6*$Q6, 2), "") | NB6: =IF(38<=$G6, MS6+NA6, "") | NC6: =IF(38<=$G6, MW6+NA6, "") | ND6: =IF(38<=$G6, ($G6-38)*$N6, "") | NE6: =IF(39<=$G6, MZ6, "") | NF6: =IF(39<=$G6, ROUND(NE6*$Q6, 2), "") | NG6: =IF(39<=$G6, $N6, "") | NH6: =IF(39<=$G6, NG6-NF6, "") | NI6: =IF(39<=$G6, NE6-NH6, "") | NJ6: =IF(39<=$G6, ROUND(NB6*$Q6, 2), "") | NK6: =IF(39<=$G6, NB6+NJ6, "") | NL6: =IF(39<=$G6, NF6+NJ6, "") | NM6: =IF(39<=$G6, ($G6-39)*$N6, "") | NN6: =IF(40<=$G6, NI6, "") | NO6: =IF(40<=$G6, ROUND(NN6*$Q6, 2), "") | NP6: =IF(40<=$G6, $N6, "") | NQ6: =IF(40<=$G6, NP6-NO6, "") | NR6: =IF(40<=$G6, NN6-NQ6, "") | NS6: =IF(40<=$G6, ROUND(NK6*$Q6, 2), "") | NT6: =IF(40<=$G6, NK6+NS6, "") | NU6: =IF(40<=$G6, NO6+NS6, "") | NV6: =IF(40<=$G6, ($G6-40)*$N6, "") | NW6: =IF(41<=$G6, NR6, "") | NX6: =IF(41<=$G6, ROUND(NW6*$Q6, 2), "") | NY6: =IF(41<=$G6, $N6, "") | NZ6: =IF(41<=$G6, NY6-NX6, "") | OA6: =IF(41<=$G6, NW6-NZ6, "") | OB6: =IF(41<=$G6, ROUND(NT6*$Q6, 2), "") | OC6: =IF(41<=$G6, NT6+OB6, "") | OD6: =IF(41<=$G6, NX6+OB6, "") | OE6: =IF(41<=$G6, ($G6-41)*$N6, "") | OF6: =IF(42<=$G6, OA6, "") | OG6: =IF(42<=$G6, ROUND(OF6*$Q6, 2), "") | OH6: =IF(42<=$G6, $N6, "") | OI6: =IF(42<=$G6, OH6-OG6, "") | OJ6: =IF(42<=$G6, OF6-OI6, "") | OK6: =IF(42<=$G6, ROUND(OC6*$Q6, 2), "") | OL6: =IF(42<=$G6, OC6+OK6, "") | OM6: =IF(42<=$G6, OG6+OK6, "") | ON6: =IF(42<=$G6, ($G6-42)*$N6, "") | OO6: =IF(43<=$G6, OJ6, "") | OP6: =IF(43<=$G6, ROUND(OO6*$Q6, 2), "") | OQ6: =IF(43<=$G6, $N6, "") | OR6: =IF(43<=$G6, OQ6-OP6, "") | OS6: =IF(43<=$G6, OO6-OR6, "") | OT6: =IF(43<=$G6, ROUND(OL6*$Q6, 2), "") | OU6: =IF(43<=$G6, OL6+OT6, "") | OV6: =IF(43<=$G6, OP6+OT6, "") | OW6: =IF(43<=$G6, ($G6-43)*$N6, "") | OX6: =IF(44<=$G6, OS6, "") | OY6: =IF(44<=$G6, ROUND(OX6*$Q6, 2), "") | OZ6: =IF(44<=$G6, $N6, "") | PA6: =IF(44<=$G6, OZ6-OY6, "") | PB6: =IF(44<=$G6, OX6-PA6, "") | PC6: =IF(44<=$G6, ROUND(OU6*$Q6, 2), "") | PD6: =IF(44<=$G6, OU6+PC6, "") | PE6: =IF(44<=$G6, OY6+PC6, "") | PF6: =IF(44<=$G6, ($G6-44)*$N6, "") | PG6: =IF(45<=$G6, PB6, "") | PH6: =IF(45<=$G6, ROUND(PG6*$Q6, 2), "") | PI6: =IF(45<=$G6, $N6, "") | PJ6: =IF(45<=$G6, PI6-PH6, "") | PK6: =IF(45<=$G6, PG6-PJ6, "") | PL6: =IF(45<=$G6, ROUND(PD6*$Q6, 2), "") | PM6: =IF(45<=$G6, PD6+PL6, "") | PN6: =IF(45<=$G6, PH6+PL6, "") | PO6: =IF(45<=$G6, ($G6-45)*$N6, "") | PP6: =IF(46<=$G6, PK6, "") | PQ6: =IF(46<=$G6, ROUND(PP6*$Q6, 2), "") | PR6: =IF(46<=$G6, $N6, "") | PS6: =IF(46<=$G6, PR6-PQ6, "") | PT6: =IF(46<=$G6, PP6-PS6, "") | PU6: =IF(46<=$G6, ROUND(PM6*$Q6, 2), "") | PV6: =IF(46<=$G6, PM6+PU6, "") | PW6: =IF(46<=$G6, PQ6+PU6, "") | PX6: =IF(46<=$G6, ($G6-46)*$N6, "") | PY6: =IF(47<=$G6, PT6, "") | PZ6: =IF(47<=$G6, ROUND(PY6*$Q6, 2), "") | QA6: =IF(47<=$G6, $N6, "") | QB6: =IF(47<=$G6, QA6-PZ6, "") | QC6: =IF(47<=$G6, PY6-QB6, "") | QD6: =IF(47<=$G6, ROUND(PV6*$Q6, 2), "") | QE6: =IF(47<=$G6, PV6+QD6, "") | QF6: =IF(47<=$G6, PZ6+QD6, "") | QG6: =IF(47<=$G6, ($G6-47)*$N6, "") | QH6: =IF(48<=$G6, QC6, "") | QI6: =IF(48<=$G6, ROUND(QH6*$Q6, 2), "") | QJ6: =IF(48<=$G6, $N6, "") | QK6: =IF(48<=$G6, QJ6-QI6, "") | QL6: =IF(48<=$G6, QH6-QK6, "") | QM6: =IF(48<=$G6, ROUND(QE6*$Q6, 2), "") | QN6: =IF(48<=$G6, QE6+QM6, "") | QO6: =IF(48<=$G6, QI6+QM6, "") | QP6: =IF(48<=$G6, ($G6-48)*$N6, "")
A7: 0504-0004 | B7: Oscar Ivan Lozano Terriquez | C7: 700 BIGHORN "S" CREW CAB MT | D7: ACTIVO | E7: 2026-01-05 | F7: 2027-01-05 | G7: 12 | H7: 352500 | I7: 0.35 | J7: =ROUND(H7*I7, 2) | K7: =ROUND(H7-J7, 2) | L7: 0.02 | M7: =ROUND(H7*L7, 2) | N7: 19654.64 | O7: 0.1 | P7: =ROUND(H7*O7, 2) | Q7: 0.02415117 | R7: =RATE(G7, -N7, K7, -P7) | S7: =ROUND(Q7*12, 8) | T7: =ROUND(((1+Q7)^12)-1, 8) | U7: =ROUND(PV(Q7, G7, 0, -P7), 2) | V7: =SUMIF($AA$4:$QP$4, "Interes_Leasing", AA7:QP7) | W7: =SUMIF($AA$4:$QP$4, "Interes_Residual", AA7:QP7) | X7: =ROUND(V7+W7, 2) | Y7: =ROUND((N7*G7+P7+M7)-K7, 2) | Z7: =ROUND(Y7/K7, 4) | AA7: =IF(1<=$G7, $K7, "") | AB7: =IF(1<=$G7, ROUND(AA7*$Q7, 2), "") | AC7: =IF(1<=$G7, $N7, "") | AD7: =IF(1<=$G7, AC7-AB7, "") | AE7: =IF(1<=$G7, AA7-AD7, "") | AF7: =IF(1<=$G7, ROUND($U7*$Q7, 2), "") | AG7: =IF(1<=$G7, $U7+AF7, "") | AH7: =IF(1<=$G7, AB7+AF7, "") | AI7: =IF(1<=$G7, ($G7-1)*$N7, "") | AJ7: =IF(2<=$G7, AE7, "") | AK7: =IF(2<=$G7, ROUND(AJ7*$Q7, 2), "") | AL7: =IF(2<=$G7, $N7, "") | AM7: =IF(2<=$G7, AL7-AK7, "") | AN7: =IF(2<=$G7, AJ7-AM7, "") | AO7: =IF(2<=$G7, ROUND(AG7*$Q7, 2), "") | AP7: =IF(2<=$G7, AG7+AO7, "") | AQ7: =IF(2<=$G7, AK7+AO7, "") | AR7: =IF(2<=$G7, ($G7-2)*$N7, "") | AS7: =IF(3<=$G7, AN7, "") | AT7: =IF(3<=$G7, ROUND(AS7*$Q7, 2), "") | AU7: =IF(3<=$G7, $N7, "") | AV7: =IF(3<=$G7, AU7-AT7, "") | AW7: =IF(3<=$G7, AS7-AV7, "") | AX7: =IF(3<=$G7, ROUND(AP7*$Q7, 2), "") | AY7: =IF(3<=$G7, AP7+AX7, "") | AZ7: =IF(3<=$G7, AT7+AX7, "") | BA7: =IF(3<=$G7, ($G7-3)*$N7, "") | BB7: =IF(4<=$G7, AW7, "") | BC7: =IF(4<=$G7, ROUND(BB7*$Q7, 2), "") | BD7: =IF(4<=$G7, $N7, "") | BE7: =IF(4<=$G7, BD7-BC7, "") | BF7: =IF(4<=$G7, BB7-BE7, "") | BG7: =IF(4<=$G7, ROUND(AY7*$Q7, 2), "") | BH7: =IF(4<=$G7, AY7+BG7, "") | BI7: =IF(4<=$G7, BC7+BG7, "") | BJ7: =IF(4<=$G7, ($G7-4)*$N7, "") | BK7: =IF(5<=$G7, BF7, "") | BL7: =IF(5<=$G7, ROUND(BK7*$Q7, 2), "") | BM7: =IF(5<=$G7, $N7, "") | BN7: =IF(5<=$G7, BM7-BL7, "") | BO7: =IF(5<=$G7, BK7-BN7, "") | BP7: =IF(5<=$G7, ROUND(BH7*$Q7, 2), "") | BQ7: =IF(5<=$G7, BH7+BP7, "") | BR7: =IF(5<=$G7, BL7+BP7, "") | BS7: =IF(5<=$G7, ($G7-5)*$N7, "") | BT7: =IF(6<=$G7, BO7, "") | BU7: =IF(6<=$G7, ROUND(BT7*$Q7, 2), "") | BV7: =IF(6<=$G7, $N7, "") | BW7: =IF(6<=$G7, BV7-BU7, "") | BX7: =IF(6<=$G7, BT7-BW7, "") | BY7: =IF(6<=$G7, ROUND(BQ7*$Q7, 2), "") | BZ7: =IF(6<=$G7, BQ7+BY7, "") | CA7: =IF(6<=$G7, BU7+BY7, "") | CB7: =IF(6<=$G7, ($G7-6)*$N7, "") | CC7: =IF(7<=$G7, BX7, "") | CD7: =IF(7<=$G7, ROUND(CC7*$Q7, 2), "") | CE7: =IF(7<=$G7, $N7, "") | CF7: =IF(7<=$G7, CE7-CD7, "") | CG7: =IF(7<=$G7, CC7-CF7, "") | CH7: =IF(7<=$G7, ROUND(BZ7*$Q7, 2), "") | CI7: =IF(7<=$G7, BZ7+CH7, "") | CJ7: =IF(7<=$G7, CD7+CH7, "") | CK7: =IF(7<=$G7, ($G7-7)*$N7, "") | CL7: =IF(8<=$G7, CG7, "") | CM7: =IF(8<=$G7, ROUND(CL7*$Q7, 2), "") | CN7: =IF(8<=$G7, $N7, "") | CO7: =IF(8<=$G7, CN7-CM7, "") | CP7: =IF(8<=$G7, CL7-CO7, "") | CQ7: =IF(8<=$G7, ROUND(CI7*$Q7, 2), "") | CR7: =IF(8<=$G7, CI7+CQ7, "") | CS7: =IF(8<=$G7, CM7+CQ7, "") | CT7: =IF(8<=$G7, ($G7-8)*$N7, "") | CU7: =IF(9<=$G7, CP7, "") | CV7: =IF(9<=$G7, ROUND(CU7*$Q7, 2), "") | CW7: =IF(9<=$G7, $N7, "") | CX7: =IF(9<=$G7, CW7-CV7, "") | CY7: =IF(9<=$G7, CU7-CX7, "") | CZ7: =IF(9<=$G7, ROUND(CR7*$Q7, 2), "") | DA7: =IF(9<=$G7, CR7+CZ7, "") | DB7: =IF(9<=$G7, CV7+CZ7, "") | DC7: =IF(9<=$G7, ($G7-9)*$N7, "") | DD7: =IF(10<=$G7, CY7, "") | DE7: =IF(10<=$G7, ROUND(DD7*$Q7, 2), "") | DF7: =IF(10<=$G7, $N7, "") | DG7: =IF(10<=$G7, DF7-DE7, "") | DH7: =IF(10<=$G7, DD7-DG7, "") | DI7: =IF(10<=$G7, ROUND(DA7*$Q7, 2), "") | DJ7: =IF(10<=$G7, DA7+DI7, "") | DK7: =IF(10<=$G7, DE7+DI7, "") | DL7: =IF(10<=$G7, ($G7-10)*$N7, "") | DM7: =IF(11<=$G7, DH7, "") | DN7: =IF(11<=$G7, ROUND(DM7*$Q7, 2), "") | DO7: =IF(11<=$G7, $N7, "") | DP7: =IF(11<=$G7, DO7-DN7, "") | DQ7: =IF(11<=$G7, DM7-DP7, "") | DR7: =IF(11<=$G7, ROUND(DJ7*$Q7, 2), "") | DS7: =IF(11<=$G7, DJ7+DR7, "") | DT7: =IF(11<=$G7, DN7+DR7, "") | DU7: =IF(11<=$G7, ($G7-11)*$N7, "") | DV7: =IF(12<=$G7, DQ7, "") | DW7: =IF(12<=$G7, ROUND(DV7*$Q7, 2), "") | DX7: =IF(12<=$G7, $N7, "") | DY7: =IF(12<=$G7, DX7-DW7, "") | DZ7: =IF(12<=$G7, DV7-DY7, "") | EA7: =IF(12<=$G7, ROUND(DS7*$Q7, 2), "") | EB7: =IF(12<=$G7, DS7+EA7, "") | EC7: =IF(12<=$G7, DW7+EA7, "") | ED7: =IF(12<=$G7, ($G7-12)*$N7, "") | EE7: =IF(13<=$G7, DZ7, "") | EF7: =IF(13<=$G7, ROUND(EE7*$Q7, 2), "") | EG7: =IF(13<=$G7, $N7, "") | EH7: =IF(13<=$G7, EG7-EF7, "") | EI7: =IF(13<=$G7, EE7-EH7, "") | EJ7: =IF(13<=$G7, ROUND(EB7*$Q7, 2), "") | EK7: =IF(13<=$G7, EB7+EJ7, "") | EL7: =IF(13<=$G7, EF7+EJ7, "") | EM7: =IF(13<=$G7, ($G7-13)*$N7, "") | EN7: =IF(14<=$G7, EI7, "") | EO7: =IF(14<=$G7, ROUND(EN7*$Q7, 2), "") | EP7: =IF(14<=$G7, $N7, "") | EQ7: =IF(14<=$G7, EP7-EO7, "") | ER7: =IF(14<=$G7, EN7-EQ7, "") | ES7: =IF(14<=$G7, ROUND(EK7*$Q7, 2), "") | ET7: =IF(14<=$G7, EK7+ES7, "") | EU7: =IF(14<=$G7, EO7+ES7, "") | EV7: =IF(14<=$G7, ($G7-14)*$N7, "") | EW7: =IF(15<=$G7, ER7, "") | EX7: =IF(15<=$G7, ROUND(EW7*$Q7, 2), "") | EY7: =IF(15<=$G7, $N7, "") | EZ7: =IF(15<=$G7, EY7-EX7, "") | FA7: =IF(15<=$G7, EW7-EZ7, "") | FB7: =IF(15<=$G7, ROUND(ET7*$Q7, 2), "") | FC7: =IF(15<=$G7, ET7+FB7, "") | FD7: =IF(15<=$G7, EX7+FB7, "") | FE7: =IF(15<=$G7, ($G7-15)*$N7, "") | FF7: =IF(16<=$G7, FA7, "") | FG7: =IF(16<=$G7, ROUND(FF7*$Q7, 2), "") | FH7: =IF(16<=$G7, $N7, "") | FI7: =IF(16<=$G7, FH7-FG7, "") | FJ7: =IF(16<=$G7, FF7-FI7, "") | FK7: =IF(16<=$G7, ROUND(FC7*$Q7, 2), "") | FL7: =IF(16<=$G7, FC7+FK7, "") | FM7: =IF(16<=$G7, FG7+FK7, "") | FN7: =IF(16<=$G7, ($G7-16)*$N7, "") | FO7: =IF(17<=$G7, FJ7, "") | FP7: =IF(17<=$G7, ROUND(FO7*$Q7, 2), "") | FQ7: =IF(17<=$G7, $N7, "") | FR7: =IF(17<=$G7, FQ7-FP7, "") | FS7: =IF(17<=$G7, FO7-FR7, "") | FT7: =IF(17<=$G7, ROUND(FL7*$Q7, 2), "") | FU7: =IF(17<=$G7, FL7+FT7, "") | FV7: =IF(17<=$G7, FP7+FT7, "") | FW7: =IF(17<=$G7, ($G7-17)*$N7, "") | FX7: =IF(18<=$G7, FS7, "") | FY7: =IF(18<=$G7, ROUND(FX7*$Q7, 2), "") | FZ7: =IF(18<=$G7, $N7, "") | GA7: =IF(18<=$G7, FZ7-FY7, "") | GB7: =IF(18<=$G7, FX7-GA7, "") | GC7: =IF(18<=$G7, ROUND(FU7*$Q7, 2), "") | GD7: =IF(18<=$G7, FU7+GC7, "") | GE7: =IF(18<=$G7, FY7+GC7, "") | GF7: =IF(18<=$G7, ($G7-18)*$N7, "") | GG7: =IF(19<=$G7, GB7, "") | GH7: =IF(19<=$G7, ROUND(GG7*$Q7, 2), "") | GI7: =IF(19<=$G7, $N7, "") | GJ7: =IF(19<=$G7, GI7-GH7, "") | GK7: =IF(19<=$G7, GG7-GJ7, "") | GL7: =IF(19<=$G7, ROUND(GD7*$Q7, 2), "") | GM7: =IF(19<=$G7, GD7+GL7, "") | GN7: =IF(19<=$G7, GH7+GL7, "") | GO7: =IF(19<=$G7, ($G7-19)*$N7, "") | GP7: =IF(20<=$G7, GK7, "") | GQ7: =IF(20<=$G7, ROUND(GP7*$Q7, 2), "") | GR7: =IF(20<=$G7, $N7, "") | GS7: =IF(20<=$G7, GR7-GQ7, "") | GT7: =IF(20<=$G7, GP7-GS7, "") | GU7: =IF(20<=$G7, ROUND(GM7*$Q7, 2), "") | GV7: =IF(20<=$G7, GM7+GU7, "") | GW7: =IF(20<=$G7, GQ7+GU7, "") | GX7: =IF(20<=$G7, ($G7-20)*$N7, "") | GY7: =IF(21<=$G7, GT7, "") | GZ7: =IF(21<=$G7, ROUND(GY7*$Q7, 2), "") | HA7: =IF(21<=$G7, $N7, "") | HB7: =IF(21<=$G7, HA7-GZ7, "") | HC7: =IF(21<=$G7, GY7-HB7, "") | HD7: =IF(21<=$G7, ROUND(GV7*$Q7, 2), "") | HE7: =IF(21<=$G7, GV7+HD7, "") | HF7: =IF(21<=$G7, GZ7+HD7, "") | HG7: =IF(21<=$G7, ($G7-21)*$N7, "") | HH7: =IF(22<=$G7, HC7, "") | HI7: =IF(22<=$G7, ROUND(HH7*$Q7, 2), "") | HJ7: =IF(22<=$G7, $N7, "") | HK7: =IF(22<=$G7, HJ7-HI7, "") | HL7: =IF(22<=$G7, HH7-HK7, "") | HM7: =IF(22<=$G7, ROUND(HE7*$Q7, 2), "") | HN7: =IF(22<=$G7, HE7+HM7, "") | HO7: =IF(22<=$G7, HI7+HM7, "") | HP7: =IF(22<=$G7, ($G7-22)*$N7, "") | HQ7: =IF(23<=$G7, HL7, "") | HR7: =IF(23<=$G7, ROUND(HQ7*$Q7, 2), "") | HS7: =IF(23<=$G7, $N7, "") | HT7: =IF(23<=$G7, HS7-HR7, "") | HU7: =IF(23<=$G7, HQ7-HT7, "") | HV7: =IF(23<=$G7, ROUND(HN7*$Q7, 2), "") | HW7: =IF(23<=$G7, HN7+HV7, "") | HX7: =IF(23<=$G7, HR7+HV7, "") | HY7: =IF(23<=$G7, ($G7-23)*$N7, "") | HZ7: =IF(24<=$G7, HU7, "") | IA7: =IF(24<=$G7, ROUND(HZ7*$Q7, 2), "") | IB7: =IF(24<=$G7, $N7, "") | IC7: =IF(24<=$G7, IB7-IA7, "") | ID7: =IF(24<=$G7, HZ7-IC7, "") | IE7: =IF(24<=$G7, ROUND(HW7*$Q7, 2), "") | IF7: =IF(24<=$G7, HW7+IE7, "") | IG7: =IF(24<=$G7, IA7+IE7, "") | IH7: =IF(24<=$G7, ($G7-24)*$N7, "") | II7: =IF(25<=$G7, ID7, "") | IJ7: =IF(25<=$G7, ROUND(II7*$Q7, 2), "") | IK7: =IF(25<=$G7, $N7, "") | IL7: =IF(25<=$G7, IK7-IJ7, "") | IM7: =IF(25<=$G7, II7-IL7, "") | IN7: =IF(25<=$G7, ROUND(IF7*$Q7, 2), "") | IO7: =IF(25<=$G7, IF7+IN7, "") | IP7: =IF(25<=$G7, IJ7+IN7, "") | IQ7: =IF(25<=$G7, ($G7-25)*$N7, "") | IR7: =IF(26<=$G7, IM7, "") | IS7: =IF(26<=$G7, ROUND(IR7*$Q7, 2), "") | IT7: =IF(26<=$G7, $N7, "") | IU7: =IF(26<=$G7, IT7-IS7, "") | IV7: =IF(26<=$G7, IR7-IU7, "") | IW7: =IF(26<=$G7, ROUND(IO7*$Q7, 2), "") | IX7: =IF(26<=$G7, IO7+IW7, "") | IY7: =IF(26<=$G7, IS7+IW7, "") | IZ7: =IF(26<=$G7, ($G7-26)*$N7, "") | JA7: =IF(27<=$G7, IV7, "") | JB7: =IF(27<=$G7, ROUND(JA7*$Q7, 2), "") | JC7: =IF(27<=$G7, $N7, "") | JD7: =IF(27<=$G7, JC7-JB7, "") | JE7: =IF(27<=$G7, JA7-JD7, "") | JF7: =IF(27<=$G7, ROUND(IX7*$Q7, 2), "") | JG7: =IF(27<=$G7, IX7+JF7, "") | JH7: =IF(27<=$G7, JB7+JF7, "") | JI7: =IF(27<=$G7, ($G7-27)*$N7, "") | JJ7: =IF(28<=$G7, JE7, "") | JK7: =IF(28<=$G7, ROUND(JJ7*$Q7, 2), "") | JL7: =IF(28<=$G7, $N7, "") | JM7: =IF(28<=$G7, JL7-JK7, "") | JN7: =IF(28<=$G7, JJ7-JM7, "") | JO7: =IF(28<=$G7, ROUND(JG7*$Q7, 2), "") | JP7: =IF(28<=$G7, JG7+JO7, "") | JQ7: =IF(28<=$G7, JK7+JO7, "") | JR7: =IF(28<=$G7, ($G7-28)*$N7, "") | JS7: =IF(29<=$G7, JN7, "") | JT7: =IF(29<=$G7, ROUND(JS7*$Q7, 2), "") | JU7: =IF(29<=$G7, $N7, "") | JV7: =IF(29<=$G7, JU7-JT7, "") | JW7: =IF(29<=$G7, JS7-JV7, "") | JX7: =IF(29<=$G7, ROUND(JP7*$Q7, 2), "") | JY7: =IF(29<=$G7, JP7+JX7, "") | JZ7: =IF(29<=$G7, JT7+JX7, "") | KA7: =IF(29<=$G7, ($G7-29)*$N7, "") | KB7: =IF(30<=$G7, JW7, "") | KC7: =IF(30<=$G7, ROUND(KB7*$Q7, 2), "") | KD7: =IF(30<=$G7, $N7, "") | KE7: =IF(30<=$G7, KD7-KC7, "") | KF7: =IF(30<=$G7, KB7-KE7, "") | KG7: =IF(30<=$G7, ROUND(JY7*$Q7, 2), "") | KH7: =IF(30<=$G7, JY7+KG7, "") | KI7: =IF(30<=$G7, KC7+KG7, "") | KJ7: =IF(30<=$G7, ($G7-30)*$N7, "") | KK7: =IF(31<=$G7, KF7, "") | KL7: =IF(31<=$G7, ROUND(KK7*$Q7, 2), "") | KM7: =IF(31<=$G7, $N7, "") | KN7: =IF(31<=$G7, KM7-KL7, "") | KO7: =IF(31<=$G7, KK7-KN7, "") | KP7: =IF(31<=$G7, ROUND(KH7*$Q7, 2), "") | KQ7: =IF(31<=$G7, KH7+KP7, "") | KR7: =IF(31<=$G7, KL7+KP7, "") | KS7: =IF(31<=$G7, ($G7-31)*$N7, "") | KT7: =IF(32<=$G7, KO7, "") | KU7: =IF(32<=$G7, ROUND(KT7*$Q7, 2), "") | KV7: =IF(32<=$G7, $N7, "") | KW7: =IF(32<=$G7, KV7-KU7, "") | KX7: =IF(32<=$G7, KT7-KW7, "") | KY7: =IF(32<=$G7, ROUND(KQ7*$Q7, 2), "") | KZ7: =IF(32<=$G7, KQ7+KY7, "") | LA7: =IF(32<=$G7, KU7+KY7, "") | LB7: =IF(32<=$G7, ($G7-32)*$N7, "") | LC7: =IF(33<=$G7, KX7, "") | LD7: =IF(33<=$G7, ROUND(LC7*$Q7, 2), "") | LE7: =IF(33<=$G7, $N7, "") | LF7: =IF(33<=$G7, LE7-LD7, "") | LG7: =IF(33<=$G7, LC7-LF7, "") | LH7: =IF(33<=$G7, ROUND(KZ7*$Q7, 2), "") | LI7: =IF(33<=$G7, KZ7+LH7, "") | LJ7: =IF(33<=$G7, LD7+LH7, "") | LK7: =IF(33<=$G7, ($G7-33)*$N7, "") | LL7: =IF(34<=$G7, LG7, "") | LM7: =IF(34<=$G7, ROUND(LL7*$Q7, 2), "") | LN7: =IF(34<=$G7, $N7, "") | LO7: =IF(34<=$G7, LN7-LM7, "") | LP7: =IF(34<=$G7, LL7-LO7, "") | LQ7: =IF(34<=$G7, ROUND(LI7*$Q7, 2), "") | LR7: =IF(34<=$G7, LI7+LQ7, "") | LS7: =IF(34<=$G7, LM7+LQ7, "") | LT7: =IF(34<=$G7, ($G7-34)*$N7, "") | LU7: =IF(35<=$G7, LP7, "") | LV7: =IF(35<=$G7, ROUND(LU7*$Q7, 2), "") | LW7: =IF(35<=$G7, $N7, "") | LX7: =IF(35<=$G7, LW7-LV7, "") | LY7: =IF(35<=$G7, LU7-LX7, "") | LZ7: =IF(35<=$G7, ROUND(LR7*$Q7, 2), "") | MA7: =IF(35<=$G7, LR7+LZ7, "") | MB7: =IF(35<=$G7, LV7+LZ7, "") | MC7: =IF(35<=$G7, ($G7-35)*$N7, "") | MD7: =IF(36<=$G7, LY7, "") | ME7: =IF(36<=$G7, ROUND(MD7*$Q7, 2), "") | MF7: =IF(36<=$G7, $N7, "") | MG7: =IF(36<=$G7, MF7-ME7, "") | MH7: =IF(36<=$G7, MD7-MG7, "") | MI7: =IF(36<=$G7, ROUND(MA7*$Q7, 2), "") | MJ7: =IF(36<=$G7, MA7+MI7, "") | MK7: =IF(36<=$G7, ME7+MI7, "") | ML7: =IF(36<=$G7, ($G7-36)*$N7, "") | MM7: =IF(37<=$G7, MH7, "") | MN7: =IF(37<=$G7, ROUND(MM7*$Q7, 2), "") | MO7: =IF(37<=$G7, $N7, "") | MP7: =IF(37<=$G7, MO7-MN7, "") | MQ7: =IF(37<=$G7, MM7-MP7, "") | MR7: =IF(37<=$G7, ROUND(MJ7*$Q7, 2), "") | MS7: =IF(37<=$G7, MJ7+MR7, "") | MT7: =IF(37<=$G7, MN7+MR7, "") | MU7: =IF(37<=$G7, ($G7-37)*$N7, "") | MV7: =IF(38<=$G7, MQ7, "") | MW7: =IF(38<=$G7, ROUND(MV7*$Q7, 2), "") | MX7: =IF(38<=$G7, $N7, "") | MY7: =IF(38<=$G7, MX7-MW7, "") | MZ7: =IF(38<=$G7, MV7-MY7, "") | NA7: =IF(38<=$G7, ROUND(MS7*$Q7, 2), "") | NB7: =IF(38<=$G7, MS7+NA7, "") | NC7: =IF(38<=$G7, MW7+NA7, "") | ND7: =IF(38<=$G7, ($G7-38)*$N7, "") | NE7: =IF(39<=$G7, MZ7, "") | NF7: =IF(39<=$G7, ROUND(NE7*$Q7, 2), "") | NG7: =IF(39<=$G7, $N7, "") | NH7: =IF(39<=$G7, NG7-NF7, "") | NI7: =IF(39<=$G7, NE7-NH7, "") | NJ7: =IF(39<=$G7, ROUND(NB7*$Q7, 2), "") | NK7: =IF(39<=$G7, NB7+NJ7, "") | NL7: =IF(39<=$G7, NF7+NJ7, "") | NM7: =IF(39<=$G7, ($G7-39)*$N7, "") | NN7: =IF(40<=$G7, NI7, "") | NO7: =IF(40<=$G7, ROUND(NN7*$Q7, 2), "") | NP7: =IF(40<=$G7, $N7, "") | NQ7: =IF(40<=$G7, NP7-NO7, "") | NR7: =IF(40<=$G7, NN7-NQ7, "") | NS7: =IF(40<=$G7, ROUND(NK7*$Q7, 2), "") | NT7: =IF(40<=$G7, NK7+NS7, "") | NU7: =IF(40<=$G7, NO7+NS7, "") | NV7: =IF(40<=$G7, ($G7-40)*$N7, "") | NW7: =IF(41<=$G7, NR7, "") | NX7: =IF(41<=$G7, ROUND(NW7*$Q7, 2), "") | NY7: =IF(41<=$G7, $N7, "") | NZ7: =IF(41<=$G7, NY7-NX7, "") | OA7: =IF(41<=$G7, NW7-NZ7, "") | OB7: =IF(41<=$G7, ROUND(NT7*$Q7, 2), "") | OC7: =IF(41<=$G7, NT7+OB7, "") | OD7: =IF(41<=$G7, NX7+OB7, "") | OE7: =IF(41<=$G7, ($G7-41)*$N7, "") | OF7: =IF(42<=$G7, OA7, "") | OG7: =IF(42<=$G7, ROUND(OF7*$Q7, 2), "") | OH7: =IF(42<=$G7, $N7, "") | OI7: =IF(42<=$G7, OH7-OG7, "") | OJ7: =IF(42<=$G7, OF7-OI7, "") | OK7: =IF(42<=$G7, ROUND(OC7*$Q7, 2), "") | OL7: =IF(42<=$G7, OC7+OK7, "") | OM7: =IF(42<=$G7, OG7+OK7, "") | ON7: =IF(42<=$G7, ($G7-42)*$N7, "") | OO7: =IF(43<=$G7, OJ7, "") | OP7: =IF(43<=$G7, ROUND(OO7*$Q7, 2), "") | OQ7: =IF(43<=$G7, $N7, "") | OR7: =IF(43<=$G7, OQ7-OP7, "") | OS7: =IF(43<=$G7, OO7-OR7, "") | OT7: =IF(43<=$G7, ROUND(OL7*$Q7, 2), "") | OU7: =IF(43<=$G7, OL7+OT7, "") | OV7: =IF(43<=$G7, OP7+OT7, "") | OW7: =IF(43<=$G7, ($G7-43)*$N7, "") | OX7: =IF(44<=$G7, OS7, "") | OY7: =IF(44<=$G7, ROUND(OX7*$Q7, 2), "") | OZ7: =IF(44<=$G7, $N7, "") | PA7: =IF(44<=$G7, OZ7-OY7, "") | PB7: =IF(44<=$G7, OX7-PA7, "") | PC7: =IF(44<=$G7, ROUND(OU7*$Q7, 2), "") | PD7: =IF(44<=$G7, OU7+PC7, "") | PE7: =IF(44<=$G7, OY7+PC7, "") | PF7: =IF(44<=$G7, ($G7-44)*$N7, "") | PG7: =IF(45<=$G7, PB7, "") | PH7: =IF(45<=$G7, ROUND(PG7*$Q7, 2), "") | PI7: =IF(45<=$G7, $N7, "") | PJ7: =IF(45<=$G7, PI7-PH7, "") | PK7: =IF(45<=$G7, PG7-PJ7, "") | PL7: =IF(45<=$G7, ROUND(PD7*$Q7, 2), "") | PM7: =IF(45<=$G7, PD7+PL7, "") | PN7: =IF(45<=$G7, PH7+PL7, "") | PO7: =IF(45<=$G7, ($G7-45)*$N7, "") | PP7: =IF(46<=$G7, PK7, "") | PQ7: =IF(46<=$G7, ROUND(PP7*$Q7, 2), "") | PR7: =IF(46<=$G7, $N7, "") | PS7: =IF(46<=$G7, PR7-PQ7, "") | PT7: =IF(46<=$G7, PP7-PS7, "") | PU7: =IF(46<=$G7, ROUND(PM7*$Q7, 2), "") | PV7: =IF(46<=$G7, PM7+PU7, "") | PW7: =IF(46<=$G7, PQ7+PU7, "") | PX7: =IF(46<=$G7, ($G7-46)*$N7, "") | PY7: =IF(47<=$G7, PT7, "") | PZ7: =IF(47<=$G7, ROUND(PY7*$Q7, 2), "") | QA7: =IF(47<=$G7, $N7, "") | QB7: =IF(47<=$G7, QA7-PZ7, "") | QC7: =IF(47<=$G7, PY7-QB7, "") | QD7: =IF(47<=$G7, ROUND(PV7*$Q7, 2), "") | QE7: =IF(47<=$G7, PV7+QD7, "") | QF7: =IF(47<=$G7, PZ7+QD7, "") | QG7: =IF(47<=$G7, ($G7-47)*$N7, "") | QH7: =IF(48<=$G7, QC7, "") | QI7: =IF(48<=$G7, ROUND(QH7*$Q7, 2), "") | QJ7: =IF(48<=$G7, $N7, "") | QK7: =IF(48<=$G7, QJ7-QI7, "") | QL7: =IF(48<=$G7, QH7-QK7, "") | QM7: =IF(48<=$G7, ROUND(QE7*$Q7, 2), "") | QN7: =IF(48<=$G7, QE7+QM7, "") | QO7: =IF(48<=$G7, QI7+QM7, "") | QP7: =IF(48<=$G7, ($G7-48)*$N7, "")
A8: 0506-0006 | B8: Electronic Accounting Sa de Cv | C8: X5 | D8: ACTIVO | E8: 2024-01-10 | F8: 2027-01-10 | G8: 36 | H8: 1622338.8 | I8: 0.1759 | J8: =ROUND(H8*I8, 2) | K8: =ROUND(H8-J8, 2) | L8: 0 | M8: =ROUND(H8*L8, 2) | N8: 35607.45 | O8: 0.35 | P8: =ROUND(H8*O8, 2) | Q8: 0.01430392 | R8: =RATE(G8, -N8, K8, -P8) | S8: =ROUND(Q8*12, 8) | T8: =ROUND(((1+Q8)^12)-1, 8) | U8: =ROUND(PV(Q8, G8, 0, -P8), 2) | V8: =SUMIF($AA$4:$QP$4, "Interes_Leasing", AA8:QP8) | W8: =SUMIF($AA$4:$QP$4, "Interes_Residual", AA8:QP8) | X8: =ROUND(V8+W8, 2) | Y8: =ROUND((N8*G8+P8+M8)-K8, 2) | Z8: =ROUND(Y8/K8, 4) | AA8: =IF(1<=$G8, $K8, "") | AB8: =IF(1<=$G8, ROUND(AA8*$Q8, 2), "") | AC8: =IF(1<=$G8, $N8, "") | AD8: =IF(1<=$G8, AC8-AB8, "") | AE8: =IF(1<=$G8, AA8-AD8, "") | AF8: =IF(1<=$G8, ROUND($U8*$Q8, 2), "") | AG8: =IF(1<=$G8, $U8+AF8, "") | AH8: =IF(1<=$G8, AB8+AF8, "") | AI8: =IF(1<=$G8, ($G8-1)*$N8, "") | AJ8: =IF(2<=$G8, AE8, "") | AK8: =IF(2<=$G8, ROUND(AJ8*$Q8, 2), "") | AL8: =IF(2<=$G8, $N8, "") | AM8: =IF(2<=$G8, AL8-AK8, "") | AN8: =IF(2<=$G8, AJ8-AM8, "") | AO8: =IF(2<=$G8, ROUND(AG8*$Q8, 2), "") | AP8: =IF(2<=$G8, AG8+AO8, "") | AQ8: =IF(2<=$G8, AK8+AO8, "") | AR8: =IF(2<=$G8, ($G8-2)*$N8, "") | AS8: =IF(3<=$G8, AN8, "") | AT8: =IF(3<=$G8, ROUND(AS8*$Q8, 2), "") | AU8: =IF(3<=$G8, $N8, "") | AV8: =IF(3<=$G8, AU8-AT8, "") | AW8: =IF(3<=$G8, AS8-AV8, "") | AX8: =IF(3<=$G8, ROUND(AP8*$Q8, 2), "") | AY8: =IF(3<=$G8, AP8+AX8, "") | AZ8: =IF(3<=$G8, AT8+AX8, "") | BA8: =IF(3<=$G8, ($G8-3)*$N8, "") | BB8: =IF(4<=$G8, AW8, "") | BC8: =IF(4<=$G8, ROUND(BB8*$Q8, 2), "") | BD8: =IF(4<=$G8, $N8, "") | BE8: =IF(4<=$G8, BD8-BC8, "") | BF8: =IF(4<=$G8, BB8-BE8, "") | BG8: =IF(4<=$G8, ROUND(AY8*$Q8, 2), "") | BH8: =IF(4<=$G8, AY8+BG8, "") | BI8: =IF(4<=$G8, BC8+BG8, "") | BJ8: =IF(4<=$G8, ($G8-4)*$N8, "") | BK8: =IF(5<=$G8, BF8, "") | BL8: =IF(5<=$G8, ROUND(BK8*$Q8, 2), "") | BM8: =IF(5<=$G8, $N8, "") | BN8: =IF(5<=$G8, BM8-BL8, "") | BO8: =IF(5<=$G8, BK8-BN8, "") | BP8: =IF(5<=$G8, ROUND(BH8*$Q8, 2), "") | BQ8: =IF(5<=$G8, BH8+BP8, "") | BR8: =IF(5<=$G8, BL8+BP8, "") | BS8: =IF(5<=$G8, ($G8-5)*$N8, "") | BT8: =IF(6<=$G8, BO8, "") | BU8: =IF(6<=$G8, ROUND(BT8*$Q8, 2), "") | BV8: =IF(6<=$G8, $N8, "") | BW8: =IF(6<=$G8, BV8-BU8, "") | BX8: =IF(6<=$G8, BT8-BW8, "") | BY8: =IF(6<=$G8, ROUND(BQ8*$Q8, 2), "") | BZ8: =IF(6<=$G8, BQ8+BY8, "") | CA8: =IF(6<=$G8, BU8+BY8, "") | CB8: =IF(6<=$G8, ($G8-6)*$N8, "") | CC8: =IF(7<=$G8, BX8, "") | CD8: =IF(7<=$G8, ROUND(CC8*$Q8, 2), "") | CE8: =IF(7<=$G8, $N8, "") | CF8: =IF(7<=$G8, CE8-CD8, "") | CG8: =IF(7<=$G8, CC8-CF8, "") | CH8: =IF(7<=$G8, ROUND(BZ8*$Q8, 2), "") | CI8: =IF(7<=$G8, BZ8+CH8, "") | CJ8: =IF(7<=$G8, CD8+CH8, "") | CK8: =IF(7<=$G8, ($G8-7)*$N8, "") | CL8: =IF(8<=$G8, CG8, "") | CM8: =IF(8<=$G8, ROUND(CL8*$Q8, 2), "") | CN8: =IF(8<=$G8, $N8, "") | CO8: =IF(8<=$G8, CN8-CM8, "") | CP8: =IF(8<=$G8, CL8-CO8, "") | CQ8: =IF(8<=$G8, ROUND(CI8*$Q8, 2), "") | CR8: =IF(8<=$G8, CI8+CQ8, "") | CS8: =IF(8<=$G8, CM8+CQ8, "") | CT8: =IF(8<=$G8, ($G8-8)*$N8, "") | CU8: =IF(9<=$G8, CP8, "") | CV8: =IF(9<=$G8, ROUND(CU8*$Q8, 2), "") | CW8: =IF(9<=$G8, $N8, "") | CX8: =IF(9<=$G8, CW8-CV8, "") | CY8: =IF(9<=$G8, CU8-CX8, "") | CZ8: =IF(9<=$G8, ROUND(CR8*$Q8, 2), "") | DA8: =IF(9<=$G8, CR8+CZ8, "") | DB8: =IF(9<=$G8, CV8+CZ8, "") | DC8: =IF(9<=$G8, ($G8-9)*$N8, "") | DD8: =IF(10<=$G8, CY8, "") | DE8: =IF(10<=$G8, ROUND(DD8*$Q8, 2), "") | DF8: =IF(10<=$G8, $N8, "") | DG8: =IF(10<=$G8, DF8-DE8, "") | DH8: =IF(10<=$G8, DD8-DG8, "") | DI8: =IF(10<=$G8, ROUND(DA8*$Q8, 2), "") | DJ8: =IF(10<=$G8, DA8+DI8, "") | DK8: =IF(10<=$G8, DE8+DI8, "") | DL8: =IF(10<=$G8, ($G8-10)*$N8, "") | DM8: =IF(11<=$G8, DH8, "") | DN8: =IF(11<=$G8, ROUND(DM8*$Q8, 2), "") | DO8: =IF(11<=$G8, $N8, "") | DP8: =IF(11<=$G8, DO8-DN8, "") | DQ8: =IF(11<=$G8, DM8-DP8, "") | DR8: =IF(11<=$G8, ROUND(DJ8*$Q8, 2), "") | DS8: =IF(11<=$G8, DJ8+DR8, "") | DT8: =IF(11<=$G8, DN8+DR8, "") | DU8: =IF(11<=$G8, ($G8-11)*$N8, "") | DV8: =IF(12<=$G8, DQ8, "") | DW8: =IF(12<=$G8, ROUND(DV8*$Q8, 2), "") | DX8: =IF(12<=$G8, $N8, "") | DY8: =IF(12<=$G8, DX8-DW8, "") | DZ8: =IF(12<=$G8, DV8-DY8, "") | EA8: =IF(12<=$G8, ROUND(DS8*$Q8, 2), "") | EB8: =IF(12<=$G8, DS8+EA8, "") | EC8: =IF(12<=$G8, DW8+EA8, "") | ED8: =IF(12<=$G8, ($G8-12)*$N8, "") | EE8: =IF(13<=$G8, DZ8, "") | EF8: =IF(13<=$G8, ROUND(EE8*$Q8, 2), "") | EG8: =IF(13<=$G8, $N8, "") | EH8: =IF(13<=$G8, EG8-EF8, "") | EI8: =IF(13<=$G8, EE8-EH8, "") | EJ8: =IF(13<=$G8, ROUND(EB8*$Q8, 2), "") | EK8: =IF(13<=$G8, EB8+EJ8, "") | EL8: =IF(13<=$G8, EF8+EJ8, "") | EM8: =IF(13<=$G8, ($G8-13)*$N8, "") | EN8: =IF(14<=$G8, EI8, "") | EO8: =IF(14<=$G8, ROUND(EN8*$Q8, 2), "") | EP8: =IF(14<=$G8, $N8, "") | EQ8: =IF(14<=$G8, EP8-EO8, "") | ER8: =IF(14<=$G8, EN8-EQ8, "") | ES8: =IF(14<=$G8, ROUND(EK8*$Q8, 2), "") | ET8: =IF(14<=$G8, EK8+ES8, "") | EU8: =IF(14<=$G8, EO8+ES8, "") | EV8: =IF(14<=$G8, ($G8-14)*$N8, "") | EW8: =IF(15<=$G8, ER8, "") | EX8: =IF(15<=$G8, ROUND(EW8*$Q8, 2), "") | EY8: =IF(15<=$G8, $N8, "") | EZ8: =IF(15<=$G8, EY8-EX8, "") | FA8: =IF(15<=$G8, EW8-EZ8, "") | FB8: =IF(15<=$G8, ROUND(ET8*$Q8, 2), "") | FC8: =IF(15<=$G8, ET8+FB8, "") | FD8: =IF(15<=$G8, EX8+FB8, "") | FE8: =IF(15<=$G8, ($G8-15)*$N8, "") | FF8: =IF(16<=$G8, FA8, "") | FG8: =IF(16<=$G8, ROUND(FF8*$Q8, 2), "") | FH8: =IF(16<=$G8, $N8, "") | FI8: =IF(16<=$G8, FH8-FG8, "") | FJ8: =IF(16<=$G8, FF8-FI8, "") | FK8: =IF(16<=$G8, ROUND(FC8*$Q8, 2), "") | FL8: =IF(16<=$G8, FC8+FK8, "") | FM8: =IF(16<=$G8, FG8+FK8, "") | FN8: =IF(16<=$G8, ($G8-16)*$N8, "") | FO8: =IF(17<=$G8, FJ8, "") | FP8: =IF(17<=$G8, ROUND(FO8*$Q8, 2), "") | FQ8: =IF(17<=$G8, $N8, "") | FR8: =IF(17<=$G8, FQ8-FP8, "") | FS8: =IF(17<=$G8, FO8-FR8, "") | FT8: =IF(17<=$G8, ROUND(FL8*$Q8, 2), "") | FU8: =IF(17<=$G8, FL8+FT8, "") | FV8: =IF(17<=$G8, FP8+FT8, "") | FW8: =IF(17<=$G8, ($G8-17)*$N8, "") | FX8: =IF(18<=$G8, FS8, "") | FY8: =IF(18<=$G8, ROUND(FX8*$Q8, 2), "") | FZ8: =IF(18<=$G8, $N8, "") | GA8: =IF(18<=$G8, FZ8-FY8, "") | GB8: =IF(18<=$G8, FX8-GA8, "") | GC8: =IF(18<=$G8, ROUND(FU8*$Q8, 2), "") | GD8: =IF(18<=$G8, FU8+GC8, "") | GE8: =IF(18<=$G8, FY8+GC8, "") | GF8: =IF(18<=$G8, ($G8-18)*$N8, "") | GG8: =IF(19<=$G8, GB8, "") | GH8: =IF(19<=$G8, ROUND(GG8*$Q8, 2), "") | GI8: =IF(19<=$G8, $N8, "") | GJ8: =IF(19<=$G8, GI8-GH8, "") | GK8: =IF(19<=$G8, GG8-GJ8, "") | GL8: =IF(19<=$G8, ROUND(GD8*$Q8, 2), "") | GM8: =IF(19<=$G8, GD8+GL8, "") | GN8: =IF(19<=$G8, GH8+GL8, "") | GO8: =IF(19<=$G8, ($G8-19)*$N8, "") | GP8: =IF(20<=$G8, GK8, "") | GQ8: =IF(20<=$G8, ROUND(GP8*$Q8, 2), "") | GR8: =IF(20<=$G8, $N8, "") | GS8: =IF(20<=$G8, GR8-GQ8, "") | GT8: =IF(20<=$G8, GP8-GS8, "") | GU8: =IF(20<=$G8, ROUND(GM8*$Q8, 2), "") | GV8: =IF(20<=$G8, GM8+GU8, "") | GW8: =IF(20<=$G8, GQ8+GU8, "") | GX8: =IF(20<=$G8, ($G8-20)*$N8, "") | GY8: =IF(21<=$G8, GT8, "") | GZ8: =IF(21<=$G8, ROUND(GY8*$Q8, 2), "") | HA8: =IF(21<=$G8, $N8, "") | HB8: =IF(21<=$G8, HA8-GZ8, "") | HC8: =IF(21<=$G8, GY8-HB8, "") | HD8: =IF(21<=$G8, ROUND(GV8*$Q8, 2), "") | HE8: =IF(21<=$G8, GV8+HD8, "") | HF8: =IF(21<=$G8, GZ8+HD8, "") | HG8: =IF(21<=$G8, ($G8-21)*$N8, "") | HH8: =IF(22<=$G8, HC8, "") | HI8: =IF(22<=$G8, ROUND(HH8*$Q8, 2), "") | HJ8: =IF(22<=$G8, $N8, "") | HK8: =IF(22<=$G8, HJ8-HI8, "") | HL8: =IF(22<=$G8, HH8-HK8, "") | HM8: =IF(22<=$G8, ROUND(HE8*$Q8, 2), "") | HN8: =IF(22<=$G8, HE8+HM8, "") | HO8: =IF(22<=$G8, HI8+HM8, "") | HP8: =IF(22<=$G8, ($G8-22)*$N8, "") | HQ8: =IF(23<=$G8, HL8, "") | HR8: =IF(23<=$G8, ROUND(HQ8*$Q8, 2), "") | HS8: =IF(23<=$G8, $N8, "") | HT8: =IF(23<=$G8, HS8-HR8, "") | HU8: =IF(23<=$G8, HQ8-HT8, "") | HV8: =IF(23<=$G8, ROUND(HN8*$Q8, 2), "") | HW8: =IF(23<=$G8, HN8+HV8, "") | HX8: =IF(23<=$G8, HR8+HV8, "") | HY8: =IF(23<=$G8, ($G8-23)*$N8, "") | HZ8: =IF(24<=$G8, HU8, "") | IA8: =IF(24<=$G8, ROUND(HZ8*$Q8, 2), "") | IB8: =IF(24<=$G8, $N8, "") | IC8: =IF(24<=$G8, IB8-IA8, "") | ID8: =IF(24<=$G8, HZ8-IC8, "") | IE8: =IF(24<=$G8, ROUND(HW8*$Q8, 2), "") | IF8: =IF(24<=$G8, HW8+IE8, "") | IG8: =IF(24<=$G8, IA8+IE8, "") | IH8: =IF(24<=$G8, ($G8-24)*$N8, "") | II8: =IF(25<=$G8, ID8, "") | IJ8: =IF(25<=$G8, ROUND(II8*$Q8, 2), "") | IK8: =IF(25<=$G8, $N8, "") | IL8: =IF(25<=$G8, IK8-IJ8, "") | IM8: =IF(25<=$G8, II8-IL8, "") | IN8: =IF(25<=$G8, ROUND(IF8*$Q8, 2), "") | IO8: =IF(25<=$G8, IF8+IN8, "") | IP8: =IF(25<=$G8, IJ8+IN8, "") | IQ8: =IF(25<=$G8, ($G8-25)*$N8, "") | IR8: =IF(26<=$G8, IM8, "") | IS8: =IF(26<=$G8, ROUND(IR8*$Q8, 2), "") | IT8: =IF(26<=$G8, $N8, "") | IU8: =IF(26<=$G8, IT8-IS8, "") | IV8: =IF(26<=$G8, IR8-IU8, "") | IW8: =IF(26<=$G8, ROUND(IO8*$Q8, 2), "") | IX8: =IF(26<=$G8, IO8+IW8, "") | IY8: =IF(26<=$G8, IS8+IW8, "") | IZ8: =IF(26<=$G8, ($G8-26)*$N8, "") | JA8: =IF(27<=$G8, IV8, "") | JB8: =IF(27<=$G8, ROUND(JA8*$Q8, 2), "") | JC8: =IF(27<=$G8, $N8, "") | JD8: =IF(27<=$G8, JC8-JB8, "") | JE8: =IF(27<=$G8, JA8-JD8, "") | JF8: =IF(27<=$G8, ROUND(IX8*$Q8, 2), "") | JG8: =IF(27<=$G8, IX8+JF8, "") | JH8: =IF(27<=$G8, JB8+JF8, "") | JI8: =IF(27<=$G8, ($G8-27)*$N8, "") | JJ8: =IF(28<=$G8, JE8, "") | JK8: =IF(28<=$G8, ROUND(JJ8*$Q8, 2), "") | JL8: =IF(28<=$G8, $N8, "") | JM8: =IF(28<=$G8, JL8-JK8, "") | JN8: =IF(28<=$G8, JJ8-JM8, "") | JO8: =IF(28<=$G8, ROUND(JG8*$Q8, 2), "") | JP8: =IF(28<=$G8, JG8+JO8, "") | JQ8: =IF(28<=$G8, JK8+JO8, "") | JR8: =IF(28<=$G8, ($G8-28)*$N8, "") | JS8: =IF(29<=$G8, JN8, "") | JT8: =IF(29<=$G8, ROUND(JS8*$Q8, 2), "") | JU8: =IF(29<=$G8, $N8, "") | JV8: =IF(29<=$G8, JU8-JT8, "") | JW8: =IF(29<=$G8, JS8-JV8, "") | JX8: =IF(29<=$G8, ROUND(JP8*$Q8, 2), "") | JY8: =IF(29<=$G8, JP8+JX8, "") | JZ8: =IF(29<=$G8, JT8+JX8, "") | KA8: =IF(29<=$G8, ($G8-29)*$N8, "") | KB8: =IF(30<=$G8, JW8, "") | KC8: =IF(30<=$G8, ROUND(KB8*$Q8, 2), "") | KD8: =IF(30<=$G8, $N8, "") | KE8: =IF(30<=$G8, KD8-KC8, "") | KF8: =IF(30<=$G8, KB8-KE8, "") | KG8: =IF(30<=$G8, ROUND(JY8*$Q8, 2), "") | KH8: =IF(30<=$G8, JY8+KG8, "") | KI8: =IF(30<=$G8, KC8+KG8, "") | KJ8: =IF(30<=$G8, ($G8-30)*$N8, "") | KK8: =IF(31<=$G8, KF8, "") | KL8: =IF(31<=$G8, ROUND(KK8*$Q8, 2), "") | KM8: =IF(31<=$G8, $N8, "") | KN8: =IF(31<=$G8, KM8-KL8, "") | KO8: =IF(31<=$G8, KK8-KN8, "") | KP8: =IF(31<=$G8, ROUND(KH8*$Q8, 2), "") | KQ8: =IF(31<=$G8, KH8+KP8, "") | KR8: =IF(31<=$G8, KL8+KP8, "") | KS8: =IF(31<=$G8, ($G8-31)*$N8, "") | KT8: =IF(32<=$G8, KO8, "") | KU8: =IF(32<=$G8, ROUND(KT8*$Q8, 2), "") | KV8: =IF(32<=$G8, $N8, "") | KW8: =IF(32<=$G8, KV8-KU8, "") | KX8: =IF(32<=$G8, KT8-KW8, "") | KY8: =IF(32<=$G8, ROUND(KQ8*$Q8, 2), "") | KZ8: =IF(32<=$G8, KQ8+KY8, "") | LA8: =IF(32<=$G8, KU8+KY8, "") | LB8: =IF(32<=$G8, ($G8-32)*$N8, "") | LC8: =IF(33<=$G8, KX8, "") | LD8: =IF(33<=$G8, ROUND(LC8*$Q8, 2), "") | LE8: =IF(33<=$G8, $N8, "") | LF8: =IF(33<=$G8, LE8-LD8, "") | LG8: =IF(33<=$G8, LC8-LF8, "") | LH8: =IF(33<=$G8, ROUND(KZ8*$Q8, 2), "") | LI8: =IF(33<=$G8, KZ8+LH8, "") | LJ8: =IF(33<=$G8, LD8+LH8, "") | LK8: =IF(33<=$G8, ($G8-33)*$N8, "") | LL8: =IF(34<=$G8, LG8, "") | LM8: =IF(34<=$G8, ROUND(LL8*$Q8, 2), "") | LN8: =IF(34<=$G8, $N8, "") | LO8: =IF(34<=$G8, LN8-LM8, "") | LP8: =IF(34<=$G8, LL8-LO8, "") | LQ8: =IF(34<=$G8, ROUND(LI8*$Q8, 2), "") | LR8: =IF(34<=$G8, LI8+LQ8, "") | LS8: =IF(34<=$G8, LM8+LQ8, "") | LT8: =IF(34<=$G8, ($G8-34)*$N8, "") | LU8: =IF(35<=$G8, LP8, "") | LV8: =IF(35<=$G8, ROUND(LU8*$Q8, 2), "") | LW8: =IF(35<=$G8, $N8, "") | LX8: =IF(35<=$G8, LW8-LV8, "") | LY8: =IF(35<=$G8, LU8-LX8, "") | LZ8: =IF(35<=$G8, ROUND(LR8*$Q8, 2), "") | MA8: =IF(35<=$G8, LR8+LZ8, "") | MB8: =IF(35<=$G8, LV8+LZ8, "") | MC8: =IF(35<=$G8, ($G8-35)*$N8, "") | MD8: =IF(36<=$G8, LY8, "") | ME8: =IF(36<=$G8, ROUND(MD8*$Q8, 2), "") | MF8: =IF(36<=$G8, $N8, "") | MG8: =IF(36<=$G8, MF8-ME8, "") | MH8: =IF(36<=$G8, MD8-MG8, "") | MI8: =IF(36<=$G8, ROUND(MA8*$Q8, 2), "") | MJ8: =IF(36<=$G8, MA8+MI8, "") | MK8: =IF(36<=$G8, ME8+MI8, "") | ML8: =IF(36<=$G8, ($G8-36)*$N8, "") | MM8: =IF(37<=$G8, MH8, "") | MN8: =IF(37<=$G8, ROUND(MM8*$Q8, 2), "") | MO8: =IF(37<=$G8, $N8, "") | MP8: =IF(37<=$G8, MO8-MN8, "") | MQ8: =IF(37<=$G8, MM8-MP8, "") | MR8: =IF(37<=$G8, ROUND(MJ8*$Q8, 2), "") | MS8: =IF(37<=$G8, MJ8+MR8, "") | MT8: =IF(37<=$G8, MN8+MR8, "") | MU8: =IF(37<=$G8, ($G8-37)*$N8, "") | MV8: =IF(38<=$G8, MQ8, "") | MW8: =IF(38<=$G8, ROUND(MV8*$Q8, 2), "") | MX8: =IF(38<=$G8, $N8, "") | MY8: =IF(38<=$G8, MX8-MW8, "") | MZ8: =IF(38<=$G8, MV8-MY8, "") | NA8: =IF(38<=$G8, ROUND(MS8*$Q8, 2), "") | NB8: =IF(38<=$G8, MS8+NA8, "") | NC8: =IF(38<=$G8, MW8+NA8, "") | ND8: =IF(38<=$G8, ($G8-38)*$N8, "") | NE8: =IF(39<=$G8, MZ8, "") | NF8: =IF(39<=$G8, ROUND(NE8*$Q8, 2), "") | NG8: =IF(39<=$G8, $N8, "") | NH8: =IF(39<=$G8, NG8-NF8, "") | NI8: =IF(39<=$G8, NE8-NH8, "") | NJ8: =IF(39<=$G8, ROUND(NB8*$Q8, 2), "") | NK8: =IF(39<=$G8, NB8+NJ8, "") | NL8: =IF(39<=$G8, NF8+NJ8, "") | NM8: =IF(39<=$G8, ($G8-39)*$N8, "") | NN8: =IF(40<=$G8, NI8, "") | NO8: =IF(40<=$G8, ROUND(NN8*$Q8, 2), "") | NP8: =IF(40<=$G8, $N8, "") | NQ8: =IF(40<=$G8, NP8-NO8, "") | NR8: =IF(40<=$G8, NN8-NQ8, "") | NS8: =IF(40<=$G8, ROUND(NK8*$Q8, 2), "") | NT8: =IF(40<=$G8, NK8+NS8, "") | NU8: =IF(40<=$G8, NO8+NS8, "") | NV8: =IF(40<=$G8, ($G8-40)*$N8, "") | NW8: =IF(41<=$G8, NR8, "") | NX8: =IF(41<=$G8, ROUND(NW8*$Q8, 2), "") | NY8: =IF(41<=$G8, $N8, "") | NZ8: =IF(41<=$G8, NY8-NX8, "") | OA8: =IF(41<=$G8, NW8-NZ8, "") | OB8: =IF(41<=$G8, ROUND(NT8*$Q8, 2), "") | OC8: =IF(41<=$G8, NT8+OB8, "") | OD8: =IF(41<=$G8, NX8+OB8, "") | OE8: =IF(41<=$G8, ($G8-41)*$N8, "") | OF8: =IF(42<=$G8, OA8, "") | OG8: =IF(42<=$G8, ROUND(OF8*$Q8, 2), "") | OH8: =IF(42<=$G8, $N8, "") | OI8: =IF(42<=$G8, OH8-OG8, "") | OJ8: =IF(42<=$G8, OF8-OI8, "") | OK8: =IF(42<=$G8, ROUND(OC8*$Q8, 2), "") | OL8: =IF(42<=$G8, OC8+OK8, "") | OM8: =IF(42<=$G8, OG8+OK8, "") | ON8: =IF(42<=$G8, ($G8-42)*$N8, "") | OO8: =IF(43<=$G8, OJ8, "") | OP8: =IF(43<=$G8, ROUND(OO8*$Q8, 2), "") | OQ8: =IF(43<=$G8, $N8, "") | OR8: =IF(43<=$G8, OQ8-OP8, "") | OS8: =IF(43<=$G8, OO8-OR8, "") | OT8: =IF(43<=$G8, ROUND(OL8*$Q8, 2), "") | OU8: =IF(43<=$G8, OL8+OT8, "") | OV8: =IF(43<=$G8, OP8+OT8, "") | OW8: =IF(43<=$G8, ($G8-43)*$N8, "") | OX8: =IF(44<=$G8, OS8, "") | OY8: =IF(44<=$G8, ROUND(OX8*$Q8, 2), "") | OZ8: =IF(44<=$G8, $N8, "") | PA8: =IF(44<=$G8, OZ8-OY8, "") | PB8: =IF(44<=$G8, OX8-PA8, "") | PC8: =IF(44<=$G8, ROUND(OU8*$Q8, 2), "") | PD8: =IF(44<=$G8, OU8+PC8, "") | PE8: =IF(44<=$G8, OY8+PC8, "") | PF8: =IF(44<=$G8, ($G8-44)*$N8, "") | PG8: =IF(45<=$G8, PB8, "") | PH8: =IF(45<=$G8, ROUND(PG8*$Q8, 2), "") | PI8: =IF(45<=$G8, $N8, "") | PJ8: =IF(45<=$G8, PI8-PH8, "") | PK8: =IF(45<=$G8, PG8-PJ8, "") | PL8: =IF(45<=$G8, ROUND(PD8*$Q8, 2), "") | PM8: =IF(45<=$G8, PD8+PL8, "") | PN8: =IF(45<=$G8, PH8+PL8, "") | PO8: =IF(45<=$G8, ($G8-45)*$N8, "") | PP8: =IF(46<=$G8, PK8, "") | PQ8: =IF(46<=$G8, ROUND(PP8*$Q8, 2), "") | PR8: =IF(46<=$G8, $N8, "") | PS8: =IF(46<=$G8, PR8-PQ8, "") | PT8: =IF(46<=$G8, PP8-PS8, "") | PU8: =IF(46<=$G8, ROUND(PM8*$Q8, 2), "") | PV8: =IF(46<=$G8, PM8+PU8, "") | PW8: =IF(46<=$G8, PQ8+PU8, "") | PX8: =IF(46<=$G8, ($G8-46)*$N8, "") | PY8: =IF(47<=$G8, PT8, "") | PZ8: =IF(47<=$G8, ROUND(PY8*$Q8, 2), "") | QA8: =IF(47<=$G8, $N8, "") | QB8: =IF(47<=$G8, QA8-PZ8, "") | QC8: =IF(47<=$G8, PY8-QB8, "") | QD8: =IF(47<=$G8, ROUND(PV8*$Q8, 2), "") | QE8: =IF(47<=$G8, PV8+QD8, "") | QF8: =IF(47<=$G8, PZ8+QD8, "") | QG8: =IF(47<=$G8, ($G8-47)*$N8, "") | QH8: =IF(48<=$G8, QC8, "") | QI8: =IF(48<=$G8, ROUND(QH8*$Q8, 2), "") | QJ8: =IF(48<=$G8, $N8, "") | QK8: =IF(48<=$G8, QJ8-QI8, "") | QL8: =IF(48<=$G8, QH8-QK8, "") | QM8: =IF(48<=$G8, ROUND(QE8*$Q8, 2), "") | QN8: =IF(48<=$G8, QE8+QM8, "") | QO8: =IF(48<=$G8, QI8+QM8, "") | QP8: =IF(48<=$G8, ($G8-48)*$N8, "")
A9: 0506-0007 | B9: Electronic Acounting | C9: L200 Glx Diesel | D9: ACTIVO | E9: 2024-09-05 | F9: 2027-09-05 | G9: 36 | H9: 536762.93 | I9: 0 | J9: =ROUND(H9*I9, 2) | K9: =ROUND(H9-J9, 2) | L9: 0 | M9: =ROUND(H9*L9, 2) | N9: 16715.69 | O9: 0.35 | P9: =ROUND(H9*O9, 2) | Q9: 0.01820217 | R9: =RATE(G9, -N9, K9, -P9) | S9: =ROUND(Q9*12, 8) | T9: =ROUND(((1+Q9)^12)-1, 8) | U9: =ROUND(PV(Q9, G9, 0, -P9), 2) | V9: =SUMIF($AA$4:$QP$4, "Interes_Leasing", AA9:QP9) | W9: =SUMIF($AA$4:$QP$4, "Interes_Residual", AA9:QP9) | X9: =ROUND(V9+W9, 2) | Y9: =ROUND((N9*G9+P9+M9)-K9, 2) | Z9: =ROUND(Y9/K9, 4) | AA9: =IF(1<=$G9, $K9, "") | AB9: =IF(1<=$G9, ROUND(AA9*$Q9, 2), "") | AC9: =IF(1<=$G9, $N9, "") | AD9: =IF(1<=$G9, AC9-AB9, "") | AE9: =IF(1<=$G9, AA9-AD9, "") | AF9: =IF(1<=$G9, ROUND($U9*$Q9, 2), "") | AG9: =IF(1<=$G9, $U9+AF9, "") | AH9: =IF(1<=$G9, AB9+AF9, "") | AI9: =IF(1<=$G9, ($G9-1)*$N9, "") | AJ9: =IF(2<=$G9, AE9, "") | AK9: =IF(2<=$G9, ROUND(AJ9*$Q9, 2), "") | AL9: =IF(2<=$G9, $N9, "") | AM9: =IF(2<=$G9, AL9-AK9, "") | AN9: =IF(2<=$G9, AJ9-AM9, "") | AO9: =IF(2<=$G9, ROUND(AG9*$Q9, 2), "") | AP9: =IF(2<=$G9, AG9+AO9, "") | AQ9: =IF(2<=$G9, AK9+AO9, "") | AR9: =IF(2<=$G9, ($G9-2)*$N9, "") | AS9: =IF(3<=$G9, AN9, "") | AT9: =IF(3<=$G9, ROUND(AS9*$Q9, 2), "") | AU9: =IF(3<=$G9, $N9, "") | AV9: =IF(3<=$G9, AU9-AT9, "") | AW9: =IF(3<=$G9, AS9-AV9, "") | AX9: =IF(3<=$G9, ROUND(AP9*$Q9, 2), "") | AY9: =IF(3<=$G9, AP9+AX9, "") | AZ9: =IF(3<=$G9, AT9+AX9, "") | BA9: =IF(3<=$G9, ($G9-3)*$N9, "") | BB9: =IF(4<=$G9, AW9, "") | BC9: =IF(4<=$G9, ROUND(BB9*$Q9, 2), "") | BD9: =IF(4<=$G9, $N9, "") | BE9: =IF(4<=$G9, BD9-BC9, "") | BF9: =IF(4<=$G9, BB9-BE9, "") | BG9: =IF(4<=$G9, ROUND(AY9*$Q9, 2), "") | BH9: =IF(4<=$G9, AY9+BG9, "") | BI9: =IF(4<=$G9, BC9+BG9, "") | BJ9: =IF(4<=$G9, ($G9-4)*$N9, "") | BK9: =IF(5<=$G9, BF9, "") | BL9: =IF(5<=$G9, ROUND(BK9*$Q9, 2), "") | BM9: =IF(5<=$G9, $N9, "") | BN9: =IF(5<=$G9, BM9-BL9, "") | BO9: =IF(5<=$G9, BK9-BN9, "") | BP9: =IF(5<=$G9, ROUND(BH9*$Q9, 2), "") | BQ9: =IF(5<=$G9, BH9+BP9, "") | BR9: =IF(5<=$G9, BL9+BP9, "") | BS9: =IF(5<=$G9, ($G9-5)*$N9, "") | BT9: =IF(6<=$G9, BO9, "") | BU9: =IF(6<=$G9, ROUND(BT9*$Q9, 2), "") | BV9: =IF(6<=$G9, $N9, "") | BW9: =IF(6<=$G9, BV9-BU9, "") | BX9: =IF(6<=$G9, BT9-BW9, "") | BY9: =IF(6<=$G9, ROUND(BQ9*$Q9, 2), "") | BZ9: =IF(6<=$G9, BQ9+BY9, "") | CA9: =IF(6<=$G9, BU9+BY9, "") | CB9: =IF(6<=$G9, ($G9-6)*$N9, "") | CC9: =IF(7<=$G9, BX9, "") | CD9: =IF(7<=$G9, ROUND(CC9*$Q9, 2), "") | CE9: =IF(7<=$G9, $N9, "") | CF9: =IF(7<=$G9, CE9-CD9, "") | CG9: =IF(7<=$G9, CC9-CF9, "") | CH9: =IF(7<=$G9, ROUND(BZ9*$Q9, 2), "") | CI9: =IF(7<=$G9, BZ9+CH9, "") | CJ9: =IF(7<=$G9, CD9+CH9, "") | CK9: =IF(7<=$G9, ($G9-7)*$N9, "") | CL9: =IF(8<=$G9, CG9, "") | CM9: =IF(8<=$G9, ROUND(CL9*$Q9, 2), "") | CN9: =IF(8<=$G9, $N9, "") | CO9: =IF(8<=$G9, CN9-CM9, "") | CP9: =IF(8<=$G9, CL9-CO9, "") | CQ9: =IF(8<=$G9, ROUND(CI9*$Q9, 2), "") | CR9: =IF(8<=$G9, CI9+CQ9, "") | CS9: =IF(8<=$G9, CM9+CQ9, "") | CT9: =IF(8<=$G9, ($G9-8)*$N9, "") | CU9: =IF(9<=$G9, CP9, "") | CV9: =IF(9<=$G9, ROUND(CU9*$Q9, 2), "") | CW9: =IF(9<=$G9, $N9, "") | CX9: =IF(9<=$G9, CW9-CV9, "") | CY9: =IF(9<=$G9, CU9-CX9, "") | CZ9: =IF(9<=$G9, ROUND(CR9*$Q9, 2), "") | DA9: =IF(9<=$G9, CR9+CZ9, "") | DB9: =IF(9<=$G9, CV9+CZ9, "") | DC9: =IF(9<=$G9, ($G9-9)*$N9, "") | DD9: =IF(10<=$G9, CY9, "") | DE9: =IF(10<=$G9, ROUND(DD9*$Q9, 2), "") | DF9: =IF(10<=$G9, $N9, "") | DG9: =IF(10<=$G9, DF9-DE9, "") | DH9: =IF(10<=$G9, DD9-DG9, "") | DI9: =IF(10<=$G9, ROUND(DA9*$Q9, 2), "") | DJ9: =IF(10<=$G9, DA9+DI9, "") | DK9: =IF(10<=$G9, DE9+DI9, "") | DL9: =IF(10<=$G9, ($G9-10)*$N9, "") | DM9: =IF(11<=$G9, DH9, "") | DN9: =IF(11<=$G9, ROUND(DM9*$Q9, 2), "") | DO9: =IF(11<=$G9, $N9, "") | DP9: =IF(11<=$G9, DO9-DN9, "") | DQ9: =IF(11<=$G9, DM9-DP9, "") | DR9: =IF(11<=$G9, ROUND(DJ9*$Q9, 2), "") | DS9: =IF(11<=$G9, DJ9+DR9, "") | DT9: =IF(11<=$G9, DN9+DR9, "") | DU9: =IF(11<=$G9, ($G9-11)*$N9, "") | DV9: =IF(12<=$G9, DQ9, "") | DW9: =IF(12<=$G9, ROUND(DV9*$Q9, 2), "") | DX9: =IF(12<=$G9, $N9, "") | DY9: =IF(12<=$G9, DX9-DW9, "") | DZ9: =IF(12<=$G9, DV9-DY9, "") | EA9: =IF(12<=$G9, ROUND(DS9*$Q9, 2), "") | EB9: =IF(12<=$G9, DS9+EA9, "") | EC9: =IF(12<=$G9, DW9+EA9, "") | ED9: =IF(12<=$G9, ($G9-12)*$N9, "") | EE9: =IF(13<=$G9, DZ9, "") | EF9: =IF(13<=$G9, ROUND(EE9*$Q9, 2), "") | EG9: =IF(13<=$G9, $N9, "") | EH9: =IF(13<=$G9, EG9-EF9, "") | EI9: =IF(13<=$G9, EE9-EH9, "") | EJ9: =IF(13<=$G9, ROUND(EB9*$Q9, 2), "") | EK9: =IF(13<=$G9, EB9+EJ9, "") | EL9: =IF(13<=$G9, EF9+EJ9, "") | EM9: =IF(13<=$G9, ($G9-13)*$N9, "") | EN9: =IF(14<=$G9, EI9, "") | EO9: =IF(14<=$G9, ROUND(EN9*$Q9, 2), "") | EP9: =IF(14<=$G9, $N9, "") | EQ9: =IF(14<=$G9, EP9-EO9, "") | ER9: =IF(14<=$G9, EN9-EQ9, "") | ES9: =IF(14<=$G9, ROUND(EK9*$Q9, 2), "") | ET9: =IF(14<=$G9, EK9+ES9, "") | EU9: =IF(14<=$G9, EO9+ES9, "") | EV9: =IF(14<=$G9, ($G9-14)*$N9, "") | EW9: =IF(15<=$G9, ER9, "") | EX9: =IF(15<=$G9, ROUND(EW9*$Q9, 2), "") | EY9: =IF(15<=$G9, $N9, "") | EZ9: =IF(15<=$G9, EY9-EX9, "") | FA9: =IF(15<=$G9, EW9-EZ9, "") | FB9: =IF(15<=$G9, ROUND(ET9*$Q9, 2), "") | FC9: =IF(15<=$G9, ET9+FB9, "") | FD9: =IF(15<=$G9, EX9+FB9, "") | FE9: =IF(15<=$G9, ($G9-15)*$N9, "") | FF9: =IF(16<=$G9, FA9, "") | FG9: =IF(16<=$G9, ROUND(FF9*$Q9, 2), "") | FH9: =IF(16<=$G9, $N9, "") | FI9: =IF(16<=$G9, FH9-FG9, "") | FJ9: =IF(16<=$G9, FF9-FI9, "") | FK9: =IF(16<=$G9, ROUND(FC9*$Q9, 2), "") | FL9: =IF(16<=$G9, FC9+FK9, "") | FM9: =IF(16<=$G9, FG9+FK9, "") | FN9: =IF(16<=$G9, ($G9-16)*$N9, "") | FO9: =IF(17<=$G9, FJ9, "") | FP9: =IF(17<=$G9, ROUND(FO9*$Q9, 2), "") | FQ9: =IF(17<=$G9, $N9, "") | FR9: =IF(17<=$G9, FQ9-FP9, "") | FS9: =IF(17<=$G9, FO9-FR9, "") | FT9: =IF(17<=$G9, ROUND(FL9*$Q9, 2), "") | FU9: =IF(17<=$G9, FL9+FT9, "") | FV9: =IF(17<=$G9, FP9+FT9, "") | FW9: =IF(17<=$G9, ($G9-17)*$N9, "") | FX9: =IF(18<=$G9, FS9, "") | FY9: =IF(18<=$G9, ROUND(FX9*$Q9, 2), "") | FZ9: =IF(18<=$G9, $N9, "") | GA9: =IF(18<=$G9, FZ9-FY9, "") | GB9: =IF(18<=$G9, FX9-GA9, "") | GC9: =IF(18<=$G9, ROUND(FU9*$Q9, 2), "") | GD9: =IF(18<=$G9, FU9+GC9, "") | GE9: =IF(18<=$G9, FY9+GC9, "") | GF9: =IF(18<=$G9, ($G9-18)*$N9, "") | GG9: =IF(19<=$G9, GB9, "") | GH9: =IF(19<=$G9, ROUND(GG9*$Q9, 2), "") | GI9: =IF(19<=$G9, $N9, "") | GJ9: =IF(19<=$G9, GI9-GH9, "") | GK9: =IF(19<=$G9, GG9-GJ9, "") | GL9: =IF(19<=$G9, ROUND(GD9*$Q9, 2), "") | GM9: =IF(19<=$G9, GD9+GL9, "") | GN9: =IF(19<=$G9, GH9+GL9, "") | GO9: =IF(19<=$G9, ($G9-19)*$N9, "") | GP9: =IF(20<=$G9, GK9, "") | GQ9: =IF(20<=$G9, ROUND(GP9*$Q9, 2), "") | GR9: =IF(20<=$G9, $N9, "") | GS9: =IF(20<=$G9, GR9-GQ9, "") | GT9: =IF(20<=$G9, GP9-GS9, "") | GU9: =IF(20<=$G9, ROUND(GM9*$Q9, 2), "") | GV9: =IF(20<=$G9, GM9+GU9, "") | GW9: =IF(20<=$G9, GQ9+GU9, "") | GX9: =IF(20<=$G9, ($G9-20)*$N9, "") | GY9: =IF(21<=$G9, GT9, "") | GZ9: =IF(21<=$G9, ROUND(GY9*$Q9, 2), "") | HA9: =IF(21<=$G9, $N9, "") | HB9: =IF(21<=$G9, HA9-GZ9, "") | HC9: =IF(21<=$G9, GY9-HB9, "") | HD9: =IF(21<=$G9, ROUND(GV9*$Q9, 2), "") | HE9: =IF(21<=$G9, GV9+HD9, "") | HF9: =IF(21<=$G9, GZ9+HD9, "") | HG9: =IF(21<=$G9, ($G9-21)*$N9, "") | HH9: =IF(22<=$G9, HC9, "") | HI9: =IF(22<=$G9, ROUND(HH9*$Q9, 2), "") | HJ9: =IF(22<=$G9, $N9, "") | HK9: =IF(22<=$G9, HJ9-HI9, "") | HL9: =IF(22<=$G9, HH9-HK9, "") | HM9: =IF(22<=$G9, ROUND(HE9*$Q9, 2), "") | HN9: =IF(22<=$G9, HE9+HM9, "") | HO9: =IF(22<=$G9, HI9+HM9, "") | HP9: =IF(22<=$G9, ($G9-22)*$N9, "") | HQ9: =IF(23<=$G9, HL9, "") | HR9: =IF(23<=$G9, ROUND(HQ9*$Q9, 2), "") | HS9: =IF(23<=$G9, $N9, "") | HT9: =IF(23<=$G9, HS9-HR9, "") | HU9: =IF(23<=$G9, HQ9-HT9, "") | HV9: =IF(23<=$G9, ROUND(HN9*$Q9, 2), "") | HW9: =IF(23<=$G9, HN9+HV9, "") | HX9: =IF(23<=$G9, HR9+HV9, "") | HY9: =IF(23<=$G9, ($G9-23)*$N9, "") | HZ9: =IF(24<=$G9, HU9, "") | IA9: =IF(24<=$G9, ROUND(HZ9*$Q9, 2), "") | IB9: =IF(24<=$G9, $N9, "") | IC9: =IF(24<=$G9, IB9-IA9, "") | ID9: =IF(24<=$G9, HZ9-IC9, "") | IE9: =IF(24<=$G9, ROUND(HW9*$Q9, 2), "") | IF9: =IF(24<=$G9, HW9+IE9, "") | IG9: =IF(24<=$G9, IA9+IE9, "") | IH9: =IF(24<=$G9, ($G9-24)*$N9, "") | II9: =IF(25<=$G9, ID9, "") | IJ9: =IF(25<=$G9, ROUND(II9*$Q9, 2), "") | IK9: =IF(25<=$G9, $N9, "") | IL9: =IF(25<=$G9, IK9-IJ9, "") | IM9: =IF(25<=$G9, II9-IL9, "") | IN9: =IF(25<=$G9, ROUND(IF9*$Q9, 2), "") | IO9: =IF(25<=$G9, IF9+IN9, "") | IP9: =IF(25<=$G9, IJ9+IN9, "") | IQ9: =IF(25<=$G9, ($G9-25)*$N9, "") | IR9: =IF(26<=$G9, IM9, "") | IS9: =IF(26<=$G9, ROUND(IR9*$Q9, 2), "") | IT9: =IF(26<=$G9, $N9, "") | IU9: =IF(26<=$G9, IT9-IS9, "") | IV9: =IF(26<=$G9, IR9-IU9, "") | IW9: =IF(26<=$G9, ROUND(IO9*$Q9, 2), "") | IX9: =IF(26<=$G9, IO9+IW9, "") | IY9: =IF(26<=$G9, IS9+IW9, "") | IZ9: =IF(26<=$G9, ($G9-26)*$N9, "") | JA9: =IF(27<=$G9, IV9, "") | JB9: =IF(27<=$G9, ROUND(JA9*$Q9, 2), "") | JC9: =IF(27<=$G9, $N9, "") | JD9: =IF(27<=$G9, JC9-JB9, "") | JE9: =IF(27<=$G9, JA9-JD9, "") | JF9: =IF(27<=$G9, ROUND(IX9*$Q9, 2), "") | JG9: =IF(27<=$G9, IX9+JF9, "") | JH9: =IF(27<=$G9, JB9+JF9, "") | JI9: =IF(27<=$G9, ($G9-27)*$N9, "") | JJ9: =IF(28<=$G9, JE9, "") | JK9: =IF(28<=$G9, ROUND(JJ9*$Q9, 2), "") | JL9: =IF(28<=$G9, $N9, "") | JM9: =IF(28<=$G9, JL9-JK9, "") | JN9: =IF(28<=$G9, JJ9-JM9, "") | JO9: =IF(28<=$G9, ROUND(JG9*$Q9, 2), "") | JP9: =IF(28<=$G9, JG9+JO9, "") | JQ9: =IF(28<=$G9, JK9+JO9, "") | JR9: =IF(28<=$G9, ($G9-28)*$N9, "") | JS9: =IF(29<=$G9, JN9, "") | JT9: =IF(29<=$G9, ROUND(JS9*$Q9, 2), "") | JU9: =IF(29<=$G9, $N9, "") | JV9: =IF(29<=$G9, JU9-JT9, "") | JW9: =IF(29<=$G9, JS9-JV9, "") | JX9: =IF(29<=$G9, ROUND(JP9*$Q9, 2), "") | JY9: =IF(29<=$G9, JP9+JX9, "") | JZ9: =IF(29<=$G9, JT9+JX9, "") | KA9: =IF(29<=$G9, ($G9-29)*$N9, "") | KB9: =IF(30<=$G9, JW9, "") | KC9: =IF(30<=$G9, ROUND(KB9*$Q9, 2), "") | KD9: =IF(30<=$G9, $N9, "") | KE9: =IF(30<=$G9, KD9-KC9, "") | KF9: =IF(30<=$G9, KB9-KE9, "") | KG9: =IF(30<=$G9, ROUND(JY9*$Q9, 2), "") | KH9: =IF(30<=$G9, JY9+KG9, "") | KI9: =IF(30<=$G9, KC9+KG9, "") | KJ9: =IF(30<=$G9, ($G9-30)*$N9, "") | KK9: =IF(31<=$G9, KF9, "") | KL9: =IF(31<=$G9, ROUND(KK9*$Q9, 2), "") | KM9: =IF(31<=$G9, $N9, "") | KN9: =IF(31<=$G9, KM9-KL9, "") | KO9: =IF(31<=$G9, KK9-KN9, "") | KP9: =IF(31<=$G9, ROUND(KH9*$Q9, 2), "") | KQ9: =IF(31<=$G9, KH9+KP9, "") | KR9: =IF(31<=$G9, KL9+KP9, "") | KS9: =IF(31<=$G9, ($G9-31)*$N9, "") | KT9: =IF(32<=$G9, KO9, "") | KU9: =IF(32<=$G9, ROUND(KT9*$Q9, 2), "") | KV9: =IF(32<=$G9, $N9, "") | KW9: =IF(32<=$G9, KV9-KU9, "") | KX9: =IF(32<=$G9, KT9-KW9, "") | KY9: =IF(32<=$G9, ROUND(KQ9*$Q9, 2), "") | KZ9: =IF(32<=$G9, KQ9+KY9, "") | LA9: =IF(32<=$G9, KU9+KY9, "") | LB9: =IF(32<=$G9, ($G9-32)*$N9, "") | LC9: =IF(33<=$G9, KX9, "") | LD9: =IF(33<=$G9, ROUND(LC9*$Q9, 2), "") | LE9: =IF(33<=$G9, $N9, "") | LF9: =IF(33<=$G9, LE9-LD9, "") | LG9: =IF(33<=$G9, LC9-LF9, "") | LH9: =IF(33<=$G9, ROUND(KZ9*$Q9, 2), "") | LI9: =IF(33<=$G9, KZ9+LH9, "") | LJ9: =IF(33<=$G9, LD9+LH9, "") | LK9: =IF(33<=$G9, ($G9-33)*$N9, "") | LL9: =IF(34<=$G9, LG9, "") | LM9: =IF(34<=$G9, ROUND(LL9*$Q9, 2), "") | LN9: =IF(34<=$G9, $N9, "") | LO9: =IF(34<=$G9, LN9-LM9, "") | LP9: =IF(34<=$G9, LL9-LO9, "") | LQ9: =IF(34<=$G9, ROUND(LI9*$Q9, 2), "") | LR9: =IF(34<=$G9, LI9+LQ9, "") | LS9: =IF(34<=$G9, LM9+LQ9, "") | LT9: =IF(34<=$G9, ($G9-34)*$N9, "") | LU9: =IF(35<=$G9, LP9, "") | LV9: =IF(35<=$G9, ROUND(LU9*$Q9, 2), "") | LW9: =IF(35<=$G9, $N9, "") | LX9: =IF(35<=$G9, LW9-LV9, "") | LY9: =IF(35<=$G9, LU9-LX9, "") | LZ9: =IF(35<=$G9, ROUND(LR9*$Q9, 2), "") | MA9: =IF(35<=$G9, LR9+LZ9, "") | MB9: =IF(35<=$G9, LV9+LZ9, "") | MC9: =IF(35<=$G9, ($G9-35)*$N9, "") | MD9: =IF(36<=$G9, LY9, "") | ME9: =IF(36<=$G9, ROUND(MD9*$Q9, 2), "") | MF9: =IF(36<=$G9, $N9, "") | MG9: =IF(36<=$G9, MF9-ME9, "") | MH9: =IF(36<=$G9, MD9-MG9, "") | MI9: =IF(36<=$G9, ROUND(MA9*$Q9, 2), "") | MJ9: =IF(36<=$G9, MA9+MI9, "") | MK9: =IF(36<=$G9, ME9+MI9, "") | ML9: =IF(36<=$G9, ($G9-36)*$N9, "") | MM9: =IF(37<=$G9, MH9, "") | MN9: =IF(37<=$G9, ROUND(MM9*$Q9, 2), "") | MO9: =IF(37<=$G9, $N9, "") | MP9: =IF(37<=$G9, MO9-MN9, "") | MQ9: =IF(37<=$G9, MM9-MP9, "") | MR9: =IF(37<=$G9, ROUND(MJ9*$Q9, 2), "") | MS9: =IF(37<=$G9, MJ9+MR9, "") | MT9: =IF(37<=$G9, MN9+MR9, "") | MU9: =IF(37<=$G9, ($G9-37)*$N9, "") | MV9: =IF(38<=$G9, MQ9, "") | MW9: =IF(38<=$G9, ROUND(MV9*$Q9, 2), "") | MX9: =IF(38<=$G9, $N9, "") | MY9: =IF(38<=$G9, MX9-MW9, "") | MZ9: =IF(38<=$G9, MV9-MY9, "") | NA9: =IF(38<=$G9, ROUND(MS9*$Q9, 2), "") | NB9: =IF(38<=$G9, MS9+NA9, "") | NC9: =IF(38<=$G9, MW9+NA9, "") | ND9: =IF(38<=$G9, ($G9-38)*$N9, "") | NE9: =IF(39<=$G9, MZ9, "") | NF9: =IF(39<=$G9, ROUND(NE9*$Q9, 2), "") | NG9: =IF(39<=$G9, $N9, "") | NH9: =IF(39<=$G9, NG9-NF9, "") | NI9: =IF(39<=$G9, NE9-NH9, "") | NJ9: =IF(39<=$G9, ROUND(NB9*$Q9, 2), "") | NK9: =IF(39<=$G9, NB9+NJ9, "") | NL9: =IF(39<=$G9, NF9+NJ9, "") | NM9: =IF(39<=$G9, ($G9-39)*$N9, "") | NN9: =IF(40<=$G9, NI9, "") | NO9: =IF(40<=$G9, ROUND(NN9*$Q9, 2), "") | NP9: =IF(40<=$G9, $N9, "") | NQ9: =IF(40<=$G9, NP9-NO9, "") | NR9: =IF(40<=$G9, NN9-NQ9, "") | NS9: =IF(40<=$G9, ROUND(NK9*$Q9, 2), "") | NT9: =IF(40<=$G9, NK9+NS9, "") | NU9: =IF(40<=$G9, NO9+NS9, "") | NV9: =IF(40<=$G9, ($G9-40)*$N9, "") | NW9: =IF(41<=$G9, NR9, "") | NX9: =IF(41<=$G9, ROUND(NW9*$Q9, 2), "") | NY9: =IF(41<=$G9, $N9, "") | NZ9: =IF(41<=$G9, NY9-NX9, "") | OA9: =IF(41<=$G9, NW9-NZ9, "") | OB9: =IF(41<=$G9, ROUND(NT9*$Q9, 2), "") | OC9: =IF(41<=$G9, NT9+OB9, "") | OD9: =IF(41<=$G9, NX9+OB9, "") | OE9: =IF(41<=$G9, ($G9-41)*$N9, "") | OF9: =IF(42<=$G9, OA9, "") | OG9: =IF(42<=$G9, ROUND(OF9*$Q9, 2), "") | OH9: =IF(42<=$G9, $N9, "") | OI9: =IF(42<=$G9, OH9-OG9, "") | OJ9: =IF(42<=$G9, OF9-OI9, "") | OK9: =IF(42<=$G9, ROUND(OC9*$Q9, 2), "") | OL9: =IF(42<=$G9, OC9+OK9, "") | OM9: =IF(42<=$G9, OG9+OK9, "") | ON9: =IF(42<=$G9, ($G9-42)*$N9, "") | OO9: =IF(43<=$G9, OJ9, "") | OP9: =IF(43<=$G9, ROUND(OO9*$Q9, 2), "") | OQ9: =IF(43<=$G9, $N9, "") | OR9: =IF(43<=$G9, OQ9-OP9, "") | OS9: =IF(43<=$G9, OO9-OR9, "") | OT9: =IF(43<=$G9, ROUND(OL9*$Q9, 2), "") | OU9: =IF(43<=$G9, OL9+OT9, "") | OV9: =IF(43<=$G9, OP9+OT9, "") | OW9: =IF(43<=$G9, ($G9-43)*$N9, "") | OX9: =IF(44<=$G9, OS9, "") | OY9: =IF(44<=$G9, ROUND(OX9*$Q9, 2), "") | OZ9: =IF(44<=$G9, $N9, "") | PA9: =IF(44<=$G9, OZ9-OY9, "") | PB9: =IF(44<=$G9, OX9-PA9, "") | PC9: =IF(44<=$G9, ROUND(OU9*$Q9, 2), "") | PD9: =IF(44<=$G9, OU9+PC9, "") | PE9: =IF(44<=$G9, OY9+PC9, "") | PF9: =IF(44<=$G9, ($G9-44)*$N9, "") | PG9: =IF(45<=$G9, PB9, "") | PH9: =IF(45<=$G9, ROUND(PG9*$Q9, 2), "") | PI9: =IF(45<=$G9, $N9, "") | PJ9: =IF(45<=$G9, PI9-PH9, "") | PK9: =IF(45<=$G9, PG9-PJ9, "") | PL9: =IF(45<=$G9, ROUND(PD9*$Q9, 2), "") | PM9: =IF(45<=$G9, PD9+PL9, "") | PN9: =IF(45<=$G9, PH9+PL9, "") | PO9: =IF(45<=$G9, ($G9-45)*$N9, "") | PP9: =IF(46<=$G9, PK9, "") | PQ9: =IF(46<=$G9, ROUND(PP9*$Q9, 2), "") | PR9: =IF(46<=$G9, $N9, "") | PS9: =IF(46<=$G9, PR9-PQ9, "") | PT9: =IF(46<=$G9, PP9-PS9, "") | PU9: =IF(46<=$G9, ROUND(PM9*$Q9, 2), "") | PV9: =IF(46<=$G9, PM9+PU9, "") | PW9: =IF(46<=$G9, PQ9+PU9, "") | PX9: =IF(46<=$G9, ($G9-46)*$N9, "") | PY9: =IF(47<=$G9, PT9, "") | PZ9: =IF(47<=$G9, ROUND(PY9*$Q9, 2), "") | QA9: =IF(47<=$G9, $N9, "") | QB9: =IF(47<=$G9, QA9-PZ9, "") | QC9: =IF(47<=$G9, PY9-QB9, "") | QD9: =IF(47<=$G9, ROUND(PV9*$Q9, 2), "") | QE9: =IF(47<=$G9, PV9+QD9, "") | QF9: =IF(47<=$G9, PZ9+QD9, "") | QG9: =IF(47<=$G9, ($G9-47)*$N9, "") | QH9: =IF(48<=$G9, QC9, "") | QI9: =IF(48<=$G9, ROUND(QH9*$Q9, 2), "") | QJ9: =IF(48<=$G9, $N9, "") | QK9: =IF(48<=$G9, QJ9-QI9, "") | QL9: =IF(48<=$G9, QH9-QK9, "") | QM9: =IF(48<=$G9, ROUND(QE9*$Q9, 2), "") | QN9: =IF(48<=$G9, QE9+QM9, "") | QO9: =IF(48<=$G9, QI9+QM9, "") | QP9: =IF(48<=$G9, ($G9-48)*$N9, "")
A10: 0519-0005 | B10: Tequilas el Mexicano S.A. de C.V. | C10: Attitude Sport | D10: ACTIVO | E10: 2025-07-14 | F10: 2029-07-14 | G10: 48 | H10: 352500 | I10: 0.1 | J10: =ROUND(H10*I10, 2) | K10: =ROUND(H10-J10, 2) | L10: 0 | M10: =ROUND(H10*L10, 2) | N10: 11483.47 | O10: 0.1 | P10: =ROUND(H10*O10, 2) | Q10: 0.02691789 | R10: =RATE(G10, -N10, K10, -P10) | S10: =ROUND(Q10*12, 8) | T10: =ROUND(((1+Q10)^12)-1, 8) | U10: =ROUND(PV(Q10, G10, 0, -P10), 2) | V10: =SUMIF($AA$4:$QP$4, "Interes_Leasing", AA10:QP10) | W10: =SUMIF($AA$4:$QP$4, "Interes_Residual", AA10:QP10) | X10: =ROUND(V10+W10, 2) | Y10: =ROUND((N10*G10+P10+M10)-K10, 2) | Z10: =ROUND(Y10/K10, 4) | AA10: =IF(1<=$G10, $K10, "") | AB10: =IF(1<=$G10, ROUND(AA10*$Q10, 2), "") | AC10: =IF(1<=$G10, $N10, "") | AD10: =IF(1<=$G10, AC10-AB10, "") | AE10: =IF(1<=$G10, AA10-AD10, "") | AF10: =IF(1<=$G10, ROUND($U10*$Q10, 2), "") | AG10: =IF(1<=$G10, $U10+AF10, "") | AH10: =IF(1<=$G10, AB10+AF10, "") | AI10: =IF(1<=$G10, ($G10-1)*$N10, "") | AJ10: =IF(2<=$G10, AE10, "") | AK10: =IF(2<=$G10, ROUND(AJ10*$Q10, 2), "") | AL10: =IF(2<=$G10, $N10, "") | AM10: =IF(2<=$G10, AL10-AK10, "") | AN10: =IF(2<=$G10, AJ10-AM10, "") | AO10: =IF(2<=$G10, ROUND(AG10*$Q10, 2), "") | AP10: =IF(2<=$G10, AG10+AO10, "") | AQ10: =IF(2<=$G10, AK10+AO10, "") | AR10: =IF(2<=$G10, ($G10-2)*$N10, "") | AS10: =IF(3<=$G10, AN10, "") | AT10: =IF(3<=$G10, ROUND(AS10*$Q10, 2), "") | AU10: =IF(3<=$G10, $N10, "") | AV10: =IF(3<=$G10, AU10-AT10, "") | AW10: =IF(3<=$G10, AS10-AV10, "") | AX10: =IF(3<=$G10, ROUND(AP10*$Q10, 2), "") | AY10: =IF(3<=$G10, AP10+AX10, "") | AZ10: =IF(3<=$G10, AT10+AX10, "") | BA10: =IF(3<=$G10, ($G10-3)*$N10, "") | BB10: =IF(4<=$G10, AW10, "") | BC10: =IF(4<=$G10, ROUND(BB10*$Q10, 2), "") | BD10: =IF(4<=$G10, $N10, "") | BE10: =IF(4<=$G10, BD10-BC10, "") | BF10: =IF(4<=$G10, BB10-BE10, "") | BG10: =IF(4<=$G10, ROUND(AY10*$Q10, 2), "") | BH10: =IF(4<=$G10, AY10+BG10, "") | BI10: =IF(4<=$G10, BC10+BG10, "") | BJ10: =IF(4<=$G10, ($G10-4)*$N10, "") | BK10: =IF(5<=$G10, BF10, "") | BL10: =IF(5<=$G10, ROUND(BK10*$Q10, 2), "") | BM10: =IF(5<=$G10, $N10, "") | BN10: =IF(5<=$G10, BM10-BL10, "") | BO10: =IF(5<=$G10, BK10-BN10, "") | BP10: =IF(5<=$G10, ROUND(BH10*$Q10, 2), "") | BQ10: =IF(5<=$G10, BH10+BP10, "") | BR10: =IF(5<=$G10, BL10+BP10, "") | BS10: =IF(5<=$G10, ($G10-5)*$N10, "") | BT10: =IF(6<=$G10, BO10, "") | BU10: =IF(6<=$G10, ROUND(BT10*$Q10, 2), "") | BV10: =IF(6<=$G10, $N10, "") | BW10: =IF(6<=$G10, BV10-BU10, "") | BX10: =IF(6<=$G10, BT10-BW10, "") | BY10: =IF(6<=$G10, ROUND(BQ10*$Q10, 2), "") | BZ10: =IF(6<=$G10, BQ10+BY10, "") | CA10: =IF(6<=$G10, BU10+BY10, "") | CB10: =IF(6<=$G10, ($G10-6)*$N10, "") | CC10: =IF(7<=$G10, BX10, "") | CD10: =IF(7<=$G10, ROUND(CC10*$Q10, 2), "") | CE10: =IF(7<=$G10, $N10, "") | CF10: =IF(7<=$G10, CE10-CD10, "") | CG10: =IF(7<=$G10, CC10-CF10, "") | CH10: =IF(7<=$G10, ROUND(BZ10*$Q10, 2), "") | CI10: =IF(7<=$G10, BZ10+CH10, "") | CJ10: =IF(7<=$G10, CD10+CH10, "") | CK10: =IF(7<=$G10, ($G10-7)*$N10, "") | CL10: =IF(8<=$G10, CG10, "") | CM10: =IF(8<=$G10, ROUND(CL10*$Q10, 2), "") | CN10: =IF(8<=$G10, $N10, "") | CO10: =IF(8<=$G10, CN10-CM10, "") | CP10: =IF(8<=$G10, CL10-CO10, "") | CQ10: =IF(8<=$G10, ROUND(CI10*$Q10, 2), "") | CR10: =IF(8<=$G10, CI10+CQ10, "") | CS10: =IF(8<=$G10, CM10+CQ10, "") | CT10: =IF(8<=$G10, ($G10-8)*$N10, "") | CU10: =IF(9<=$G10, CP10, "") | CV10: =IF(9<=$G10, ROUND(CU10*$Q10, 2), "") | CW10: =IF(9<=$G10, $N10, "") | CX10: =IF(9<=$G10, CW10-CV10, "") | CY10: =IF(9<=$G10, CU10-CX10, "") | CZ10: =IF(9<=$G10, ROUND(CR10*$Q10, 2), "") | DA10: =IF(9<=$G10, CR10+CZ10, "") | DB10: =IF(9<=$G10, CV10+CZ10, "") | DC10: =IF(9<=$G10, ($G10-9)*$N10, "") | DD10: =IF(10<=$G10, CY10, "") | DE10: =IF(10<=$G10, ROUND(DD10*$Q10, 2), "") | DF10: =IF(10<=$G10, $N10, "") | DG10: =IF(10<=$G10, DF10-DE10, "") | DH10: =IF(10<=$G10, DD10-DG10, "") | DI10: =IF(10<=$G10, ROUND(DA10*$Q10, 2), "") | DJ10: =IF(10<=$G10, DA10+DI10, "") | DK10: =IF(10<=$G10, DE10+DI10, "") | DL10: =IF(10<=$G10, ($G10-10)*$N10, "") | DM10: =IF(11<=$G10, DH10, "") | DN10: =IF(11<=$G10, ROUND(DM10*$Q10, 2), "") | DO10: =IF(11<=$G10, $N10, "") | DP10: =IF(11<=$G10, DO10-DN10, "") | DQ10: =IF(11<=$G10, DM10-DP10, "") | DR10: =IF(11<=$G10, ROUND(DJ10*$Q10, 2), "") | DS10: =IF(11<=$G10, DJ10+DR10, "") | DT10: =IF(11<=$G10, DN10+DR10, "") | DU10: =IF(11<=$G10, ($G10-11)*$N10, "") | DV10: =IF(12<=$G10, DQ10, "") | DW10: =IF(12<=$G10, ROUND(DV10*$Q10, 2), "") | DX10: =IF(12<=$G10, $N10, "") | DY10: =IF(12<=$G10, DX10-DW10, "") | DZ10: =IF(12<=$G10, DV10-DY10, "") | EA10: =IF(12<=$G10, ROUND(DS10*$Q10, 2), "") | EB10: =IF(12<=$G10, DS10+EA10, "") | EC10: =IF(12<=$G10, DW10+EA10, "") | ED10: =IF(12<=$G10, ($G10-12)*$N10, "") | EE10: =IF(13<=$G10, DZ10, "") | EF10: =IF(13<=$G10, ROUND(EE10*$Q10, 2), "") | EG10: =IF(13<=$G10, $N10, "") | EH10: =IF(13<=$G10, EG10-EF10, "") | EI10: =IF(13<=$G10, EE10-EH10, "") | EJ10: =IF(13<=$G10, ROUND(EB10*$Q10, 2), "") | EK10: =IF(13<=$G10, EB10+EJ10, "") | EL10: =IF(13<=$G10, EF10+EJ10, "") | EM10: =IF(13<=$G10, ($G10-13)*$N10, "") | EN10: =IF(14<=$G10, EI10, "") | EO10: =IF(14<=$G10, ROUND(EN10*$Q10, 2), "") | EP10: =IF(14<=$G10, $N10, "") | EQ10: =IF(14<=$G10, EP10-EO10, "") | ER10: =IF(14<=$G10, EN10-EQ10, "") | ES10: =IF(14<=$G10, ROUND(EK10*$Q10, 2), "") | ET10: =IF(14<=$G10, EK10+ES10, "") | EU10: =IF(14<=$G10, EO10+ES10, "") | EV10: =IF(14<=$G10, ($G10-14)*$N10, "") | EW10: =IF(15<=$G10, ER10, "") | EX10: =IF(15<=$G10, ROUND(EW10*$Q10, 2), "") | EY10: =IF(15<=$G10, $N10, "") | EZ10: =IF(15<=$G10, EY10-EX10, "") | FA10: =IF(15<=$G10, EW10-EZ10, "") | FB10: =IF(15<=$G10, ROUND(ET10*$Q10, 2), "") | FC10: =IF(15<=$G10, ET10+FB10, "") | FD10: =IF(15<=$G10, EX10+FB10, "") | FE10: =IF(15<=$G10, ($G10-15)*$N10, "") | FF10: =IF(16<=$G10, FA10, "") | FG10: =IF(16<=$G10, ROUND(FF10*$Q10, 2), "") | FH10: =IF(16<=$G10, $N10, "") | FI10: =IF(16<=$G10, FH10-FG10, "") | FJ10: =IF(16<=$G10, FF10-FI10, "") | FK10: =IF(16<=$G10, ROUND(FC10*$Q10, 2), "") | FL10: =IF(16<=$G10, FC10+FK10, "") | FM10: =IF(16<=$G10, FG10+FK10, "") | FN10: =IF(16<=$G10, ($G10-16)*$N10, "") | FO10: =IF(17<=$G10, FJ10, "") | FP10: =IF(17<=$G10, ROUND(FO10*$Q10, 2), "") | FQ10: =IF(17<=$G10, $N10, "") | FR10: =IF(17<=$G10, FQ10-FP10, "") | FS10: =IF(17<=$G10, FO10-FR10, "") | FT10: =IF(17<=$G10, ROUND(FL10*$Q10, 2), "") | FU10: =IF(17<=$G10, FL10+FT10, "") | FV10: =IF(17<=$G10, FP10+FT10, "") | FW10: =IF(17<=$G10, ($G10-17)*$N10, "") | FX10: =IF(18<=$G10, FS10, "") | FY10: =IF(18<=$G10, ROUND(FX10*$Q10, 2), "") | FZ10: =IF(18<=$G10, $N10, "") | GA10: =IF(18<=$G10, FZ10-FY10, "") | GB10: =IF(18<=$G10, FX10-GA10, "") | GC10: =IF(18<=$G10, ROUND(FU10*$Q10, 2), "") | GD10: =IF(18<=$G10, FU10+GC10, "") | GE10: =IF(18<=$G10, FY10+GC10, "") | GF10: =IF(18<=$G10, ($G10-18)*$N10, "") | GG10: =IF(19<=$G10, GB10, "") | GH10: =IF(19<=$G10, ROUND(GG10*$Q10, 2), "") | GI10: =IF(19<=$G10, $N10, "") | GJ10: =IF(19<=$G10, GI10-GH10, "") | GK10: =IF(19<=$G10, GG10-GJ10, "") | GL10: =IF(19<=$G10, ROUND(GD10*$Q10, 2), "") | GM10: =IF(19<=$G10, GD10+GL10, "") | GN10: =IF(19<=$G10, GH10+GL10, "") | GO10: =IF(19<=$G10, ($G10-19)*$N10, "") | GP10: =IF(20<=$G10, GK10, "") | GQ10: =IF(20<=$G10, ROUND(GP10*$Q10, 2), "") | GR10: =IF(20<=$G10, $N10, "") | GS10: =IF(20<=$G10, GR10-GQ10, "") | GT10: =IF(20<=$G10, GP10-GS10, "") | GU10: =IF(20<=$G10, ROUND(GM10*$Q10, 2), "") | GV10: =IF(20<=$G10, GM10+GU10, "") | GW10: =IF(20<=$G10, GQ10+GU10, "") | GX10: =IF(20<=$G10, ($G10-20)*$N10, "") | GY10: =IF(21<=$G10, GT10, "") | GZ10: =IF(21<=$G10, ROUND(GY10*$Q10, 2), "") | HA10: =IF(21<=$G10, $N10, "") | HB10: =IF(21<=$G10, HA10-GZ10, "") | HC10: =IF(21<=$G10, GY10-HB10, "") | HD10: =IF(21<=$G10, ROUND(GV10*$Q10, 2), "") | HE10: =IF(21<=$G10, GV10+HD10, "") | HF10: =IF(21<=$G10, GZ10+HD10, "") | HG10: =IF(21<=$G10, ($G10-21)*$N10, "") | HH10: =IF(22<=$G10, HC10, "") | HI10: =IF(22<=$G10, ROUND(HH10*$Q10, 2), "") | HJ10: =IF(22<=$G10, $N10, "") | HK10: =IF(22<=$G10, HJ10-HI10, "") | HL10: =IF(22<=$G10, HH10-HK10, "") | HM10: =IF(22<=$G10, ROUND(HE10*$Q10, 2), "") | HN10: =IF(22<=$G10, HE10+HM10, "") | HO10: =IF(22<=$G10, HI10+HM10, "") | HP10: =IF(22<=$G10, ($G10-22)*$N10, "") | HQ10: =IF(23<=$G10, HL10, "") | HR10: =IF(23<=$G10, ROUND(HQ10*$Q10, 2), "") | HS10: =IF(23<=$G10, $N10, "") | HT10: =IF(23<=$G10, HS10-HR10, "") | HU10: =IF(23<=$G10, HQ10-HT10, "") | HV10: =IF(23<=$G10, ROUND(HN10*$Q10, 2), "") | HW10: =IF(23<=$G10, HN10+HV10, "") | HX10: =IF(23<=$G10, HR10+HV10, "") | HY10: =IF(23<=$G10, ($G10-23)*$N10, "") | HZ10: =IF(24<=$G10, HU10, "") | IA10: =IF(24<=$G10, ROUND(HZ10*$Q10, 2), "") | IB10: =IF(24<=$G10, $N10, "") | IC10: =IF(24<=$G10, IB10-IA10, "") | ID10: =IF(24<=$G10, HZ10-IC10, "") | IE10: =IF(24<=$G10, ROUND(HW10*$Q10, 2), "") | IF10: =IF(24<=$G10, HW10+IE10, "") | IG10: =IF(24<=$G10, IA10+IE10, "") | IH10: =IF(24<=$G10, ($G10-24)*$N10, "") | II10: =IF(25<=$G10, ID10, "") | IJ10: =IF(25<=$G10, ROUND(II10*$Q10, 2), "") | IK10: =IF(25<=$G10, $N10, "") | IL10: =IF(25<=$G10, IK10-IJ10, "") | IM10: =IF(25<=$G10, II10-IL10, "") | IN10: =IF(25<=$G10, ROUND(IF10*$Q10, 2), "") | IO10: =IF(25<=$G10, IF10+IN10, "") | IP10: =IF(25<=$G10, IJ10+IN10, "") | IQ10: =IF(25<=$G10, ($G10-25)*$N10, "") | IR10: =IF(26<=$G10, IM10, "") | IS10: =IF(26<=$G10, ROUND(IR10*$Q10, 2), "") | IT10: =IF(26<=$G10, $N10, "") | IU10: =IF(26<=$G10, IT10-IS10, "") | IV10: =IF(26<=$G10, IR10-IU10, "") | IW10: =IF(26<=$G10, ROUND(IO10*$Q10, 2), "") | IX10: =IF(26<=$G10, IO10+IW10, "") | IY10: =IF(26<=$G10, IS10+IW10, "") | IZ10: =IF(26<=$G10, ($G10-26)*$N10, "") | JA10: =IF(27<=$G10, IV10, "") | JB10: =IF(27<=$G10, ROUND(JA10*$Q10, 2), "") | JC10: =IF(27<=$G10, $N10, "") | JD10: =IF(27<=$G10, JC10-JB10, "") | JE10: =IF(27<=$G10, JA10-JD10, "") | JF10: =IF(27<=$G10, ROUND(IX10*$Q10, 2), "") | JG10: =IF(27<=$G10, IX10+JF10, "") | JH10: =IF(27<=$G10, JB10+JF10, "") | JI10: =IF(27<=$G10, ($G10-27)*$N10, "") | JJ10: =IF(28<=$G10, JE10, "") | JK10: =IF(28<=$G10, ROUND(JJ10*$Q10, 2), "") | JL10: =IF(28<=$G10, $N10, "") | JM10: =IF(28<=$G10, JL10-JK10, "") | JN10: =IF(28<=$G10, JJ10-JM10, "") | JO10: =IF(28<=$G10, ROUND(JG10*$Q10, 2), "") | JP10: =IF(28<=$G10, JG10+JO10, "") | JQ10: =IF(28<=$G10, JK10+JO10, "") | JR10: =IF(28<=$G10, ($G10-28)*$N10, "") | JS10: =IF(29<=$G10, JN10, "") | JT10: =IF(29<=$G10, ROUND(JS10*$Q10, 2), "") | JU10: =IF(29<=$G10, $N10, "") | JV10: =IF(29<=$G10, JU10-JT10, "") | JW10: =IF(29<=$G10, JS10-JV10, "") | JX10: =IF(29<=$G10, ROUND(JP10*$Q10, 2), "") | JY10: =IF(29<=$G10, JP10+JX10, "") | JZ10: =IF(29<=$G10, JT10+JX10, "") | KA10: =IF(29<=$G10, ($G10-29)*$N10, "") | KB10: =IF(30<=$G10, JW10, "") | KC10: =IF(30<=$G10, ROUND(KB10*$Q10, 2), "") | KD10: =IF(30<=$G10, $N10, "") | KE10: =IF(30<=$G10, KD10-KC10, "") | KF10: =IF(30<=$G10, KB10-KE10, "") | KG10: =IF(30<=$G10, ROUND(JY10*$Q10, 2), "") | KH10: =IF(30<=$G10, JY10+KG10, "") | KI10: =IF(30<=$G10, KC10+KG10, "") | KJ10: =IF(30<=$G10, ($G10-30)*$N10, "") | KK10: =IF(31<=$G10, KF10, "") | KL10: =IF(31<=$G10, ROUND(KK10*$Q10, 2), "") | KM10: =IF(31<=$G10, $N10, "") | KN10: =IF(31<=$G10, KM10-KL10, "") | KO10: =IF(31<=$G10, KK10-KN10, "") | KP10: =IF(31<=$G10, ROUND(KH10*$Q10, 2), "") | KQ10: =IF(31<=$G10, KH10+KP10, "") | KR10: =IF(31<=$G10, KL10+KP10, "") | KS10: =IF(31<=$G10, ($G10-31)*$N10, "") | KT10: =IF(32<=$G10, KO10, "") | KU10: =IF(32<=$G10, ROUND(KT10*$Q10, 2), "") | KV10: =IF(32<=$G10, $N10, "") | KW10: =IF(32<=$G10, KV10-KU10, "") | KX10: =IF(32<=$G10, KT10-KW10, "") | KY10: =IF(32<=$G10, ROUND(KQ10*$Q10, 2), "") | KZ10: =IF(32<=$G10, KQ10+KY10, "") | LA10: =IF(32<=$G10, KU10+KY10, "") | LB10: =IF(32<=$G10, ($G10-32)*$N10, "") | LC10: =IF(33<=$G10, KX10, "") | LD10: =IF(33<=$G10, ROUND(LC10*$Q10, 2), "") | LE10: =IF(33<=$G10, $N10, "") | LF10: =IF(33<=$G10, LE10-LD10, "") | LG10: =IF(33<=$G10, LC10-LF10, "") | LH10: =IF(33<=$G10, ROUND(KZ10*$Q10, 2), "") | LI10: =IF(33<=$G10, KZ10+LH10, "") | LJ10: =IF(33<=$G10, LD10+LH10, "") | LK10: =IF(33<=$G10, ($G10-33)*$N10, "") | LL10: =IF(34<=$G10, LG10, "") | LM10: =IF(34<=$G10, ROUND(LL10*$Q10, 2), "") | LN10: =IF(34<=$G10, $N10, "") | LO10: =IF(34<=$G10, LN10-LM10, "") | LP10: =IF(34<=$G10, LL10-LO10, "") | LQ10: =IF(34<=$G10, ROUND(LI10*$Q10, 2), "") | LR10: =IF(34<=$G10, LI10+LQ10, "") | LS10: =IF(34<=$G10, LM10+LQ10, "") | LT10: =IF(34<=$G10, ($G10-34)*$N10, "") | LU10: =IF(35<=$G10, LP10, "") | LV10: =IF(35<=$G10, ROUND(LU10*$Q10, 2), "") | LW10: =IF(35<=$G10, $N10, "") | LX10: =IF(35<=$G10, LW10-LV10, "") | LY10: =IF(35<=$G10, LU10-LX10, "") | LZ10: =IF(35<=$G10, ROUND(LR10*$Q10, 2), "") | MA10: =IF(35<=$G10, LR10+LZ10, "") | MB10: =IF(35<=$G10, LV10+LZ10, "") | MC10: =IF(35<=$G10, ($G10-35)*$N10, "") | MD10: =IF(36<=$G10, LY10, "") | ME10: =IF(36<=$G10, ROUND(MD10*$Q10, 2), "") | MF10: =IF(36<=$G10, $N10, "") | MG10: =IF(36<=$G10, MF10-ME10, "") | MH10: =IF(36<=$G10, MD10-MG10, "") | MI10: =IF(36<=$G10, ROUND(MA10*$Q10, 2), "") | MJ10: =IF(36<=$G10, MA10+MI10, "") | MK10: =IF(36<=$G10, ME10+MI10, "") | ML10: =IF(36<=$G10, ($G10-36)*$N10, "") | MM10: =IF(37<=$G10, MH10, "") | MN10: =IF(37<=$G10, ROUND(MM10*$Q10, 2), "") | MO10: =IF(37<=$G10, $N10, "") | MP10: =IF(37<=$G10, MO10-MN10, "") | MQ10: =IF(37<=$G10, MM10-MP10, "") | MR10: =IF(37<=$G10, ROUND(MJ10*$Q10, 2), "") | MS10: =IF(37<=$G10, MJ10+MR10, "") | MT10: =IF(37<=$G10, MN10+MR10, "") | MU10: =IF(37<=$G10, ($G10-37)*$N10, "") | MV10: =IF(38<=$G10, MQ10, "") | MW10: =IF(38<=$G10, ROUND(MV10*$Q10, 2), "") | MX10: =IF(38<=$G10, $N10, "") | MY10: =IF(38<=$G10, MX10-MW10, "") | MZ10: =IF(38<=$G10, MV10-MY10, "") | NA10: =IF(38<=$G10, ROUND(MS10*$Q10, 2), "") | NB10: =IF(38<=$G10, MS10+NA10, "") | NC10: =IF(38<=$G10, MW10+NA10, "") | ND10: =IF(38<=$G10, ($G10-38)*$N10, "") | NE10: =IF(39<=$G10, MZ10, "") | NF10: =IF(39<=$G10, ROUND(NE10*$Q10, 2), "") | NG10: =IF(39<=$G10, $N10, "") | NH10: =IF(39<=$G10, NG10-NF10, "") | NI10: =IF(39<=$G10, NE10-NH10, "") | NJ10: =IF(39<=$G10, ROUND(NB10*$Q10, 2), "") | NK10: =IF(39<=$G10, NB10+NJ10, "") | NL10: =IF(39<=$G10, NF10+NJ10, "") | NM10: =IF(39<=$G10, ($G10-39)*$N10, "") | NN10: =IF(40<=$G10, NI10, "") | NO10: =IF(40<=$G10, ROUND(NN10*$Q10, 2), "") | NP10: =IF(40<=$G10, $N10, "") | NQ10: =IF(40<=$G10, NP10-NO10, "") | NR10: =IF(40<=$G10, NN10-NQ10, "") | NS10: =IF(40<=$G10, ROUND(NK10*$Q10, 2), "") | NT10: =IF(40<=$G10, NK10+NS10, "") | NU10: =IF(40<=$G10, NO10+NS10, "") | NV10: =IF(40<=$G10, ($G10-40)*$N10, "") | NW10: =IF(41<=$G10, NR10, "") | NX10: =IF(41<=$G10, ROUND(NW10*$Q10, 2), "") | NY10: =IF(41<=$G10, $N10, "") | NZ10: =IF(41<=$G10, NY10-NX10, "") | OA10: =IF(41<=$G10, NW10-NZ10, "") | OB10: =IF(41<=$G10, ROUND(NT10*$Q10, 2), "") | OC10: =IF(41<=$G10, NT10+OB10, "") | OD10: =IF(41<=$G10, NX10+OB10, "") | OE10: =IF(41<=$G10, ($G10-41)*$N10, "") | OF10: =IF(42<=$G10, OA10, "") | OG10: =IF(42<=$G10, ROUND(OF10*$Q10, 2), "") | OH10: =IF(42<=$G10, $N10, "") | OI10: =IF(42<=$G10, OH10-OG10, "") | OJ10: =IF(42<=$G10, OF10-OI10, "") | OK10: =IF(42<=$G10, ROUND(OC10*$Q10, 2), "") | OL10: =IF(42<=$G10, OC10+OK10, "") | OM10: =IF(42<=$G10, OG10+OK10, "") | ON10: =IF(42<=$G10, ($G10-42)*$N10, "") | OO10: =IF(43<=$G10, OJ10, "") | OP10: =IF(43<=$G10, ROUND(OO10*$Q10, 2), "") | OQ10: =IF(43<=$G10, $N10, "") | OR10: =IF(43<=$G10, OQ10-OP10, "") | OS10: =IF(43<=$G10, OO10-OR10, "") | OT10: =IF(43<=$G10, ROUND(OL10*$Q10, 2), "") | OU10: =IF(43<=$G10, OL10+OT10, "") | OV10: =IF(43<=$G10, OP10+OT10, "") | OW10: =IF(43<=$G10, ($G10-43)*$N10, "") | OX10: =IF(44<=$G10, OS10, "") | OY10: =IF(44<=$G10, ROUND(OX10*$Q10, 2), "") | OZ10: =IF(44<=$G10, $N10, "") | PA10: =IF(44<=$G10, OZ10-OY10, "") | PB10: =IF(44<=$G10, OX10-PA10, "") | PC10: =IF(44<=$G10, ROUND(OU10*$Q10, 2), "") | PD10: =IF(44<=$G10, OU10+PC10, "") | PE10: =IF(44<=$G10, OY10+PC10, "") | PF10: =IF(44<=$G10, ($G10-44)*$N10, "") | PG10: =IF(45<=$G10, PB10, "") | PH10: =IF(45<=$G10, ROUND(PG10*$Q10, 2), "") | PI10: =IF(45<=$G10, $N10, "") | PJ10: =IF(45<=$G10, PI10-PH10, "") | PK10: =IF(45<=$G10, PG10-PJ10, "") | PL10: =IF(45<=$G10, ROUND(PD10*$Q10, 2), "") | PM10: =IF(45<=$G10, PD10+PL10, "") | PN10: =IF(45<=$G10, PH10+PL10, "") | PO10: =IF(45<=$G10, ($G10-45)*$N10, "") | PP10: =IF(46<=$G10, PK10, "") | PQ10: =IF(46<=$G10, ROUND(PP10*$Q10, 2), "") | PR10: =IF(46<=$G10, $N10, "") | PS10: =IF(46<=$G10, PR10-PQ10, "") | PT10: =IF(46<=$G10, PP10-PS10, "") | PU10: =IF(46<=$G10, ROUND(PM10*$Q10, 2), "") | PV10: =IF(46<=$G10, PM10+PU10, "") | PW10: =IF(46<=$G10, PQ10+PU10, "") | PX10: =IF(46<=$G10, ($G10-46)*$N10, "") | PY10: =IF(47<=$G10, PT10, "") | PZ10: =IF(47<=$G10, ROUND(PY10*$Q10, 2), "") | QA10: =IF(47<=$G10, $N10, "") | QB10: =IF(47<=$G10, QA10-PZ10, "") | QC10: =IF(47<=$G10, PY10-QB10, "") | QD10: =IF(47<=$G10, ROUND(PV10*$Q10, 2), "") | QE10: =IF(47<=$G10, PV10+QD10, "") | QF10: =IF(47<=$G10, PZ10+QD10, "") | QG10: =IF(47<=$G10, ($G10-47)*$N10, "") | QH10: =IF(48<=$G10, QC10, "") | QI10: =IF(48<=$G10, ROUND(QH10*$Q10, 2), "") | QJ10: =IF(48<=$G10, $N10, "") | QK10: =IF(48<=$G10, QJ10-QI10, "") | QL10: =IF(48<=$G10, QH10-QK10, "") | QM10: =IF(48<=$G10, ROUND(QE10*$Q10, 2), "") | QN10: =IF(48<=$G10, QE10+QM10, "") | QO10: =IF(48<=$G10, QI10+QM10, "") | QP10: =IF(48<=$G10, ($G10-48)*$N10, "")
A11: 0520-0003 | B11: Tractomotriz Diesel Leal, S.A. de C.V. | C11: Montero Sport | D11: ACTIVO | E11: 2025-11-28 | F11: 2028-11-28 | G11: 36 | H11: 621465.52 | I11: 0.4 | J11: =ROUND(H11*I11, 2) | K11: =ROUND(H11-J11, 2) | L11: 1 | M11: =ROUND(H11*L11, 2) | N11: 15182.88 | O11: 0.1 | P11: =ROUND(H11*O11, 2) | Q11: 0.02663641 | R11: =RATE(G11, -N11, K11, -P11) | S11: =ROUND(Q11*12, 8) | T11: =ROUND(((1+Q11)^12)-1, 8) | U11: =ROUND(PV(Q11, G11, 0, -P11), 2) | V11: =SUMIF($AA$4:$QP$4, "Interes_Leasing", AA11:QP11) | W11: =SUMIF($AA$4:$QP$4, "Interes_Residual", AA11:QP11) | X11: =ROUND(V11+W11, 2) | Y11: =ROUND((N11*G11+P11+M11)-K11, 2) | Z11: =ROUND(Y11/K11, 4) | AA11: =IF(1<=$G11, $K11, "") | AB11: =IF(1<=$G11, ROUND(AA11*$Q11, 2), "") | AC11: =IF(1<=$G11, $N11, "") | AD11: =IF(1<=$G11, AC11-AB11, "") | AE11: =IF(1<=$G11, AA11-AD11, "") | AF11: =IF(1<=$G11, ROUND($U11*$Q11, 2), "") | AG11: =IF(1<=$G11, $U11+AF11, "") | AH11: =IF(1<=$G11, AB11+AF11, "") | AI11: =IF(1<=$G11, ($G11-1)*$N11, "") | AJ11: =IF(2<=$G11, AE11, "") | AK11: =IF(2<=$G11, ROUND(AJ11*$Q11, 2), "") | AL11: =IF(2<=$G11, $N11, "") | AM11: =IF(2<=$G11, AL11-AK11, "") | AN11: =IF(2<=$G11, AJ11-AM11, "") | AO11: =IF(2<=$G11, ROUND(AG11*$Q11, 2), "") | AP11: =IF(2<=$G11, AG11+AO11, "") | AQ11: =IF(2<=$G11, AK11+AO11, "") | AR11: =IF(2<=$G11, ($G11-2)*$N11, "") | AS11: =IF(3<=$G11, AN11, "") | AT11: =IF(3<=$G11, ROUND(AS11*$Q11, 2), "") | AU11: =IF(3<=$G11, $N11, "") | AV11: =IF(3<=$G11, AU11-AT11, "") | AW11: =IF(3<=$G11, AS11-AV11, "") | AX11: =IF(3<=$G11, ROUND(AP11*$Q11, 2), "") | AY11: =IF(3<=$G11, AP11+AX11, "") | AZ11: =IF(3<=$G11, AT11+AX11, "") | BA11: =IF(3<=$G11, ($G11-3)*$N11, "") | BB11: =IF(4<=$G11, AW11, "") | BC11: =IF(4<=$G11, ROUND(BB11*$Q11, 2), "") | BD11: =IF(4<=$G11, $N11, "") | BE11: =IF(4<=$G11, BD11-BC11, "") | BF11: =IF(4<=$G11, BB11-BE11, "") | BG11: =IF(4<=$G11, ROUND(AY11*$Q11, 2), "") | BH11: =IF(4<=$G11, AY11+BG11, "") | BI11: =IF(4<=$G11, BC11+BG11, "") | BJ11: =IF(4<=$G11, ($G11-4)*$N11, "") | BK11: =IF(5<=$G11, BF11, "") | BL11: =IF(5<=$G11, ROUND(BK11*$Q11, 2), "") | BM11: =IF(5<=$G11, $N11, "") | BN11: =IF(5<=$G11, BM11-BL11, "") | BO11: =IF(5<=$G11, BK11-BN11, "") | BP11: =IF(5<=$G11, ROUND(BH11*$Q11, 2), "") | BQ11: =IF(5<=$G11, BH11+BP11, "") | BR11: =IF(5<=$G11, BL11+BP11, "") | BS11: =IF(5<=$G11, ($G11-5)*$N11, "") | BT11: =IF(6<=$G11, BO11, "") | BU11: =IF(6<=$G11, ROUND(BT11*$Q11, 2), "") | BV11: =IF(6<=$G11, $N11, "") | BW11: =IF(6<=$G11, BV11-BU11, "") | BX11: =IF(6<=$G11, BT11-BW11, "") | BY11: =IF(6<=$G11, ROUND(BQ11*$Q11, 2), "") | BZ11: =IF(6<=$G11, BQ11+BY11, "") | CA11: =IF(6<=$G11, BU11+BY11, "") | CB11: =IF(6<=$G11, ($G11-6)*$N11, "") | CC11: =IF(7<=$G11, BX11, "") | CD11: =IF(7<=$G11, ROUND(CC11*$Q11, 2), "") | CE11: =IF(7<=$G11, $N11, "") | CF11: =IF(7<=$G11, CE11-CD11, "") | CG11: =IF(7<=$G11, CC11-CF11, "") | CH11: =IF(7<=$G11, ROUND(BZ11*$Q11, 2), "") | CI11: =IF(7<=$G11, BZ11+CH11, "") | CJ11: =IF(7<=$G11, CD11+CH11, "") | CK11: =IF(7<=$G11, ($G11-7)*$N11, "") | CL11: =IF(8<=$G11, CG11, "") | CM11: =IF(8<=$G11, ROUND(CL11*$Q11, 2), "") | CN11: =IF(8<=$G11, $N11, "") | CO11: =IF(8<=$G11, CN11-CM11, "") | CP11: =IF(8<=$G11, CL11-CO11, "") | CQ11: =IF(8<=$G11, ROUND(CI11*$Q11, 2), "") | CR11: =IF(8<=$G11, CI11+CQ11, "") | CS11: =IF(8<=$G11, CM11+CQ11, "") | CT11: =IF(8<=$G11, ($G11-8)*$N11, "") | CU11: =IF(9<=$G11, CP11, "") | CV11: =IF(9<=$G11, ROUND(CU11*$Q11, 2), "") | CW11: =IF(9<=$G11, $N11, "") | CX11: =IF(9<=$G11, CW11-CV11, "") | CY11: =IF(9<=$G11, CU11-CX11, "") | CZ11: =IF(9<=$G11, ROUND(CR11*$Q11, 2), "") | DA11: =IF(9<=$G11, CR11+CZ11, "") | DB11: =IF(9<=$G11, CV11+CZ11, "") | DC11: =IF(9<=$G11, ($G11-9)*$N11, "") | DD11: =IF(10<=$G11, CY11, "") | DE11: =IF(10<=$G11, ROUND(DD11*$Q11, 2), "") | DF11: =IF(10<=$G11, $N11, "") | DG11: =IF(10<=$G11, DF11-DE11, "") | DH11: =IF(10<=$G11, DD11-DG11, "") | DI11: =IF(10<=$G11, ROUND(DA11*$Q11, 2), "") | DJ11: =IF(10<=$G11, DA11+DI11, "") | DK11: =IF(10<=$G11, DE11+DI11, "") | DL11: =IF(10<=$G11, ($G11-10)*$N11, "") | DM11: =IF(11<=$G11, DH11, "") | DN11: =IF(11<=$G11, ROUND(DM11*$Q11, 2), "") | DO11: =IF(11<=$G11, $N11, "") | DP11: =IF(11<=$G11, DO11-DN11, "") | DQ11: =IF(11<=$G11, DM11-DP11, "") | DR11: =IF(11<=$G11, ROUND(DJ11*$Q11, 2), "") | DS11: =IF(11<=$G11, DJ11+DR11, "") | DT11: =IF(11<=$G11, DN11+DR11, "") | DU11: =IF(11<=$G11, ($G11-11)*$N11, "") | DV11: =IF(12<=$G11, DQ11, "") | DW11: =IF(12<=$G11, ROUND(DV11*$Q11, 2), "") | DX11: =IF(12<=$G11, $N11, "") | DY11: =IF(12<=$G11, DX11-DW11, "") | DZ11: =IF(12<=$G11, DV11-DY11, "") | EA11: =IF(12<=$G11, ROUND(DS11*$Q11, 2), "") | EB11: =IF(12<=$G11, DS11+EA11, "") | EC11: =IF(12<=$G11, DW11+EA11, "") | ED11: =IF(12<=$G11, ($G11-12)*$N11, "") | EE11: =IF(13<=$G11, DZ11, "") | EF11: =IF(13<=$G11, ROUND(EE11*$Q11, 2), "") | EG11: =IF(13<=$G11, $N11, "") | EH11: =IF(13<=$G11, EG11-EF11, "") | EI11: =IF(13<=$G11, EE11-EH11, "") | EJ11: =IF(13<=$G11, ROUND(EB11*$Q11, 2), "") | EK11: =IF(13<=$G11, EB11+EJ11, "") | EL11: =IF(13<=$G11, EF11+EJ11, "") | EM11: =IF(13<=$G11, ($G11-13)*$N11, "") | EN11: =IF(14<=$G11, EI11, "") | EO11: =IF(14<=$G11, ROUND(EN11*$Q11, 2), "") | EP11: =IF(14<=$G11, $N11, "") | EQ11: =IF(14<=$G11, EP11-EO11, "") | ER11: =IF(14<=$G11, EN11-EQ11, "") | ES11: =IF(14<=$G11, ROUND(EK11*$Q11, 2), "") | ET11: =IF(14<=$G11, EK11+ES11, "") | EU11: =IF(14<=$G11, EO11+ES11, "") | EV11: =IF(14<=$G11, ($G11-14)*$N11, "") | EW11: =IF(15<=$G11, ER11, "") | EX11: =IF(15<=$G11, ROUND(EW11*$Q11, 2), "") | EY11: =IF(15<=$G11, $N11, "") | EZ11: =IF(15<=$G11, EY11-EX11, "") | FA11: =IF(15<=$G11, EW11-EZ11, "") | FB11: =IF(15<=$G11, ROUND(ET11*$Q11, 2), "") | FC11: =IF(15<=$G11, ET11+FB11, "") | FD11: =IF(15<=$G11, EX11+FB11, "") | FE11: =IF(15<=$G11, ($G11-15)*$N11, "") | FF11: =IF(16<=$G11, FA11, "") | FG11: =IF(16<=$G11, ROUND(FF11*$Q11, 2), "") | FH11: =IF(16<=$G11, $N11, "") | FI11: =IF(16<=$G11, FH11-FG11, "") | FJ11: =IF(16<=$G11, FF11-FI11, "") | FK11: =IF(16<=$G11, ROUND(FC11*$Q11, 2), "") | FL11: =IF(16<=$G11, FC11+FK11, "") | FM11: =IF(16<=$G11, FG11+FK11, "") | FN11: =IF(16<=$G11, ($G11-16)*$N11, "") | FO11: =IF(17<=$G11, FJ11, "") | FP11: =IF(17<=$G11, ROUND(FO11*$Q11, 2), "") | FQ11: =IF(17<=$G11, $N11, "") | FR11: =IF(17<=$G11, FQ11-FP11, "") | FS11: =IF(17<=$G11, FO11-FR11, "") | FT11: =IF(17<=$G11, ROUND(FL11*$Q11, 2), "") | FU11: =IF(17<=$G11, FL11+FT11, "") | FV11: =IF(17<=$G11, FP11+FT11, "") | FW11: =IF(17<=$G11, ($G11-17)*$N11, "") | FX11: =IF(18<=$G11, FS11, "") | FY11: =IF(18<=$G11, ROUND(FX11*$Q11, 2), "") | FZ11: =IF(18<=$G11, $N11, "") | GA11: =IF(18<=$G11, FZ11-FY11, "") | GB11: =IF(18<=$G11, FX11-GA11, "") | GC11: =IF(18<=$G11, ROUND(FU11*$Q11, 2), "") | GD11: =IF(18<=$G11, FU11+GC11, "") | GE11: =IF(18<=$G11, FY11+GC11, "") | GF11: =IF(18<=$G11, ($G11-18)*$N11, "") | GG11: =IF(19<=$G11, GB11, "") | GH11: =IF(19<=$G11, ROUND(GG11*$Q11, 2), "") | GI11: =IF(19<=$G11, $N11, "") | GJ11: =IF(19<=$G11, GI11-GH11, "") | GK11: =IF(19<=$G11, GG11-GJ11, "") | GL11: =IF(19<=$G11, ROUND(GD11*$Q11, 2), "") | GM11: =IF(19<=$G11, GD11+GL11, "") | GN11: =IF(19<=$G11, GH11+GL11, "") | GO11: =IF(19<=$G11, ($G11-19)*$N11, "") | GP11: =IF(20<=$G11, GK11, "") | GQ11: =IF(20<=$G11, ROUND(GP11*$Q11, 2), "") | GR11: =IF(20<=$G11, $N11, "") | GS11: =IF(20<=$G11, GR11-GQ11, "") | GT11: =IF(20<=$G11, GP11-GS11, "") | GU11: =IF(20<=$G11, ROUND(GM11*$Q11, 2), "") | GV11: =IF(20<=$G11, GM11+GU11, "") | GW11: =IF(20<=$G11, GQ11+GU11, "") | GX11: =IF(20<=$G11, ($G11-20)*$N11, "") | GY11: =IF(21<=$G11, GT11, "") | GZ11: =IF(21<=$G11, ROUND(GY11*$Q11, 2), "") | HA11: =IF(21<=$G11, $N11, "") | HB11: =IF(21<=$G11, HA11-GZ11, "") | HC11: =IF(21<=$G11, GY11-HB11, "") | HD11: =IF(21<=$G11, ROUND(GV11*$Q11, 2), "") | HE11: =IF(21<=$G11, GV11+HD11, "") | HF11: =IF(21<=$G11, GZ11+HD11, "") | HG11: =IF(21<=$G11, ($G11-21)*$N11, "") | HH11: =IF(22<=$G11, HC11, "") | HI11: =IF(22<=$G11, ROUND(HH11*$Q11, 2), "") | HJ11: =IF(22<=$G11, $N11, "") | HK11: =IF(22<=$G11, HJ11-HI11, "") | HL11: =IF(22<=$G11, HH11-HK11, "") | HM11: =IF(22<=$G11, ROUND(HE11*$Q11, 2), "") | HN11: =IF(22<=$G11, HE11+HM11, "") | HO11: =IF(22<=$G11, HI11+HM11, "") | HP11: =IF(22<=$G11, ($G11-22)*$N11, "") | HQ11: =IF(23<=$G11, HL11, "") | HR11: =IF(23<=$G11, ROUND(HQ11*$Q11, 2), "") | HS11: =IF(23<=$G11, $N11, "") | HT11: =IF(23<=$G11, HS11-HR11, "") | HU11: =IF(23<=$G11, HQ11-HT11, "") | HV11: =IF(23<=$G11, ROUND(HN11*$Q11, 2), "") | HW11: =IF(23<=$G11, HN11+HV11, "") | HX11: =IF(23<=$G11, HR11+HV11, "") | HY11: =IF(23<=$G11, ($G11-23)*$N11, "") | HZ11: =IF(24<=$G11, HU11, "") | IA11: =IF(24<=$G11, ROUND(HZ11*$Q11, 2), "") | IB11: =IF(24<=$G11, $N11, "") | IC11: =IF(24<=$G11, IB11-IA11, "") | ID11: =IF(24<=$G11, HZ11-IC11, "") | IE11: =IF(24<=$G11, ROUND(HW11*$Q11, 2), "") | IF11: =IF(24<=$G11, HW11+IE11, "") | IG11: =IF(24<=$G11, IA11+IE11, "") | IH11: =IF(24<=$G11, ($G11-24)*$N11, "") | II11: =IF(25<=$G11, ID11, "") | IJ11: =IF(25<=$G11, ROUND(II11*$Q11, 2), "") | IK11: =IF(25<=$G11, $N11, "") | IL11: =IF(25<=$G11, IK11-IJ11, "") | IM11: =IF(25<=$G11, II11-IL11, "") | IN11: =IF(25<=$G11, ROUND(IF11*$Q11, 2), "") | IO11: =IF(25<=$G11, IF11+IN11, "") | IP11: =IF(25<=$G11, IJ11+IN11, "") | IQ11: =IF(25<=$G11, ($G11-25)*$N11, "") | IR11: =IF(26<=$G11, IM11, "") | IS11: =IF(26<=$G11, ROUND(IR11*$Q11, 2), "") | IT11: =IF(26<=$G11, $N11, "") | IU11: =IF(26<=$G11, IT11-IS11, "") | IV11: =IF(26<=$G11, IR11-IU11, "") | IW11: =IF(26<=$G11, ROUND(IO11*$Q11, 2), "") | IX11: =IF(26<=$G11, IO11+IW11, "") | IY11: =IF(26<=$G11, IS11+IW11, "") | IZ11: =IF(26<=$G11, ($G11-26)*$N11, "") | JA11: =IF(27<=$G11, IV11, "") | JB11: =IF(27<=$G11, ROUND(JA11*$Q11, 2), "") | JC11: =IF(27<=$G11, $N11, "") | JD11: =IF(27<=$G11, JC11-JB11, "") | JE11: =IF(27<=$G11, JA11-JD11, "") | JF11: =IF(27<=$G11, ROUND(IX11*$Q11, 2), "") | JG11: =IF(27<=$G11, IX11+JF11, "") | JH11: =IF(27<=$G11, JB11+JF11, "") | JI11: =IF(27<=$G11, ($G11-27)*$N11, "") | JJ11: =IF(28<=$G11, JE11, "") | JK11: =IF(28<=$G11, ROUND(JJ11*$Q11, 2), "") | JL11: =IF(28<=$G11, $N11, "") | JM11: =IF(28<=$G11, JL11-JK11, "") | JN11: =IF(28<=$G11, JJ11-JM11, "") | JO11: =IF(28<=$G11, ROUND(JG11*$Q11, 2), "") | JP11: =IF(28<=$G11, JG11+JO11, "") | JQ11: =IF(28<=$G11, JK11+JO11, "") | JR11: =IF(28<=$G11, ($G11-28)*$N11, "") | JS11: =IF(29<=$G11, JN11, "") | JT11: =IF(29<=$G11, ROUND(JS11*$Q11, 2), "") | JU11: =IF(29<=$G11, $N11, "") | JV11: =IF(29<=$G11, JU11-JT11, "") | JW11: =IF(29<=$G11, JS11-JV11, "") | JX11: =IF(29<=$G11, ROUND(JP11*$Q11, 2), "") | JY11: =IF(29<=$G11, JP11+JX11, "") | JZ11: =IF(29<=$G11, JT11+JX11, "") | KA11: =IF(29<=$G11, ($G11-29)*$N11, "") | KB11: =IF(30<=$G11, JW11, "") | KC11: =IF(30<=$G11, ROUND(KB11*$Q11, 2), "") | KD11: =IF(30<=$G11, $N11, "") | KE11: =IF(30<=$G11, KD11-KC11, "") | KF11: =IF(30<=$G11, KB11-KE11, "") | KG11: =IF(30<=$G11, ROUND(JY11*$Q11, 2), "") | KH11: =IF(30<=$G11, JY11+KG11, "") | KI11: =IF(30<=$G11, KC11+KG11, "") | KJ11: =IF(30<=$G11, ($G11-30)*$N11, "") | KK11: =IF(31<=$G11, KF11, "") | KL11: =IF(31<=$G11, ROUND(KK11*$Q11, 2), "") | KM11: =IF(31<=$G11, $N11, "") | KN11: =IF(31<=$G11, KM11-KL11, "") | KO11: =IF(31<=$G11, KK11-KN11, "") | KP11: =IF(31<=$G11, ROUND(KH11*$Q11, 2), "") | KQ11: =IF(31<=$G11, KH11+KP11, "") | KR11: =IF(31<=$G11, KL11+KP11, "") | KS11: =IF(31<=$G11, ($G11-31)*$N11, "") | KT11: =IF(32<=$G11, KO11, "") | KU11: =IF(32<=$G11, ROUND(KT11*$Q11, 2), "") | KV11: =IF(32<=$G11, $N11, "") | KW11: =IF(32<=$G11, KV11-KU11, "") | KX11: =IF(32<=$G11, KT11-KW11, "") | KY11: =IF(32<=$G11, ROUND(KQ11*$Q11, 2), "") | KZ11: =IF(32<=$G11, KQ11+KY11, "") | LA11: =IF(32<=$G11, KU11+KY11, "") | LB11: =IF(32<=$G11, ($G11-32)*$N11, "") | LC11: =IF(33<=$G11, KX11, "") | LD11: =IF(33<=$G11, ROUND(LC11*$Q11, 2), "") | LE11: =IF(33<=$G11, $N11, "") | LF11: =IF(33<=$G11, LE11-LD11, "") | LG11: =IF(33<=$G11, LC11-LF11, "") | LH11: =IF(33<=$G11, ROUND(KZ11*$Q11, 2), "") | LI11: =IF(33<=$G11, KZ11+LH11, "") | LJ11: =IF(33<=$G11, LD11+LH11, "") | LK11: =IF(33<=$G11, ($G11-33)*$N11, "") | LL11: =IF(34<=$G11, LG11, "") | LM11: =IF(34<=$G11, ROUND(LL11*$Q11, 2), "") | LN11: =IF(34<=$G11, $N11, "") | LO11: =IF(34<=$G11, LN11-LM11, "") | LP11: =IF(34<=$G11, LL11-LO11, "") | LQ11: =IF(34<=$G11, ROUND(LI11*$Q11, 2), "") | LR11: =IF(34<=$G11, LI11+LQ11, "") | LS11: =IF(34<=$G11, LM11+LQ11, "") | LT11: =IF(34<=$G11, ($G11-34)*$N11, "") | LU11: =IF(35<=$G11, LP11, "") | LV11: =IF(35<=$G11, ROUND(LU11*$Q11, 2), "") | LW11: =IF(35<=$G11, $N11, "") | LX11: =IF(35<=$G11, LW11-LV11, "") | LY11: =IF(35<=$G11, LU11-LX11, "") | LZ11: =IF(35<=$G11, ROUND(LR11*$Q11, 2), "") | MA11: =IF(35<=$G11, LR11+LZ11, "") | MB11: =IF(35<=$G11, LV11+LZ11, "") | MC11: =IF(35<=$G11, ($G11-35)*$N11, "") | MD11: =IF(36<=$G11, LY11, "") | ME11: =IF(36<=$G11, ROUND(MD11*$Q11, 2), "") | MF11: =IF(36<=$G11, $N11, "") | MG11: =IF(36<=$G11, MF11-ME11, "") | MH11: =IF(36<=$G11, MD11-MG11, "") | MI11: =IF(36<=$G11, ROUND(MA11*$Q11, 2), "") | MJ11: =IF(36<=$G11, MA11+MI11, "") | MK11: =IF(36<=$G11, ME11+MI11, "") | ML11: =IF(36<=$G11, ($G11-36)*$N11, "") | MM11: =IF(37<=$G11, MH11, "") | MN11: =IF(37<=$G11, ROUND(MM11*$Q11, 2), "") | MO11: =IF(37<=$G11, $N11, "") | MP11: =IF(37<=$G11, MO11-MN11, "") | MQ11: =IF(37<=$G11, MM11-MP11, "") | MR11: =IF(37<=$G11, ROUND(MJ11*$Q11, 2), "") | MS11: =IF(37<=$G11, MJ11+MR11, "") | MT11: =IF(37<=$G11, MN11+MR11, "") | MU11: =IF(37<=$G11, ($G11-37)*$N11, "") | MV11: =IF(38<=$G11, MQ11, "") | MW11: =IF(38<=$G11, ROUND(MV11*$Q11, 2), "") | MX11: =IF(38<=$G11, $N11, "") | MY11: =IF(38<=$G11, MX11-MW11, "") | MZ11: =IF(38<=$G11, MV11-MY11, "") | NA11: =IF(38<=$G11, ROUND(MS11*$Q11, 2), "") | NB11: =IF(38<=$G11, MS11+NA11, "") | NC11: =IF(38<=$G11, MW11+NA11, "") | ND11: =IF(38<=$G11, ($G11-38)*$N11, "") | NE11: =IF(39<=$G11, MZ11, "") | NF11: =IF(39<=$G11, ROUND(NE11*$Q11, 2), "") | NG11: =IF(39<=$G11, $N11, "") | NH11: =IF(39<=$G11, NG11-NF11, "") | NI11: =IF(39<=$G11, NE11-NH11, "") | NJ11: =IF(39<=$G11, ROUND(NB11*$Q11, 2), "") | NK11: =IF(39<=$G11, NB11+NJ11, "") | NL11: =IF(39<=$G11, NF11+NJ11, "") | NM11: =IF(39<=$G11, ($G11-39)*$N11, "") | NN11: =IF(40<=$G11, NI11, "") | NO11: =IF(40<=$G11, ROUND(NN11*$Q11, 2), "") | NP11: =IF(40<=$G11, $N11, "") | NQ11: =IF(40<=$G11, NP11-NO11, "") | NR11: =IF(40<=$G11, NN11-NQ11, "") | NS11: =IF(40<=$G11, ROUND(NK11*$Q11, 2), "") | NT11: =IF(40<=$G11, NK11+NS11, "") | NU11: =IF(40<=$G11, NO11+NS11, "") | NV11: =IF(40<=$G11, ($G11-40)*$N11, "") | NW11: =IF(41<=$G11, NR11, "") | NX11: =IF(41<=$G11, ROUND(NW11*$Q11, 2), "") | NY11: =IF(41<=$G11, $N11, "") | NZ11: =IF(41<=$G11, NY11-NX11, "") | OA11: =IF(41<=$G11, NW11-NZ11, "") | OB11: =IF(41<=$G11, ROUND(NT11*$Q11, 2), "") | OC11: =IF(41<=$G11, NT11+OB11, "") | OD11: =IF(41<=$G11, NX11+OB11, "") | OE11: =IF(41<=$G11, ($G11-41)*$N11, "") | OF11: =IF(42<=$G11, OA11, "") | OG11: =IF(42<=$G11, ROUND(OF11*$Q11, 2), "") | OH11: =IF(42<=$G11, $N11, "") | OI11: =IF(42<=$G11, OH11-OG11, "") | OJ11: =IF(42<=$G11, OF11-OI11, "") | OK11: =IF(42<=$G11, ROUND(OC11*$Q11, 2), "") | OL11: =IF(42<=$G11, OC11+OK11, "") | OM11: =IF(42<=$G11, OG11+OK11, "") | ON11: =IF(42<=$G11, ($G11-42)*$N11, "") | OO11: =IF(43<=$G11, OJ11, "") | OP11: =IF(43<=$G11, ROUND(OO11*$Q11, 2), "") | OQ11: =IF(43<=$G11, $N11, "") | OR11: =IF(43<=$G11, OQ11-OP11, "") | OS11: =IF(43<=$G11, OO11-OR11, "") | OT11: =IF(43<=$G11, ROUND(OL11*$Q11, 2), "") | OU11: =IF(43<=$G11, OL11+OT11, "") | OV11: =IF(43<=$G11, OP11+OT11, "") | OW11: =IF(43<=$G11, ($G11-43)*$N11, "") | OX11: =IF(44<=$G11, OS11, "") | OY11: =IF(44<=$G11, ROUND(OX11*$Q11, 2), "") | OZ11: =IF(44<=$G11, $N11, "") | PA11: =IF(44<=$G11, OZ11-OY11, "") | PB11: =IF(44<=$G11, OX11-PA11, "") | PC11: =IF(44<=$G11, ROUND(OU11*$Q11, 2), "") | PD11: =IF(44<=$G11, OU11+PC11, "") | PE11: =IF(44<=$G11, OY11+PC11, "") | PF11: =IF(44<=$G11, ($G11-44)*$N11, "") | PG11: =IF(45<=$G11, PB11, "") | PH11: =IF(45<=$G11, ROUND(PG11*$Q11, 2), "") | PI11: =IF(45<=$G11, $N11, "") | PJ11: =IF(45<=$G11, PI11-PH11, "") | PK11: =IF(45<=$G11, PG11-PJ11, "") | PL11: =IF(45<=$G11, ROUND(PD11*$Q11, 2), "") | PM11: =IF(45<=$G11, PD11+PL11, "") | PN11: =IF(45<=$G11, PH11+PL11, "") | PO11: =IF(45<=$G11, ($G11-45)*$N11, "") | PP11: =IF(46<=$G11, PK11, "") | PQ11: =IF(46<=$G11, ROUND(PP11*$Q11, 2), "") | PR11: =IF(46<=$G11, $N11, "") | PS11: =IF(46<=$G11, PR11-PQ11, "") | PT11: =IF(46<=$G11, PP11-PS11, "") | PU11: =IF(46<=$G11, ROUND(PM11*$Q11, 2), "") | PV11: =IF(46<=$G11, PM11+PU11, "") | PW11: =IF(46<=$G11, PQ11+PU11, "") | PX11: =IF(46<=$G11, ($G11-46)*$N11, "") | PY11: =IF(47<=$G11, PT11, "") | PZ11: =IF(47<=$G11, ROUND(PY11*$Q11, 2), "") | QA11: =IF(47<=$G11, $N11, "") | QB11: =IF(47<=$G11, QA11-PZ11, "") | QC11: =IF(47<=$G11, PY11-QB11, "") | QD11: =IF(47<=$G11, ROUND(PV11*$Q11, 2), "") | QE11: =IF(47<=$G11, PV11+QD11, "") | QF11: =IF(47<=$G11, PZ11+QD11, "") | QG11: =IF(47<=$G11, ($G11-47)*$N11, "") | QH11: =IF(48<=$G11, QC11, "") | QI11: =IF(48<=$G11, ROUND(QH11*$Q11, 2), "") | QJ11: =IF(48<=$G11, $N11, "") | QK11: =IF(48<=$G11, QJ11-QI11, "") | QL11: =IF(48<=$G11, QH11-QK11, "") | QM11: =IF(48<=$G11, ROUND(QE11*$Q11, 2), "") | QN11: =IF(48<=$G11, QE11+QM11, "") | QO11: =IF(48<=$G11, QI11+QM11, "") | QP11: =IF(48<=$G11, ($G11-48)*$N11, "")
A12: 0520-0004 | B12: Tractomotriz Diesel Leal, S.A. de C.V. | C12: Partner Maxi Pack | D12: ACTIVO | E12: 2025-12-04 | F12: 2028-12-04 | G12: 36 | H12: 400363.79 | I12: 0.4 | J12: =ROUND(H12*I12, 2) | K12: =ROUND(H12-J12, 2) | L12: 1 | M12: =ROUND(H12*L12, 2) | N12: 9781.2 | O12: 0.1 | P12: =ROUND(H12*O12, 2) | Q12: 0.02663643 | R12: =RATE(G12, -N12, K12, -P12) | S12: =ROUND(Q12*12, 8) | T12: =ROUND(((1+Q12)^12)-1, 8) | U12: =ROUND(PV(Q12, G12, 0, -P12), 2) | V12: =SUMIF($AA$4:$QP$4, "Interes_Leasing", AA12:QP12) | W12: =SUMIF($AA$4:$QP$4, "Interes_Residual", AA12:QP12) | X12: =ROUND(V12+W12, 2) | Y12: =ROUND((N12*G12+P12+M12)-K12, 2) | Z12: =ROUND(Y12/K12, 4) | AA12: =IF(1<=$G12, $K12, "") | AB12: =IF(1<=$G12, ROUND(AA12*$Q12, 2), "") | AC12: =IF(1<=$G12, $N12, "") | AD12: =IF(1<=$G12, AC12-AB12, "") | AE12: =IF(1<=$G12, AA12-AD12, "") | AF12: =IF(1<=$G12, ROUND($U12*$Q12, 2), "") | AG12: =IF(1<=$G12, $U12+AF12, "") | AH12: =IF(1<=$G12, AB12+AF12, "") | AI12: =IF(1<=$G12, ($G12-1)*$N12, "") | AJ12: =IF(2<=$G12, AE12, "") | AK12: =IF(2<=$G12, ROUND(AJ12*$Q12, 2), "") | AL12: =IF(2<=$G12, $N12, "") | AM12: =IF(2<=$G12, AL12-AK12, "") | AN12: =IF(2<=$G12, AJ12-AM12, "") | AO12: =IF(2<=$G12, ROUND(AG12*$Q12, 2), "") | AP12: =IF(2<=$G12, AG12+AO12, "") | AQ12: =IF(2<=$G12, AK12+AO12, "") | AR12: =IF(2<=$G12, ($G12-2)*$N12, "") | AS12: =IF(3<=$G12, AN12, "") | AT12: =IF(3<=$G12, ROUND(AS12*$Q12, 2), "") | AU12: =IF(3<=$G12, $N12, "") | AV12: =IF(3<=$G12, AU12-AT12, "") | AW12: =IF(3<=$G12, AS12-AV12, "") | AX12: =IF(3<=$G12, ROUND(AP12*$Q12, 2), "") | AY12: =IF(3<=$G12, AP12+AX12, "") | AZ12: =IF(3<=$G12, AT12+AX12, "") | BA12: =IF(3<=$G12, ($G12-3)*$N12, "") | BB12: =IF(4<=$G12, AW12, "") | BC12: =IF(4<=$G12, ROUND(BB12*$Q12, 2), "") | BD12: =IF(4<=$G12, $N12, "") | BE12: =IF(4<=$G12, BD12-BC12, "") | BF12: =IF(4<=$G12, BB12-BE12, "") | BG12: =IF(4<=$G12, ROUND(AY12*$Q12, 2), "") | BH12: =IF(4<=$G12, AY12+BG12, "") | BI12: =IF(4<=$G12, BC12+BG12, "") | BJ12: =IF(4<=$G12, ($G12-4)*$N12, "") | BK12: =IF(5<=$G12, BF12, "") | BL12: =IF(5<=$G12, ROUND(BK12*$Q12, 2), "") | BM12: =IF(5<=$G12, $N12, "") | BN12: =IF(5<=$G12, BM12-BL12, "") | BO12: =IF(5<=$G12, BK12-BN12, "") | BP12: =IF(5<=$G12, ROUND(BH12*$Q12, 2), "") | BQ12: =IF(5<=$G12, BH12+BP12, "") | BR12: =IF(5<=$G12, BL12+BP12, "") | BS12: =IF(5<=$G12, ($G12-5)*$N12, "") | BT12: =IF(6<=$G12, BO12, "") | BU12: =IF(6<=$G12, ROUND(BT12*$Q12, 2), "") | BV12: =IF(6<=$G12, $N12, "") | BW12: =IF(6<=$G12, BV12-BU12, "") | BX12: =IF(6<=$G12, BT12-BW12, "") | BY12: =IF(6<=$G12, ROUND(BQ12*$Q12, 2), "") | BZ12: =IF(6<=$G12, BQ12+BY12, "") | CA12: =IF(6<=$G12, BU12+BY12, "") | CB12: =IF(6<=$G12, ($G12-6)*$N12, "") | CC12: =IF(7<=$G12, BX12, "") | CD12: =IF(7<=$G12, ROUND(CC12*$Q12, 2), "") | CE12: =IF(7<=$G12, $N12, "") | CF12: =IF(7<=$G12, CE12-CD12, "") | CG12: =IF(7<=$G12, CC12-CF12, "") | CH12: =IF(7<=$G12, ROUND(BZ12*$Q12, 2), "") | CI12: =IF(7<=$G12, BZ12+CH12, "") | CJ12: =IF(7<=$G12, CD12+CH12, "") | CK12: =IF(7<=$G12, ($G12-7)*$N12, "") | CL12: =IF(8<=$G12, CG12, "") | CM12: =IF(8<=$G12, ROUND(CL12*$Q12, 2), "") | CN12: =IF(8<=$G12, $N12, "") | CO12: =IF(8<=$G12, CN12-CM12, "") | CP12: =IF(8<=$G12, CL12-CO12, "") | CQ12: =IF(8<=$G12, ROUND(CI12*$Q12, 2), "") | CR12: =IF(8<=$G12, CI12+CQ12, "") | CS12: =IF(8<=$G12, CM12+CQ12, "") | CT12: =IF(8<=$G12, ($G12-8)*$N12, "") | CU12: =IF(9<=$G12, CP12, "") | CV12: =IF(9<=$G12, ROUND(CU12*$Q12, 2), "") | CW12: =IF(9<=$G12, $N12, "") | CX12: =IF(9<=$G12, CW12-CV12, "") | CY12: =IF(9<=$G12, CU12-CX12, "") | CZ12: =IF(9<=$G12, ROUND(CR12*$Q12, 2), "") | DA12: =IF(9<=$G12, CR12+CZ12, "") | DB12: =IF(9<=$G12, CV12+CZ12, "") | DC12: =IF(9<=$G12, ($G12-9)*$N12, "") | DD12: =IF(10<=$G12, CY12, "") | DE12: =IF(10<=$G12, ROUND(DD12*$Q12, 2), "") | DF12: =IF(10<=$G12, $N12, "") | DG12: =IF(10<=$G12, DF12-DE12, "") | DH12: =IF(10<=$G12, DD12-DG12, "") | DI12: =IF(10<=$G12, ROUND(DA12*$Q12, 2), "") | DJ12: =IF(10<=$G12, DA12+DI12, "") | DK12: =IF(10<=$G12, DE12+DI12, "") | DL12: =IF(10<=$G12, ($G12-10)*$N12, "") | DM12: =IF(11<=$G12, DH12, "") | DN12: =IF(11<=$G12, ROUND(DM12*$Q12, 2), "") | DO12: =IF(11<=$G12, $N12, "") | DP12: =IF(11<=$G12, DO12-DN12, "") | DQ12: =IF(11<=$G12, DM12-DP12, "") | DR12: =IF(11<=$G12, ROUND(DJ12*$Q12, 2), "") | DS12: =IF(11<=$G12, DJ12+DR12, "") | DT12: =IF(11<=$G12, DN12+DR12, "") | DU12: =IF(11<=$G12, ($G12-11)*$N12, "") | DV12: =IF(12<=$G12, DQ12, "") | DW12: =IF(12<=$G12, ROUND(DV12*$Q12, 2), "") | DX12: =IF(12<=$G12, $N12, "") | DY12: =IF(12<=$G12, DX12-DW12, "") | DZ12: =IF(12<=$G12, DV12-DY12, "") | EA12: =IF(12<=$G12, ROUND(DS12*$Q12, 2), "") | EB12: =IF(12<=$G12, DS12+EA12, "") | EC12: =IF(12<=$G12, DW12+EA12, "") | ED12: =IF(12<=$G12, ($G12-12)*$N12, "") | EE12: =IF(13<=$G12, DZ12, "") | EF12: =IF(13<=$G12, ROUND(EE12*$Q12, 2), "") | EG12: =IF(13<=$G12, $N12, "") | EH12: =IF(13<=$G12, EG12-EF12, "") | EI12: =IF(13<=$G12, EE12-EH12, "") | EJ12: =IF(13<=$G12, ROUND(EB12*$Q12, 2), "") | EK12: =IF(13<=$G12, EB12+EJ12, "") | EL12: =IF(13<=$G12, EF12+EJ12, "") | EM12: =IF(13<=$G12, ($G12-13)*$N12, "") | EN12: =IF(14<=$G12, EI12, "") | EO12: =IF(14<=$G12, ROUND(EN12*$Q12, 2), "") | EP12: =IF(14<=$G12, $N12, "") | EQ12: =IF(14<=$G12, EP12-EO12, "") | ER12: =IF(14<=$G12, EN12-EQ12, "") | ES12: =IF(14<=$G12, ROUND(EK12*$Q12, 2), "") | ET12: =IF(14<=$G12, EK12+ES12, "") | EU12: =IF(14<=$G12, EO12+ES12, "") | EV12: =IF(14<=$G12, ($G12-14)*$N12, "") | EW12: =IF(15<=$G12, ER12, "") | EX12: =IF(15<=$G12, ROUND(EW12*$Q12, 2), "") | EY12: =IF(15<=$G12, $N12, "") | EZ12: =IF(15<=$G12, EY12-EX12, "") | FA12: =IF(15<=$G12, EW12-EZ12, "") | FB12: =IF(15<=$G12, ROUND(ET12*$Q12, 2), "") | FC12: =IF(15<=$G12, ET12+FB12, "") | FD12: =IF(15<=$G12, EX12+FB12, "") | FE12: =IF(15<=$G12, ($G12-15)*$N12, "") | FF12: =IF(16<=$G12, FA12, "") | FG12: =IF(16<=$G12, ROUND(FF12*$Q12, 2), "") | FH12: =IF(16<=$G12, $N12, "") | FI12: =IF(16<=$G12, FH12-FG12, "") | FJ12: =IF(16<=$G12, FF12-FI12, "") | FK12: =IF(16<=$G12, ROUND(FC12*$Q12, 2), "") | FL12: =IF(16<=$G12, FC12+FK12, "") | FM12: =IF(16<=$G12, FG12+FK12, "") | FN12: =IF(16<=$G12, ($G12-16)*$N12, "") | FO12: =IF(17<=$G12, FJ12, "") | FP12: =IF(17<=$G12, ROUND(FO12*$Q12, 2), "") | FQ12: =IF(17<=$G12, $N12, "") | FR12: =IF(17<=$G12, FQ12-FP12, "") | FS12: =IF(17<=$G12, FO12-FR12, "") | FT12: =IF(17<=$G12, ROUND(FL12*$Q12, 2), "") | FU12: =IF(17<=$G12, FL12+FT12, "") | FV12: =IF(17<=$G12, FP12+FT12, "") | FW12: =IF(17<=$G12, ($G12-17)*$N12, "") | FX12: =IF(18<=$G12, FS12, "") | FY12: =IF(18<=$G12, ROUND(FX12*$Q12, 2), "") | FZ12: =IF(18<=$G12, $N12, "") | GA12: =IF(18<=$G12, FZ12-FY12, "") | GB12: =IF(18<=$G12, FX12-GA12, "") | GC12: =IF(18<=$G12, ROUND(FU12*$Q12, 2), "") | GD12: =IF(18<=$G12, FU12+GC12, "") | GE12: =IF(18<=$G12, FY12+GC12, "") | GF12: =IF(18<=$G12, ($G12-18)*$N12, "") | GG12: =IF(19<=$G12, GB12, "") | GH12: =IF(19<=$G12, ROUND(GG12*$Q12, 2), "") | GI12: =IF(19<=$G12, $N12, "") | GJ12: =IF(19<=$G12, GI12-GH12, "") | GK12: =IF(19<=$G12, GG12-GJ12, "") | GL12: =IF(19<=$G12, ROUND(GD12*$Q12, 2), "") | GM12: =IF(19<=$G12, GD12+GL12, "") | GN12: =IF(19<=$G12, GH12+GL12, "") | GO12: =IF(19<=$G12, ($G12-19)*$N12, "") | GP12: =IF(20<=$G12, GK12, "") | GQ12: =IF(20<=$G12, ROUND(GP12*$Q12, 2), "") | GR12: =IF(20<=$G12, $N12, "") | GS12: =IF(20<=$G12, GR12-GQ12, "") | GT12: =IF(20<=$G12, GP12-GS12, "") | GU12: =IF(20<=$G12, ROUND(GM12*$Q12, 2), "") | GV12: =IF(20<=$G12, GM12+GU12, "") | GW12: =IF(20<=$G12, GQ12+GU12, "") | GX12: =IF(20<=$G12, ($G12-20)*$N12, "") | GY12: =IF(21<=$G12, GT12, "") | GZ12: =IF(21<=$G12, ROUND(GY12*$Q12, 2), "") | HA12: =IF(21<=$G12, $N12, "") | HB12: =IF(21<=$G12, HA12-GZ12, "") | HC12: =IF(21<=$G12, GY12-HB12, "") | HD12: =IF(21<=$G12, ROUND(GV12*$Q12, 2), "") | HE12: =IF(21<=$G12, GV12+HD12, "") | HF12: =IF(21<=$G12, GZ12+HD12, "") | HG12: =IF(21<=$G12, ($G12-21)*$N12, "") | HH12: =IF(22<=$G12, HC12, "") | HI12: =IF(22<=$G12, ROUND(HH12*$Q12, 2), "") | HJ12: =IF(22<=$G12, $N12, "") | HK12: =IF(22<=$G12, HJ12-HI12, "") | HL12: =IF(22<=$G12, HH12-HK12, "") | HM12: =IF(22<=$G12, ROUND(HE12*$Q12, 2), "") | HN12: =IF(22<=$G12, HE12+HM12, "") | HO12: =IF(22<=$G12, HI12+HM12, "") | HP12: =IF(22<=$G12, ($G12-22)*$N12, "") | HQ12: =IF(23<=$G12, HL12, "") | HR12: =IF(23<=$G12, ROUND(HQ12*$Q12, 2), "") | HS12: =IF(23<=$G12, $N12, "") | HT12: =IF(23<=$G12, HS12-HR12, "") | HU12: =IF(23<=$G12, HQ12-HT12, "") | HV12: =IF(23<=$G12, ROUND(HN12*$Q12, 2), "") | HW12: =IF(23<=$G12, HN12+HV12, "") | HX12: =IF(23<=$G12, HR12+HV12, "") | HY12: =IF(23<=$G12, ($G12-23)*$N12, "") | HZ12: =IF(24<=$G12, HU12, "") | IA12: =IF(24<=$G12, ROUND(HZ12*$Q12, 2), "") | IB12: =IF(24<=$G12, $N12, "") | IC12: =IF(24<=$G12, IB12-IA12, "") | ID12: =IF(24<=$G12, HZ12-IC12, "") | IE12: =IF(24<=$G12, ROUND(HW12*$Q12, 2), "") | IF12: =IF(24<=$G12, HW12+IE12, "") | IG12: =IF(24<=$G12, IA12+IE12, "") | IH12: =IF(24<=$G12, ($G12-24)*$N12, "") | II12: =IF(25<=$G12, ID12, "") | IJ12: =IF(25<=$G12, ROUND(II12*$Q12, 2), "") | IK12: =IF(25<=$G12, $N12, "") | IL12: =IF(25<=$G12, IK12-IJ12, "") | IM12: =IF(25<=$G12, II12-IL12, "") | IN12: =IF(25<=$G12, ROUND(IF12*$Q12, 2), "") | IO12: =IF(25<=$G12, IF12+IN12, "") | IP12: =IF(25<=$G12, IJ12+IN12, "") | IQ12: =IF(25<=$G12, ($G12-25)*$N12, "") | IR12: =IF(26<=$G12, IM12, "") | IS12: =IF(26<=$G12, ROUND(IR12*$Q12, 2), "") | IT12: =IF(26<=$G12, $N12, "") | IU12: =IF(26<=$G12, IT12-IS12, "") | IV12: =IF(26<=$G12, IR12-IU12, "") | IW12: =IF(26<=$G12, ROUND(IO12*$Q12, 2), "") | IX12: =IF(26<=$G12, IO12+IW12, "") | IY12: =IF(26<=$G12, IS12+IW12, "") | IZ12: =IF(26<=$G12, ($G12-26)*$N12, "") | JA12: =IF(27<=$G12, IV12, "") | JB12: =IF(27<=$G12, ROUND(JA12*$Q12, 2), "") | JC12: =IF(27<=$G12, $N12, "") | JD12: =IF(27<=$G12, JC12-JB12, "") | JE12: =IF(27<=$G12, JA12-JD12, "") | JF12: =IF(27<=$G12, ROUND(IX12*$Q12, 2), "") | JG12: =IF(27<=$G12, IX12+JF12, "") | JH12: =IF(27<=$G12, JB12+JF12, "") | JI12: =IF(27<=$G12, ($G12-27)*$N12, "") | JJ12: =IF(28<=$G12, JE12, "") | JK12: =IF(28<=$G12, ROUND(JJ12*$Q12, 2), "") | JL12: =IF(28<=$G12, $N12, "") | JM12: =IF(28<=$G12, JL12-JK12, "") | JN12: =IF(28<=$G12, JJ12-JM12, "") | JO12: =IF(28<=$G12, ROUND(JG12*$Q12, 2), "") | JP12: =IF(28<=$G12, JG12+JO12, "") | JQ12: =IF(28<=$G12, JK12+JO12, "") | JR12: =IF(28<=$G12, ($G12-28)*$N12, "") | JS12: =IF(29<=$G12, JN12, "") | JT12: =IF(29<=$G12, ROUND(JS12*$Q12, 2), "") | JU12: =IF(29<=$G12, $N12, "") | JV12: =IF(29<=$G12, JU12-JT12, "") | JW12: =IF(29<=$G12, JS12-JV12, "") | JX12: =IF(29<=$G12, ROUND(JP12*$Q12, 2), "") | JY12: =IF(29<=$G12, JP12+JX12, "") | JZ12: =IF(29<=$G12, JT12+JX12, "") | KA12: =IF(29<=$G12, ($G12-29)*$N12, "") | KB12: =IF(30<=$G12, JW12, "") | KC12: =IF(30<=$G12, ROUND(KB12*$Q12, 2), "") | KD12: =IF(30<=$G12, $N12, "") | KE12: =IF(30<=$G12, KD12-KC12, "") | KF12: =IF(30<=$G12, KB12-KE12, "") | KG12: =IF(30<=$G12, ROUND(JY12*$Q12, 2), "") | KH12: =IF(30<=$G12, JY12+KG12, "") | KI12: =IF(30<=$G12, KC12+KG12, "") | KJ12: =IF(30<=$G12, ($G12-30)*$N12, "") | KK12: =IF(31<=$G12, KF12, "") | KL12: =IF(31<=$G12, ROUND(KK12*$Q12, 2), "") | KM12: =IF(31<=$G12, $N12, "") | KN12: =IF(31<=$G12, KM12-KL12, "") | KO12: =IF(31<=$G12, KK12-KN12, "") | KP12: =IF(31<=$G12, ROUND(KH12*$Q12, 2), "") | KQ12: =IF(31<=$G12, KH12+KP12, "") | KR12: =IF(31<=$G12, KL12+KP12, "") | KS12: =IF(31<=$G12, ($G12-31)*$N12, "") | KT12: =IF(32<=$G12, KO12, "") | KU12: =IF(32<=$G12, ROUND(KT12*$Q12, 2), "") | KV12: =IF(32<=$G12, $N12, "") | KW12: =IF(32<=$G12, KV12-KU12, "") | KX12: =IF(32<=$G12, KT12-KW12, "") | KY12: =IF(32<=$G12, ROUND(KQ12*$Q12, 2), "") | KZ12: =IF(32<=$G12, KQ12+KY12, "") | LA12: =IF(32<=$G12, KU12+KY12, "") | LB12: =IF(32<=$G12, ($G12-32)*$N12, "") | LC12: =IF(33<=$G12, KX12, "") | LD12: =IF(33<=$G12, ROUND(LC12*$Q12, 2), "") | LE12: =IF(33<=$G12, $N12, "") | LF12: =IF(33<=$G12, LE12-LD12, "") | LG12: =IF(33<=$G12, LC12-LF12, "") | LH12: =IF(33<=$G12, ROUND(KZ12*$Q12, 2), "") | LI12: =IF(33<=$G12, KZ12+LH12, "") | LJ12: =IF(33<=$G12, LD12+LH12, "") | LK12: =IF(33<=$G12, ($G12-33)*$N12, "") | LL12: =IF(34<=$G12, LG12, "") | LM12: =IF(34<=$G12, ROUND(LL12*$Q12, 2), "") | LN12: =IF(34<=$G12, $N12, "") | LO12: =IF(34<=$G12, LN12-LM12, "") | LP12: =IF(34<=$G12, LL12-LO12, "") | LQ12: =IF(34<=$G12, ROUND(LI12*$Q12, 2), "") | LR12: =IF(34<=$G12, LI12+LQ12, "") | LS12: =IF(34<=$G12, LM12+LQ12, "") | LT12: =IF(34<=$G12, ($G12-34)*$N12, "") | LU12: =IF(35<=$G12, LP12, "") | LV12: =IF(35<=$G12, ROUND(LU12*$Q12, 2), "") | LW12: =IF(35<=$G12, $N12, "") | LX12: =IF(35<=$G12, LW12-LV12, "") | LY12: =IF(35<=$G12, LU12-LX12, "") | LZ12: =IF(35<=$G12, ROUND(LR12*$Q12, 2), "") | MA12: =IF(35<=$G12, LR12+LZ12, "") | MB12: =IF(35<=$G12, LV12+LZ12, "") | MC12: =IF(35<=$G12, ($G12-35)*$N12, "") | MD12: =IF(36<=$G12, LY12, "") | ME12: =IF(36<=$G12, ROUND(MD12*$Q12, 2), "") | MF12: =IF(36<=$G12, $N12, "") | MG12: =IF(36<=$G12, MF12-ME12, "") | MH12: =IF(36<=$G12, MD12-MG12, "") | MI12: =IF(36<=$G12, ROUND(MA12*$Q12, 2), "") | MJ12: =IF(36<=$G12, MA12+MI12, "") | MK12: =IF(36<=$G12, ME12+MI12, "") | ML12: =IF(36<=$G12, ($G12-36)*$N12, "") | MM12: =IF(37<=$G12, MH12, "") | MN12: =IF(37<=$G12, ROUND(MM12*$Q12, 2), "") | MO12: =IF(37<=$G12, $N12, "") | MP12: =IF(37<=$G12, MO12-MN12, "") | MQ12: =IF(37<=$G12, MM12-MP12, "") | MR12: =IF(37<=$G12, ROUND(MJ12*$Q12, 2), "") | MS12: =IF(37<=$G12, MJ12+MR12, "") | MT12: =IF(37<=$G12, MN12+MR12, "") | MU12: =IF(37<=$G12, ($G12-37)*$N12, "") | MV12: =IF(38<=$G12, MQ12, "") | MW12: =IF(38<=$G12, ROUND(MV12*$Q12, 2), "") | MX12: =IF(38<=$G12, $N12, "") | MY12: =IF(38<=$G12, MX12-MW12, "") | MZ12: =IF(38<=$G12, MV12-MY12, "") | NA12: =IF(38<=$G12, ROUND(MS12*$Q12, 2), "") | NB12: =IF(38<=$G12, MS12+NA12, "") | NC12: =IF(38<=$G12, MW12+NA12, "") | ND12: =IF(38<=$G12, ($G12-38)*$N12, "") | NE12: =IF(39<=$G12, MZ12, "") | NF12: =IF(39<=$G12, ROUND(NE12*$Q12, 2), "") | NG12: =IF(39<=$G12, $N12, "") | NH12: =IF(39<=$G12, NG12-NF12, "") | NI12: =IF(39<=$G12, NE12-NH12, "") | NJ12: =IF(39<=$G12, ROUND(NB12*$Q12, 2), "") | NK12: =IF(39<=$G12, NB12+NJ12, "") | NL12: =IF(39<=$G12, NF12+NJ12, "") | NM12: =IF(39<=$G12, ($G12-39)*$N12, "") | NN12: =IF(40<=$G12, NI12, "") | NO12: =IF(40<=$G12, ROUND(NN12*$Q12, 2), "") | NP12: =IF(40<=$G12, $N12, "") | NQ12: =IF(40<=$G12, NP12-NO12, "") | NR12: =IF(40<=$G12, NN12-NQ12, "") | NS12: =IF(40<=$G12, ROUND(NK12*$Q12, 2), "") | NT12: =IF(40<=$G12, NK12+NS12, "") | NU12: =IF(40<=$G12, NO12+NS12, "") | NV12: =IF(40<=$G12, ($G12-40)*$N12, "") | NW12: =IF(41<=$G12, NR12, "") | NX12: =IF(41<=$G12, ROUND(NW12*$Q12, 2), "") | NY12: =IF(41<=$G12, $N12, "") | NZ12: =IF(41<=$G12, NY12-NX12, "") | OA12: =IF(41<=$G12, NW12-NZ12, "") | OB12: =IF(41<=$G12, ROUND(NT12*$Q12, 2), "") | OC12: =IF(41<=$G12, NT12+OB12, "") | OD12: =IF(41<=$G12, NX12+OB12, "") | OE12: =IF(41<=$G12, ($G12-41)*$N12, "") | OF12: =IF(42<=$G12, OA12, "") | OG12: =IF(42<=$G12, ROUND(OF12*$Q12, 2), "") | OH12: =IF(42<=$G12, $N12, "") | OI12: =IF(42<=$G12, OH12-OG12, "") | OJ12: =IF(42<=$G12, OF12-OI12, "") | OK12: =IF(42<=$G12, ROUND(OC12*$Q12, 2), "") | OL12: =IF(42<=$G12, OC12+OK12, "") | OM12: =IF(42<=$G12, OG12+OK12, "") | ON12: =IF(42<=$G12, ($G12-42)*$N12, "") | OO12: =IF(43<=$G12, OJ12, "") | OP12: =IF(43<=$G12, ROUND(OO12*$Q12, 2), "") | OQ12: =IF(43<=$G12, $N12, "") | OR12: =IF(43<=$G12, OQ12-OP12, "") | OS12: =IF(43<=$G12, OO12-OR12, "") | OT12: =IF(43<=$G12, ROUND(OL12*$Q12, 2), "") | OU12: =IF(43<=$G12, OL12+OT12, "") | OV12: =IF(43<=$G12, OP12+OT12, "") | OW12: =IF(43<=$G12, ($G12-43)*$N12, "") | OX12: =IF(44<=$G12, OS12, "") | OY12: =IF(44<=$G12, ROUND(OX12*$Q12, 2), "") | OZ12: =IF(44<=$G12, $N12, "") | PA12: =IF(44<=$G12, OZ12-OY12, "") | PB12: =IF(44<=$G12, OX12-PA12, "") | PC12: =IF(44<=$G12, ROUND(OU12*$Q12, 2), "") | PD12: =IF(44<=$G12, OU12+PC12, "") | PE12: =IF(44<=$G12, OY12+PC12, "") | PF12: =IF(44<=$G12, ($G12-44)*$N12, "") | PG12: =IF(45<=$G12, PB12, "") | PH12: =IF(45<=$G12, ROUND(PG12*$Q12, 2), "") | PI12: =IF(45<=$G12, $N12, "") | PJ12: =IF(45<=$G12, PI12-PH12, "") | PK12: =IF(45<=$G12, PG12-PJ12, "") | PL12: =IF(45<=$G12, ROUND(PD12*$Q12, 2), "") | PM12: =IF(45<=$G12, PD12+PL12, "") | PN12: =IF(45<=$G12, PH12+PL12, "") | PO12: =IF(45<=$G12, ($G12-45)*$N12, "") | PP12: =IF(46<=$G12, PK12, "") | PQ12: =IF(46<=$G12, ROUND(PP12*$Q12, 2), "") | PR12: =IF(46<=$G12, $N12, "") | PS12: =IF(46<=$G12, PR12-PQ12, "") | PT12: =IF(46<=$G12, PP12-PS12, "") | PU12: =IF(46<=$G12, ROUND(PM12*$Q12, 2), "") | PV12: =IF(46<=$G12, PM12+PU12, "") | PW12: =IF(46<=$G12, PQ12+PU12, "") | PX12: =IF(46<=$G12, ($G12-46)*$N12, "") | PY12: =IF(47<=$G12, PT12, "") | PZ12: =IF(47<=$G12, ROUND(PY12*$Q12, 2), "") | QA12: =IF(47<=$G12, $N12, "") | QB12: =IF(47<=$G12, QA12-PZ12, "") | QC12: =IF(47<=$G12, PY12-QB12, "") | QD12: =IF(47<=$G12, ROUND(PV12*$Q12, 2), "") | QE12: =IF(47<=$G12, PV12+QD12, "") | QF12: =IF(47<=$G12, PZ12+QD12, "") | QG12: =IF(47<=$G12, ($G12-47)*$N12, "") | QH12: =IF(48<=$G12, QC12, "") | QI12: =IF(48<=$G12, ROUND(QH12*$Q12, 2), "") | QJ12: =IF(48<=$G12, $N12, "") | QK12: =IF(48<=$G12, QJ12-QI12, "") | QL12: =IF(48<=$G12, QH12-QK12, "") | QM12: =IF(48<=$G12, ROUND(QE12*$Q12, 2), "") | QN12: =IF(48<=$G12, QE12+QM12, "") | QO12: =IF(48<=$G12, QI12+QM12, "") | QP12: =IF(48<=$G12, ($G12-48)*$N12, "")
A13: 0521-0002 | B13: Carlos Hiram leal Leal | C13: Xpander | D13: ACTIVO | E13: 2025-09-08 | F13: 2028-09-08 | G13: 36 | H13: 365988.79 | I13: 0.1 | J13: =ROUND(H13*I13, 2) | K13: =ROUND(H13-J13, 2) | L13: 1 | M13: =ROUND(H13*L13, 2) | N13: 13100.96 | O13: 0.2 | P13: =ROUND(H13*O13, 2) | Q13: 0.02662861 | R13: =RATE(G13, -N13, K13, -P13) | S13: =ROUND(Q13*12, 8) | T13: =ROUND(((1+Q13)^12)-1, 8) | U13: =ROUND(PV(Q13, G13, 0, -P13), 2) | V13: =SUMIF($AA$4:$QP$4, "Interes_Leasing", AA13:QP13) | W13: =SUMIF($AA$4:$QP$4, "Interes_Residual", AA13:QP13) | X13: =ROUND(V13+W13, 2) | Y13: =ROUND((N13*G13+P13+M13)-K13, 2) | Z13: =ROUND(Y13/K13, 4) | AA13: =IF(1<=$G13, $K13, "") | AB13: =IF(1<=$G13, ROUND(AA13*$Q13, 2), "") | AC13: =IF(1<=$G13, $N13, "") | AD13: =IF(1<=$G13, AC13-AB13, "") | AE13: =IF(1<=$G13, AA13-AD13, "") | AF13: =IF(1<=$G13, ROUND($U13*$Q13, 2), "") | AG13: =IF(1<=$G13, $U13+AF13, "") | AH13: =IF(1<=$G13, AB13+AF13, "") | AI13: =IF(1<=$G13, ($G13-1)*$N13, "") | AJ13: =IF(2<=$G13, AE13, "") | AK13: =IF(2<=$G13, ROUND(AJ13*$Q13, 2), "") | AL13: =IF(2<=$G13, $N13, "") | AM13: =IF(2<=$G13, AL13-AK13, "") | AN13: =IF(2<=$G13, AJ13-AM13, "") | AO13: =IF(2<=$G13, ROUND(AG13*$Q13, 2), "") | AP13: =IF(2<=$G13, AG13+AO13, "") | AQ13: =IF(2<=$G13, AK13+AO13, "") | AR13: =IF(2<=$G13, ($G13-2)*$N13, "") | AS13: =IF(3<=$G13, AN13, "") | AT13: =IF(3<=$G13, ROUND(AS13*$Q13, 2), "") | AU13: =IF(3<=$G13, $N13, "") | AV13: =IF(3<=$G13, AU13-AT13, "") | AW13: =IF(3<=$G13, AS13-AV13, "") | AX13: =IF(3<=$G13, ROUND(AP13*$Q13, 2), "") | AY13: =IF(3<=$G13, AP13+AX13, "") | AZ13: =IF(3<=$G13, AT13+AX13, "") | BA13: =IF(3<=$G13, ($G13-3)*$N13, "") | BB13: =IF(4<=$G13, AW13, "") | BC13: =IF(4<=$G13, ROUND(BB13*$Q13, 2), "") | BD13: =IF(4<=$G13, $N13, "") | BE13: =IF(4<=$G13, BD13-BC13, "") | BF13: =IF(4<=$G13, BB13-BE13, "") | BG13: =IF(4<=$G13, ROUND(AY13*$Q13, 2), "") | BH13: =IF(4<=$G13, AY13+BG13, "") | BI13: =IF(4<=$G13, BC13+BG13, "") | BJ13: =IF(4<=$G13, ($G13-4)*$N13, "") | BK13: =IF(5<=$G13, BF13, "") | BL13: =IF(5<=$G13, ROUND(BK13*$Q13, 2), "") | BM13: =IF(5<=$G13, $N13, "") | BN13: =IF(5<=$G13, BM13-BL13, "") | BO13: =IF(5<=$G13, BK13-BN13, "") | BP13: =IF(5<=$G13, ROUND(BH13*$Q13, 2), "") | BQ13: =IF(5<=$G13, BH13+BP13, "") | BR13: =IF(5<=$G13, BL13+BP13, "") | BS13: =IF(5<=$G13, ($G13-5)*$N13, "") | BT13: =IF(6<=$G13, BO13, "") | BU13: =IF(6<=$G13, ROUND(BT13*$Q13, 2), "") | BV13: =IF(6<=$G13, $N13, "") | BW13: =IF(6<=$G13, BV13-BU13, "") | BX13: =IF(6<=$G13, BT13-BW13, "") | BY13: =IF(6<=$G13, ROUND(BQ13*$Q13, 2), "") | BZ13: =IF(6<=$G13, BQ13+BY13, "") | CA13: =IF(6<=$G13, BU13+BY13, "") | CB13: =IF(6<=$G13, ($G13-6)*$N13, "") | CC13: =IF(7<=$G13, BX13, "") | CD13: =IF(7<=$G13, ROUND(CC13*$Q13, 2), "") | CE13: =IF(7<=$G13, $N13, "") | CF13: =IF(7<=$G13, CE13-CD13, "") | CG13: =IF(7<=$G13, CC13-CF13, "") | CH13: =IF(7<=$G13, ROUND(BZ13*$Q13, 2), "") | CI13: =IF(7<=$G13, BZ13+CH13, "") | CJ13: =IF(7<=$G13, CD13+CH13, "") | CK13: =IF(7<=$G13, ($G13-7)*$N13, "") | CL13: =IF(8<=$G13, CG13, "") | CM13: =IF(8<=$G13, ROUND(CL13*$Q13, 2), "") | CN13: =IF(8<=$G13, $N13, "") | CO13: =IF(8<=$G13, CN13-CM13, "") | CP13: =IF(8<=$G13, CL13-CO13, "") | CQ13: =IF(8<=$G13, ROUND(CI13*$Q13, 2), "") | CR13: =IF(8<=$G13, CI13+CQ13, "") | CS13: =IF(8<=$G13, CM13+CQ13, "") | CT13: =IF(8<=$G13, ($G13-8)*$N13, "") | CU13: =IF(9<=$G13, CP13, "") | CV13: =IF(9<=$G13, ROUND(CU13*$Q13, 2), "") | CW13: =IF(9<=$G13, $N13, "") | CX13: =IF(9<=$G13, CW13-CV13, "") | CY13: =IF(9<=$G13, CU13-CX13, "") | CZ13: =IF(9<=$G13, ROUND(CR13*$Q13, 2), "") | DA13: =IF(9<=$G13, CR13+CZ13, "") | DB13: =IF(9<=$G13, CV13+CZ13, "") | DC13: =IF(9<=$G13, ($G13-9)*$N13, "") | DD13: =IF(10<=$G13, CY13, "") | DE13: =IF(10<=$G13, ROUND(DD13*$Q13, 2), "") | DF13: =IF(10<=$G13, $N13, "") | DG13: =IF(10<=$G13, DF13-DE13, "") | DH13: =IF(10<=$G13, DD13-DG13, "") | DI13: =IF(10<=$G13, ROUND(DA13*$Q13, 2), "") | DJ13: =IF(10<=$G13, DA13+DI13, "") | DK13: =IF(10<=$G13, DE13+DI13, "") | DL13: =IF(10<=$G13, ($G13-10)*$N13, "") | DM13: =IF(11<=$G13, DH13, "") | DN13: =IF(11<=$G13, ROUND(DM13*$Q13, 2), "") | DO13: =IF(11<=$G13, $N13, "") | DP13: =IF(11<=$G13, DO13-DN13, "") | DQ13: =IF(11<=$G13, DM13-DP13, "") | DR13: =IF(11<=$G13, ROUND(DJ13*$Q13, 2), "") | DS13: =IF(11<=$G13, DJ13+DR13, "") | DT13: =IF(11<=$G13, DN13+DR13, "") | DU13: =IF(11<=$G13, ($G13-11)*$N13, "") | DV13: =IF(12<=$G13, DQ13, "") | DW13: =IF(12<=$G13, ROUND(DV13*$Q13, 2), "") | DX13: =IF(12<=$G13, $N13, "") | DY13: =IF(12<=$G13, DX13-DW13, "") | DZ13: =IF(12<=$G13, DV13-DY13, "") | EA13: =IF(12<=$G13, ROUND(DS13*$Q13, 2), "") | EB13: =IF(12<=$G13, DS13+EA13, "") | EC13: =IF(12<=$G13, DW13+EA13, "") | ED13: =IF(12<=$G13, ($G13-12)*$N13, "") | EE13: =IF(13<=$G13, DZ13, "") | EF13: =IF(13<=$G13, ROUND(EE13*$Q13, 2), "") | EG13: =IF(13<=$G13, $N13, "") | EH13: =IF(13<=$G13, EG13-EF13, "") | EI13: =IF(13<=$G13, EE13-EH13, "") | EJ13: =IF(13<=$G13, ROUND(EB13*$Q13, 2), "") | EK13: =IF(13<=$G13, EB13+EJ13, "") | EL13: =IF(13<=$G13, EF13+EJ13, "") | EM13: =IF(13<=$G13, ($G13-13)*$N13, "") | EN13: =IF(14<=$G13, EI13, "") | EO13: =IF(14<=$G13, ROUND(EN13*$Q13, 2), "") | EP13: =IF(14<=$G13, $N13, "") | EQ13: =IF(14<=$G13, EP13-EO13, "") | ER13: =IF(14<=$G13, EN13-EQ13, "") | ES13: =IF(14<=$G13, ROUND(EK13*$Q13, 2), "") | ET13: =IF(14<=$G13, EK13+ES13, "") | EU13: =IF(14<=$G13, EO13+ES13, "") | EV13: =IF(14<=$G13, ($G13-14)*$N13, "") | EW13: =IF(15<=$G13, ER13, "") | EX13: =IF(15<=$G13, ROUND(EW13*$Q13, 2), "") | EY13: =IF(15<=$G13, $N13, "") | EZ13: =IF(15<=$G13, EY13-EX13, "") | FA13: =IF(15<=$G13, EW13-EZ13, "") | FB13: =IF(15<=$G13, ROUND(ET13*$Q13, 2), "") | FC13: =IF(15<=$G13, ET13+FB13, "") | FD13: =IF(15<=$G13, EX13+FB13, "") | FE13: =IF(15<=$G13, ($G13-15)*$N13, "") | FF13: =IF(16<=$G13, FA13, "") | FG13: =IF(16<=$G13, ROUND(FF13*$Q13, 2), "") | FH13: =IF(16<=$G13, $N13, "") | FI13: =IF(16<=$G13, FH13-FG13, "") | FJ13: =IF(16<=$G13, FF13-FI13, "") | FK13: =IF(16<=$G13, ROUND(FC13*$Q13, 2), "") | FL13: =IF(16<=$G13, FC13+FK13, "") | FM13: =IF(16<=$G13, FG13+FK13, "") | FN13: =IF(16<=$G13, ($G13-16)*$N13, "") | FO13: =IF(17<=$G13, FJ13, "") | FP13: =IF(17<=$G13, ROUND(FO13*$Q13, 2), "") | FQ13: =IF(17<=$G13, $N13, "") | FR13: =IF(17<=$G13, FQ13-FP13, "") | FS13: =IF(17<=$G13, FO13-FR13, "") | FT13: =IF(17<=$G13, ROUND(FL13*$Q13, 2), "") | FU13: =IF(17<=$G13, FL13+FT13, "") | FV13: =IF(17<=$G13, FP13+FT13, "") | FW13: =IF(17<=$G13, ($G13-17)*$N13, "") | FX13: =IF(18<=$G13, FS13, "") | FY13: =IF(18<=$G13, ROUND(FX13*$Q13, 2), "") | FZ13: =IF(18<=$G13, $N13, "") | GA13: =IF(18<=$G13, FZ13-FY13, "") | GB13: =IF(18<=$G13, FX13-GA13, "") | GC13: =IF(18<=$G13, ROUND(FU13*$Q13, 2), "") | GD13: =IF(18<=$G13, FU13+GC13, "") | GE13: =IF(18<=$G13, FY13+GC13, "") | GF13: =IF(18<=$G13, ($G13-18)*$N13, "") | GG13: =IF(19<=$G13, GB13, "") | GH13: =IF(19<=$G13, ROUND(GG13*$Q13, 2), "") | GI13: =IF(19<=$G13, $N13, "") | GJ13: =IF(19<=$G13, GI13-GH13, "") | GK13: =IF(19<=$G13, GG13-GJ13, "") | GL13: =IF(19<=$G13, ROUND(GD13*$Q13, 2), "") | GM13: =IF(19<=$G13, GD13+GL13, "") | GN13: =IF(19<=$G13, GH13+GL13, "") | GO13: =IF(19<=$G13, ($G13-19)*$N13, "") | GP13: =IF(20<=$G13, GK13, "") | GQ13: =IF(20<=$G13, ROUND(GP13*$Q13, 2), "") | GR13: =IF(20<=$G13, $N13, "") | GS13: =IF(20<=$G13, GR13-GQ13, "") | GT13: =IF(20<=$G13, GP13-GS13, "") | GU13: =IF(20<=$G13, ROUND(GM13*$Q13, 2), "") | GV13: =IF(20<=$G13, GM13+GU13, "") | GW13: =IF(20<=$G13, GQ13+GU13, "") | GX13: =IF(20<=$G13, ($G13-20)*$N13, "") | GY13: =IF(21<=$G13, GT13, "") | GZ13: =IF(21<=$G13, ROUND(GY13*$Q13, 2), "") | HA13: =IF(21<=$G13, $N13, "") | HB13: =IF(21<=$G13, HA13-GZ13, "") | HC13: =IF(21<=$G13, GY13-HB13, "") | HD13: =IF(21<=$G13, ROUND(GV13*$Q13, 2), "") | HE13: =IF(21<=$G13, GV13+HD13, "") | HF13: =IF(21<=$G13, GZ13+HD13, "") | HG13: =IF(21<=$G13, ($G13-21)*$N13, "") | HH13: =IF(22<=$G13, HC13, "") | HI13: =IF(22<=$G13, ROUND(HH13*$Q13, 2), "") | HJ13: =IF(22<=$G13, $N13, "") | HK13: =IF(22<=$G13, HJ13-HI13, "") | HL13: =IF(22<=$G13, HH13-HK13, "") | HM13: =IF(22<=$G13, ROUND(HE13*$Q13, 2), "") | HN13: =IF(22<=$G13, HE13+HM13, "") | HO13: =IF(22<=$G13, HI13+HM13, "") | HP13: =IF(22<=$G13, ($G13-22)*$N13, "") | HQ13: =IF(23<=$G13, HL13, "") | HR13: =IF(23<=$G13, ROUND(HQ13*$Q13, 2), "") | HS13: =IF(23<=$G13, $N13, "") | HT13: =IF(23<=$G13, HS13-HR13, "") | HU13: =IF(23<=$G13, HQ13-HT13, "") | HV13: =IF(23<=$G13, ROUND(HN13*$Q13, 2), "") | HW13: =IF(23<=$G13, HN13+HV13, "") | HX13: =IF(23<=$G13, HR13+HV13, "") | HY13: =IF(23<=$G13, ($G13-23)*$N13, "") | HZ13: =IF(24<=$G13, HU13, "") | IA13: =IF(24<=$G13, ROUND(HZ13*$Q13, 2), "") | IB13: =IF(24<=$G13, $N13, "") | IC13: =IF(24<=$G13, IB13-IA13, "") | ID13: =IF(24<=$G13, HZ13-IC13, "") | IE13: =IF(24<=$G13, ROUND(HW13*$Q13, 2), "") | IF13: =IF(24<=$G13, HW13+IE13, "") | IG13: =IF(24<=$G13, IA13+IE13, "") | IH13: =IF(24<=$G13, ($G13-24)*$N13, "") | II13: =IF(25<=$G13, ID13, "") | IJ13: =IF(25<=$G13, ROUND(II13*$Q13, 2), "") | IK13: =IF(25<=$G13, $N13, "") | IL13: =IF(25<=$G13, IK13-IJ13, "") | IM13: =IF(25<=$G13, II13-IL13, "") | IN13: =IF(25<=$G13, ROUND(IF13*$Q13, 2), "") | IO13: =IF(25<=$G13, IF13+IN13, "") | IP13: =IF(25<=$G13, IJ13+IN13, "") | IQ13: =IF(25<=$G13, ($G13-25)*$N13, "") | IR13: =IF(26<=$G13, IM13, "") | IS13: =IF(26<=$G13, ROUND(IR13*$Q13, 2), "") | IT13: =IF(26<=$G13, $N13, "") | IU13: =IF(26<=$G13, IT13-IS13, "") | IV13: =IF(26<=$G13, IR13-IU13, "") | IW13: =IF(26<=$G13, ROUND(IO13*$Q13, 2), "") | IX13: =IF(26<=$G13, IO13+IW13, "") | IY13: =IF(26<=$G13, IS13+IW13, "") | IZ13: =IF(26<=$G13, ($G13-26)*$N13, "") | JA13: =IF(27<=$G13, IV13, "") | JB13: =IF(27<=$G13, ROUND(JA13*$Q13, 2), "") | JC13: =IF(27<=$G13, $N13, "") | JD13: =IF(27<=$G13, JC13-JB13, "") | JE13: =IF(27<=$G13, JA13-JD13, "") | JF13: =IF(27<=$G13, ROUND(IX13*$Q13, 2), "") | JG13: =IF(27<=$G13, IX13+JF13, "") | JH13: =IF(27<=$G13, JB13+JF13, "") | JI13: =IF(27<=$G13, ($G13-27)*$N13, "") | JJ13: =IF(28<=$G13, JE13, "") | JK13: =IF(28<=$G13, ROUND(JJ13*$Q13, 2), "") | JL13: =IF(28<=$G13, $N13, "") | JM13: =IF(28<=$G13, JL13-JK13, "") | JN13: =IF(28<=$G13, JJ13-JM13, "") | JO13: =IF(28<=$G13, ROUND(JG13*$Q13, 2), "") | JP13: =IF(28<=$G13, JG13+JO13, "") | JQ13: =IF(28<=$G13, JK13+JO13, "") | JR13: =IF(28<=$G13, ($G13-28)*$N13, "") | JS13: =IF(29<=$G13, JN13, "") | JT13: =IF(29<=$G13, ROUND(JS13*$Q13, 2), "") | JU13: =IF(29<=$G13, $N13, "") | JV13: =IF(29<=$G13, JU13-JT13, "") | JW13: =IF(29<=$G13, JS13-JV13, "") | JX13: =IF(29<=$G13, ROUND(JP13*$Q13, 2), "") | JY13: =IF(29<=$G13, JP13+JX13, "") | JZ13: =IF(29<=$G13, JT13+JX13, "") | KA13: =IF(29<=$G13, ($G13-29)*$N13, "") | KB13: =IF(30<=$G13, JW13, "") | KC13: =IF(30<=$G13, ROUND(KB13*$Q13, 2), "") | KD13: =IF(30<=$G13, $N13, "") | KE13: =IF(30<=$G13, KD13-KC13, "") | KF13: =IF(30<=$G13, KB13-KE13, "") | KG13: =IF(30<=$G13, ROUND(JY13*$Q13, 2), "") | KH13: =IF(30<=$G13, JY13+KG13, "") | KI13: =IF(30<=$G13, KC13+KG13, "") | KJ13: =IF(30<=$G13, ($G13-30)*$N13, "") | KK13: =IF(31<=$G13, KF13, "") | KL13: =IF(31<=$G13, ROUND(KK13*$Q13, 2), "") | KM13: =IF(31<=$G13, $N13, "") | KN13: =IF(31<=$G13, KM13-KL13, "") | KO13: =IF(31<=$G13, KK13-KN13, "") | KP13: =IF(31<=$G13, ROUND(KH13*$Q13, 2), "") | KQ13: =IF(31<=$G13, KH13+KP13, "") | KR13: =IF(31<=$G13, KL13+KP13, "") | KS13: =IF(31<=$G13, ($G13-31)*$N13, "") | KT13: =IF(32<=$G13, KO13, "") | KU13: =IF(32<=$G13, ROUND(KT13*$Q13, 2), "") | KV13: =IF(32<=$G13, $N13, "") | KW13: =IF(32<=$G13, KV13-KU13, "") | KX13: =IF(32<=$G13, KT13-KW13, "") | KY13: =IF(32<=$G13, ROUND(KQ13*$Q13, 2), "") | KZ13: =IF(32<=$G13, KQ13+KY13, "") | LA13: =IF(32<=$G13, KU13+KY13, "") | LB13: =IF(32<=$G13, ($G13-32)*$N13, "") | LC13: =IF(33<=$G13, KX13, "") | LD13: =IF(33<=$G13, ROUND(LC13*$Q13, 2), "") | LE13: =IF(33<=$G13, $N13, "") | LF13: =IF(33<=$G13, LE13-LD13, "") | LG13: =IF(33<=$G13, LC13-LF13, "") | LH13: =IF(33<=$G13, ROUND(KZ13*$Q13, 2), "") | LI13: =IF(33<=$G13, KZ13+LH13, "") | LJ13: =IF(33<=$G13, LD13+LH13, "") | LK13: =IF(33<=$G13, ($G13-33)*$N13, "") | LL13: =IF(34<=$G13, LG13, "") | LM13: =IF(34<=$G13, ROUND(LL13*$Q13, 2), "") | LN13: =IF(34<=$G13, $N13, "") | LO13: =IF(34<=$G13, LN13-LM13, "") | LP13: =IF(34<=$G13, LL13-LO13, "") | LQ13: =IF(34<=$G13, ROUND(LI13*$Q13, 2), "") | LR13: =IF(34<=$G13, LI13+LQ13, "") | LS13: =IF(34<=$G13, LM13+LQ13, "") | LT13: =IF(34<=$G13, ($G13-34)*$N13, "") | LU13: =IF(35<=$G13, LP13, "") | LV13: =IF(35<=$G13, ROUND(LU13*$Q13, 2), "") | LW13: =IF(35<=$G13, $N13, "") | LX13: =IF(35<=$G13, LW13-LV13, "") | LY13: =IF(35<=$G13, LU13-LX13, "") | LZ13: =IF(35<=$G13, ROUND(LR13*$Q13, 2), "") | MA13: =IF(35<=$G13, LR13+LZ13, "") | MB13: =IF(35<=$G13, LV13+LZ13, "") | MC13: =IF(35<=$G13, ($G13-35)*$N13, "") | MD13: =IF(36<=$G13, LY13, "") | ME13: =IF(36<=$G13, ROUND(MD13*$Q13, 2), "") | MF13: =IF(36<=$G13, $N13, "") | MG13: =IF(36<=$G13, MF13-ME13, "") | MH13: =IF(36<=$G13, MD13-MG13, "") | MI13: =IF(36<=$G13, ROUND(MA13*$Q13, 2), "") | MJ13: =IF(36<=$G13, MA13+MI13, "") | MK13: =IF(36<=$G13, ME13+MI13, "") | ML13: =IF(36<=$G13, ($G13-36)*$N13, "") | MM13: =IF(37<=$G13, MH13, "") | MN13: =IF(37<=$G13, ROUND(MM13*$Q13, 2), "") | MO13: =IF(37<=$G13, $N13, "") | MP13: =IF(37<=$G13, MO13-MN13, "") | MQ13: =IF(37<=$G13, MM13-MP13, "") | MR13: =IF(37<=$G13, ROUND(MJ13*$Q13, 2), "") | MS13: =IF(37<=$G13, MJ13+MR13, "") | MT13: =IF(37<=$G13, MN13+MR13, "") | MU13: =IF(37<=$G13, ($G13-37)*$N13, "") | MV13: =IF(38<=$G13, MQ13, "") | MW13: =IF(38<=$G13, ROUND(MV13*$Q13, 2), "") | MX13: =IF(38<=$G13, $N13, "") | MY13: =IF(38<=$G13, MX13-MW13, "") | MZ13: =IF(38<=$G13, MV13-MY13, "") | NA13: =IF(38<=$G13, ROUND(MS13*$Q13, 2), "") | NB13: =IF(38<=$G13, MS13+NA13, "") | NC13: =IF(38<=$G13, MW13+NA13, "") | ND13: =IF(38<=$G13, ($G13-38)*$N13, "") | NE13: =IF(39<=$G13, MZ13, "") | NF13: =IF(39<=$G13, ROUND(NE13*$Q13, 2), "") | NG13: =IF(39<=$G13, $N13, "") | NH13: =IF(39<=$G13, NG13-NF13, "") | NI13: =IF(39<=$G13, NE13-NH13, "") | NJ13: =IF(39<=$G13, ROUND(NB13*$Q13, 2), "") | NK13: =IF(39<=$G13, NB13+NJ13, "") | NL13: =IF(39<=$G13, NF13+NJ13, "") | NM13: =IF(39<=$G13, ($G13-39)*$N13, "") | NN13: =IF(40<=$G13, NI13, "") | NO13: =IF(40<=$G13, ROUND(NN13*$Q13, 2), "") | NP13: =IF(40<=$G13, $N13, "") | NQ13: =IF(40<=$G13, NP13-NO13, "") | NR13: =IF(40<=$G13, NN13-NQ13, "") | NS13: =IF(40<=$G13, ROUND(NK13*$Q13, 2), "") | NT13: =IF(40<=$G13, NK13+NS13, "") | NU13: =IF(40<=$G13, NO13+NS13, "") | NV13: =IF(40<=$G13, ($G13-40)*$N13, "") | NW13: =IF(41<=$G13, NR13, "") | NX13: =IF(41<=$G13, ROUND(NW13*$Q13, 2), "") | NY13: =IF(41<=$G13, $N13, "") | NZ13: =IF(41<=$G13, NY13-NX13, "") | OA13: =IF(41<=$G13, NW13-NZ13, "") | OB13: =IF(41<=$G13, ROUND(NT13*$Q13, 2), "") | OC13: =IF(41<=$G13, NT13+OB13, "") | OD13: =IF(41<=$G13, NX13+OB13, "") | OE13: =IF(41<=$G13, ($G13-41)*$N13, "") | OF13: =IF(42<=$G13, OA13, "") | OG13: =IF(42<=$G13, ROUND(OF13*$Q13, 2), "") | OH13: =IF(42<=$G13, $N13, "") | OI13: =IF(42<=$G13, OH13-OG13, "") | OJ13: =IF(42<=$G13, OF13-OI13, "") | OK13: =IF(42<=$G13, ROUND(OC13*$Q13, 2), "") | OL13: =IF(42<=$G13, OC13+OK13, "") | OM13: =IF(42<=$G13, OG13+OK13, "") | ON13: =IF(42<=$G13, ($G13-42)*$N13, "") | OO13: =IF(43<=$G13, OJ13, "") | OP13: =IF(43<=$G13, ROUND(OO13*$Q13, 2), "") | OQ13: =IF(43<=$G13, $N13, "") | OR13: =IF(43<=$G13, OQ13-OP13, "") | OS13: =IF(43<=$G13, OO13-OR13, "") | OT13: =IF(43<=$G13, ROUND(OL13*$Q13, 2), "") | OU13: =IF(43<=$G13, OL13+OT13, "") | OV13: =IF(43<=$G13, OP13+OT13, "") | OW13: =IF(43<=$G13, ($G13-43)*$N13, "") | OX13: =IF(44<=$G13, OS13, "") | OY13: =IF(44<=$G13, ROUND(OX13*$Q13, 2), "") | OZ13: =IF(44<=$G13, $N13, "") | PA13: =IF(44<=$G13, OZ13-OY13, "") | PB13: =IF(44<=$G13, OX13-PA13, "") | PC13: =IF(44<=$G13, ROUND(OU13*$Q13, 2), "") | PD13: =IF(44<=$G13, OU13+PC13, "") | PE13: =IF(44<=$G13, OY13+PC13, "") | PF13: =IF(44<=$G13, ($G13-44)*$N13, "") | PG13: =IF(45<=$G13, PB13, "") | PH13: =IF(45<=$G13, ROUND(PG13*$Q13, 2), "") | PI13: =IF(45<=$G13, $N13, "") | PJ13: =IF(45<=$G13, PI13-PH13, "") | PK13: =IF(45<=$G13, PG13-PJ13, "") | PL13: =IF(45<=$G13, ROUND(PD13*$Q13, 2), "") | PM13: =IF(45<=$G13, PD13+PL13, "") | PN13: =IF(45<=$G13, PH13+PL13, "") | PO13: =IF(45<=$G13, ($G13-45)*$N13, "") | PP13: =IF(46<=$G13, PK13, "") | PQ13: =IF(46<=$G13, ROUND(PP13*$Q13, 2), "") | PR13: =IF(46<=$G13, $N13, "") | PS13: =IF(46<=$G13, PR13-PQ13, "") | PT13: =IF(46<=$G13, PP13-PS13, "") | PU13: =IF(46<=$G13, ROUND(PM13*$Q13, 2), "") | PV13: =IF(46<=$G13, PM13+PU13, "") | PW13: =IF(46<=$G13, PQ13+PU13, "") | PX13: =IF(46<=$G13, ($G13-46)*$N13, "") | PY13: =IF(47<=$G13, PT13, "") | PZ13: =IF(47<=$G13, ROUND(PY13*$Q13, 2), "") | QA13: =IF(47<=$G13, $N13, "") | QB13: =IF(47<=$G13, QA13-PZ13, "") | QC13: =IF(47<=$G13, PY13-QB13, "") | QD13: =IF(47<=$G13, ROUND(PV13*$Q13, 2), "") | QE13: =IF(47<=$G13, PV13+QD13, "") | QF13: =IF(47<=$G13, PZ13+QD13, "") | QG13: =IF(47<=$G13, ($G13-47)*$N13, "") | QH13: =IF(48<=$G13, QC13, "") | QI13: =IF(48<=$G13, ROUND(QH13*$Q13, 2), "") | QJ13: =IF(48<=$G13, $N13, "") | QK13: =IF(48<=$G13, QJ13-QI13, "") | QL13: =IF(48<=$G13, QH13-QK13, "") | QM13: =IF(48<=$G13, ROUND(QE13*$Q13, 2), "") | QN13: =IF(48<=$G13, QE13+QM13, "") | QO13: =IF(48<=$G13, QI13+QM13, "") | QP13: =IF(48<=$G13, ($G13-48)*$N13, "")
A14: 0524-0007 | B14: Lider En Derecho De Via y Construcción SA DE CV | C14: L200 Gls | D14: ACTIVO | E14: 2025-08-15 | F14: 2027-08-15 | G14: 24 | H14: 649987.07 | I14: 0.1 | J14: =ROUND(H14*I14, 2) | K14: =ROUND(H14-J14, 2) | L14: 0 | M14: =ROUND(H14*L14, 2) | N14: 27206.74 | O14: 0.3 | P14: =ROUND(H14*O14, 2) | Q14: 0.02620493 | R14: =RATE(G14, -N14, K14, -P14) | S14: =ROUND(Q14*12, 8) | T14: =ROUND(((1+Q14)^12)-1, 8) | U14: =ROUND(PV(Q14, G14, 0, -P14), 2) | V14: =SUMIF($AA$4:$QP$4, "Interes_Leasing", AA14:QP14) | W14: =SUMIF($AA$4:$QP$4, "Interes_Residual", AA14:QP14) | X14: =ROUND(V14+W14, 2) | Y14: =ROUND((N14*G14+P14+M14)-K14, 2) | Z14: =ROUND(Y14/K14, 4) | AA14: =IF(1<=$G14, $K14, "") | AB14: =IF(1<=$G14, ROUND(AA14*$Q14, 2), "") | AC14: =IF(1<=$G14, $N14, "") | AD14: =IF(1<=$G14, AC14-AB14, "") | AE14: =IF(1<=$G14, AA14-AD14, "") | AF14: =IF(1<=$G14, ROUND($U14*$Q14, 2), "") | AG14: =IF(1<=$G14, $U14+AF14, "") | AH14: =IF(1<=$G14, AB14+AF14, "") | AI14: =IF(1<=$G14, ($G14-1)*$N14, "") | AJ14: =IF(2<=$G14, AE14, "") | AK14: =IF(2<=$G14, ROUND(AJ14*$Q14, 2), "") | AL14: =IF(2<=$G14, $N14, "") | AM14: =IF(2<=$G14, AL14-AK14, "") | AN14: =IF(2<=$G14, AJ14-AM14, "") | AO14: =IF(2<=$G14, ROUND(AG14*$Q14, 2), "") | AP14: =IF(2<=$G14, AG14+AO14, "") | AQ14: =IF(2<=$G14, AK14+AO14, "") | AR14: =IF(2<=$G14, ($G14-2)*$N14, "") | AS14: =IF(3<=$G14, AN14, "") | AT14: =IF(3<=$G14, ROUND(AS14*$Q14, 2), "") | AU14: =IF(3<=$G14, $N14, "") | AV14: =IF(3<=$G14, AU14-AT14, "") | AW14: =IF(3<=$G14, AS14-AV14, "") | AX14: =IF(3<=$G14, ROUND(AP14*$Q14, 2), "") | AY14: =IF(3<=$G14, AP14+AX14, "") | AZ14: =IF(3<=$G14, AT14+AX14, "") | BA14: =IF(3<=$G14, ($G14-3)*$N14, "") | BB14: =IF(4<=$G14, AW14, "") | BC14: =IF(4<=$G14, ROUND(BB14*$Q14, 2), "") | BD14: =IF(4<=$G14, $N14, "") | BE14: =IF(4<=$G14, BD14-BC14, "") | BF14: =IF(4<=$G14, BB14-BE14, "") | BG14: =IF(4<=$G14, ROUND(AY14*$Q14, 2), "") | BH14: =IF(4<=$G14, AY14+BG14, "") | BI14: =IF(4<=$G14, BC14+BG14, "") | BJ14: =IF(4<=$G14, ($G14-4)*$N14, "") | BK14: =IF(5<=$G14, BF14, "") | BL14: =IF(5<=$G14, ROUND(BK14*$Q14, 2), "") | BM14: =IF(5<=$G14, $N14, "") | BN14: =IF(5<=$G14, BM14-BL14, "") | BO14: =IF(5<=$G14, BK14-BN14, "") | BP14: =IF(5<=$G14, ROUND(BH14*$Q14, 2), "") | BQ14: =IF(5<=$G14, BH14+BP14, "") | BR14: =IF(5<=$G14, BL14+BP14, "") | BS14: =IF(5<=$G14, ($G14-5)*$N14, "") | BT14: =IF(6<=$G14, BO14, "") | BU14: =IF(6<=$G14, ROUND(BT14*$Q14, 2), "") | BV14: =IF(6<=$G14, $N14, "") | BW14: =IF(6<=$G14, BV14-BU14, "") | BX14: =IF(6<=$G14, BT14-BW14, "") | BY14: =IF(6<=$G14, ROUND(BQ14*$Q14, 2), "") | BZ14: =IF(6<=$G14, BQ14+BY14, "") | CA14: =IF(6<=$G14, BU14+BY14, "") | CB14: =IF(6<=$G14, ($G14-6)*$N14, "") | CC14: =IF(7<=$G14, BX14, "") | CD14: =IF(7<=$G14, ROUND(CC14*$Q14, 2), "") | CE14: =IF(7<=$G14, $N14, "") | CF14: =IF(7<=$G14, CE14-CD14, "") | CG14: =IF(7<=$G14, CC14-CF14, "") | CH14: =IF(7<=$G14, ROUND(BZ14*$Q14, 2), "") | CI14: =IF(7<=$G14, BZ14+CH14, "") | CJ14: =IF(7<=$G14, CD14+CH14, "") | CK14: =IF(7<=$G14, ($G14-7)*$N14, "") | CL14: =IF(8<=$G14, CG14, "") | CM14: =IF(8<=$G14, ROUND(CL14*$Q14, 2), "") | CN14: =IF(8<=$G14, $N14, "") | CO14: =IF(8<=$G14, CN14-CM14, "") | CP14: =IF(8<=$G14, CL14-CO14, "") | CQ14: =IF(8<=$G14, ROUND(CI14*$Q14, 2), "") | CR14: =IF(8<=$G14, CI14+CQ14, "") | CS14: =IF(8<=$G14, CM14+CQ14, "") | CT14: =IF(8<=$G14, ($G14-8)*$N14, "") | CU14: =IF(9<=$G14, CP14, "") | CV14: =IF(9<=$G14, ROUND(CU14*$Q14, 2), "") | CW14: =IF(9<=$G14, $N14, "") | CX14: =IF(9<=$G14, CW14-CV14, "") | CY14: =IF(9<=$G14, CU14-CX14, "") | CZ14: =IF(9<=$G14, ROUND(CR14*$Q14, 2), "") | DA14: =IF(9<=$G14, CR14+CZ14, "") | DB14: =IF(9<=$G14, CV14+CZ14, "") | DC14: =IF(9<=$G14, ($G14-9)*$N14, "") | DD14: =IF(10<=$G14, CY14, "") | DE14: =IF(10<=$G14, ROUND(DD14*$Q14, 2), "") | DF14: =IF(10<=$G14, $N14, "") | DG14: =IF(10<=$G14, DF14-DE14, "") | DH14: =IF(10<=$G14, DD14-DG14, "") | DI14: =IF(10<=$G14, ROUND(DA14*$Q14, 2), "") | DJ14: =IF(10<=$G14, DA14+DI14, "") | DK14: =IF(10<=$G14, DE14+DI14, "") | DL14: =IF(10<=$G14, ($G14-10)*$N14, "") | DM14: =IF(11<=$G14, DH14, "") | DN14: =IF(11<=$G14, ROUND(DM14*$Q14, 2), "") | DO14: =IF(11<=$G14, $N14, "") | DP14: =IF(11<=$G14, DO14-DN14, "") | DQ14: =IF(11<=$G14, DM14-DP14, "") | DR14: =IF(11<=$G14, ROUND(DJ14*$Q14, 2), "") | DS14: =IF(11<=$G14, DJ14+DR14, "") | DT14: =IF(11<=$G14, DN14+DR14, "") | DU14: =IF(11<=$G14, ($G14-11)*$N14, "") | DV14: =IF(12<=$G14, DQ14, "") | DW14: =IF(12<=$G14, ROUND(DV14*$Q14, 2), "") | DX14: =IF(12<=$G14, $N14, "") | DY14: =IF(12<=$G14, DX14-DW14, "") | DZ14: =IF(12<=$G14, DV14-DY14, "") | EA14: =IF(12<=$G14, ROUND(DS14*$Q14, 2), "") | EB14: =IF(12<=$G14, DS14+EA14, "") | EC14: =IF(12<=$G14, DW14+EA14, "") | ED14: =IF(12<=$G14, ($G14-12)*$N14, "") | EE14: =IF(13<=$G14, DZ14, "") | EF14: =IF(13<=$G14, ROUND(EE14*$Q14, 2), "") | EG14: =IF(13<=$G14, $N14, "") | EH14: =IF(13<=$G14, EG14-EF14, "") | EI14: =IF(13<=$G14, EE14-EH14, "") | EJ14: =IF(13<=$G14, ROUND(EB14*$Q14, 2), "") | EK14: =IF(13<=$G14, EB14+EJ14, "") | EL14: =IF(13<=$G14, EF14+EJ14, "") | EM14: =IF(13<=$G14, ($G14-13)*$N14, "") | EN14: =IF(14<=$G14, EI14, "") | EO14: =IF(14<=$G14, ROUND(EN14*$Q14, 2), "") | EP14: =IF(14<=$G14, $N14, "") | EQ14: =IF(14<=$G14, EP14-EO14, "") | ER14: =IF(14<=$G14, EN14-EQ14, "") | ES14: =IF(14<=$G14, ROUND(EK14*$Q14, 2), "") | ET14: =IF(14<=$G14, EK14+ES14, "") | EU14: =IF(14<=$G14, EO14+ES14, "") | EV14: =IF(14<=$G14, ($G14-14)*$N14, "") | EW14: =IF(15<=$G14, ER14, "") | EX14: =IF(15<=$G14, ROUND(EW14*$Q14, 2), "") | EY14: =IF(15<=$G14, $N14, "") | EZ14: =IF(15<=$G14, EY14-EX14, "") | FA14: =IF(15<=$G14, EW14-EZ14, "") | FB14: =IF(15<=$G14, ROUND(ET14*$Q14, 2), "") | FC14: =IF(15<=$G14, ET14+FB14, "") | FD14: =IF(15<=$G14, EX14+FB14, "") | FE14: =IF(15<=$G14, ($G14-15)*$N14, "") | FF14: =IF(16<=$G14, FA14, "") | FG14: =IF(16<=$G14, ROUND(FF14*$Q14, 2), "") | FH14: =IF(16<=$G14, $N14, "") | FI14: =IF(16<=$G14, FH14-FG14, "") | FJ14: =IF(16<=$G14, FF14-FI14, "") | FK14: =IF(16<=$G14, ROUND(FC14*$Q14, 2), "") | FL14: =IF(16<=$G14, FC14+FK14, "") | FM14: =IF(16<=$G14, FG14+FK14, "") | FN14: =IF(16<=$G14, ($G14-16)*$N14, "") | FO14: =IF(17<=$G14, FJ14, "") | FP14: =IF(17<=$G14, ROUND(FO14*$Q14, 2), "") | FQ14: =IF(17<=$G14, $N14, "") | FR14: =IF(17<=$G14, FQ14-FP14, "") | FS14: =IF(17<=$G14, FO14-FR14, "") | FT14: =IF(17<=$G14, ROUND(FL14*$Q14, 2), "") | FU14: =IF(17<=$G14, FL14+FT14, "") | FV14: =IF(17<=$G14, FP14+FT14, "") | FW14: =IF(17<=$G14, ($G14-17)*$N14, "") | FX14: =IF(18<=$G14, FS14, "") | FY14: =IF(18<=$G14, ROUND(FX14*$Q14, 2), "") | FZ14: =IF(18<=$G14, $N14, "") | GA14: =IF(18<=$G14, FZ14-FY14, "") | GB14: =IF(18<=$G14, FX14-GA14, "") | GC14: =IF(18<=$G14, ROUND(FU14*$Q14, 2), "") | GD14: =IF(18<=$G14, FU14+GC14, "") | GE14: =IF(18<=$G14, FY14+GC14, "") | GF14: =IF(18<=$G14, ($G14-18)*$N14, "") | GG14: =IF(19<=$G14, GB14, "") | GH14: =IF(19<=$G14, ROUND(GG14*$Q14, 2), "") | GI14: =IF(19<=$G14, $N14, "") | GJ14: =IF(19<=$G14, GI14-GH14, "") | GK14: =IF(19<=$G14, GG14-GJ14, "") | GL14: =IF(19<=$G14, ROUND(GD14*$Q14, 2), "") | GM14: =IF(19<=$G14, GD14+GL14, "") | GN14: =IF(19<=$G14, GH14+GL14, "") | GO14: =IF(19<=$G14, ($G14-19)*$N14, "") | GP14: =IF(20<=$G14, GK14, "") | GQ14: =IF(20<=$G14, ROUND(GP14*$Q14, 2), "") | GR14: =IF(20<=$G14, $N14, "") | GS14: =IF(20<=$G14, GR14-GQ14, "") | GT14: =IF(20<=$G14, GP14-GS14, "") | GU14: =IF(20<=$G14, ROUND(GM14*$Q14, 2), "") | GV14: =IF(20<=$G14, GM14+GU14, "") | GW14: =IF(20<=$G14, GQ14+GU14, "") | GX14: =IF(20<=$G14, ($G14-20)*$N14, "") | GY14: =IF(21<=$G14, GT14, "") | GZ14: =IF(21<=$G14, ROUND(GY14*$Q14, 2), "") | HA14: =IF(21<=$G14, $N14, "") | HB14: =IF(21<=$G14, HA14-GZ14, "") | HC14: =IF(21<=$G14, GY14-HB14, "") | HD14: =IF(21<=$G14, ROUND(GV14*$Q14, 2), "") | HE14: =IF(21<=$G14, GV14+HD14, "") | HF14: =IF(21<=$G14, GZ14+HD14, "") | HG14: =IF(21<=$G14, ($G14-21)*$N14, "") | HH14: =IF(22<=$G14, HC14, "") | HI14: =IF(22<=$G14, ROUND(HH14*$Q14, 2), "") | HJ14: =IF(22<=$G14, $N14, "") | HK14: =IF(22<=$G14, HJ14-HI14, "") | HL14: =IF(22<=$G14, HH14-HK14, "") | HM14: =IF(22<=$G14, ROUND(HE14*$Q14, 2), "") | HN14: =IF(22<=$G14, HE14+HM14, "") | HO14: =IF(22<=$G14, HI14+HM14, "") | HP14: =IF(22<=$G14, ($G14-22)*$N14, "") | HQ14: =IF(23<=$G14, HL14, "") | HR14: =IF(23<=$G14, ROUND(HQ14*$Q14, 2), "") | HS14: =IF(23<=$G14, $N14, "") | HT14: =IF(23<=$G14, HS14-HR14, "") | HU14: =IF(23<=$G14, HQ14-HT14, "") | HV14: =IF(23<=$G14, ROUND(HN14*$Q14, 2), "") | HW14: =IF(23<=$G14, HN14+HV14, "") | HX14: =IF(23<=$G14, HR14+HV14, "") | HY14: =IF(23<=$G14, ($G14-23)*$N14, "") | HZ14: =IF(24<=$G14, HU14, "") | IA14: =IF(24<=$G14, ROUND(HZ14*$Q14, 2), "") | IB14: =IF(24<=$G14, $N14, "") | IC14: =IF(24<=$G14, IB14-IA14, "") | ID14: =IF(24<=$G14, HZ14-IC14, "") | IE14: =IF(24<=$G14, ROUND(HW14*$Q14, 2), "") | IF14: =IF(24<=$G14, HW14+IE14, "") | IG14: =IF(24<=$G14, IA14+IE14, "") | IH14: =IF(24<=$G14, ($G14-24)*$N14, "") | II14: =IF(25<=$G14, ID14, "") | IJ14: =IF(25<=$G14, ROUND(II14*$Q14, 2), "") | IK14: =IF(25<=$G14, $N14, "") | IL14: =IF(25<=$G14, IK14-IJ14, "") | IM14: =IF(25<=$G14, II14-IL14, "") | IN14: =IF(25<=$G14, ROUND(IF14*$Q14, 2), "") | IO14: =IF(25<=$G14, IF14+IN14, "") | IP14: =IF(25<=$G14, IJ14+IN14, "") | IQ14: =IF(25<=$G14, ($G14-25)*$N14, "") | IR14: =IF(26<=$G14, IM14, "") | IS14: =IF(26<=$G14, ROUND(IR14*$Q14, 2), "") | IT14: =IF(26<=$G14, $N14, "") | IU14: =IF(26<=$G14, IT14-IS14, "") | IV14: =IF(26<=$G14, IR14-IU14, "") | IW14: =IF(26<=$G14, ROUND(IO14*$Q14, 2), "") | IX14: =IF(26<=$G14, IO14+IW14, "") | IY14: =IF(26<=$G14, IS14+IW14, "") | IZ14: =IF(26<=$G14, ($G14-26)*$N14, "") | JA14: =IF(27<=$G14, IV14, "") | JB14: =IF(27<=$G14, ROUND(JA14*$Q14, 2), "") | JC14: =IF(27<=$G14, $N14, "") | JD14: =IF(27<=$G14, JC14-JB14, "") | JE14: =IF(27<=$G14, JA14-JD14, "") | JF14: =IF(27<=$G14, ROUND(IX14*$Q14, 2), "") | JG14: =IF(27<=$G14, IX14+JF14, "") | JH14: =IF(27<=$G14, JB14+JF14, "") | JI14: =IF(27<=$G14, ($G14-27)*$N14, "") | JJ14: =IF(28<=$G14, JE14, "") | JK14: =IF(28<=$G14, ROUND(JJ14*$Q14, 2), "") | JL14: =IF(28<=$G14, $N14, "") | JM14: =IF(28<=$G14, JL14-JK14, "") | JN14: =IF(28<=$G14, JJ14-JM14, "") | JO14: =IF(28<=$G14, ROUND(JG14*$Q14, 2), "") | JP14: =IF(28<=$G14, JG14+JO14, "") | JQ14: =IF(28<=$G14, JK14+JO14, "") | JR14: =IF(28<=$G14, ($G14-28)*$N14, "") | JS14: =IF(29<=$G14, JN14, "") | JT14: =IF(29<=$G14, ROUND(JS14*$Q14, 2), "") | JU14: =IF(29<=$G14, $N14, "") | JV14: =IF(29<=$G14, JU14-JT14, "") | JW14: =IF(29<=$G14, JS14-JV14, "") | JX14: =IF(29<=$G14, ROUND(JP14*$Q14, 2), "") | JY14: =IF(29<=$G14, JP14+JX14, "") | JZ14: =IF(29<=$G14, JT14+JX14, "") | KA14: =IF(29<=$G14, ($G14-29)*$N14, "") | KB14: =IF(30<=$G14, JW14, "") | KC14: =IF(30<=$G14, ROUND(KB14*$Q14, 2), "") | KD14: =IF(30<=$G14, $N14, "") | KE14: =IF(30<=$G14, KD14-KC14, "") | KF14: =IF(30<=$G14, KB14-KE14, "") | KG14: =IF(30<=$G14, ROUND(JY14*$Q14, 2), "") | KH14: =IF(30<=$G14, JY14+KG14, "") | KI14: =IF(30<=$G14, KC14+KG14, "") | KJ14: =IF(30<=$G14, ($G14-30)*$N14, "") | KK14: =IF(31<=$G14, KF14, "") | KL14: =IF(31<=$G14, ROUND(KK14*$Q14, 2), "") | KM14: =IF(31<=$G14, $N14, "") | KN14: =IF(31<=$G14, KM14-KL14, "") | KO14: =IF(31<=$G14, KK14-KN14, "") | KP14: =IF(31<=$G14, ROUND(KH14*$Q14, 2), "") | KQ14: =IF(31<=$G14, KH14+KP14, "") | KR14: =IF(31<=$G14, KL14+KP14, "") | KS14: =IF(31<=$G14, ($G14-31)*$N14, "") | KT14: =IF(32<=$G14, KO14, "") | KU14: =IF(32<=$G14, ROUND(KT14*$Q14, 2), "") | KV14: =IF(32<=$G14, $N14, "") | KW14: =IF(32<=$G14, KV14-KU14, "") | KX14: =IF(32<=$G14, KT14-KW14, "") | KY14: =IF(32<=$G14, ROUND(KQ14*$Q14, 2), "") | KZ14: =IF(32<=$G14, KQ14+KY14, "") | LA14: =IF(32<=$G14, KU14+KY14, "") | LB14: =IF(32<=$G14, ($G14-32)*$N14, "") | LC14: =IF(33<=$G14, KX14, "") | LD14: =IF(33<=$G14, ROUND(LC14*$Q14, 2), "") | LE14: =IF(33<=$G14, $N14, "") | LF14: =IF(33<=$G14, LE14-LD14, "") | LG14: =IF(33<=$G14, LC14-LF14, "") | LH14: =IF(33<=$G14, ROUND(KZ14*$Q14, 2), "") | LI14: =IF(33<=$G14, KZ14+LH14, "") | LJ14: =IF(33<=$G14, LD14+LH14, "") | LK14: =IF(33<=$G14, ($G14-33)*$N14, "") | LL14: =IF(34<=$G14, LG14, "") | LM14: =IF(34<=$G14, ROUND(LL14*$Q14, 2), "") | LN14: =IF(34<=$G14, $N14, "") | LO14: =IF(34<=$G14, LN14-LM14, "") | LP14: =IF(34<=$G14, LL14-LO14, "") | LQ14: =IF(34<=$G14, ROUND(LI14*$Q14, 2), "") | LR14: =IF(34<=$G14, LI14+LQ14, "") | LS14: =IF(34<=$G14, LM14+LQ14, "") | LT14: =IF(34<=$G14, ($G14-34)*$N14, "") | LU14: =IF(35<=$G14, LP14, "") | LV14: =IF(35<=$G14, ROUND(LU14*$Q14, 2), "") | LW14: =IF(35<=$G14, $N14, "") | LX14: =IF(35<=$G14, LW14-LV14, "") | LY14: =IF(35<=$G14, LU14-LX14, "") | LZ14: =IF(35<=$G14, ROUND(LR14*$Q14, 2), "") | MA14: =IF(35<=$G14, LR14+LZ14, "") | MB14: =IF(35<=$G14, LV14+LZ14, "") | MC14: =IF(35<=$G14, ($G14-35)*$N14, "") | MD14: =IF(36<=$G14, LY14, "") | ME14: =IF(36<=$G14, ROUND(MD14*$Q14, 2), "") | MF14: =IF(36<=$G14, $N14, "") | MG14: =IF(36<=$G14, MF14-ME14, "") | MH14: =IF(36<=$G14, MD14-MG14, "") | MI14: =IF(36<=$G14, ROUND(MA14*$Q14, 2), "") | MJ14: =IF(36<=$G14, MA14+MI14, "") | MK14: =IF(36<=$G14, ME14+MI14, "") | ML14: =IF(36<=$G14, ($G14-36)*$N14, "") | MM14: =IF(37<=$G14, MH14, "") | MN14: =IF(37<=$G14, ROUND(MM14*$Q14, 2), "") | MO14: =IF(37<=$G14, $N14, "") | MP14: =IF(37<=$G14, MO14-MN14, "") | MQ14: =IF(37<=$G14, MM14-MP14, "") | MR14: =IF(37<=$G14, ROUND(MJ14*$Q14, 2), "") | MS14: =IF(37<=$G14, MJ14+MR14, "") | MT14: =IF(37<=$G14, MN14+MR14, "") | MU14: =IF(37<=$G14, ($G14-37)*$N14, "") | MV14: =IF(38<=$G14, MQ14, "") | MW14: =IF(38<=$G14, ROUND(MV14*$Q14, 2), "") | MX14: =IF(38<=$G14, $N14, "") | MY14: =IF(38<=$G14, MX14-MW14, "") | MZ14: =IF(38<=$G14, MV14-MY14, "") | NA14: =IF(38<=$G14, ROUND(MS14*$Q14, 2), "") | NB14: =IF(38<=$G14, MS14+NA14, "") | NC14: =IF(38<=$G14, MW14+NA14, "") | ND14: =IF(38<=$G14, ($G14-38)*$N14, "") | NE14: =IF(39<=$G14, MZ14, "") | NF14: =IF(39<=$G14, ROUND(NE14*$Q14, 2), "") | NG14: =IF(39<=$G14, $N14, "") | NH14: =IF(39<=$G14, NG14-NF14, "") | NI14: =IF(39<=$G14, NE14-NH14, "") | NJ14: =IF(39<=$G14, ROUND(NB14*$Q14, 2), "") | NK14: =IF(39<=$G14, NB14+NJ14, "") | NL14: =IF(39<=$G14, NF14+NJ14, "") | NM14: =IF(39<=$G14, ($G14-39)*$N14, "") | NN14: =IF(40<=$G14, NI14, "") | NO14: =IF(40<=$G14, ROUND(NN14*$Q14, 2), "") | NP14: =IF(40<=$G14, $N14, "") | NQ14: =IF(40<=$G14, NP14-NO14, "") | NR14: =IF(40<=$G14, NN14-NQ14, "") | NS14: =IF(40<=$G14, ROUND(NK14*$Q14, 2), "") | NT14: =IF(40<=$G14, NK14+NS14, "") | NU14: =IF(40<=$G14, NO14+NS14, "") | NV14: =IF(40<=$G14, ($G14-40)*$N14, "") | NW14: =IF(41<=$G14, NR14, "") | NX14: =IF(41<=$G14, ROUND(NW14*$Q14, 2), "") | NY14: =IF(41<=$G14, $N14, "") | NZ14: =IF(41<=$G14, NY14-NX14, "") | OA14: =IF(41<=$G14, NW14-NZ14, "") | OB14: =IF(41<=$G14, ROUND(NT14*$Q14, 2), "") | OC14: =IF(41<=$G14, NT14+OB14, "") | OD14: =IF(41<=$G14, NX14+OB14, "") | OE14: =IF(41<=$G14, ($G14-41)*$N14, "") | OF14: =IF(42<=$G14, OA14, "") | OG14: =IF(42<=$G14, ROUND(OF14*$Q14, 2), "") | OH14: =IF(42<=$G14, $N14, "") | OI14: =IF(42<=$G14, OH14-OG14, "") | OJ14: =IF(42<=$G14, OF14-OI14, "") | OK14: =IF(42<=$G14, ROUND(OC14*$Q14, 2), "") | OL14: =IF(42<=$G14, OC14+OK14, "") | OM14: =IF(42<=$G14, OG14+OK14, "") | ON14: =IF(42<=$G14, ($G14-42)*$N14, "") | OO14: =IF(43<=$G14, OJ14, "") | OP14: =IF(43<=$G14, ROUND(OO14*$Q14, 2), "") | OQ14: =IF(43<=$G14, $N14, "") | OR14: =IF(43<=$G14, OQ14-OP14, "") | OS14: =IF(43<=$G14, OO14-OR14, "") | OT14: =IF(43<=$G14, ROUND(OL14*$Q14, 2), "") | OU14: =IF(43<=$G14, OL14+OT14, "") | OV14: =IF(43<=$G14, OP14+OT14, "") | OW14: =IF(43<=$G14, ($G14-43)*$N14, "") | OX14: =IF(44<=$G14, OS14, "") | OY14: =IF(44<=$G14, ROUND(OX14*$Q14, 2), "") | OZ14: =IF(44<=$G14, $N14, "") | PA14: =IF(44<=$G14, OZ14-OY14, "") | PB14: =IF(44<=$G14, OX14-PA14, "") | PC14: =IF(44<=$G14, ROUND(OU14*$Q14, 2), "") | PD14: =IF(44<=$G14, OU14+PC14, "") | PE14: =IF(44<=$G14, OY14+PC14, "") | PF14: =IF(44<=$G14, ($G14-44)*$N14, "") | PG14: =IF(45<=$G14, PB14, "") | PH14: =IF(45<=$G14, ROUND(PG14*$Q14, 2), "") | PI14: =IF(45<=$G14, $N14, "") | PJ14: =IF(45<=$G14, PI14-PH14, "") | PK14: =IF(45<=$G14, PG14-PJ14, "") | PL14: =IF(45<=$G14, ROUND(PD14*$Q14, 2), "") | PM14: =IF(45<=$G14, PD14+PL14, "") | PN14: =IF(45<=$G14, PH14+PL14, "") | PO14: =IF(45<=$G14, ($G14-45)*$N14, "") | PP14: =IF(46<=$G14, PK14, "") | PQ14: =IF(46<=$G14, ROUND(PP14*$Q14, 2), "") | PR14: =IF(46<=$G14, $N14, "") | PS14: =IF(46<=$G14, PR14-PQ14, "") | PT14: =IF(46<=$G14, PP14-PS14, "") | PU14: =IF(46<=$G14, ROUND(PM14*$Q14, 2), "") | PV14: =IF(46<=$G14, PM14+PU14, "") | PW14: =IF(46<=$G14, PQ14+PU14, "") | PX14: =IF(46<=$G14, ($G14-46)*$N14, "") | PY14: =IF(47<=$G14, PT14, "") | PZ14: =IF(47<=$G14, ROUND(PY14*$Q14, 2), "") | QA14: =IF(47<=$G14, $N14, "") | QB14: =IF(47<=$G14, QA14-PZ14, "") | QC14: =IF(47<=$G14, PY14-QB14, "") | QD14: =IF(47<=$G14, ROUND(PV14*$Q14, 2), "") | QE14: =IF(47<=$G14, PV14+QD14, "") | QF14: =IF(47<=$G14, PZ14+QD14, "") | QG14: =IF(47<=$G14, ($G14-47)*$N14, "") | QH14: =IF(48<=$G14, QC14, "") | QI14: =IF(48<=$G14, ROUND(QH14*$Q14, 2), "") | QJ14: =IF(48<=$G14, $N14, "") | QK14: =IF(48<=$G14, QJ14-QI14, "") | QL14: =IF(48<=$G14, QH14-QK14, "") | QM14: =IF(48<=$G14, ROUND(QE14*$Q14, 2), "") | QN14: =IF(48<=$G14, QE14+QM14, "") | QO14: =IF(48<=$G14, QI14+QM14, "") | QP14: =IF(48<=$G14, ($G14-48)*$N14, "")
A15: 0524-0011 | B15: Lider En Derecho De Via y Construcción SA DE CV | C15: Wrangler Unlimited Sahara | D15: ACTIVO | E15: 2025-12-31 | F15: 2029-12-31 | G15: 48 | H15: 1058554.3 | I15: 0.2 | J15: =ROUND(H15*I15, 2) | K15: =ROUND(H15-J15, 2) | L15: 0.02 | M15: =ROUND(H15*L15, 2) | N15: 30510.75 | O15: 0.1 | P15: =ROUND(H15*O15, 2) | Q15: 0.0268869 | R15: =RATE(G15, -N15, K15, -P15) | S15: =ROUND(Q15*12, 8) | T15: =ROUND(((1+Q15)^12)-1, 8) | U15: =ROUND(PV(Q15, G15, 0, -P15), 2) | V15: =SUMIF($AA$4:$QP$4, "Interes_Leasing", AA15:QP15) | W15: =SUMIF($AA$4:$QP$4, "Interes_Residual", AA15:QP15) | X15: =ROUND(V15+W15, 2) | Y15: =ROUND((N15*G15+P15+M15)-K15, 2) | Z15: =ROUND(Y15/K15, 4) | AA15: =IF(1<=$G15, $K15, "") | AB15: =IF(1<=$G15, ROUND(AA15*$Q15, 2), "") | AC15: =IF(1<=$G15, $N15, "") | AD15: =IF(1<=$G15, AC15-AB15, "") | AE15: =IF(1<=$G15, AA15-AD15, "") | AF15: =IF(1<=$G15, ROUND($U15*$Q15, 2), "") | AG15: =IF(1<=$G15, $U15+AF15, "") | AH15: =IF(1<=$G15, AB15+AF15, "") | AI15: =IF(1<=$G15, ($G15-1)*$N15, "") | AJ15: =IF(2<=$G15, AE15, "") | AK15: =IF(2<=$G15, ROUND(AJ15*$Q15, 2), "") | AL15: =IF(2<=$G15, $N15, "") | AM15: =IF(2<=$G15, AL15-AK15, "") | AN15: =IF(2<=$G15, AJ15-AM15, "") | AO15: =IF(2<=$G15, ROUND(AG15*$Q15, 2), "") | AP15: =IF(2<=$G15, AG15+AO15, "") | AQ15: =IF(2<=$G15, AK15+AO15, "") | AR15: =IF(2<=$G15, ($G15-2)*$N15, "") | AS15: =IF(3<=$G15, AN15, "") | AT15: =IF(3<=$G15, ROUND(AS15*$Q15, 2), "") | AU15: =IF(3<=$G15, $N15, "") | AV15: =IF(3<=$G15, AU15-AT15, "") | AW15: =IF(3<=$G15, AS15-AV15, "") | AX15: =IF(3<=$G15, ROUND(AP15*$Q15, 2), "") | AY15: =IF(3<=$G15, AP15+AX15, "") | AZ15: =IF(3<=$G15, AT15+AX15, "") | BA15: =IF(3<=$G15, ($G15-3)*$N15, "") | BB15: =IF(4<=$G15, AW15, "") | BC15: =IF(4<=$G15, ROUND(BB15*$Q15, 2), "") | BD15: =IF(4<=$G15, $N15, "") | BE15: =IF(4<=$G15, BD15-BC15, "") | BF15: =IF(4<=$G15, BB15-BE15, "") | BG15: =IF(4<=$G15, ROUND(AY15*$Q15, 2), "") | BH15: =IF(4<=$G15, AY15+BG15, "") | BI15: =IF(4<=$G15, BC15+BG15, "") | BJ15: =IF(4<=$G15, ($G15-4)*$N15, "") | BK15: =IF(5<=$G15, BF15, "") | BL15: =IF(5<=$G15, ROUND(BK15*$Q15, 2), "") | BM15: =IF(5<=$G15, $N15, "") | BN15: =IF(5<=$G15, BM15-BL15, "") | BO15: =IF(5<=$G15, BK15-BN15, "") | BP15: =IF(5<=$G15, ROUND(BH15*$Q15, 2), "") | BQ15: =IF(5<=$G15, BH15+BP15, "") | BR15: =IF(5<=$G15, BL15+BP15, "") | BS15: =IF(5<=$G15, ($G15-5)*$N15, "") | BT15: =IF(6<=$G15, BO15, "") | BU15: =IF(6<=$G15, ROUND(BT15*$Q15, 2), "") | BV15: =IF(6<=$G15, $N15, "") | BW15: =IF(6<=$G15, BV15-BU15, "") | BX15: =IF(6<=$G15, BT15-BW15, "") | BY15: =IF(6<=$G15, ROUND(BQ15*$Q15, 2), "") | BZ15: =IF(6<=$G15, BQ15+BY15, "") | CA15: =IF(6<=$G15, BU15+BY15, "") | CB15: =IF(6<=$G15, ($G15-6)*$N15, "") | CC15: =IF(7<=$G15, BX15, "") | CD15: =IF(7<=$G15, ROUND(CC15*$Q15, 2), "") | CE15: =IF(7<=$G15, $N15, "") | CF15: =IF(7<=$G15, CE15-CD15, "") | CG15: =IF(7<=$G15, CC15-CF15, "") | CH15: =IF(7<=$G15, ROUND(BZ15*$Q15, 2), "") | CI15: =IF(7<=$G15, BZ15+CH15, "") | CJ15: =IF(7<=$G15, CD15+CH15, "") | CK15: =IF(7<=$G15, ($G15-7)*$N15, "") | CL15: =IF(8<=$G15, CG15, "") | CM15: =IF(8<=$G15, ROUND(CL15*$Q15, 2), "") | CN15: =IF(8<=$G15, $N15, "") | CO15: =IF(8<=$G15, CN15-CM15, "") | CP15: =IF(8<=$G15, CL15-CO15, "") | CQ15: =IF(8<=$G15, ROUND(CI15*$Q15, 2), "") | CR15: =IF(8<=$G15, CI15+CQ15, "") | CS15: =IF(8<=$G15, CM15+CQ15, "") | CT15: =IF(8<=$G15, ($G15-8)*$N15, "") | CU15: =IF(9<=$G15, CP15, "") | CV15: =IF(9<=$G15, ROUND(CU15*$Q15, 2), "") | CW15: =IF(9<=$G15, $N15, "") | CX15: =IF(9<=$G15, CW15-CV15, "") | CY15: =IF(9<=$G15, CU15-CX15, "") | CZ15: =IF(9<=$G15, ROUND(CR15*$Q15, 2), "") | DA15: =IF(9<=$G15, CR15+CZ15, "") | DB15: =IF(9<=$G15, CV15+CZ15, "") | DC15: =IF(9<=$G15, ($G15-9)*$N15, "") | DD15: =IF(10<=$G15, CY15, "") | DE15: =IF(10<=$G15, ROUND(DD15*$Q15, 2), "") | DF15: =IF(10<=$G15, $N15, "") | DG15: =IF(10<=$G15, DF15-DE15, "") | DH15: =IF(10<=$G15, DD15-DG15, "") | DI15: =IF(10<=$G15, ROUND(DA15*$Q15, 2), "") | DJ15: =IF(10<=$G15, DA15+DI15, "") | DK15: =IF(10<=$G15, DE15+DI15, "") | DL15: =IF(10<=$G15, ($G15-10)*$N15, "") | DM15: =IF(11<=$G15, DH15, "") | DN15: =IF(11<=$G15, ROUND(DM15*$Q15, 2), "") | DO15: =IF(11<=$G15, $N15, "") | DP15: =IF(11<=$G15, DO15-DN15, "") | DQ15: =IF(11<=$G15, DM15-DP15, "") | DR15: =IF(11<=$G15, ROUND(DJ15*$Q15, 2), "") | DS15: =IF(11<=$G15, DJ15+DR15, "") | DT15: =IF(11<=$G15, DN15+DR15, "") | DU15: =IF(11<=$G15, ($G15-11)*$N15, "") | DV15: =IF(12<=$G15, DQ15, "") | DW15: =IF(12<=$G15, ROUND(DV15*$Q15, 2), "") | DX15: =IF(12<=$G15, $N15, "") | DY15: =IF(12<=$G15, DX15-DW15, "") | DZ15: =IF(12<=$G15, DV15-DY15, "") | EA15: =IF(12<=$G15, ROUND(DS15*$Q15, 2), "") | EB15: =IF(12<=$G15, DS15+EA15, "") | EC15: =IF(12<=$G15, DW15+EA15, "") | ED15: =IF(12<=$G15, ($G15-12)*$N15, "") | EE15: =IF(13<=$G15, DZ15, "") | EF15: =IF(13<=$G15, ROUND(EE15*$Q15, 2), "") | EG15: =IF(13<=$G15, $N15, "") | EH15: =IF(13<=$G15, EG15-EF15, "") | EI15: =IF(13<=$G15, EE15-EH15, "") | EJ15: =IF(13<=$G15, ROUND(EB15*$Q15, 2), "") | EK15: =IF(13<=$G15, EB15+EJ15, "") | EL15: =IF(13<=$G15, EF15+EJ15, "") | EM15: =IF(13<=$G15, ($G15-13)*$N15, "") | EN15: =IF(14<=$G15, EI15, "") | EO15: =IF(14<=$G15, ROUND(EN15*$Q15, 2), "") | EP15: =IF(14<=$G15, $N15, "") | EQ15: =IF(14<=$G15, EP15-EO15, "") | ER15: =IF(14<=$G15, EN15-EQ15, "") | ES15: =IF(14<=$G15, ROUND(EK15*$Q15, 2), "") | ET15: =IF(14<=$G15, EK15+ES15, "") | EU15: =IF(14<=$G15, EO15+ES15, "") | EV15: =IF(14<=$G15, ($G15-14)*$N15, "") | EW15: =IF(15<=$G15, ER15, "") | EX15: =IF(15<=$G15, ROUND(EW15*$Q15, 2), "") | EY15: =IF(15<=$G15, $N15, "") | EZ15: =IF(15<=$G15, EY15-EX15, "") | FA15: =IF(15<=$G15, EW15-EZ15, "") | FB15: =IF(15<=$G15, ROUND(ET15*$Q15, 2), "") | FC15: =IF(15<=$G15, ET15+FB15, "") | FD15: =IF(15<=$G15, EX15+FB15, "") | FE15: =IF(15<=$G15, ($G15-15)*$N15, "") | FF15: =IF(16<=$G15, FA15, "") | FG15: =IF(16<=$G15, ROUND(FF15*$Q15, 2), "") | FH15: =IF(16<=$G15, $N15, "") | FI15: =IF(16<=$G15, FH15-FG15, "") | FJ15: =IF(16<=$G15, FF15-FI15, "") | FK15: =IF(16<=$G15, ROUND(FC15*$Q15, 2), "") | FL15: =IF(16<=$G15, FC15+FK15, "") | FM15: =IF(16<=$G15, FG15+FK15, "") | FN15: =IF(16<=$G15, ($G15-16)*$N15, "") | FO15: =IF(17<=$G15, FJ15, "") | FP15: =IF(17<=$G15, ROUND(FO15*$Q15, 2), "") | FQ15: =IF(17<=$G15, $N15, "") | FR15: =IF(17<=$G15, FQ15-FP15, "") | FS15: =IF(17<=$G15, FO15-FR15, "") | FT15: =IF(17<=$G15, ROUND(FL15*$Q15, 2), "") | FU15: =IF(17<=$G15, FL15+FT15, "") | FV15: =IF(17<=$G15, FP15+FT15, "") | FW15: =IF(17<=$G15, ($G15-17)*$N15, "") | FX15: =IF(18<=$G15, FS15, "") | FY15: =IF(18<=$G15, ROUND(FX15*$Q15, 2), "") | FZ15: =IF(18<=$G15, $N15, "") | GA15: =IF(18<=$G15, FZ15-FY15, "") | GB15: =IF(18<=$G15, FX15-GA15, "") | GC15: =IF(18<=$G15, ROUND(FU15*$Q15, 2), "") | GD15: =IF(18<=$G15, FU15+GC15, "") | GE15: =IF(18<=$G15, FY15+GC15, "") | GF15: =IF(18<=$G15, ($G15-18)*$N15, "") | GG15: =IF(19<=$G15, GB15, "") | GH15: =IF(19<=$G15, ROUND(GG15*$Q15, 2), "") | GI15: =IF(19<=$G15, $N15, "") | GJ15: =IF(19<=$G15, GI15-GH15, "") | GK15: =IF(19<=$G15, GG15-GJ15, "") | GL15: =IF(19<=$G15, ROUND(GD15*$Q15, 2), "") | GM15: =IF(19<=$G15, GD15+GL15, "") | GN15: =IF(19<=$G15, GH15+GL15, "") | GO15: =IF(19<=$G15, ($G15-19)*$N15, "") | GP15: =IF(20<=$G15, GK15, "") | GQ15: =IF(20<=$G15, ROUND(GP15*$Q15, 2), "") | GR15: =IF(20<=$G15, $N15, "") | GS15: =IF(20<=$G15, GR15-GQ15, "") | GT15: =IF(20<=$G15, GP15-GS15, "") | GU15: =IF(20<=$G15, ROUND(GM15*$Q15, 2), "") | GV15: =IF(20<=$G15, GM15+GU15, "") | GW15: =IF(20<=$G15, GQ15+GU15, "") | GX15: =IF(20<=$G15, ($G15-20)*$N15, "") | GY15: =IF(21<=$G15, GT15, "") | GZ15: =IF(21<=$G15, ROUND(GY15*$Q15, 2), "") | HA15: =IF(21<=$G15, $N15, "") | HB15: =IF(21<=$G15, HA15-GZ15, "") | HC15: =IF(21<=$G15, GY15-HB15, "") | HD15: =IF(21<=$G15, ROUND(GV15*$Q15, 2), "") | HE15: =IF(21<=$G15, GV15+HD15, "") | HF15: =IF(21<=$G15, GZ15+HD15, "") | HG15: =IF(21<=$G15, ($G15-21)*$N15, "") | HH15: =IF(22<=$G15, HC15, "") | HI15: =IF(22<=$G15, ROUND(HH15*$Q15, 2), "") | HJ15: =IF(22<=$G15, $N15, "") | HK15: =IF(22<=$G15, HJ15-HI15, "") | HL15: =IF(22<=$G15, HH15-HK15, "") | HM15: =IF(22<=$G15, ROUND(HE15*$Q15, 2), "") | HN15: =IF(22<=$G15, HE15+HM15, "") | HO15: =IF(22<=$G15, HI15+HM15, "") | HP15: =IF(22<=$G15, ($G15-22)*$N15, "") | HQ15: =IF(23<=$G15, HL15, "") | HR15: =IF(23<=$G15, ROUND(HQ15*$Q15, 2), "") | HS15: =IF(23<=$G15, $N15, "") | HT15: =IF(23<=$G15, HS15-HR15, "") | HU15: =IF(23<=$G15, HQ15-HT15, "") | HV15: =IF(23<=$G15, ROUND(HN15*$Q15, 2), "") | HW15: =IF(23<=$G15, HN15+HV15, "") | HX15: =IF(23<=$G15, HR15+HV15, "") | HY15: =IF(23<=$G15, ($G15-23)*$N15, "") | HZ15: =IF(24<=$G15, HU15, "") | IA15: =IF(24<=$G15, ROUND(HZ15*$Q15, 2), "") | IB15: =IF(24<=$G15, $N15, "") | IC15: =IF(24<=$G15, IB15-IA15, "") | ID15: =IF(24<=$G15, HZ15-IC15, "") | IE15: =IF(24<=$G15, ROUND(HW15*$Q15, 2), "") | IF15: =IF(24<=$G15, HW15+IE15, "") | IG15: =IF(24<=$G15, IA15+IE15, "") | IH15: =IF(24<=$G15, ($G15-24)*$N15, "") | II15: =IF(25<=$G15, ID15, "") | IJ15: =IF(25<=$G15, ROUND(II15*$Q15, 2), "") | IK15: =IF(25<=$G15, $N15, "") | IL15: =IF(25<=$G15, IK15-IJ15, "") | IM15: =IF(25<=$G15, II15-IL15, "") | IN15: =IF(25<=$G15, ROUND(IF15*$Q15, 2), "") | IO15: =IF(25<=$G15, IF15+IN15, "") | IP15: =IF(25<=$G15, IJ15+IN15, "") | IQ15: =IF(25<=$G15, ($G15-25)*$N15, "") | IR15: =IF(26<=$G15, IM15, "") | IS15: =IF(26<=$G15, ROUND(IR15*$Q15, 2), "") | IT15: =IF(26<=$G15, $N15, "") | IU15: =IF(26<=$G15, IT15-IS15, "") | IV15: =IF(26<=$G15, IR15-IU15, "") | IW15: =IF(26<=$G15, ROUND(IO15*$Q15, 2), "") | IX15: =IF(26<=$G15, IO15+IW15, "") | IY15: =IF(26<=$G15, IS15+IW15, "") | IZ15: =IF(26<=$G15, ($G15-26)*$N15, "") | JA15: =IF(27<=$G15, IV15, "") | JB15: =IF(27<=$G15, ROUND(JA15*$Q15, 2), "") | JC15: =IF(27<=$G15, $N15, "") | JD15: =IF(27<=$G15, JC15-JB15, "") | JE15: =IF(27<=$G15, JA15-JD15, "") | JF15: =IF(27<=$G15, ROUND(IX15*$Q15, 2), "") | JG15: =IF(27<=$G15, IX15+JF15, "") | JH15: =IF(27<=$G15, JB15+JF15, "") | JI15: =IF(27<=$G15, ($G15-27)*$N15, "") | JJ15: =IF(28<=$G15, JE15, "") | JK15: =IF(28<=$G15, ROUND(JJ15*$Q15, 2), "") | JL15: =IF(28<=$G15, $N15, "") | JM15: =IF(28<=$G15, JL15-JK15, "") | JN15: =IF(28<=$G15, JJ15-JM15, "") | JO15: =IF(28<=$G15, ROUND(JG15*$Q15, 2), "") | JP15: =IF(28<=$G15, JG15+JO15, "") | JQ15: =IF(28<=$G15, JK15+JO15, "") | JR15: =IF(28<=$G15, ($G15-28)*$N15, "") | JS15: =IF(29<=$G15, JN15, "") | JT15: =IF(29<=$G15, ROUND(JS15*$Q15, 2), "") | JU15: =IF(29<=$G15, $N15, "") | JV15: =IF(29<=$G15, JU15-JT15, "") | JW15: =IF(29<=$G15, JS15-JV15, "") | JX15: =IF(29<=$G15, ROUND(JP15*$Q15, 2), "") | JY15: =IF(29<=$G15, JP15+JX15, "") | JZ15: =IF(29<=$G15, JT15+JX15, "") | KA15: =IF(29<=$G15, ($G15-29)*$N15, "") | KB15: =IF(30<=$G15, JW15, "") | KC15: =IF(30<=$G15, ROUND(KB15*$Q15, 2), "") | KD15: =IF(30<=$G15, $N15, "") | KE15: =IF(30<=$G15, KD15-KC15, "") | KF15: =IF(30<=$G15, KB15-KE15, "") | KG15: =IF(30<=$G15, ROUND(JY15*$Q15, 2), "") | KH15: =IF(30<=$G15, JY15+KG15, "") | KI15: =IF(30<=$G15, KC15+KG15, "") | KJ15: =IF(30<=$G15, ($G15-30)*$N15, "") | KK15: =IF(31<=$G15, KF15, "") | KL15: =IF(31<=$G15, ROUND(KK15*$Q15, 2), "") | KM15: =IF(31<=$G15, $N15, "") | KN15: =IF(31<=$G15, KM15-KL15, "") | KO15: =IF(31<=$G15, KK15-KN15, "") | KP15: =IF(31<=$G15, ROUND(KH15*$Q15, 2), "") | KQ15: =IF(31<=$G15, KH15+KP15, "") | KR15: =IF(31<=$G15, KL15+KP15, "") | KS15: =IF(31<=$G15, ($G15-31)*$N15, "") | KT15: =IF(32<=$G15, KO15, "") | KU15: =IF(32<=$G15, ROUND(KT15*$Q15, 2), "") | KV15: =IF(32<=$G15, $N15, "") | KW15: =IF(32<=$G15, KV15-KU15, "") | KX15: =IF(32<=$G15, KT15-KW15, "") | KY15: =IF(32<=$G15, ROUND(KQ15*$Q15, 2), "") | KZ15: =IF(32<=$G15, KQ15+KY15, "") | LA15: =IF(32<=$G15, KU15+KY15, "") | LB15: =IF(32<=$G15, ($G15-32)*$N15, "") | LC15: =IF(33<=$G15, KX15, "") | LD15: =IF(33<=$G15, ROUND(LC15*$Q15, 2), "") | LE15: =IF(33<=$G15, $N15, "") | LF15: =IF(33<=$G15, LE15-LD15, "") | LG15: =IF(33<=$G15, LC15-LF15, "") | LH15: =IF(33<=$G15, ROUND(KZ15*$Q15, 2), "") | LI15: =IF(33<=$G15, KZ15+LH15, "") | LJ15: =IF(33<=$G15, LD15+LH15, "") | LK15: =IF(33<=$G15, ($G15-33)*$N15, "") | LL15: =IF(34<=$G15, LG15, "") | LM15: =IF(34<=$G15, ROUND(LL15*$Q15, 2), "") | LN15: =IF(34<=$G15, $N15, "") | LO15: =IF(34<=$G15, LN15-LM15, "") | LP15: =IF(34<=$G15, LL15-LO15, "") | LQ15: =IF(34<=$G15, ROUND(LI15*$Q15, 2), "") | LR15: =IF(34<=$G15, LI15+LQ15, "") | LS15: =IF(34<=$G15, LM15+LQ15, "") | LT15: =IF(34<=$G15, ($G15-34)*$N15, "") | LU15: =IF(35<=$G15, LP15, "") | LV15: =IF(35<=$G15, ROUND(LU15*$Q15, 2), "") | LW15: =IF(35<=$G15, $N15, "") | LX15: =IF(35<=$G15, LW15-LV15, "") | LY15: =IF(35<=$G15, LU15-LX15, "") | LZ15: =IF(35<=$G15, ROUND(LR15*$Q15, 2), "") | MA15: =IF(35<=$G15, LR15+LZ15, "") | MB15: =IF(35<=$G15, LV15+LZ15, "") | MC15: =IF(35<=$G15, ($G15-35)*$N15, "") | MD15: =IF(36<=$G15, LY15, "") | ME15: =IF(36<=$G15, ROUND(MD15*$Q15, 2), "") | MF15: =IF(36<=$G15, $N15, "") | MG15: =IF(36<=$G15, MF15-ME15, "") | MH15: =IF(36<=$G15, MD15-MG15, "") | MI15: =IF(36<=$G15, ROUND(MA15*$Q15, 2), "") | MJ15: =IF(36<=$G15, MA15+MI15, "") | MK15: =IF(36<=$G15, ME15+MI15, "") | ML15: =IF(36<=$G15, ($G15-36)*$N15, "") | MM15: =IF(37<=$G15, MH15, "") | MN15: =IF(37<=$G15, ROUND(MM15*$Q15, 2), "") | MO15: =IF(37<=$G15, $N15, "") | MP15: =IF(37<=$G15, MO15-MN15, "") | MQ15: =IF(37<=$G15, MM15-MP15, "") | MR15: =IF(37<=$G15, ROUND(MJ15*$Q15, 2), "") | MS15: =IF(37<=$G15, MJ15+MR15, "") | MT15: =IF(37<=$G15, MN15+MR15, "") | MU15: =IF(37<=$G15, ($G15-37)*$N15, "") | MV15: =IF(38<=$G15, MQ15, "") | MW15: =IF(38<=$G15, ROUND(MV15*$Q15, 2), "") | MX15: =IF(38<=$G15, $N15, "") | MY15: =IF(38<=$G15, MX15-MW15, "") | MZ15: =IF(38<=$G15, MV15-MY15, "") | NA15: =IF(38<=$G15, ROUND(MS15*$Q15, 2), "") | NB15: =IF(38<=$G15, MS15+NA15, "") | NC15: =IF(38<=$G15, MW15+NA15, "") | ND15: =IF(38<=$G15, ($G15-38)*$N15, "") | NE15: =IF(39<=$G15, MZ15, "") | NF15: =IF(39<=$G15, ROUND(NE15*$Q15, 2), "") | NG15: =IF(39<=$G15, $N15, "") | NH15: =IF(39<=$G15, NG15-NF15, "") | NI15: =IF(39<=$G15, NE15-NH15, "") | NJ15: =IF(39<=$G15, ROUND(NB15*$Q15, 2), "") | NK15: =IF(39<=$G15, NB15+NJ15, "") | NL15: =IF(39<=$G15, NF15+NJ15, "") | NM15: =IF(39<=$G15, ($G15-39)*$N15, "") | NN15: =IF(40<=$G15, NI15, "") | NO15: =IF(40<=$G15, ROUND(NN15*$Q15, 2), "") | NP15: =IF(40<=$G15, $N15, "") | NQ15: =IF(40<=$G15, NP15-NO15, "") | NR15: =IF(40<=$G15, NN15-NQ15, "") | NS15: =IF(40<=$G15, ROUND(NK15*$Q15, 2), "") | NT15: =IF(40<=$G15, NK15+NS15, "") | NU15: =IF(40<=$G15, NO15+NS15, "") | NV15: =IF(40<=$G15, ($G15-40)*$N15, "") | NW15: =IF(41<=$G15, NR15, "") | NX15: =IF(41<=$G15, ROUND(NW15*$Q15, 2), "") | NY15: =IF(41<=$G15, $N15, "") | NZ15: =IF(41<=$G15, NY15-NX15, "") | OA15: =IF(41<=$G15, NW15-NZ15, "") | OB15: =IF(41<=$G15, ROUND(NT15*$Q15, 2), "") | OC15: =IF(41<=$G15, NT15+OB15, "") | OD15: =IF(41<=$G15, NX15+OB15, "") | OE15: =IF(41<=$G15, ($G15-41)*$N15, "") | OF15: =IF(42<=$G15, OA15, "") | OG15: =IF(42<=$G15, ROUND(OF15*$Q15, 2), "") | OH15: =IF(42<=$G15, $N15, "") | OI15: =IF(42<=$G15, OH15-OG15, "") | OJ15: =IF(42<=$G15, OF15-OI15, "") | OK15: =IF(42<=$G15, ROUND(OC15*$Q15, 2), "") | OL15: =IF(42<=$G15, OC15+OK15, "") | OM15: =IF(42<=$G15, OG15+OK15, "") | ON15: =IF(42<=$G15, ($G15-42)*$N15, "") | OO15: =IF(43<=$G15, OJ15, "") | OP15: =IF(43<=$G15, ROUND(OO15*$Q15, 2), "") | OQ15: =IF(43<=$G15, $N15, "") | OR15: =IF(43<=$G15, OQ15-OP15, "") | OS15: =IF(43<=$G15, OO15-OR15, "") | OT15: =IF(43<=$G15, ROUND(OL15*$Q15, 2), "") | OU15: =IF(43<=$G15, OL15+OT15, "") | OV15: =IF(43<=$G15, OP15+OT15, "") | OW15: =IF(43<=$G15, ($G15-43)*$N15, "") | OX15: =IF(44<=$G15, OS15, "") | OY15: =IF(44<=$G15, ROUND(OX15*$Q15, 2), "") | OZ15: =IF(44<=$G15, $N15, "") | PA15: =IF(44<=$G15, OZ15-OY15, "") | PB15: =IF(44<=$G15, OX15-PA15, "") | PC15: =IF(44<=$G15, ROUND(OU15*$Q15, 2), "") | PD15: =IF(44<=$G15, OU15+PC15, "") | PE15: =IF(44<=$G15, OY15+PC15, "") | PF15: =IF(44<=$G15, ($G15-44)*$N15, "") | PG15: =IF(45<=$G15, PB15, "") | PH15: =IF(45<=$G15, ROUND(PG15*$Q15, 2), "") | PI15: =IF(45<=$G15, $N15, "") | PJ15: =IF(45<=$G15, PI15-PH15, "") | PK15: =IF(45<=$G15, PG15-PJ15, "") | PL15: =IF(45<=$G15, ROUND(PD15*$Q15, 2), "") | PM15: =IF(45<=$G15, PD15+PL15, "") | PN15: =IF(45<=$G15, PH15+PL15, "") | PO15: =IF(45<=$G15, ($G15-45)*$N15, "") | PP15: =IF(46<=$G15, PK15, "") | PQ15: =IF(46<=$G15, ROUND(PP15*$Q15, 2), "") | PR15: =IF(46<=$G15, $N15, "") | PS15: =IF(46<=$G15, PR15-PQ15, "") | PT15: =IF(46<=$G15, PP15-PS15, "") | PU15: =IF(46<=$G15, ROUND(PM15*$Q15, 2), "") | PV15: =IF(46<=$G15, PM15+PU15, "") | PW15: =IF(46<=$G15, PQ15+PU15, "") | PX15: =IF(46<=$G15, ($G15-46)*$N15, "") | PY15: =IF(47<=$G15, PT15, "") | PZ15: =IF(47<=$G15, ROUND(PY15*$Q15, 2), "") | QA15: =IF(47<=$G15, $N15, "") | QB15: =IF(47<=$G15, QA15-PZ15, "") | QC15: =IF(47<=$G15, PY15-QB15, "") | QD15: =IF(47<=$G15, ROUND(PV15*$Q15, 2), "") | QE15: =IF(47<=$G15, PV15+QD15, "") | QF15: =IF(47<=$G15, PZ15+QD15, "") | QG15: =IF(47<=$G15, ($G15-47)*$N15, "") | QH15: =IF(48<=$G15, QC15, "") | QI15: =IF(48<=$G15, ROUND(QH15*$Q15, 2), "") | QJ15: =IF(48<=$G15, $N15, "") | QK15: =IF(48<=$G15, QJ15-QI15, "") | QL15: =IF(48<=$G15, QH15-QK15, "") | QM15: =IF(48<=$G15, ROUND(QE15*$Q15, 2), "") | QN15: =IF(48<=$G15, QE15+QM15, "") | QO15: =IF(48<=$G15, QI15+QM15, "") | QP15: =IF(48<=$G15, ($G15-48)*$N15, "")
